Workbook

Sheet Annahmen
A1: LADEKLAR – Finanzmodell: Annahmen
A2: Alle Beträge netto in Euro (zzgl. 19 % USt.). Blaue Schrift auf gelbem Grund = Eingabe/Annahme; schwarze Zellen = Formel. Monat 1 = Startmonat (siehe unten). Stand 16.10.2026.
A3: Legende: | B3: Eingabe | C3: Formel
A5: A Allgemein | B5: Wert | C5: Einheit | G5: Quelle / Begründung
A6: Startmonat des Modells (Monat 1) | B6: 46388 | C6: Datum | G6: Annahme: Pilotphase Nov./Dez. 2026, regulärer Verkaufsstart Januar 2027
A7: Zahlende Pilotkunden zum Start | B7: 5 | C7: Kunden | G7: Annahme: 5 Pilotbetriebe aus der Testphase Q4/2026 wandeln zum 01.01.2027 um
A9: B Preise (lt. PLAN.md, netto je Monat) | B9: Wert | C9: Einheit | G9: Quelle / Begründung
A10: Tarif Start | B10: 49 | C10: €/Monat | G10: PLAN.md Kap. 6: 3 Fahrer, 6 Fahrzeuge, 1 Disponent
A11: Tarif Flotte | B11: 129 | C11: €/Monat | G11: PLAN.md Kap. 6: 15 Fahrer, 40 Fahrzeuge, 5 Disponenten
A12: Tarif Premium | B12: 299 | C12: €/Monat | G12: PLAN.md Kap. 6: 40 Fahrer, unbegrenzt Fahrzeuge/Disponenten, API, SLA
A13: Zusatzfahrer Flotte | B13: 7 | C13: €/Fahrer/Monat | G13: PLAN.md Kap. 6
A14: Zusatzfahrer Premium | B14: 6 | C14: €/Fahrer/Monat | G14: PLAN.md Kap. 6
A15: White-Label-Store-App: Einrichtung | B15: 1990 | C15: € einmalig | G15: PLAN.md Kap. 6 (Premium-Zusatz)
A16: White-Label-Store-App: laufend | B16: 99 | C16: €/Monat | G16: PLAN.md Kap. 6 (Premium-Zusatz)
A18: C Tarifmix der Neukunden und Nutzung | B18: Wert | C18: Einheit | G18: Quelle / Begründung
A19: Anteil Start an Neukunden | B19: 0.5 | C19: % | G19: Annahme; 53 % der Betriebe haben 1–3 Fahrzeuge (BAG-Strukturbericht), digitale Tools werden von größeren Betrieben eher gekauft
A20: Anteil Flotte an Neukunden | B20: 0.38 | C20: % | G20: Annahme; 30 % der Betriebe haben 4–10 Fahrzeuge (BAG-Strukturbericht)
A21: Anteil Premium an Neukunden | B21: =1-B19-B20 -> 0.12 | C21: % | G21: Rest auf 100 %
A22: Ø Zusatzfahrer je Flotte-Kunde | B22: 1.5 | C22: Fahrer | G22: Annahme (Flotte enthält 15 Fahrer; nur ein Teil der Kunden liegt darüber)
A23: Ø Zusatzfahrer je Premium-Kunde | B23: 5 | C23: Fahrer | G23: Annahme (Premium enthält 40 Fahrer)
A24: Store-App-Quote (Anteil neuer Premium-Kunden) | B24: 0.2 | C24: % | G24: Annahme
A25: Anteil Jahreszahler | B25: 0.3 | C25: % | G25: Annahme; Jahreszahlung = 2 Monate geschenkt (PLAN.md)
A26: Geschenkte Monate bei Jahreszahlung | B26: 2 | C26: Monate | G26: PLAN.md Kap. 6
A27: Effektiver Rabatt auf den MRR | B27: =B25*B26/12 -> 0.05 | C27: % | G27: Formel: Anteil Jahreszahler × 2/12. Vorauszahlungen der Jahreszahler werden konservativ NICHT als Liquiditätsvorteil gerechnet
A28: Umwandlung Test (30 Tage) → zahlend | B28: 0.35 | C28: % | G28: Annahme; nur zur Berechnung der nötigen Testzugänge
A30: D Kündigungen (Churn) je Monat | B30: Wert | C30: Einheit | G30: Quelle / Begründung
A31: Churn Start | B31: 0.03 | C31: % je Monat | G31: Annahme; SMB-SaaS 3–7 % je Monat (Vena Solutions 2025), entspricht ca. 31 % p. a.
A32: Churn Flotte | B32: 0.02 | C32: % je Monat | G32: Annahme; ca. 22 % p. a.
A33: Churn Premium | B33: 0.012 | C33: % je Monat | G33: Annahme; ca. 13 % p. a.
A35: E Neue zahlende Kunden je Monat (nach 30-Tage-Test) | B35: Wert | C35: Einheit | G35: Quelle / Begründung
A36: Jahr 1 (2027), Quartal 1: Neukunden je Monat | B36: 3 | C36: Kunden/Monat | G36: Annahme; Jahr 1 gründergetriebener Vertrieb, ab Jahr 2 Partner und Vertriebsteam
A37: Jahr 1 (2027), Quartal 2: Neukunden je Monat | B37: 6 | C37: Kunden/Monat | G37: Annahme
A38: Jahr 1 (2027), Quartal 3: Neukunden je Monat | B38: 9 | C38: Kunden/Monat | G38: Annahme
A39: Jahr 1 (2027), Quartal 4: Neukunden je Monat | B39: 12 | C39: Kunden/Monat | G39: Annahme
A40: Jahr 2 (2028), Quartal 1: Neukunden je Monat | B40: 16 | C40: Kunden/Monat | G40: Annahme
A41: Jahr 2 (2028), Quartal 2: Neukunden je Monat | B41: 20 | C41: Kunden/Monat | G41: Annahme
A42: Jahr 2 (2028), Quartal 3: Neukunden je Monat | B42: 24 | C42: Kunden/Monat | G42: Annahme
A43: Jahr 2 (2028), Quartal 4: Neukunden je Monat | B43: 28 | C43: Kunden/Monat | G43: Annahme
A44: Jahr 3 (2029), Quartal 1: Neukunden je Monat | B44: 30 | C44: Kunden/Monat | G44: Annahme
A45: Jahr 3 (2029), Quartal 2: Neukunden je Monat | B45: 33 | C45: Kunden/Monat | G45: Annahme
A46: Jahr 3 (2029), Quartal 3: Neukunden je Monat | B46: 36 | C46: Kunden/Monat | G46: Annahme
A47: Jahr 3 (2029), Quartal 4: Neukunden je Monat | B47: 40 | C47: Kunden/Monat | G47: Annahme
... A49: Jahr 5 (2031): Neukunden je Monat | B49: 55 | C49: Kunden/Monat | G49: Annahme
A51: F Variable Kosten | B51: Wert | C51: Einheit | G51: Quelle / Begründung
A52: Hosting/Speicher je Start-Kunde | B52: 0.8 | C52: €/Kunde/Monat | G52: Annahme; Hosting in Deutschland, 5 GB Lieferschein-Speicher
A53: Hosting/Speicher je Flotte-Kunde | B53: 2 | C53: €/Kunde/Monat | G53: Annahme; 50 GB Speicher
A54: Hosting/Speicher je Premium-Kunde | B54: 5 | C54: €/Kunde/Monat | G54: Annahme; 250 GB Speicher, SLA 99,5 %
A55: Zahlungs-/Rechnungsgebühren in % vom Umsatz | B55: 0.008 | C55: % | G55: Annahme auf Basis Stripe Invoicing 0,4 % + Puffer (meetergo, Stand 10/2026)
A56: Zahlungsgebühr je Kunde und Monat (SEPA-Lastschrift) | B56: 0.35 | C56: €/Kunde/Monat | G56: Stripe SEPA 0,35 € je Transaktion (qualimero / ki-syndikat, 2026)
A57: Partnerprovision (Reseller, Verbände, Telematik-Händler) | B57: 0.25 | C57: % vom Partnerumsatz | G57: PLAN.md: 20–30 % Provision
A58: Anteil Umsatz über Partner (Jahr 1–5) | B58: 0 | C58: 0.1 | D58: 0.2 | E58: 0.25 | F58: 0.3 | G58: % · Annahme
A59: Fremdkosten je Store-App-Einrichtung | B59: 150 | C59: € je Einrichtung | G59: Annahme (Icons, Store-Texte, Testgeräte); Arbeitszeit steckt im Personal
A61: G Fixkosten je Monat nach Jahr | B61: Jahr 1 | C61: Jahr 2 | D61: Jahr 3 | E61: Jahr 4 | F61: Jahr 5 | G61: Quelle / Begründung
A62: Hosting-Grundkosten (Server DE, Backup, Monitoring, E-Mail) | B62: 300 | C62: 400 | D62: 600 | E62: 800 | F62: 1000 | G62: €/Monat · Annahme; Hetzner hat 2026 zweimal erhöht (+30–40 % bei CX), daher Puffer
A63: Marketing laufend (Google Ads, Social, Fachpresse, Druck) | B63: 2500 | C63: 4000 | D63: 6000 | E63: 8000 | F63: 10000 | G63: €/Monat · Annahme; Aufteilung siehe BUSINESSPLAN.md Kap. 7
A64: Miete / Coworking | B64: 250 | C64: 600 | D64: 1500 | E64: 2200 | F64: 2800 | G64: €/Monat · Annahme
A65: Versicherungen (Cyber-/IT-Haftpflicht, D&O, Inhalt) | B65: 120 | C65: 150 | D65: 220 | E65: 300 | F65: 380 | G65: €/Monat · Annahme
A66: Steuerberatung und Buchhaltung | B66: 350 | C66: 500 | D66: 800 | E66: 1000 | F66: 1200 | G66: €/Monat · Annahme
A67: Recht und Datenschutz (Anwalt, externer DSB) | B67: 300 | C67: 350 | D67: 450 | E67: 550 | F67: 600 | G67: €/Monat · Annahme
A68: Reisekosten, Fahrzeug, Kundenbesuche | B68: 500 | C68: 800 | D68: 1200 | E68: 1600 | F68: 2000 | G68: €/Monat · Annahme
A69: Sonstiges (Telefon, Bank, IHK, Büromaterial) | B69: 150 | C69: 200 | D69: 300 | E69: 400 | F69: 500 | G69: €/Monat · Annahme
A70: Software-Werkzeuge Grundbetrag | B70: 150 | C70: €/Monat | G70: Annahme (CRM, Buchhaltung, Telefonie, Office)
A71: Software-Werkzeuge je Kopf | B71: 40 | C71: €/Kopf/Monat | G71: Annahme
A72: Ausstattung je Neueinstellung (Laptop, Handy) | B72: 1800 | C72: € einmalig | G72: Annahme; sofort als Aufwand (Nutzungsdauer 1 Jahr lt. BMF)
A73: Einmalkosten Gründung in Monat 1 | B73: 8000 | C73: € einmalig | G73: Annahme: Notar/Handelsregister, Marke DPMA/EUIPO, anwaltliche Prüfung AGB/AVV, Gestaltung
A75: H Messen und Veranstaltungen | B75: Monat-Nr. | C75: Kosten € | G75: Termin / Begründung
A76: LogiMAT 2027 Stuttgart (Besuch) | B76: 3 | C76: 800 | G76: 16.–18.03.2027 (Veranstalter-Broschüre)
A77: transport logistic 2027 München (Start-up-/Gemeinschaftsstand) | B77: 4 | C77: 9000 | G77: 26.–29.04.2027 (Messe München); Kosten Annahme
A78: Verbandstage / Unternehmerabende Herbst 2027 | B78: 10 | C78: 2500 | G78: Annahme: 3–4 Landesverbands-Termine
A79: LogiMAT 2028 Stuttgart (Kleinstand) | B79: 15 | C79: 7000 | G79: März 2028, Termin noch nicht veröffentlicht – Annahme
A80: IAA Transportation 2028 Hannover (Stand) | B80: 21 | C80: 14000 | G80: 19.–24.09.2028 (VDA); Kosten Annahme
A81: Verbandstage Herbst 2028 | B81: 22 | C81: 3000 | G81: Annahme
A82: transport logistic 2029 München (Stand) | B82: 28 | C82: 15000 | G82: Zweijahresrhythmus; Termin 2029 noch offen – Annahme April 2029
A83: Verbandstage Herbst 2029 | B83: 34 | C83: 4000 | G83: Annahme
A84: LogiMAT 2030 Stuttgart (Stand) | B84: 39 | C84: 10000 | G84: Annahme März 2030
A85: IAA Transportation 2030 Hannover (Stand) | B85: 45 | C85: 18000 | G85: Zweijahresrhythmus – Annahme Sept. 2030
A86: transport logistic 2031 München (Stand) | B86: 52 | C86: 18000 | G86: Annahme April 2031
A87: Verbandstage Herbst 2031 | B87: 58 | C87: 5000 | G87: Annahme
A89: I Personal | B89: Kategorie | C89: Start Monat | D89: Brutto €/Monat | E89: AG-Faktor | G89: Begründung
A90: Gründer/Geschäftsführer: Gehalt je Monat (Jahr 1–5) | B90: 2500 | C90: 4000 | D90: 5500 | E90: 6500 | F90: 7000 | G90: €/Monat · Annahme; Gesellschafter-Geschäftsführer, i. d. R. sozialversicherungsfrei (Statusprüfung!)
A91: Gründer: Kostenfaktor | B91: 1 | C91: Faktor | G91: Annahme: keine AG-Anteile; Kranken-/Rentenvorsorge privat
A92: Gehaltssteigerung je Modelljahr | B92: 0.03 | C92: % p. a. | G92: Annahme
A93: Angestellte (Rolle)
A94: Vertrieb & Kundenerfolg 1 (mehrsprachig, Ex-Disposition) | B94: Vertrieb | C94: 7 | D94: 3800 | E94: 1.21 | G94: Gehalt Annahme (Marktwerte: Disponent Median 3.710 €, gehalt.de; Senior Full-Stack 54.700–75.264 € p. a., StepStone/Indeed); AG-Faktor 1,21 = Brutto + ca. 21 % SV-Arbeitgeberanteil
A95: Softwareentwicklung 1 (Full-Stack) | B95: Technik | C95: 10 | D95: 5200 | E95: 1.21 | G95: Gehalt Annahme (Marktwerte: Disponent Median 3.710 €, gehalt.de; Senior Full-Stack 54.700–75.264 € p. a., StepStone/Indeed); AG-Faktor 1,21 = Brutto + ca. 21 % SV-Arbeitgeberanteil
A96: Vertrieb 2 / Partnermanagement | B96: Vertrieb | C96: 13 | D96: 4200 | E96: 1.21 | G96: Gehalt Annahme (Marktwerte: Disponent Median 3.710 €, gehalt.de; Senior Full-Stack 54.700–75.264 € p. a., StepStone/Indeed); AG-Faktor 1,21 = Brutto + ca. 21 % SV-Arbeitgeberanteil
A97: Support Teilzeit (PL/RO/TR) | B97: Support | C97: 13 | D97: 1600 | E97: 1.21 | G97: Gehalt Annahme (Marktwerte: Disponent Median 3.710 €, gehalt.de; Senior Full-Stack 54.700–75.264 € p. a., StepStone/Indeed); AG-Faktor 1,21 = Brutto + ca. 21 % SV-Arbeitgeberanteil
A98: Softwareentwicklung 2 | B98: Technik | C98: 22 | D98: 5200 | E98: 1.21 | G98: Gehalt Annahme (Marktwerte: Disponent Median 3.710 €, gehalt.de; Senior Full-Stack 54.700–75.264 € p. a., StepStone/Indeed); AG-Faktor 1,21 = Brutto + ca. 21 % SV-Arbeitgeberanteil
A99: Kundenerfolg 2 | B99: Support | C99: 28 | D99: 3800 | E99: 1.21 | G99: Gehalt Annahme (Marktwerte: Disponent Median 3.710 €, gehalt.de; Senior Full-Stack 54.700–75.264 € p. a., StepStone/Indeed); AG-Faktor 1,21 = Brutto + ca. 21 % SV-Arbeitgeberanteil
A100: Marketing | B100: Marketing | C100: 31 | D100: 4000 | E100: 1.21 | G100: Gehalt Annahme (Marktwerte: Disponent Median 3.710 €, gehalt.de; Senior Full-Stack 54.700–75.264 € p. a., StepStone/Indeed); AG-Faktor 1,21 = Brutto + ca. 21 % SV-Arbeitgeberanteil
A101: Softwareentwicklung 3 | B101: Technik | C101: 37 | D101: 5400 | E101: 1.21 | G101: Gehalt Annahme (Marktwerte: Disponent Median 3.710 €, gehalt.de; Senior Full-Stack 54.700–75.264 € p. a., StepStone/Indeed); AG-Faktor 1,21 = Brutto + ca. 21 % SV-Arbeitgeberanteil
A102: Vertrieb 3 | B102: Vertrieb | C102: 37 | D102: 4200 | E102: 1.21 | G102: Gehalt Annahme (Marktwerte: Disponent Median 3.710 €, gehalt.de; Senior Full-Stack 54.700–75.264 € p. a., StepStone/Indeed); AG-Faktor 1,21 = Brutto + ca. 21 % SV-Arbeitgeberanteil
A103: Kundenerfolg 3 | B103: Support | C103: 43 | D103: 3800 | E103: 1.21 | G103: Gehalt Annahme (Marktwerte: Disponent Median 3.710 €, gehalt.de; Senior Full-Stack 54.700–75.264 € p. a., StepStone/Indeed); AG-Faktor 1,21 = Brutto + ca. 21 % SV-Arbeitgeberanteil
A104: Vertrieb 4 | B104: Vertrieb | C104: 49 | D104: 4200 | E104: 1.21 | G104: Gehalt Annahme (Marktwerte: Disponent Median 3.710 €, gehalt.de; Senior Full-Stack 54.700–75.264 € p. a., StepStone/Indeed); AG-Faktor 1,21 = Brutto + ca. 21 % SV-Arbeitgeberanteil
A105: Support 2 (Vollzeit) | B105: Support | C105: 49 | D105: 3000 | E105: 1.21 | G105: Gehalt Annahme (Marktwerte: Disponent Median 3.710 €, gehalt.de; Senior Full-Stack 54.700–75.264 € p. a., StepStone/Indeed); AG-Faktor 1,21 = Brutto + ca. 21 % SV-Arbeitgeberanteil
A107: J Finanzierung | B107: Wert | C107: Einheit | G107: Quelle / Begründung
A108: Eigenkapital Gründer (Stammkapital GmbH) | B108: 25000 | C108: € | G108: Annahme; Einzahlung Monat 1
A109: Eigenkapital: Monat | B109: 1 | C109: Monat
A110: KfW ERP-Gründerkredit StartGeld | B110: 125000 | C110: € | G110: Höchstbetrag lt. Handwerksblatt auf 200.000 € erhöht – bei KfW/Hausbank prüfen; 80 % Haftungsfreistellung
A111: KfW-Kredit: Auszahlung im Monat | B111: 1 | C111: Monat
...

Sheet Monat 1–36
A1: LADEKLAR – Monatsplan Monat 1–36 | B1: Anfang
A2: Monat-Nr. | B2: 0 | C2: =B2+1 -> 1 | D2: =C2+1 -> 2 | E2: =D2+1 -> 3 | F2: =E2+1 -> 4 | G2: =F2+1 -> 5 | H2: =G2+1 -> 6 | I2: =H2+1 -> 7 | J2: =I2+1 -> 8 | ... AL2: =AK2+1 -> 36
A3: Monat | C3: =EDATE(Annahmen!$B$6,C$2-1) -> 46388 | D3: =EDATE(Annahmen!$B$6,D$2-1) -> 46419 | E3: =EDATE(Annahmen!$B$6,E$2-1) -> 46447 | F3: =EDATE(Annahmen!$B$6,F$2-1) -> 46478 | G3: =EDATE(Annahmen!$B$6,G$2-1) -> 46508 | H3: =EDATE(Annahmen!$B$6,H$2-1) -> 46539 | I3: =EDATE(Annahmen!$B$6,I$2-1) -> 46569 | J3: =EDATE(Annahmen!$B$6,J$2-1) -> 46600 | ... AL3: =EDATE(Annahmen!$B$6,AL$2-1) -> 47453
A4: Modelljahr | C4: =INT((C$2-1)/12)+1 -> 1 | D4: =INT((D$2-1)/12)+1 -> 1 | E4: =INT((E$2-1)/12)+1 -> 1 | F4: =INT((F$2-1)/12)+1 -> 1 | G4: =INT((G$2-1)/12)+1 -> 1 | H4: =INT((H$2-1)/12)+1 -> 1 | I4: =INT((I$2-1)/12)+1 -> 1 | J4: =INT((J$2-1)/12)+1 -> 1 | ... AL4: =INT((AL$2-1)/12)+1 -> 3
A5: Kunden
A6: Neukunden zahlend | C6: =IF(C$2<=36,INDEX(Annahmen!$B$36:$B$47,INT((C$2-1)/3)+1,1),IF(C$2<=48,Annahmen!$B$48,Annahmen!$B$49)) -> 3 | D6: =IF(D$2<=36,INDEX(Annahmen!$B$36:$B$47,INT((D$2-1)/3)+1,1),IF(D$2<=48,Annahmen!$B$48,Annahmen!$B$49)) -> 3 | E6: =IF(E$2<=36,INDEX(Annahmen!$B$36:$B$47,INT((E$2-1)/3)+1,1),IF(E$2<=48,Annahmen!$B$48,Annahmen!$B$49)) -> 3 | F6: =IF(F$2<=36,INDEX(Annahmen!$B$36:$B$47,INT((F$2-1)/3)+1,1),IF(F$2<=48,Annahmen!$B$48,Annahmen!$B$49)) -> 6 | G6: =IF(G$2<=36,INDEX(Annahmen!$B$36:$B$47,INT((G$2-1)/3)+1,1),IF(G$2<=48,Annahmen!$B$48,Annahmen!$B$49)) -> 6 | H6: =IF(H$2<=36,INDEX(Annahmen!$B$36:$B$47,INT((H$2-1)/3)+1,1),IF(H$2<=48,Annahmen!$B$48,Annahmen!$B$49)) -> 6 | I6: =IF(I$2<=36,INDEX(Annahmen!$B$36:$B$47,INT((I$2-1)/3)+1,1),IF(I$2<=48,Annahmen!$B$48,Annahmen!$B$49)) -> 9 | J6: =IF(J$2<=36,INDEX(Annahmen!$B$36:$B$47,INT((J$2-1)/3)+1,1),IF(J$2<=48,Annahmen!$B$48,Annahmen!$B$49)) -> 9 | ... AL6: =IF(AL$2<=36,INDEX(Annahmen!$B$36:$B$47,INT((AL$2-1)/3)+1,1),IF(AL$2<=48,Annahmen!$B$48,Annahmen!$B$49)) -> 40
A7: davon Start | C7: =C6*Annahmen!$B$19 -> 1.5 | D7: =D6*Annahmen!$B$19 -> 1.5 | E7: =E6*Annahmen!$B$19 -> 1.5 | F7: =F6*Annahmen!$B$19 -> 3 | G7: =G6*Annahmen!$B$19 -> 3 | H7: =H6*Annahmen!$B$19 -> 3 | I7: =I6*Annahmen!$B$19 -> 4.5 | J7: =J6*Annahmen!$B$19 -> 4.5 | ... AL7: =AL6*Annahmen!$B$19 -> 20
A8: davon Flotte | C8: =C6*Annahmen!$B$20 -> 1.14 | D8: =D6*Annahmen!$B$20 -> 1.14 | E8: =E6*Annahmen!$B$20 -> 1.14 | F8: =F6*Annahmen!$B$20 -> 2.28 | G8: =G6*Annahmen!$B$20 -> 2.28 | H8: =H6*Annahmen!$B$20 -> 2.28 | I8: =I6*Annahmen!$B$20 -> 3.42 | J8: =J6*Annahmen!$B$20 -> 3.42 | ... AL8: =AL6*Annahmen!$B$20 -> 15.2
A9: davon Premium | C9: =C6*Annahmen!$B$21 -> 0.36 | D9: =D6*Annahmen!$B$21 -> 0.36 | E9: =E6*Annahmen!$B$21 -> 0.36 | F9: =F6*Annahmen!$B$21 -> 0.72 | G9: =G6*Annahmen!$B$21 -> 0.72 | H9: =H6*Annahmen!$B$21 -> 0.72 | I9: =I6*Annahmen!$B$21 -> 1.08 | J9: =J6*Annahmen!$B$21 -> 1.08 | ... AL9: =AL6*Annahmen!$B$21 -> 4.8
A10: Kunden Start (Monatsende) | B10: =Annahmen!$B$7*Annahmen!$B$19 -> 2.5 | C10: =B10*(1-Annahmen!$B$31)+C7 -> 3.925 | D10: =C10*(1-Annahmen!$B$31)+D7 -> 5.30725 | E10: =D10*(1-Annahmen!$B$31)+E7 -> 6.6480325 | F10: =E10*(1-Annahmen!$B$31)+F7 -> 9.4485915 | G10: =F10*(1-Annahmen!$B$31)+G7 -> 12.165134 | H10: =G10*(1-Annahmen!$B$31)+H7 -> 14.80018 | I10: =H10*(1-Annahmen!$B$31)+I7 -> 18.856174 | J10: =I10*(1-Annahmen!$B$31)+J7 -> 22.790489 | ... AL10: =AK10*(1-Annahmen!$B$31)+AL7 -> 278.84198
A11: Kunden Flotte (Monatsende) | B11: =Annahmen!$B$7*Annahmen!$B$20 -> 1.9 | C11: =B11*(1-Annahmen!$B$32)+C8 -> 3.002 | D11: =C11*(1-Annahmen!$B$32)+D8 -> 4.08196 | E11: =D11*(1-Annahmen!$B$32)+E8 -> 5.1403208 | F11: =E11*(1-Annahmen!$B$32)+F8 -> 7.3175144 | G11: =F11*(1-Annahmen!$B$32)+G8 -> 9.4511641 | H11: =G11*(1-Annahmen!$B$32)+H8 -> 11.542141 | I11: =H11*(1-Annahmen!$B$32)+I8 -> 14.731298 | J11: =I11*(1-Annahmen!$B$32)+J8 -> 17.856672 | ... AL11: =AK11*(1-Annahmen!$B$32)+AL8 -> 235.13214
A12: Kunden Premium (Monatsende) | B12: =Annahmen!$B$7*Annahmen!$B$21 -> 0.6 | C12: =B12*(1-Annahmen!$B$33)+C9 -> 0.9528 | D12: =C12*(1-Annahmen!$B$33)+D9 -> 1.3013664 | E12: =D12*(1-Annahmen!$B$33)+E9 -> 1.64575 | F12: =E12*(1-Annahmen!$B$33)+F9 -> 2.346001 | G12: =F12*(1-Annahmen!$B$33)+G9 -> 3.037849 | H12: =G12*(1-Annahmen!$B$33)+H9 -> 3.7213948 | I12: =H12*(1-Annahmen!$B$33)+I9 -> 4.7567381 | J12: =I12*(1-Annahmen!$B$33)+J9 -> 5.7796572 | ... AL12: =AK12*(1-Annahmen!$B$33)+AL9 -> 81.043962
A13: Kunden gesamt | B13: =B10+B11+B12 -> 5 | C13: =C10+C11+C12 -> 7.8798 | D13: =D10+D11+D12 -> 10.690576 | E13: =E10+E11+E12 -> 13.434103 | F13: =F10+F11+F12 -> 19.112107 | G13: =G10+G11+G12 -> 24.654147 | H13: =H10+H11+H12 -> 30.063715 | I13: =I10+I11+I12 -> 38.34421 | ... AL13: =AL10+AL11+AL12 -> 595.01808
A14: Kündigungen im Monat | C14: =B10*Annahmen!$B$31+B11*Annahmen!$B$32+B12*Annahmen!$B$33 -> 0.1202 | D14: =C10*Annahmen!$B$31+C11*Annahmen!$B$32+C12*Annahmen!$B$33 -> 0.1892236 | E14: =D10*Annahmen!$B$31+D11*Annahmen!$B$32+D12*Annahmen!$B$33 -> 0.2564731 | F14: =E10*Annahmen!$B$31+E11*Annahmen!$B$32+E12*Annahmen!$B$33 -> 0.32199639 | G14: =F10*Annahmen!$B$31+F11*Annahmen!$B$32+F12*Annahmen!$B$33 -> 0.45796005 | H14: =G10*Annahmen!$B$31+G11*Annahmen!$B$32+G12*Annahmen!$B$33 -> 0.59043148 | I14: =H10*Annahmen!$B$31+H11*Annahmen!$B$32+H12*Annahmen!$B$33 -> 0.71950495 | J14: =I10*Annahmen!$B$31+I11*Annahmen!$B$32+I12*Annahmen!$B$33 -> 0.91739205 | ... AL14: =AK10*Annahmen!$B$31+AK11*Annahmen!$B$32+AK12*Annahmen!$B$33 -> 13.419873
A15: Neue Store-Apps | C15: =C9*Annahmen!$B$24 -> 0.072 | D15: =D9*Annahmen!$B$24 -> 0.072 | E15: =E9*Annahmen!$B$24 -> 0.072 | F15: =F9*Annahmen!$B$24 -> 0.144 | G15: =G9*Annahmen!$B$24 -> 0.144 | H15: =H9*Annahmen!$B$24 -> 0.144 | I15: =I9*Annahmen!$B$24 -> 0.216 | J15: =J9*Annahmen!$B$24 -> 0.216 | ... AL15: =AL9*Annahmen!$B$24 -> 0.96
A16: Store-Apps aktiv | B16: =Annahmen!$B$7*Annahmen!$B$21*Annahmen!$B$24 -> 0.12 | C16: =B16*(1-Annahmen!$B$33)+C15 -> 0.19056 | D16: =C16*(1-Annahmen!$B$33)+D15 -> 0.26027328 | E16: =D16*(1-Annahmen!$B$33)+E15 -> 0.32915 | F16: =E16*(1-Annahmen!$B$33)+F15 -> 0.4692002 | G16: =F16*(1-Annahmen!$B$33)+G15 -> 0.6075698 | H16: =G16*(1-Annahmen!$B$33)+H15 -> 0.74427896 | I16: =H16*(1-Annahmen!$B$33)+I15 -> 0.95134761 | J16: =I16*(1-Annahmen!$B$33)+J15 -> 1.1559314 | ... AL16: =AK16*(1-Annahmen!$B$33)+AL15 -> 16.208792
A17: Nötige Testzugänge (Info) | C17: =C6/Annahmen!$B$28 -> 8.5714286 | D17: =D6/Annahmen!$B$28 -> 8.5714286 | E17: =E6/Annahmen!$B$28 -> 8.5714286 | F17: =F6/Annahmen!$B$28 -> 17.142857 | G17: =G6/Annahmen!$B$28 -> 17.142857 | H17: =H6/Annahmen!$B$28 -> 17.142857 | I17: =I6/Annahmen!$B$28 -> 25.714286 | J17: =J6/Annahmen!$B$28 -> 25.714286 | ... AL17: =AL6/Annahmen!$B$28 -> 114.28571
A18: Umsatz
A19: MRR Start | C19: =C10*Annahmen!$B$10 -> 192.325 | D19: =D10*Annahmen!$B$10 -> 260.05525 | E19: =E10*Annahmen!$B$10 -> 325.75359 | F19: =F10*Annahmen!$B$10 -> 462.98098 | G19: =G10*Annahmen!$B$10 -> 596.09156 | H19: =H10*Annahmen!$B$10 -> 725.20881 | I19: =I10*Annahmen!$B$10 -> 923.95254 | J19: =J10*Annahmen!$B$10 -> 1116.734 | ... AL19: =AL10*Annahmen!$B$10 -> 13663.257
A20: MRR Flotte inkl. Zusatzfahrer | C20: =C11*(Annahmen!$B$11+Annahmen!$B$13*Annahmen!$B$22) -> 418.779 | D20: =D11*(Annahmen!$B$11+Annahmen!$B$13*Annahmen!$B$22) -> 569.43342 | E20: =E11*(Annahmen!$B$11+Annahmen!$B$13*Annahmen!$B$22) -> 717.07475 | F20: =F11*(Annahmen!$B$11+Annahmen!$B$13*Annahmen!$B$22) -> 1020.7933 | G20: =G11*(Annahmen!$B$11+Annahmen!$B$13*Annahmen!$B$22) -> 1318.4374 | H20: =H11*(Annahmen!$B$11+Annahmen!$B$13*Annahmen!$B$22) -> 1610.1286 | I20: =I11*(Annahmen!$B$11+Annahmen!$B$13*Annahmen!$B$22) -> 2055.0161 | J20: =J11*(Annahmen!$B$11+Annahmen!$B$13*Annahmen!$B$22) -> 2491.0057 | ... AL20: =AL11*(Annahmen!$B$11+Annahmen!$B$13*Annahmen!$B$22) -> 32800.933
A21: MRR Premium inkl. Zusatzfahrer | C21: =C12*(Annahmen!$B$12+Annahmen!$B$14*Annahmen!$B$23) -> 313.4712 | D21: =D12*(Annahmen!$B$12+Annahmen!$B$14*Annahmen!$B$23) -> 428.14955 | E21: =E12*(Annahmen!$B$12+Annahmen!$B$14*Annahmen!$B$23) -> 541.45175 | F21: =F12*(Annahmen!$B$12+Annahmen!$B$14*Annahmen!$B$23) -> 771.83433 | G21: =G12*(Annahmen!$B$12+Annahmen!$B$14*Annahmen!$B$23) -> 999.45232 | H21: =H12*(Annahmen!$B$12+Annahmen!$B$14*Annahmen!$B$23) -> 1224.3389 | I21: =I12*(Annahmen!$B$12+Annahmen!$B$14*Annahmen!$B$23) -> 1564.9668 | J21: =J12*(Annahmen!$B$12+Annahmen!$B$14*Annahmen!$B$23) -> 1901.5072 | ... AL21: =AL12*(Annahmen!$B$12+Annahmen!$B$14*Annahmen!$B$23) -> 26663.464
A22: MRR Store-App | C22: =C16*Annahmen!$B$16 -> 18.86544 | D22: =D16*Annahmen!$B$16 -> 25.767055 | E22: =E16*Annahmen!$B$16 -> 32.58585 | F22: =F16*Annahmen!$B$16 -> 46.45082 | G22: =G16*Annahmen!$B$16 -> 60.14941 | H22: =H16*Annahmen!$B$16 -> 73.683617 | I22: =I16*Annahmen!$B$16 -> 94.183414 | J22: =J16*Annahmen!$B$16 -> 114.43721 | ... AL22: =AL16*Annahmen!$B$16 -> 1604.6704
A23: MRR gesamt (Listenpreis) | C23: =SUM(C19:C22) -> 943.44064 | D23: =SUM(D19:D22) -> 1283.4053 | E23: =SUM(E19:E22) -> 1616.8659 | F23: =SUM(F19:F22) -> 2302.0594 | G23: =SUM(G19:G22) -> 2974.1307 | H23: =SUM(H19:H22) -> 3633.36 | I23: =SUM(I19:I22) -> 4638.1189 | J23: =SUM(J19:J22) -> 5623.6842 | ... AL23: =SUM(AL19:AL22) -> 74732.324
A24: Rabatt Jahreszahler | C24: =-C23*Annahmen!$B$27 -> -47.172032 | D24: =-D23*Annahmen!$B$27 -> -64.170264 | E24: =-E23*Annahmen!$B$27 -> -80.843297 | F24: =-F23*Annahmen!$B$27 -> -115.10297 | G24: =-G23*Annahmen!$B$27 -> -148.70653 | H24: =-H23*Annahmen!$B$27 -> -181.668 | I24: =-I23*Annahmen!$B$27 -> -231.90594 | J24: =-J23*Annahmen!$B$27 -> -281.18421 | ... AL24: =-AL23*Annahmen!$B$27 -> -3736.6162
A25: Einrichtung Store-App (einmalig) | C25: =C15*Annahmen!$B$15 -> 143.28 | D25: =D15*Annahmen!$B$15 -> 143.28 | E25: =E15*Annahmen!$B$15 -> 143.28 | F25: =F15*Annahmen!$B$15 -> 286.56 | G25: =G15*Annahmen!$B$15 -> 286.56 | H25: =H15*Annahmen!$B$15 -> 286.56 | I25: =I15*Annahmen!$B$15 -> 429.84 | J25: =J15*Annahmen!$B$15 -> 429.84 | ... AL25: =AL15*Annahmen!$B$15 -> 1910.4
A26: Umsatz gesamt | C26: =C23+C24+C25 -> 1039.5486 | D26: =D23+D24+D25 -> 1362.515 | E26: =E23+E24+E25 -> 1679.3026 | F26: =F23+F24+F25 -> 2473.5164 | G26: =G23+G24+G25 -> 3111.9841 | H26: =H23+H24+H25 -> 3738.252 | I26: =I23+I24+I25 -> 4836.0529 | J26: =J23+J24+J25 -> 5772.3399 | ... AL26: =AL23+AL24+AL25 -> 72906.108
A27: ARR (MRR × 12) | C27: =C23*12 -> 11321.288 | D27: =D23*12 -> 15400.863 | E27: =E23*12 -> 19402.391 | F27: =F23*12 -> 27624.713 | G27: =G23*12 -> 35689.568 | H27: =H23*12 -> 43600.32 | I27: =I23*12 -> 55657.426 | J27: =J23*12 -> 67484.21 | ... AL27: =AL23*12 -> 896787.89
A28: ARPA (MRR je Kunde) | C28: =IF(C13>0,C23/C13,0) -> 119.72901 | D28: =IF(D13>0,D23/D13,0) -> 120.05015 | E28: =IF(E13>0,E23/E13,0) -> 120.35533 | F28: =IF(F13>0,F23/F13,0) -> 120.45032 | G28: =IF(G13>0,G23/G13,0) -> 120.63409 | H28: =IF(H13>0,H23/H13,0) -> 120.85532 | I28: =IF(I13>0,I23/I13,0) -> 120.96008 | J28: =IF(J13>0,J23/J13,0) -> 121.13008 | ... AL28: =IF(AL13>0,AL23/AL13,0) -> 125.59673
A29: Variable Kosten
A30: Hosting/Speicher variabel | C30: =C10*Annahmen!$B$52+C11*Annahmen!$B$53+C12*Annahmen!$B$54 -> 13.908 | D30: =D10*Annahmen!$B$52+D11*Annahmen!$B$53+D12*Annahmen!$B$54 -> 18.916552 | E30: =E10*Annahmen!$B$52+E11*Annahmen!$B$53+E12*Annahmen!$B$54 -> 23.827818 | F30: =F10*Annahmen!$B$52+F11*Annahmen!$B$53+F12*Annahmen!$B$54 -> 33.923907 | G30: =G10*Annahmen!$B$52+G11*Annahmen!$B$53+G12*Annahmen!$B$54 -> 43.82368 | H30: =H10*Annahmen!$B$52+H11*Annahmen!$B$53+H12*Annahmen!$B$54 -> 53.531399 | I30: =I10*Annahmen!$B$52+I11*Annahmen!$B$53+I12*Annahmen!$B$54 -> 68.331226 | J30: =J10*Annahmen!$B$52+J11*Annahmen!$B$53+J12*Annahmen!$B$54 -> 82.844021 | ... AL30: =AL10*Annahmen!$B$52+AL11*Annahmen!$B$53+AL12*Annahmen!$B$54 -> 1098.5577
A31: Zahlungsgebühren | C31: =C26*Annahmen!$B$55+C13*Annahmen!$B$56 -> 11.074319 | D31: =D26*Annahmen!$B$55+D13*Annahmen!$B$56 -> 14.641822 | E31: =E26*Annahmen!$B$55+E13*Annahmen!$B$56 -> 18.136357 | F31: =F26*Annahmen!$B$55+F13*Annahmen!$B$56 -> 26.477369 | G31: =G26*Annahmen!$B$55+G13*Annahmen!$B$56 -> 33.524825 | H31: =H26*Annahmen!$B$55+H13*Annahmen!$B$56 -> 40.428316 | I31: =I26*Annahmen!$B$55+I13*Annahmen!$B$56 -> 52.108897 | J31: =J26*Annahmen!$B$55+J13*Annahmen!$B$56 -> 62.428106 | ... AL31: =AL26*Annahmen!$B$55+AL13*Annahmen!$B$56 -> 791.50519
A32: Partnerprovision | C32: =C26*INDEX(Annahmen!$B$58:$F$58,1,C$4)*Annahmen!$B$57 -> 0 | D32: =D26*INDEX(Annahmen!$B$58:$F$58,1,D$4)*Annahmen!$B$57 -> 0 | E32: =E26*INDEX(Annahmen!$B$58:$F$58,1,E$4)*Annahmen!$B$57 -> 0 | F32: =F26*INDEX(Annahmen!$B$58:$F$58,1,F$4)*Annahmen!$B$57 -> 0 | G32: =G26*INDEX(Annahmen!$B$58:$F$58,1,G$4)*Annahmen!$B$57 -> 0 | H32: =H26*INDEX(Annahmen!$B$58:$F$58,1,H$4)*Annahmen!$B$57 -> 0 | I32: =I26*INDEX(Annahmen!$B$58:$F$58,1,I$4)*Annahmen!$B$57 -> 0 | J32: =J26*INDEX(Annahmen!$B$58:$F$58,1,J$4)*Annahmen!$B$57 -> 0 | ... AL32: =AL26*INDEX(Annahmen!$B$58:$F$58,1,AL$4)*Annahmen!$B$57 -> 3645.3054
A33: Fremdkosten Store-App-Einrichtung | C33: =C15*Annahmen!$B$59 -> 10.8 | D33: =D15*Annahmen!$B$59 -> 10.8 | E33: =E15*Annahmen!$B$59 -> 10.8 | F33: =F15*Annahmen!$B$59 -> 21.6 | G33: =G15*Annahmen!$B$59 -> 21.6 | H33: =H15*Annahmen!$B$59 -> 21.6 | I33: =I15*Annahmen!$B$59 -> 32.4 | J33: =J15*Annahmen!$B$59 -> 32.4 | ... AL33: =AL15*Annahmen!$B$59 -> 144
A34: Variable Kosten gesamt | C34: =SUM(C30:C33) -> 35.782319 | D34: =SUM(D30:D33) -> 44.358374 | E34: =SUM(E30:E33) -> 52.764175 | F34: =SUM(F30:F33) -> 82.001276 | G34: =SUM(G30:G33) -> 98.948505 | H34: =SUM(H30:H33) -> 115.55972 | I34: =SUM(I30:I33) -> 152.84012 | J34: =SUM(J30:J33) -> 177.67213 | ... AL34: =SUM(AL30:AL33) -> 5679.3683
A35: Deckungsbeitrag | C35: =C26-C34 -> 1003.7663 | D35: =D26-D34 -> 1318.1566 | E35: =E26-E34 -> 1626.5385 | F35: =F26-F34 -> 2391.5151 | G35: =G26-G34 -> 3013.0356 | H35: =H26-H34 -> 3622.6922 | I35: =I26-I34 -> 4683.2128 | J35: =J26-J34 -> 5594.6678 | ... AL35: =AL26-AL34 -> 67226.74
A36: Personal
A37: Gründer/Geschäftsführer | C37: =INDEX(Annahmen!$B$90:$F$90,1,C$4)*Annahmen!$B$91 -> 2500 | D37: =INDEX(Annahmen!$B$90:$F$90,1,D$4)*Annahmen!$B$91 -> 2500 | E37: =INDEX(Annahmen!$B$90:$F$90,1,E$4)*Annahmen!$B$91 -> 2500 | F37: =INDEX(Annahmen!$B$90:$F$90,1,F$4)*Annahmen!$B$91 -> 2500 | G37: =INDEX(Annahmen!$B$90:$F$90,1,G$4)*Annahmen!$B$91 -> 2500 | H37: =INDEX(Annahmen!$B$90:$F$90,1,H$4)*Annahmen!$B$91 -> 2500 | I37: =INDEX(Annahmen!$B$90:$F$90,1,I$4)*Annahmen!$B$91 -> 2500 | J37: =INDEX(Annahmen!$B$90:$F$90,1,J$4)*Annahmen!$B$91 -> 2500 | ... AL37: =INDEX(Annahmen!$B$90:$F$90,1,AL$4)*Annahmen!$B$91 -> 5500
A38: Vertrieb & Kundenerfolg 1 (mehrsprachig, Ex-Disposition) | C38: =IF(C$2>=Annahmen!$C$94,Annahmen!$D$94*(1+Annahmen!$B$92)^(C$4-1)*Annahmen!$E$94,0) -> 0 | D38: =IF(D$2>=Annahmen!$C$94,Annahmen!$D$94*(1+Annahmen!$B$92)^(D$4-1)*Annahmen!$E$94,0) -> 0 | E38: =IF(E$2>=Annahmen!$C$94,Annahmen!$D$94*(1+Annahmen!$B$92)^(E$4-1)*Annahmen!$E$94,0) -> 0 | F38: =IF(F$2>=Annahmen!$C$94,Annahmen!$D$94*(1+Annahmen!$B$92)^(F$4-1)*Annahmen!$E$94,0) -> 0 | G38: =IF(G$2>=Annahmen!$C$94,Annahmen!$D$94*(1+Annahmen!$B$92)^(G$4-1)*Annahmen!$E$94,0) -> 0 | H38: =IF(H$2>=Annahmen!$C$94,Annahmen!$D$94*(1+Annahmen!$B$92)^(H$4-1)*Annahmen!$E$94,0) -> 0 | I38: =IF(I$2>=Annahmen!$C$94,Annahmen!$D$94*(1+Annahmen!$B$92)^(I$4-1)*Annahmen!$E$94,0) -> 4598 | J38: =IF(J$2>=Annahmen!$C$94,Annahmen!$D$94*(1+Annahmen!$B$92)^(J$4-1)*Annahmen!$E$94,0) -> 4598 | ... AL38: =IF(AL$2>=Annahmen!$C$94,Annahmen!$D$94*(1+Annahmen!$B$92)^(AL$4-1)*Annahmen!$E$94,0) -> 4878.0182
A39: Softwareentwicklung 1 (Full-Stack) | C39: =IF(C$2>=Annahmen!$C$95,Annahmen!$D$95*(1+Annahmen!$B$92)^(C$4-1)*Annahmen!$E$95,0) -> 0 | D39: =IF(D$2>=Annahmen!$C$95,Annahmen!$D$95*(1+Annahmen!$B$92)^(D$4-1)*Annahmen!$E$95,0) -> 0 | E39: =IF(E$2>=Annahmen!$C$95,Annahmen!$D$95*(1+Annahmen!$B$92)^(E$4-1)*Annahmen!$E$95,0) -> 0 | F39: =IF(F$2>=Annahmen!$C$95,Annahmen!$D$95*(1+Annahmen!$B$92)^(F$4-1)*Annahmen!$E$95,0) -> 0 | G39: =IF(G$2>=Annahmen!$C$95,Annahmen!$D$95*(1+Annahmen!$B$92)^(G$4-1)*Annahmen!$E$95,0) -> 0 | H39: =IF(H$2>=Annahmen!$C$95,Annahmen!$D$95*(1+Annahmen!$B$92)^(H$4-1)*Annahmen!$E$95,0) -> 0 | I39: =IF(I$2>=Annahmen!$C$95,Annahmen!$D$95*(1+Annahmen!$B$92)^(I$4-1)*Annahmen!$E$95,0) -> 0 | J39: =IF(J$2>=Annahmen!$C$95,Annahmen!$D$95*(1+Annahmen!$B$92)^(J$4-1)*Annahmen!$E$95,0) -> 0 | ... AL39: =IF(AL$2>=Annahmen!$C$95,Annahmen!$D$95*(1+Annahmen!$B$92)^(AL$4-1)*Annahmen!$E$95,0) -> 6675.1828
A40: Vertrieb 2 / Partnermanagement | C40: =IF(C$2>=Annahmen!$C$96,Annahmen!$D$96*(1+Annahmen!$B$92)^(C$4-1)*Annahmen!$E$96,0) -> 0 | D40: =IF(D$2>=Annahmen!$C$96,Annahmen!$D$96*(1+Annahmen!$B$92)^(D$4-1)*Annahmen!$E$96,0) -> 0 | E40: =IF(E$2>=Annahmen!$C$96,Annahmen!$D$96*(1+Annahmen!$B$92)^(E$4-1)*Annahmen!$E$96,0) -> 0 | F40: =IF(F$2>=Annahmen!$C$96,Annahmen!$D$96*(1+Annahmen!$B$92)^(F$4-1)*Annahmen!$E$96,0) -> 0 | G40: =IF(G$2>=Annahmen!$C$96,Annahmen!$D$96*(1+Annahmen!$B$92)^(G$4-1)*Annahmen!$E$96,0) -> 0 | H40: =IF(H$2>=Annahmen!$C$96,Annahmen!$D$96*(1+Annahmen!$B$92)^(H$4-1)*Annahmen!$E$96,0) -> 0 | I40: =IF(I$2>=Annahmen!$C$96,Annahmen!$D$96*(1+Annahmen!$B$92)^(I$4-1)*Annahmen!$E$96,0) -> 0 | J40: =IF(J$2>=Annahmen!$C$96,Annahmen!$D$96*(1+Annahmen!$B$92)^(J$4-1)*Annahmen!$E$96,0) -> 0 | ... AL40: =IF(AL$2>=Annahmen!$C$96,Annahmen!$D$96*(1+Annahmen!$B$92)^(AL$4-1)*Annahmen!$E$96,0) -> 5391.4938
A41: Support Teilzeit (PL/RO/TR) | C41: =IF(C$2>=Annahmen!$C$97,Annahmen!$D$97*(1+Annahmen!$B$92)^(C$4-1)*Annahmen!$E$97,0) -> 0 | D41: =IF(D$2>=Annahmen!$C$97,Annahmen!$D$97*(1+Annahmen!$B$92)^(D$4-1)*Annahmen!$E$97,0) -> 0 | E41: =IF(E$2>=Annahmen!$C$97,Annahmen!$D$97*(1+Annahmen!$B$92)^(E$4-1)*Annahmen!$E$97,0) -> 0 | F41: =IF(F$2>=Annahmen!$C$97,Annahmen!$D$97*(1+Annahmen!$B$92)^(F$4-1)*Annahmen!$E$97,0) -> 0 | G41: =IF(G$2>=Annahmen!$C$97,Annahmen!$D$97*(1+Annahmen!$B$92)^(G$4-1)*Annahmen!$E$97,0) -> 0 | H41: =IF(H$2>=Annahmen!$C$97,Annahmen!$D$97*(1+Annahmen!$B$92)^(H$4-1)*Annahmen!$E$97,0) -> 0 | I41: =IF(I$2>=Annahmen!$C$97,Annahmen!$D$97*(1+Annahmen!$B$92)^(I$4-1)*Annahmen!$E$97,0) -> 0 | J41: =IF(J$2>=Annahmen!$C$97,Annahmen!$D$97*(1+Annahmen!$B$92)^(J$4-1)*Annahmen!$E$97,0) -> 0 | ... AL41: =IF(AL$2>=Annahmen!$C$97,Annahmen!$D$97*(1+Annahmen!$B$92)^(AL$4-1)*Annahmen!$E$97,0) -> 2053.9024
A42: Softwareentwicklung 2 | C42: =IF(C$2>=Annahmen!$C$98,Annahmen!$D$98*(1+Annahmen!$B$92)^(C$4-1)*Annahmen!$E$98,0) -> 0 | D42: =IF(D$2>=Annahmen!$C$98,Annahmen!$D$98*(1+Annahmen!$B$92)^(D$4-1)*Annahmen!$E$98,0) -> 0 | E42: =IF(E$2>=Annahmen!$C$98,Annahmen!$D$98*(1+Annahmen!$B$92)^(E$4-1)*Annahmen!$E$98,0) -> 0 | F42: =IF(F$2>=Annahmen!$C$98,Annahmen!$D$98*(1+Annahmen!$B$92)^(F$4-1)*Annahmen!$E$98,0) -> 0 | G42: =IF(G$2>=Annahmen!$C$98,Annahmen!$D$98*(1+Annahmen!$B$92)^(G$4-1)*Annahmen!$E$98,0) -> 0 | H42: =IF(H$2>=Annahmen!$C$98,Annahmen!$D$98*(1+Annahmen!$B$92)^(H$4-1)*Annahmen!$E$98,0) -> 0 | I42: =IF(I$2>=Annahmen!$C$98,Annahmen!$D$98*(1+Annahmen!$B$92)^(I$4-1)*Annahmen!$E$98,0) -> 0 | J42: =IF(J$2>=Annahmen!$C$98,Annahmen!$D$98*(1+Annahmen!$B$92)^(J$4-1)*Annahmen!$E$98,0) -> 0 | ... AL42: =IF(AL$2>=Annahmen!$C$98,Annahmen!$D$98*(1+Annahmen!$B$92)^(AL$4-1)*Annahmen!$E$98,0) -> 6675.1828
A43: Kundenerfolg 2 | C43: =IF(C$2>=Annahmen!$C$99,Annahmen!$D$99*(1+Annahmen!$B$92)^(C$4-1)*Annahmen!$E$99,0) -> 0 | D43: =IF(D$2>=Annahmen!$C$99,Annahmen!$D$99*(1+Annahmen!$B$92)^(D$4-1)*Annahmen!$E$99,0) -> 0 | E43: =IF(E$2>=Annahmen!$C$99,Annahmen!$D$99*(1+Annahmen!$B$92)^(E$4-1)*Annahmen!$E$99,0) -> 0 | F43: =IF(F$2>=Annahmen!$C$99,Annahmen!$D$99*(1+Annahmen!$B$92)^(F$4-1)*Annahmen!$E$99,0) -> 0 | G43: =IF(G$2>=Annahmen!$C$99,Annahmen!$D$99*(1+Annahmen!$B$92)^(G$4-1)*Annahmen!$E$99,0) -> 0 | H43: =IF(H$2>=Annahmen!$C$99,Annahmen!$D$99*(1+Annahmen!$B$92)^(H$4-1)*Annahmen!$E$99,0) -> 0 | I43: =IF(I$2>=Annahmen!$C$99,Annahmen!$D$99*(1+Annahmen!$B$92)^(I$4-1)*Annahmen!$E$99,0) -> 0 | J43: =IF(J$2>=Annahmen!$C$99,Annahmen!$D$99*(1+Annahmen!$B$92)^(J$4-1)*Annahmen!$E$99,0) -> 0 | ... AL43: =IF(AL$2>=Annahmen!$C$99,Annahmen!$D$99*(1+Annahmen!$B$92)^(AL$4-1)*Annahmen!$E$99,0) -> 4878.0182
A44: Marketing | C44: =IF(C$2>=Annahmen!$C$100,Annahmen!$D$100*(1+Annahmen!$B$92)^(C$4-1)*Annahmen!$E$100,0) -> 0 | D44: =IF(D$2>=Annahmen!$C$100,Annahmen!$D$100*(1+Annahmen!$B$92)^(D$4-1)*Annahmen!$E$100,0) -> 0 | E44: =IF(E$2>=Annahmen!$C$100,Annahmen!$D$100*(1+Annahmen!$B$92)^(E$4-1)*Annahmen!$E$100,0) -> 0 | F44: =IF(F$2>=Annahmen!$C$100,Annahmen!$D$100*(1+Annahmen!$B$92)^(F$4-1)*Annahmen!$E$100,0) -> 0 | G44: =IF(G$2>=Annahmen!$C$100,Annahmen!$D$100*(1+Annahmen!$B$92)^(G$4-1)*Annahmen!$E$100,0) -> 0 | H44: =IF(H$2>=Annahmen!$C$100,Annahmen!$D$100*(1+Annahmen!$B$92)^(H$4-1)*Annahmen!$E$100,0) -> 0 | I44: =IF(I$2>=Annahmen!$C$100,Annahmen!$D$100*(1+Annahmen!$B$92)^(I$4-1)*Annahmen!$E$100,0) -> 0 | J44: =IF(J$2>=Annahmen!$C$100,Annahmen!$D$100*(1+Annahmen!$B$92)^(J$4-1)*Annahmen!$E$100,0) -> 0 | ... AL44: =IF(AL$2>=Annahmen!$C$100,Annahmen!$D$100*(1+Annahmen!$B$92)^(AL$4-1)*Annahmen!$E$100,0) -> 5134.756
A45: Softwareentwicklung 3 | C45: =IF(C$2>=Annahmen!$C$101,Annahmen!$D$101*(1+Annahmen!$B$92)^(C$4-1)*Annahmen!$E$101,0) -> 0 | D45: =IF(D$2>=Annahmen!$C$101,Annahmen!$D$101*(1+Annahmen!$B$92)^(D$4-1)*Annahmen!$E$101,0) -> 0 | E45: =IF(E$2>=Annahmen!$C$101,Annahmen!$D$101*(1+Annahmen!$B$92)^(E$4-1)*Annahmen!$E$101,0) -> 0 | F45: =IF(F$2>=Annahmen!$C$101,Annahmen!$D$101*(1+Annahmen!$B$92)^(F$4-1)*Annahmen!$E$101,0) -> 0 | G45: =IF(G$2>=Annahmen!$C$101,Annahmen!$D$101*(1+Annahmen!$B$92)^(G$4-1)*Annahmen!$E$101,0) -> 0 | H45: =IF(H$2>=Annahmen!$C$101,Annahmen!$D$101*(1+Annahmen!$B$92)^(H$4-1)*Annahmen!$E$101,0) -> 0 | I45: =IF(I$2>=Annahmen!$C$101,Annahmen!$D$101*(1+Annahmen!$B$92)^(I$4-1)*Annahmen!$E$101,0) -> 0 | J45: =IF(J$2>=Annahmen!$C$101,Annahmen!$D$101*(1+Annahmen!$B$92)^(J$4-1)*Annahmen!$E$101,0) -> 0 | ... AL45: =IF(AL$2>=Annahmen!$C$101,Annahmen!$D$101*(1+Annahmen!$B$92)^(AL$4-1)*Annahmen!$E$101,0) -> 0
A46: Vertrieb 3 | C46: =IF(C$2>=Annahmen!$C$102,Annahmen!$D$102*(1+Annahmen!$B$92)^(C$4-1)*Annahmen!$E$102,0) -> 0 | D46: =IF(D$2>=Annahmen!$C$102,Annahmen!$D$102*(1+Annahmen!$B$92)^(D$4-1)*Annahmen!$E$102,0) -> 0 | E46: =IF(E$2>=Annahmen!$C$102,Annahmen!$D$102*(1+Annahmen!$B$92)^(E$4-1)*Annahmen!$E$102,0) -> 0 | F46: =IF(F$2>=Annahmen!$C$102,Annahmen!$D$102*(1+Annahmen!$B$92)^(F$4-1)*Annahmen!$E$102,0) -> 0 | G46: =IF(G$2>=Annahmen!$C$102,Annahmen!$D$102*(1+Annahmen!$B$92)^(G$4-1)*Annahmen!$E$102,0) -> 0 | H46: =IF(H$2>=Annahmen!$C$102,Annahmen!$D$102*(1+Annahmen!$B$92)^(H$4-1)*Annahmen!$E$102,0) -> 0 | I46: =IF(I$2>=Annahmen!$C$102,Annahmen!$D$102*(1+Annahmen!$B$92)^(I$4-1)*Annahmen!$E$102,0) -> 0 | J46: =IF(J$2>=Annahmen!$C$102,Annahmen!$D$102*(1+Annahmen!$B$92)^(J$4-1)*Annahmen!$E$102,0) -> 0 | ... AL46: =IF(AL$2>=Annahmen!$C$102,Annahmen!$D$102*(1+Annahmen!$B$92)^(AL$4-1)*Annahmen!$E$102,0) -> 0
A47: Kundenerfolg 3 | C47: =IF(C$2>=Annahmen!$C$103,Annahmen!$D$103*(1+Annahmen!$B$92)^(C$4-1)*Annahmen!$E$103,0) -> 0 | D47: =IF(D$2>=Annahmen!$C$103,Annahmen!$D$103*(1+Annahmen!$B$92)^(D$4-1)*Annahmen!$E$103,0) -> 0 | E47: =IF(E$2>=Annahmen!$C$103,Annahmen!$D$103*(1+Annahmen!$B$92)^(E$4-1)*Annahmen!$E$103,0) -> 0 | F47: =IF(F$2>=Annahmen!$C$103,Annahmen!$D$103*(1+Annahmen!$B$92)^(F$4-1)*Annahmen!$E$103,0) -> 0 | G47: =IF(G$2>=Annahmen!$C$103,Annahmen!$D$103*(1+Annahmen!$B$92)^(G$4-1)*Annahmen!$E$103,0) -> 0 | H47: =IF(H$2>=Annahmen!$C$103,Annahmen!$D$103*(1+Annahmen!$B$92)^(H$4-1)*Annahmen!$E$103,0) -> 0 | I47: =IF(I$2>=Annahmen!$C$103,Annahmen!$D$103*(1+Annahmen!$B$92)^(I$4-1)*Annahmen!$E$103,0) -> 0 | J47: =IF(J$2>=Annahmen!$C$103,Annahmen!$D$103*(1+Annahmen!$B$92)^(J$4-1)*Annahmen!$E$103,0) -> 0 | ... AL47: =IF(AL$2>=Annahmen!$C$103,Annahmen!$D$103*(1+Annahmen!$B$92)^(AL$4-1)*Annahmen!$E$103,0) -> 0
A48: Vertrieb 4 | C48: =IF(C$2>=Annahmen!$C$104,Annahmen!$D$104*(1+Annahmen!$B$92)^(C$4-1)*Annahmen!$E$104,0) -> 0 | D48: =IF(D$2>=Annahmen!$C$104,Annahmen!$D$104*(1+Annahmen!$B$92)^(D$4-1)*Annahmen!$E$104,0) -> 0 | E48: =IF(E$2>=Annahmen!$C$104,Annahmen!$D$104*(1+Annahmen!$B$92)^(E$4-1)*Annahmen!$E$104,0) -> 0 | F48: =IF(F$2>=Annahmen!$C$104,Annahmen!$D$104*(1+Annahmen!$B$92)^(F$4-1)*Annahmen!$E$104,0) -> 0 | G48: =IF(G$2>=Annahmen!$C$104,Annahmen!$D$104*(1+Annahmen!$B$92)^(G$4-1)*Annahmen!$E$104,0) -> 0 | H48: =IF(H$2>=Annahmen!$C$104,Annahmen!$D$104*(1+Annahmen!$B$92)^(H$4-1)*Annahmen!$E$104,0) -> 0 | I48: =IF(I$2>=Annahmen!$C$104,Annahmen!$D$104*(1+Annahmen!$B$92)^(I$4-1)*Annahmen!$E$104,0) -> 0 | J48: =IF(J$2>=Annahmen!$C$104,Annahmen!$D$104*(1+Annahmen!$B$92)^(J$4-1)*Annahmen!$E$104,0) -> 0 | ... AL48: =IF(AL$2>=Annahmen!$C$104,Annahmen!$D$104*(1+Annahmen!$B$92)^(AL$4-1)*Annahmen!$E$104,0) -> 0
A49: Support 2 (Vollzeit) | C49: =IF(C$2>=Annahmen!$C$105,Annahmen!$D$105*(1+Annahmen!$B$92)^(C$4-1)*Annahmen!$E$105,0) -> 0 | D49: =IF(D$2>=Annahmen!$C$105,Annahmen!$D$105*(1+Annahmen!$B$92)^(D$4-1)*Annahmen!$E$105,0) -> 0 | E49: =IF(E$2>=Annahmen!$C$105,Annahmen!$D$105*(1+Annahmen!$B$92)^(E$4-1)*Annahmen!$E$105,0) -> 0 | F49: =IF(F$2>=Annahmen!$C$105,Annahmen!$D$105*(1+Annahmen!$B$92)^(F$4-1)*Annahmen!$E$105,0) -> 0 | G49: =IF(G$2>=Annahmen!$C$105,Annahmen!$D$105*(1+Annahmen!$B$92)^(G$4-1)*Annahmen!$E$105,0) -> 0 | H49: =IF(H$2>=Annahmen!$C$105,Annahmen!$D$105*(1+Annahmen!$B$92)^(H$4-1)*Annahmen!$E$105,0) -> 0 | I49: =IF(I$2>=Annahmen!$C$105,Annahmen!$D$105*(1+Annahmen!$B$92)^(I$4-1)*Annahmen!$E$105,0) -> 0 | J49: =IF(J$2>=Annahmen!$C$105,Annahmen!$D$105*(1+Annahmen!$B$92)^(J$4-1)*Annahmen!$E$105,0) -> 0 | ... AL49: =IF(AL$2>=Annahmen!$C$105,Annahmen!$D$105*(1+Annahmen!$B$92)^(AL$4-1)*Annahmen!$E$105,0) -> 0
A50: Personal gesamt | C50: =SUM(C37:C49) -> 2500 | D50: =SUM(D37:D49) -> 2500 | E50: =SUM(E37:E49) -> 2500 | F50: =SUM(F37:F49) -> 2500 | G50: =SUM(G37:G49) -> 2500 | H50: =SUM(H37:H49) -> 2500 | I50: =SUM(I37:I49) -> 7098 | J50: =SUM(J37:J49) -> 7098 | ... AL50: =SUM(AL37:AL49) -> 41186.554
A51: davon Vertrieb & Marketing | C51: =SUMIF(Annahmen!$B$94:$B$105,"Vertrieb",C38:C49)+SUMIF(Annahmen!$B$94:$B$105,"Marketing",C38:C49) -> 0 | D51: =SUMIF(Annahmen!$B$94:$B$105,"Vertrieb",D38:D49)+SUMIF(Annahmen!$B$94:$B$105,"Marketing",D38:D49) -> 0 | E51: =SUMIF(Annahmen!$B$94:$B$105,"Vertrieb",E38:E49)+SUMIF(Annahmen!$B$94:$B$105,"Marketing",E38:E49) -> 0 | F51: =SUMIF(Annahmen!$B$94:$B$105,"Vertrieb",F38:F49)+SUMIF(Annahmen!$B$94:$B$105,"Marketing",F38:F49) -> 0 | G51: =SUMIF(Annahmen!$B$94:$B$105,"Vertrieb",G38:G49)+SUMIF(Annahmen!$B$94:$B$105,"Marketing",G38:G49) -> 0 | H51: =SUMIF(Annahmen!$B$94:$B$105,"Vertrieb",H38:H49)+SUMIF(Annahmen!$B$94:$B$105,"Marketing",H38:H49) -> 0 | I51: =SUMIF(Annahmen!$B$94:$B$105,"Vertrieb",I38:I49)+SUMIF(Annahmen!$B$94:$B$105,"Marketing",I38:I49) -> 4598 | J51: =SUMIF(Annahmen!$B$94:$B$105,"Vertrieb",J38:J49)+SUMIF(Annahmen!$B$94:$B$105,"Marketing",J38:J49) -> 4598 | ... AL51: =SUMIF(Annahmen!$B$94:$B$105,"Vertrieb",AL38:AL49)+SUMIF(Annahmen!$B$94:$B$105,"Marketing",AL38:AL49) -> 15404.268
A52: Köpfe (inkl. Gründer) | B52: 0 | C52: =1+COUNTIF(Annahmen!$C$94:$C$105,"<="&C$2) -> 1 | D52: =1+COUNTIF(Annahmen!$C$94:$C$105,"<="&D$2) -> 1 | E52: =1+COUNTIF(Annahmen!$C$94:$C$105,"<="&E$2) -> 1 | F52: =1+COUNTIF(Annahmen!$C$94:$C$105,"<="&F$2) -> 1 | G52: =1+COUNTIF(Annahmen!$C$94:$C$105,"<="&G$2) -> 1 | H52: =1+COUNTIF(Annahmen!$C$94:$C$105,"<="&H$2) -> 1 | I52: =1+COUNTIF(Annahmen!$C$94:$C$105,"<="&I$2) -> 2 | J52: =1+COUNTIF(Annahmen!$C$94:$C$105,"<="&J$2) -> 2 | ... AL52: =1+COUNTIF(Annahmen!$C$94:$C$105,"<="&AL$2) -> 8
A53: Fixkosten
A54: Marketing laufend | C54: =INDEX(Annahmen!$B$63:$F$63,1,C$4) -> 2500 | D54: =INDEX(Annahmen!$B$63:$F$63,1,D$4) -> 2500 | E54: =INDEX(Annahmen!$B$63:$F$63,1,E$4) -> 2500 | F54: =INDEX(Annahmen!$B$63:$F$63,1,F$4) -> 2500 | G54: =INDEX(Annahmen!$B$63:$F$63,1,G$4) -> 2500 | H54: =INDEX(Annahmen!$B$63:$F$63,1,H$4) -> 2500 | I54: =INDEX(Annahmen!$B$63:$F$63,1,I$4) -> 2500 | J54: =INDEX(Annahmen!$B$63:$F$63,1,J$4) -> 2500 | ... AL54: =INDEX(Annahmen!$B$63:$F$63,1,AL$4) -> 6000
A55: Messen & Veranstaltungen | C55: =SUMIF(Annahmen!$B$76:$B$87,C$2,Annahmen!$C$76:$C$87) -> 0 | D55: =SUMIF(Annahmen!$B$76:$B$87,D$2,Annahmen!$C$76:$C$87) -> 0 | E55: =SUMIF(Annahmen!$B$76:$B$87,E$2,Annahmen!$C$76:$C$87) -> 800 | F55: =SUMIF(Annahmen!$B$76:$B$87,F$2,Annahmen!$C$76:$C$87) -> 9000 | G55: =SUMIF(Annahmen!$B$76:$B$87,G$2,Annahmen!$C$76:$C$87) -> 0 | H55: =SUMIF(Annahmen!$B$76:$B$87,H$2,Annahmen!$C$76:$C$87) -> 0 | I55: =SUMIF(Annahmen!$B$76:$B$87,I$2,Annahmen!$C$76:$C$87) -> 0 | J55: =SUMIF(Annahmen!$B$76:$B$87,J$2,Annahmen!$C$76:$C$87) -> 0 | ... AL55: =SUMIF(Annahmen!$B$76:$B$87,AL$2,Annahmen!$C$76:$C$87) -> 0
A56: Hosting-Grundkosten | C56: =INDEX(Annahmen!$B$62:$F$62,1,C$4) -> 300 | D56: =INDEX(Annahmen!$B$62:$F$62,1,D$4) -> 300 | E56: =INDEX(Annahmen!$B$62:$F$62,1,E$4) -> 300 | F56: =INDEX(Annahmen!$B$62:$F$62,1,F$4) -> 300 | G56: =INDEX(Annahmen!$B$62:$F$62,1,G$4) -> 300 | H56: =INDEX(Annahmen!$B$62:$F$62,1,H$4) -> 300 | I56: =INDEX(Annahmen!$B$62:$F$62,1,I$4) -> 300 | J56: =INDEX(Annahmen!$B$62:$F$62,1,J$4) -> 300 | ... AL56: =INDEX(Annahmen!$B$62:$F$62,1,AL$4) -> 600
A57: Miete / Coworking | C57: =INDEX(Annahmen!$B$64:$F$64,1,C$4) -> 250 | D57: =INDEX(Annahmen!$B$64:$F$64,1,D$4) -> 250 | E57: =INDEX(Annahmen!$B$64:$F$64,1,E$4) -> 250 | F57: =INDEX(Annahmen!$B$64:$F$64,1,F$4) -> 250 | G57: =INDEX(Annahmen!$B$64:$F$64,1,G$4) -> 250 | H57: =INDEX(Annahmen!$B$64:$F$64,1,H$4) -> 250 | I57: =INDEX(Annahmen!$B$64:$F$64,1,I$4) -> 250 | J57: =INDEX(Annahmen!$B$64:$F$64,1,J$4) -> 250 | ... AL57: =INDEX(Annahmen!$B$64:$F$64,1,AL$4) -> 1500
A58: Versicherungen | C58: =INDEX(Annahmen!$B$65:$F$65,1,C$4) -> 120 | D58: =INDEX(Annahmen!$B$65:$F$65,1,D$4) -> 120 | E58: =INDEX(Annahmen!$B$65:$F$65,1,E$4) -> 120 | F58: =INDEX(Annahmen!$B$65:$F$65,1,F$4) -> 120 | G58: =INDEX(Annahmen!$B$65:$F$65,1,G$4) -> 120 | H58: =INDEX(Annahmen!$B$65:$F$65,1,H$4) -> 120 | I58: =INDEX(Annahmen!$B$65:$F$65,1,I$4) -> 120 | J58: =INDEX(Annahmen!$B$65:$F$65,1,J$4) -> 120 | ... AL58: =INDEX(Annahmen!$B$65:$F$65,1,AL$4) -> 220
A59: Steuerberatung/Buchhaltung | C59: =INDEX(Annahmen!$B$66:$F$66,1,C$4) -> 350 | D59: =INDEX(Annahmen!$B$66:$F$66,1,D$4) -> 350 | E59: =INDEX(Annahmen!$B$66:$F$66,1,E$4) -> 350 | F59: =INDEX(Annahmen!$B$66:$F$66,1,F$4) -> 350 | G59: =INDEX(Annahmen!$B$66:$F$66,1,G$4) -> 350 | H59: =INDEX(Annahmen!$B$66:$F$66,1,H$4) -> 350 | I59: =INDEX(Annahmen!$B$66:$F$66,1,I$4) -> 350 | J59: =INDEX(Annahmen!$B$66:$F$66,1,J$4) -> 350 | ... AL59: =INDEX(Annahmen!$B$66:$F$66,1,AL$4) -> 800
A60: Recht & Datenschutz | C60: =INDEX(Annahmen!$B$67:$F$67,1,C$4) -> 300 | D60: =INDEX(Annahmen!$B$67:$F$67,1,D$4) -> 300 | E60: =INDEX(Annahmen!$B$67:$F$67,1,E$4) -> 300 | F60: =INDEX(Annahmen!$B$67:$F$67,1,F$4) -> 300 | G60: =INDEX(Annahmen!$B$67:$F$67,1,G$4) -> 300 | H60: =INDEX(Annahmen!$B$67:$F$67,1,H$4) -> 300 | I60: =INDEX(Annahmen!$B$67:$F$67,1,I$4) -> 300 | J60: =INDEX(Annahmen!$B$67:$F$67,1,J$4) -> 300 | ... AL60: =INDEX(Annahmen!$B$67:$F$67,1,AL$4) -> 450
A61: Reisekosten/Fahrzeug | C61: =INDEX(Annahmen!$B$68:$F$68,1,C$4) -> 500 | D61: =INDEX(Annahmen!$B$68:$F$68,1,D$4) -> 500 | E61: =INDEX(Annahmen!$B$68:$F$68,1,E$4) -> 500 | F61: =INDEX(Annahmen!$B$68:$F$68,1,F$4) -> 500 | G61: =INDEX(Annahmen!$B$68:$F$68,1,G$4) -> 500 | H61: =INDEX(Annahmen!$B$68:$F$68,1,H$4) -> 500 | I61: =INDEX(Annahmen!$B$68:$F$68,1,I$4) -> 500 | J61: =INDEX(Annahmen!$B$68:$F$68,1,J$4) -> 500 | ... AL61: =INDEX(Annahmen!$B$68:$F$68,1,AL$4) -> 1200
A62: Sonstiges | C62: =INDEX(Annahmen!$B$69:$F$69,1,C$4) -> 150 | D62: =INDEX(Annahmen!$B$69:$F$69,1,D$4) -> 150 | E62: =INDEX(Annahmen!$B$69:$F$69,1,E$4) -> 150 | F62: =INDEX(Annahmen!$B$69:$F$69,1,F$4) -> 150 | G62: =INDEX(Annahmen!$B$69:$F$69,1,G$4) -> 150 | H62: =INDEX(Annahmen!$B$69:$F$69,1,H$4) -> 150 | I62: =INDEX(Annahmen!$B$69:$F$69,1,I$4) -> 150 | J62: =INDEX(Annahmen!$B$69:$F$69,1,J$4) -> 150 | ... AL62: =INDEX(Annahmen!$B$69:$F$69,1,AL$4) -> 300
A63: Software-Werkzeuge | C63: =Annahmen!$B$70+Annahmen!$B$71*C52 -> 190 | D63: =Annahmen!$B$70+Annahmen!$B$71*D52 -> 190 | E63: =Annahmen!$B$70+Annahmen!$B$71*E52 -> 190 | F63: =Annahmen!$B$70+Annahmen!$B$71*F52 -> 190 | G63: =Annahmen!$B$70+Annahmen!$B$71*G52 -> 190 | H63: =Annahmen!$B$70+Annahmen!$B$71*H52 -> 190 | I63: =Annahmen!$B$70+Annahmen!$B$71*I52 -> 230 | J63: =Annahmen!$B$70+Annahmen!$B$71*J52 -> 230 | ... AL63: =Annahmen!$B$70+Annahmen!$B$71*AL52 -> 470
A64: Ausstattung Neueinstellungen | C64: =MAX(0,C52-B52)*Annahmen!$B$72 -> 1800 | D64: =MAX(0,D52-C52)*Annahmen!$B$72 -> 0 | E64: =MAX(0,E52-D52)*Annahmen!$B$72 -> 0 | F64: =MAX(0,F52-E52)*Annahmen!$B$72 -> 0 | G64: =MAX(0,G52-F52)*Annahmen!$B$72 -> 0 | H64: =MAX(0,H52-G52)*Annahmen!$B$72 -> 0 | I64: =MAX(0,I52-H52)*Annahmen!$B$72 -> 1800 | J64: =MAX(0,J52-I52)*Annahmen!$B$72 -> 0 | ... AL64: =MAX(0,AL52-AK52)*Annahmen!$B$72 -> 0
A65: Einmalkosten Gründung | C65: =IF(C$2=1,Annahmen!$B$73,0) -> 8000 | D65: =IF(D$2=1,Annahmen!$B$73,0) -> 0 | E65: =IF(E$2=1,Annahmen!$B$73,0) -> 0 | F65: =IF(F$2=1,Annahmen!$B$73,0) -> 0 | G65: =IF(G$2=1,Annahmen!$B$73,0) -> 0 | H65: =IF(H$2=1,Annahmen!$B$73,0) -> 0 | I65: =IF(I$2=1,Annahmen!$B$73,0) -> 0 | J65: =IF(J$2=1,Annahmen!$B$73,0) -> 0 | ... AL65: =IF(AL$2=1,Annahmen!$B$73,0) -> 0
A66: Fixkosten ohne Personal | C66: =SUM(C54:C65) -> 14460 | D66: =SUM(D54:D65) -> 4660 | E66: =SUM(E54:E65) -> 5460 | F66: =SUM(F54:F65) -> 13660 | G66: =SUM(G54:G65) -> 4660 | H66: =SUM(H54:H65) -> 4660 | I66: =SUM(I54:I65) -> 6500 | J66: =SUM(J54:J65) -> 4700 | ... AL66: =SUM(AL54:AL65) -> 11540
A67: Fixkosten gesamt (inkl. Personal) | C67: =C50+C66 -> 16960 | D67: =D50+D66 -> 7160 | E67: =E50+E66 -> 7960 | F67: =F50+F66 -> 16160 | G67: =G50+G66 -> 7160 | H67: =H50+H66 -> 7160 | I67: =I50+I66 -> 13598 | J67: =J50+J66 -> 11798 | ... AL67: =AL50+AL66 -> 52726.554
A68: Ergebnis
A69: Kosten gesamt | C69: =C34+C67 -> 16995.782 | D69: =D34+D67 -> 7204.3584 | E69: =E34+E67 -> 8012.7642 | F69: =F34+F67 -> 16242.001 | G69: =G34+G67 -> 7258.9485 | H69: =H34+H67 -> 7275.5597 | I69: =I34+I67 -> 13750.84 | J69: =J34+J67 -> 11975.672 | ... AL69: =AL34+AL67 -> 58405.922
A70: EBITDA | C70: =C26-C69 -> -15956.234 | D70: =D26-D69 -> -5841.8434 | E70: =E26-E69 -> -6333.4615 | F70: =F26-F69 -> -13768.485 | G70: =G26-G69 -> -4146.9644 | H70: =H26-H69 -> -3537.3078 | I70: =I26-I69 -> -8914.7872 | J70: =J26-J69 -> -6203.3322 | ... AL70: =AL26-AL69 -> 14500.186
A71: Finanzierung und Liquidität
A72: Einzahlung Eigenkapital | C72: =IF(C$2=Annahmen!$B$109,Annahmen!$B$108,0) -> 25000 | D72: =IF(D$2=Annahmen!$B$109,Annahmen!$B$108,0) -> 0 | E72: =IF(E$2=Annahmen!$B$109,Annahmen!$B$108,0) -> 0 | F72: =IF(F$2=Annahmen!$B$109,Annahmen!$B$108,0) -> 0 | G72: =IF(G$2=Annahmen!$B$109,Annahmen!$B$108,0) -> 0 | H72: =IF(H$2=Annahmen!$B$109,Annahmen!$B$108,0) -> 0 | I72: =IF(I$2=Annahmen!$B$109,Annahmen!$B$108,0) -> 0 | J72: =IF(J$2=Annahmen!$B$109,Annahmen!$B$108,0) -> 0 | ... AL72: =IF(AL$2=Annahmen!$B$109,Annahmen!$B$108,0) -> 0
A73: Auszahlung KfW-Kredit | C73: =IF(C$2=Annahmen!$B$111,Annahmen!$B$110,0) -> 125000 | D73: =IF(D$2=Annahmen!$B$111,Annahmen!$B$110,0) -> 0 | E73: =IF(E$2=Annahmen!$B$111,Annahmen!$B$110,0) -> 0 | F73: =IF(F$2=Annahmen!$B$111,Annahmen!$B$110,0) -> 0 | G73: =IF(G$2=Annahmen!$B$111,Annahmen!$B$110,0) -> 0 | H73: =IF(H$2=Annahmen!$B$111,Annahmen!$B$110,0) -> 0 | I73: =IF(I$2=Annahmen!$B$111,Annahmen!$B$110,0) -> 0 | J73: =IF(J$2=Annahmen!$B$111,Annahmen!$B$110,0) -> 0 | ... AL73: =IF(AL$2=Annahmen!$B$111,Annahmen!$B$110,0) -> 0
A74: Business Angel / Pre-Seed | C74: =IF(C$2=Annahmen!$B$116,Annahmen!$B$115,0) -> 0 | D74: =IF(D$2=Annahmen!$B$116,Annahmen!$B$115,0) -> 0 | E74: =IF(E$2=Annahmen!$B$116,Annahmen!$B$115,0) -> 0 | F74: =IF(F$2=Annahmen!$B$116,Annahmen!$B$115,0) -> 0 | G74: =IF(G$2=Annahmen!$B$116,Annahmen!$B$115,0) -> 0 | H74: =IF(H$2=Annahmen!$B$116,Annahmen!$B$115,0) -> 0 | I74: =IF(I$2=Annahmen!$B$116,Annahmen!$B$115,0) -> 0 | J74: =IF(J$2=Annahmen!$B$116,Annahmen!$B$115,0) -> 0 | ... AL74: =IF(AL$2=Annahmen!$B$116,Annahmen!$B$115,0) -> 0
A75: Gründungszuschuss / Förderung | C75: =IF(C$2<=6,Annahmen!$B$117,IF(C$2<=15,Annahmen!$B$118,0)) -> 0 | D75: =IF(D$2<=6,Annahmen!$B$117,IF(D$2<=15,Annahmen!$B$118,0)) -> 0 | E75: =IF(E$2<=6,Annahmen!$B$117,IF(E$2<=15,Annahmen!$B$118,0)) -> 0 | F75: =IF(F$2<=6,Annahmen!$B$117,IF(F$2<=15,Annahmen!$B$118,0)) -> 0 | G75: =IF(G$2<=6,Annahmen!$B$117,IF(G$2<=15,Annahmen!$B$118,0)) -> 0 | H75: =IF(H$2<=6,Annahmen!$B$117,IF(H$2<=15,Annahmen!$B$118,0)) -> 0 | I75: =IF(I$2<=6,Annahmen!$B$117,IF(I$2<=15,Annahmen!$B$118,0)) -> 0 | J75: =IF(J$2<=6,Annahmen!$B$117,IF(J$2<=15,Annahmen!$B$118,0)) -> 0 | ... AL75: =IF(AL$2<=6,Annahmen!$B$117,IF(AL$2<=15,Annahmen!$B$118,0)) -> 0
A76: Zinsen KfW-Kredit | C76: =(B78+C73)*Annahmen!$B$112/12 -> 416.66667 | D76: =(C78+D73)*Annahmen!$B$112/12 -> 416.66667 | E76: =(D78+E73)*Annahmen!$B$112/12 -> 416.66667 | F76: =(E78+F73)*Annahmen!$B$112/12 -> 416.66667 | G76: =(F78+G73)*Annahmen!$B$112/12 -> 416.66667 | H76: =(G78+H73)*Annahmen!$B$112/12 -> 416.66667 | I76: =(H78+I73)*Annahmen!$B$112/12 -> 416.66667 | J76: =(I78+J73)*Annahmen!$B$112/12 -> 416.66667 | ... AL76: =(AK78+AL73)*Annahmen!$B$112/12 -> 368.92361
A77: Tilgung KfW-Kredit | C77: =IF(C$2>Annahmen!$B$111-1+Annahmen!$B$113,MIN(B78,Annahmen!$B$110/(Annahmen!$B$114-Annahmen!$B$113)),0) -> 0 | D77: =IF(D$2>Annahmen!$B$111-1+Annahmen!$B$113,MIN(C78,Annahmen!$B$110/(Annahmen!$B$114-Annahmen!$B$113)),0) -> 0 | E77: =IF(E$2>Annahmen!$B$111-1+Annahmen!$B$113,MIN(D78,Annahmen!$B$110/(Annahmen!$B$114-Annahmen!$B$113)),0) -> 0 | F77: =IF(F$2>Annahmen!$B$111-1+Annahmen!$B$113,MIN(E78,Annahmen!$B$110/(Annahmen!$B$114-Annahmen!$B$113)),0) -> 0 | G77: =IF(G$2>Annahmen!$B$111-1+Annahmen!$B$113,MIN(F78,Annahmen!$B$110/(Annahmen!$B$114-Annahmen!$B$113)),0) -> 0 | H77: =IF(H$2>Annahmen!$B$111-1+Annahmen!$B$113,MIN(G78,Annahmen!$B$110/(Annahmen!$B$114-Annahmen!$B$113)),0) -> 0 | I77: =IF(I$2>Annahmen!$B$111-1+Annahmen!$B$113,MIN(H78,Annahmen!$B$110/(Annahmen!$B$114-Annahmen!$B$113)),0) -> 0 | J77: =IF(J$2>Annahmen!$B$111-1+Annahmen!$B$113,MIN(I78,Annahmen!$B$110/(Annahmen!$B$114-Annahmen!$B$113)),0) -> 0 | ... AL77: =IF(AL$2>Annahmen!$B$111-1+Annahmen!$B$113,MIN(AK78,Annahmen!$B$110/(Annahmen!$B$114-Annahmen!$B$113)),0) -> 1302.0833
A78: KfW-Restschuld (Monatsende) | B78: 0 | C78: =B78+C73-C77 -> 125000 | D78: =C78+D73-D77 -> 125000 | E78: =D78+E73-E77 -> 125000 | F78: =E78+F73-F77 -> 125000 | G78: =F78+G73-G77 -> 125000 | H78: =G78+H73-H77 -> 125000 | I78: =H78+I73-I77 -> 125000 | J78: =I78+J73-J77 -> 125000 | ... AL78: =AK78+AL73-AL77 -> 109375
A79: Ergebnis vor Steuern (EBITDA − Zinsen) | C79: =C70-C76 -> -16372.9 | D79: =D70-D76 -> -6258.51 | E79: =E70-E76 -> -6750.1282 | F79: =F70-F76 -> -14185.152 | G79: =G70-G76 -> -4563.631 | H79: =H70-H76 -> -3953.9744 | I79: =I70-I76 -> -9331.4539 | J79: =J70-J76 -> -6619.9988 | ... AL79: =AL70-AL76 -> 14131.262
A80: Steuerzahlung (Vorjahressteuer im Juni) | C80: =IF(AND(MOD(C$2,12)=6,C$2>12),INDEX('5 Jahre'!$B$46:$F$46,1,C$4-1),0) -> 0 | D80: =IF(AND(MOD(D$2,12)=6,D$2>12),INDEX('5 Jahre'!$B$46:$F$46,1,D$4-1),0) -> 0 | E80: =IF(AND(MOD(E$2,12)=6,E$2>12),INDEX('5 Jahre'!$B$46:$F$46,1,E$4-1),0) -> 0 | F80: =IF(AND(MOD(F$2,12)=6,F$2>12),INDEX('5 Jahre'!$B$46:$F$46,1,F$4-1),0) -> 0 | G80: =IF(AND(MOD(G$2,12)=6,G$2>12),INDEX('5 Jahre'!$B$46:$F$46,1,G$4-1),0) -> 0 | H80: =IF(AND(MOD(H$2,12)=6,H$2>12),INDEX('5 Jahre'!$B$46:$F$46,1,H$4-1),0) -> 0 | I80: =IF(AND(MOD(I$2,12)=6,I$2>12),INDEX('5 Jahre'!$B$46:$F$46,1,I$4-1),0) -> 0 | J80: =IF(AND(MOD(J$2,12)=6,J$2>12),INDEX('5 Jahre'!$B$46:$F$46,1,J$4-1),0) -> 0 | ... AL80: =IF(AND(MOD(AL$2,12)=6,AL$2>12),INDEX('5 Jahre'!$B$46:$F$46,1,AL$4-1),0) -> 0
A81: Cashflow gesamt | C81: =C70-C76-C77-C80+C72+C73+C74+C75 -> 133627.1 | D81: =D70-D76-D77-D80+D72+D73+D74+D75 -> -6258.51 | E81: =E70-E76-E77-E80+E72+E73+E74+E75 -> -6750.1282 | F81: =F70-F76-F77-F80+F72+F73+F74+F75 -> -14185.152 | G81: =G70-G76-G77-G80+G72+G73+G74+G75 -> -4563.631 | H81: =H70-H76-H77-H80+H72+H73+H74+H75 -> -3953.9744 | I81: =I70-I76-I77-I80+I72+I73+I74+I75 -> -9331.4539 | J81: =J70-J76-J77-J80+J72+J73+J74+J75 -> -6619.9988 | ... AL81: =AL70-AL76-AL77-AL80+AL72+AL73+AL74+AL75 -> 12829.179
A82: Kasse (Monatsende) | B82: 0 | C82: =B82+C81 -> 133627.1 | D82: =C82+D81 -> 127368.59 | E82: =D82+E81 -> 120618.46 | F82: =E82+F81 -> 106433.31 | G82: =F82+G81 -> 101869.68 | H82: =G82+H81 -> 97915.704 | I82: =H82+I81 -> 88584.251 | J82: =I82+J81 -> 81964.252 | ... AL82: =AK82+AL81 -> 82140.558
A83: Kumulierter Cashflow ohne Finanzierung | B83: 0 | C83: =B83+C70-C76-C77-C80 -> -16372.9 | D83: =C83+D70-D76-D77-D80 -> -22631.41 | E83: =D83+E70-E76-E77-E80 -> -29381.539 | F83: =E83+F70-F76-F77-F80 -> -43566.69 | G83: =F83+G70-G76-G77-G80 -> -48130.321 | H83: =G83+H70-H76-H77-H80 -> -52084.296 | I83: =H83+I70-I76-I77-I80 -> -61415.749 | J83: =I83+J70-J76-J77-J80 -> -68035.748 | ... AL83: =AK83+AL70-AL76-AL77-AL80 -> -267859.44
A84: Hilfszeile: Monat mit EBITDA ≥ 0 (sonst 999) | C84: =IF(C70>=0,C$2,999) -> 999 | D84: =IF(D70>=0,D$2,999) -> 999 | E84: =IF(E70>=0,E$2,999) -> 999 | F84: =IF(F70>=0,F$2,999) -> 999 | G84: =IF(G70>=0,G$2,999) -> 999 | H84: =IF(H70>=0,H$2,999) -> 999 | I84: =IF(I70>=0,I$2,999) -> 999 | J84: =IF(J70>=0,J$2,999) -> 999 | ... AL84: =IF(AL70>=0,AL$2,999) -> 36
A85: Hilfszeile: Monat mit EBITDA < 0 (sonst 0) | C85: =IF(C70<0,C$2,0) -> 1 | D85: =IF(D70<0,D$2,0) -> 2 | E85: =IF(E70<0,E$2,0) -> 3 | F85: =IF(F70<0,F$2,0) -> 4 | G85: =IF(G70<0,G$2,0) -> 5 | H85: =IF(H70<0,H$2,0) -> 6 | I85: =IF(I70<0,I$2,0) -> 7 | J85: =IF(J70<0,J$2,0) -> 8 | ... AL85: =IF(AL70<0,AL$2,0) -> 0
A86: Hilfszeile: kum. Cashflow ≥ 0 nach Tiefpunkt (sonst 999) | C86: =IF(AND(C83>=0,C$2>1),C$2,999) -> 999 | D86: =IF(AND(D83>=0,D$2>1),D$2,999) -> 999 | E86: =IF(AND(E83>=0,E$2>1),E$2,999) -> 999 | F86: =IF(AND(F83>=0,F$2>1),F$2,999) -> 999 | G86: =IF(AND(G83>=0,G$2>1),G$2,999) -> 999 | H86: =IF(AND(H83>=0,H$2>1),H$2,999) -> 999 | I86: =IF(AND(I83>=0,I$2>1),I$2,999) -> 999 | J86: =IF(AND(J83>=0,J$2>1),J$2,999) -> 999 | ... AL86: =IF(AND(AL83>=0,AL$2>1),AL$2,999) -> 999

Sheet Monat 37–60
A1: LADEKLAR – Monatsplan Monat 37–60 | B1: Anfang
A2: Monat-Nr. | B2: ='Monat 1–36'!$AL$2 -> 36 | C2: =B2+1 -> 37 | D2: =C2+1 -> 38 | E2: =D2+1 -> 39 | F2: =E2+1 -> 40 | G2: =F2+1 -> 41 | H2: =G2+1 -> 42 | I2: =H2+1 -> 43 | J2: =I2+1 -> 44 | ... Z2: =Y2+1 -> 60
A3: Monat | C3: =EDATE(Annahmen!$B$6,C$2-1) -> 47484 | D3: =EDATE(Annahmen!$B$6,D$2-1) -> 47515 | E3: =EDATE(Annahmen!$B$6,E$2-1) -> 47543 | F3: =EDATE(Annahmen!$B$6,F$2-1) -> 47574 | G3: =EDATE(Annahmen!$B$6,G$2-1) -> 47604 | H3: =EDATE(Annahmen!$B$6,H$2-1) -> 47635 | I3: =EDATE(Annahmen!$B$6,I$2-1) -> 47665 | J3: =EDATE(Annahmen!$B$6,J$2-1) -> 47696 | ... Z3: =EDATE(Annahmen!$B$6,Z$2-1) -> 48183
A4: Modelljahr | C4: =INT((C$2-1)/12)+1 -> 4 | D4: =INT((D$2-1)/12)+1 -> 4 | E4: =INT((E$2-1)/12)+1 -> 4 | F4: =INT((F$2-1)/12)+1 -> 4 | G4: =INT((G$2-1)/12)+1 -> 4 | H4: =INT((H$2-1)/12)+1 -> 4 | I4: =INT((I$2-1)/12)+1 -> 4 | J4: =INT((J$2-1)/12)+1 -> 4 | ... Z4: =INT((Z$2-1)/12)+1 -> 5
A5: Kunden
A6: Neukunden zahlend | C6: =IF(C$2<=36,INDEX(Annahmen!$B$36:$B$47,INT((C$2-1)/3)+1,1),IF(C$2<=48,Annahmen!$B$48,Annahmen!$B$49)) -> 45 | D6: =IF(D$2<=36,INDEX(Annahmen!$B$36:$B$47,INT((D$2-1)/3)+1,1),IF(D$2<=48,Annahmen!$B$48,Annahmen!$B$49)) -> 45 | E6: =IF(E$2<=36,INDEX(Annahmen!$B$36:$B$47,INT((E$2-1)/3)+1,1),IF(E$2<=48,Annahmen!$B$48,Annahmen!$B$49)) -> 45 | F6: =IF(F$2<=36,INDEX(Annahmen!$B$36:$B$47,INT((F$2-1)/3)+1,1),IF(F$2<=48,Annahmen!$B$48,Annahmen!$B$49)) -> 45 | G6: =IF(G$2<=36,INDEX(Annahmen!$B$36:$B$47,INT((G$2-1)/3)+1,1),IF(G$2<=48,Annahmen!$B$48,Annahmen!$B$49)) -> 45 | H6: =IF(H$2<=36,INDEX(Annahmen!$B$36:$B$47,INT((H$2-1)/3)+1,1),IF(H$2<=48,Annahmen!$B$48,Annahmen!$B$49)) -> 45 | I6: =IF(I$2<=36,INDEX(Annahmen!$B$36:$B$47,INT((I$2-1)/3)+1,1),IF(I$2<=48,Annahmen!$B$48,Annahmen!$B$49)) -> 45 | J6: =IF(J$2<=36,INDEX(Annahmen!$B$36:$B$47,INT((J$2-1)/3)+1,1),IF(J$2<=48,Annahmen!$B$48,Annahmen!$B$49)) -> 45 | ... Z6: =IF(Z$2<=36,INDEX(Annahmen!$B$36:$B$47,INT((Z$2-1)/3)+1,1),IF(Z$2<=48,Annahmen!$B$48,Annahmen!$B$49)) -> 55
A7: davon Start | C7: =C6*Annahmen!$B$19 -> 22.5 | D7: =D6*Annahmen!$B$19 -> 22.5 | E7: =E6*Annahmen!$B$19 -> 22.5 | F7: =F6*Annahmen!$B$19 -> 22.5 | G7: =G6*Annahmen!$B$19 -> 22.5 | H7: =H6*Annahmen!$B$19 -> 22.5 | I7: =I6*Annahmen!$B$19 -> 22.5 | J7: =J6*Annahmen!$B$19 -> 22.5 | ... Z7: =Z6*Annahmen!$B$19 -> 27.5
A8: davon Flotte | C8: =C6*Annahmen!$B$20 -> 17.1 | D8: =D6*Annahmen!$B$20 -> 17.1 | E8: =E6*Annahmen!$B$20 -> 17.1 | F8: =F6*Annahmen!$B$20 -> 17.1 | G8: =G6*Annahmen!$B$20 -> 17.1 | H8: =H6*Annahmen!$B$20 -> 17.1 | I8: =I6*Annahmen!$B$20 -> 17.1 | J8: =J6*Annahmen!$B$20 -> 17.1 | ... Z8: =Z6*Annahmen!$B$20 -> 20.9
A9: davon Premium | C9: =C6*Annahmen!$B$21 -> 5.4 | D9: =D6*Annahmen!$B$21 -> 5.4 | E9: =E6*Annahmen!$B$21 -> 5.4 | F9: =F6*Annahmen!$B$21 -> 5.4 | G9: =G6*Annahmen!$B$21 -> 5.4 | H9: =H6*Annahmen!$B$21 -> 5.4 | I9: =I6*Annahmen!$B$21 -> 5.4 | J9: =J6*Annahmen!$B$21 -> 5.4 | ... Z9: =Z6*Annahmen!$B$21 -> 6.6
A10: Kunden Start (Monatsende) | B10: ='Monat 1–36'!$AL$10 -> 278.84198 | C10: =B10*(1-Annahmen!$B$31)+C7 -> 292.97672 | D10: =C10*(1-Annahmen!$B$31)+D7 -> 306.68742 | E10: =D10*(1-Annahmen!$B$31)+E7 -> 319.9868 | F10: =E10*(1-Annahmen!$B$31)+F7 -> 332.88719 | G10: =F10*(1-Annahmen!$B$31)+G7 -> 345.40058 | H10: =G10*(1-Annahmen!$B$31)+H7 -> 357.53856 | I10: =H10*(1-Annahmen!$B$31)+I7 -> 369.3124 | J10: =I10*(1-Annahmen!$B$31)+J7 -> 380.73303 | ... Z10: =Y10*(1-Annahmen!$B$31)+Z7 -> 574.20269
A11: Kunden Flotte (Monatsende) | B11: ='Monat 1–36'!$AL$11 -> 235.13214 | C11: =B11*(1-Annahmen!$B$32)+C8 -> 247.5295 | D11: =C11*(1-Annahmen!$B$32)+D8 -> 259.67891 | E11: =D11*(1-Annahmen!$B$32)+E8 -> 271.58533 | F11: =E11*(1-Annahmen!$B$32)+F8 -> 283.25362 | G11: =F11*(1-Annahmen!$B$32)+G8 -> 294.68855 | H11: =G11*(1-Annahmen!$B$32)+H8 -> 305.89478 | I11: =H11*(1-Annahmen!$B$32)+I8 -> 316.87688 | J11: =I11*(1-Annahmen!$B$32)+J8 -> 327.63935 | ... Z11: =Y11*(1-Annahmen!$B$32)+Z8 -> 514.20138
A12: Kunden Premium (Monatsende) | B12: ='Monat 1–36'!$AL$12 -> 81.043962 | C12: =B12*(1-Annahmen!$B$33)+C9 -> 85.471434 | D12: =C12*(1-Annahmen!$B$33)+D9 -> 89.845777 | E12: =D12*(1-Annahmen!$B$33)+E9 -> 94.167628 | F12: =E12*(1-Annahmen!$B$33)+F9 -> 98.437616 | G12: =F12*(1-Annahmen!$B$33)+G9 -> 102.65637 | H12: =G12*(1-Annahmen!$B$33)+H9 -> 106.82449 | I12: =H12*(1-Annahmen!$B$33)+I9 -> 110.94259 | J12: =I12*(1-Annahmen!$B$33)+J9 -> 115.01128 | ... Z12: =Y12*(1-Annahmen!$B$33)+Z9 -> 187.339
A13: Kunden gesamt | B13: =B10+B11+B12 -> 595.01808 | C13: =C10+C11+C12 -> 625.97765 | D13: =D10+D11+D12 -> 656.2121 | E13: =E10+E11+E12 -> 685.73975 | F13: =F10+F11+F12 -> 714.57843 | G13: =G10+G11+G12 -> 742.74549 | H13: =H10+H11+H12 -> 770.25783 | I13: =I10+I11+I12 -> 797.13188 | ... Z13: =Z10+Z11+Z12 -> 1275.7431
A14: Kündigungen im Monat | C14: =B10*Annahmen!$B$31+B11*Annahmen!$B$32+B12*Annahmen!$B$33 -> 14.04043 | D14: =C10*Annahmen!$B$31+C11*Annahmen!$B$32+C12*Annahmen!$B$33 -> 14.765549 | E14: =D10*Annahmen!$B$31+D11*Annahmen!$B$32+D12*Annahmen!$B$33 -> 15.47235 | F14: =E10*Annahmen!$B$31+E11*Annahmen!$B$32+E12*Annahmen!$B$33 -> 16.161322 | G14: =F10*Annahmen!$B$31+F11*Annahmen!$B$32+F12*Annahmen!$B$33 -> 16.83294 | H14: =G10*Annahmen!$B$31+G11*Annahmen!$B$32+G12*Annahmen!$B$33 -> 17.487665 | I14: =H10*Annahmen!$B$31+H11*Annahmen!$B$32+H12*Annahmen!$B$33 -> 18.125946 | J14: =I10*Annahmen!$B$31+I11*Annahmen!$B$32+I12*Annahmen!$B$33 -> 18.748221 | ... Z14: =Y10*Annahmen!$B$31+Y11*Annahmen!$B$32+Y12*Annahmen!$B$33 -> 29.170916
A15: Neue Store-Apps | C15: =C9*Annahmen!$B$24 -> 1.08 | D15: =D9*Annahmen!$B$24 -> 1.08 | E15: =E9*Annahmen!$B$24 -> 1.08 | F15: =F9*Annahmen!$B$24 -> 1.08 | G15: =G9*Annahmen!$B$24 -> 1.08 | H15: =H9*Annahmen!$B$24 -> 1.08 | I15: =I9*Annahmen!$B$24 -> 1.08 | J15: =J9*Annahmen!$B$24 -> 1.08 | ... Z15: =Z9*Annahmen!$B$24 -> 1.32
A16: Store-Apps aktiv | B16: ='Monat 1–36'!$AL$16 -> 16.208792 | C16: =B16*(1-Annahmen!$B$33)+C15 -> 17.094287 | D16: =C16*(1-Annahmen!$B$33)+D15 -> 17.969155 | E16: =D16*(1-Annahmen!$B$33)+E15 -> 18.833526 | F16: =E16*(1-Annahmen!$B$33)+F15 -> 19.687523 | G16: =F16*(1-Annahmen!$B$33)+G15 -> 20.531273 | H16: =G16*(1-Annahmen!$B$33)+H15 -> 21.364898 | I16: =H16*(1-Annahmen!$B$33)+I15 -> 22.188519 | J16: =I16*(1-Annahmen!$B$33)+J15 -> 23.002257 | ... Z16: =Y16*(1-Annahmen!$B$33)+Z15 -> 37.467799
A17: Nötige Testzugänge (Info) | C17: =C6/Annahmen!$B$28 -> 128.57143 | D17: =D6/Annahmen!$B$28 -> 128.57143 | E17: =E6/Annahmen!$B$28 -> 128.57143 | F17: =F6/Annahmen!$B$28 -> 128.57143 | G17: =G6/Annahmen!$B$28 -> 128.57143 | H17: =H6/Annahmen!$B$28 -> 128.57143 | I17: =I6/Annahmen!$B$28 -> 128.57143 | J17: =J6/Annahmen!$B$28 -> 128.57143 | ... Z17: =Z6/Annahmen!$B$28 -> 157.14286
A18: Umsatz
A19: MRR Start | C19: =C10*Annahmen!$B$10 -> 14355.859 | D19: =D10*Annahmen!$B$10 -> 15027.684 | E19: =E10*Annahmen!$B$10 -> 15679.353 | F19: =F10*Annahmen!$B$10 -> 16311.472 | G19: =G10*Annahmen!$B$10 -> 16924.628 | H19: =H10*Annahmen!$B$10 -> 17519.389 | I19: =I10*Annahmen!$B$10 -> 18096.308 | J19: =J10*Annahmen!$B$10 -> 18655.919 | ... Z19: =Z10*Annahmen!$B$10 -> 28135.932
A20: MRR Flotte inkl. Zusatzfahrer | C20: =C11*(Annahmen!$B$11+Annahmen!$B$13*Annahmen!$B$22) -> 34530.365 | D20: =D11*(Annahmen!$B$11+Annahmen!$B$13*Annahmen!$B$22) -> 36225.207 | E20: =E11*(Annahmen!$B$11+Annahmen!$B$13*Annahmen!$B$22) -> 37886.153 | F20: =F11*(Annahmen!$B$11+Annahmen!$B$13*Annahmen!$B$22) -> 39513.88 | G20: =G11*(Annahmen!$B$11+Annahmen!$B$13*Annahmen!$B$22) -> 41109.053 | H20: =H11*(Annahmen!$B$11+Annahmen!$B$13*Annahmen!$B$22) -> 42672.322 | I20: =I11*(Annahmen!$B$11+Annahmen!$B$13*Annahmen!$B$22) -> 44204.325 | J20: =J11*(Annahmen!$B$11+Annahmen!$B$13*Annahmen!$B$22) -> 45705.689 | ... Z20: =Z11*(Annahmen!$B$11+Annahmen!$B$13*Annahmen!$B$22) -> 71731.093
A21: MRR Premium inkl. Zusatzfahrer | C21: =C12*(Annahmen!$B$12+Annahmen!$B$14*Annahmen!$B$23) -> 28120.102 | D21: =D12*(Annahmen!$B$12+Annahmen!$B$14*Annahmen!$B$23) -> 29559.261 | E21: =E12*(Annahmen!$B$12+Annahmen!$B$14*Annahmen!$B$23) -> 30981.15 | F21: =F12*(Annahmen!$B$12+Annahmen!$B$14*Annahmen!$B$23) -> 32385.976 | G21: =G12*(Annahmen!$B$12+Annahmen!$B$14*Annahmen!$B$23) -> 33773.944 | H21: =H12*(Annahmen!$B$12+Annahmen!$B$14*Annahmen!$B$23) -> 35145.257 | I21: =I12*(Annahmen!$B$12+Annahmen!$B$14*Annahmen!$B$23) -> 36500.114 | J21: =J12*(Annahmen!$B$12+Annahmen!$B$14*Annahmen!$B$23) -> 37838.712 | ... Z21: =Z12*(Annahmen!$B$12+Annahmen!$B$14*Annahmen!$B$23) -> 61634.53
A22: MRR Store-App | C22: =C16*Annahmen!$B$16 -> 1692.3344 | D22: =D16*Annahmen!$B$16 -> 1778.9464 | E22: =E16*Annahmen!$B$16 -> 1864.519 | F22: =F16*Annahmen!$B$16 -> 1949.0648 | G22: =G16*Annahmen!$B$16 -> 2032.596 | H22: =H16*Annahmen!$B$16 -> 2115.1249 | I22: =I16*Annahmen!$B$16 -> 2196.6634 | J22: =J16*Annahmen!$B$16 -> 2277.2234 | ... Z22: =Z16*Annahmen!$B$16 -> 3709.3121
A23: MRR gesamt (Listenpreis) | C23: =SUM(C19:C22) -> 78698.66 | D23: =SUM(D19:D22) -> 82591.098 | E23: =SUM(E19:E22) -> 86411.175 | F23: =SUM(F19:F22) -> 90160.393 | G23: =SUM(G19:G22) -> 93840.221 | H23: =SUM(H19:H22) -> 97452.093 | I23: =SUM(I19:I22) -> 100997.41 | J23: =SUM(J19:J22) -> 104477.54 | ... Z23: =SUM(Z19:Z22) -> 165210.87
A24: Rabatt Jahreszahler | C24: =-C23*Annahmen!$B$27 -> -3934.933 | D24: =-D23*Annahmen!$B$27 -> -4129.5549 | E24: =-E23*Annahmen!$B$27 -> -4320.5587 | F24: =-F23*Annahmen!$B$27 -> -4508.0197 | G24: =-G23*Annahmen!$B$27 -> -4692.0111 | H24: =-H23*Annahmen!$B$27 -> -4872.6046 | I24: =-I23*Annahmen!$B$27 -> -5049.8705 | J24: =-J23*Annahmen!$B$27 -> -5223.8771 | ... Z24: =-Z23*Annahmen!$B$27 -> -8260.5433
A25: Einrichtung Store-App (einmalig) | C25: =C15*Annahmen!$B$15 -> 2149.2 | D25: =D15*Annahmen!$B$15 -> 2149.2 | E25: =E15*Annahmen!$B$15 -> 2149.2 | F25: =F15*Annahmen!$B$15 -> 2149.2 | G25: =G15*Annahmen!$B$15 -> 2149.2 | H25: =H15*Annahmen!$B$15 -> 2149.2 | I25: =I15*Annahmen!$B$15 -> 2149.2 | J25: =J15*Annahmen!$B$15 -> 2149.2 | ... Z25: =Z15*Annahmen!$B$15 -> 2626.8
A26: Umsatz gesamt | C26: =C23+C24+C25 -> 76912.927 | D26: =D23+D24+D25 -> 80610.743 | E26: =E23+E24+E25 -> 84239.816 | F26: =F23+F24+F25 -> 87801.574 | G26: =G23+G24+G25 -> 91297.41 | H26: =H23+H24+H25 -> 94728.688 | I26: =I23+I24+I25 -> 98096.739 | J26: =J23+J24+J25 -> 101402.87 | ... Z26: =Z23+Z24+Z25 -> 159577.12
A27: ARR (MRR × 12) | C27: =C23*12 -> 944383.93 | D27: =D23*12 -> 991093.18 | E27: =E23*12 -> 1036934.1 | F27: =F23*12 -> 1081924.7 | G27: =G23*12 -> 1126082.7 | H27: =H23*12 -> 1169425.1 | I27: =I23*12 -> 1211968.9 | J27: =J23*12 -> 1253730.5 | ... Z27: =Z23*12 -> 1982530.4
A28: ARPA (MRR je Kunde) | C28: =IF(C13>0,C23/C13,0) -> 125.7212 | D28: =IF(D13>0,D23/D13,0) -> 125.86037 | E28: =IF(E13>0,E23/E13,0) -> 126.01162 | F28: =IF(F13>0,F23/F13,0) -> 126.17284 | G28: =IF(G13>0,G23/G13,0) -> 126.34236 | H28: =IF(H13>0,H23/H13,0) -> 126.5188 | I28: =IF(I13>0,I23/I13,0) -> 126.701 | J28: =IF(J13>0,J23/J13,0) -> 126.88805 | ... Z28: =IF(Z13>0,Z23/Z13,0) -> 129.50168
A29: Variable Kosten
A30: Hosting/Speicher variabel | C30: =C10*Annahmen!$B$52+C11*Annahmen!$B$53+C12*Annahmen!$B$54 -> 1156.7975 | D30: =D10*Annahmen!$B$52+D11*Annahmen!$B$53+D12*Annahmen!$B$54 -> 1213.9366 | E30: =E10*Annahmen!$B$52+E11*Annahmen!$B$53+E12*Annahmen!$B$54 -> 1269.9982 | F30: =F10*Annahmen!$B$52+F11*Annahmen!$B$53+F12*Annahmen!$B$54 -> 1325.0051 | G30: =G10*Annahmen!$B$52+G11*Annahmen!$B$53+G12*Annahmen!$B$54 -> 1378.9794 | H30: =H10*Annahmen!$B$52+H11*Annahmen!$B$53+H12*Annahmen!$B$54 -> 1431.9428 | I30: =I10*Annahmen!$B$52+I11*Annahmen!$B$53+I12*Annahmen!$B$54 -> 1483.9167 | J30: =J10*Annahmen!$B$52+J11*Annahmen!$B$53+J12*Annahmen!$B$54 -> 1534.9215 | ... Z30: =Z10*Annahmen!$B$52+Z11*Annahmen!$B$53+Z12*Annahmen!$B$54 -> 2424.4599
A31: Zahlungsgebühren | C31: =C26*Annahmen!$B$55+C13*Annahmen!$B$56 -> 834.3956 | D31: =D26*Annahmen!$B$55+D13*Annahmen!$B$56 -> 874.56018 | E31: =E26*Annahmen!$B$55+E13*Annahmen!$B$56 -> 913.92744 | F31: =F26*Annahmen!$B$55+F13*Annahmen!$B$56 -> 952.51504 | G31: =G26*Annahmen!$B$55+G13*Annahmen!$B$56 -> 990.3402 | H31: =H26*Annahmen!$B$55+H13*Annahmen!$B$56 -> 1027.4197 | I31: =I26*Annahmen!$B$55+I13*Annahmen!$B$56 -> 1063.7701 | J31: =J26*Annahmen!$B$55+J13*Annahmen!$B$56 -> 1099.4072 | ... Z31: =Z26*Annahmen!$B$55+Z13*Annahmen!$B$56 -> 1723.1271
A32: Partnerprovision | C32: =C26*INDEX(Annahmen!$B$58:$F$58,1,C$4)*Annahmen!$B$57 -> 4807.058 | D32: =D26*INDEX(Annahmen!$B$58:$F$58,1,D$4)*Annahmen!$B$57 -> 5038.1715 | E32: =E26*INDEX(Annahmen!$B$58:$F$58,1,E$4)*Annahmen!$B$57 -> 5264.9885 | F32: =F26*INDEX(Annahmen!$B$58:$F$58,1,F$4)*Annahmen!$B$57 -> 5487.5984 | G32: =G26*INDEX(Annahmen!$B$58:$F$58,1,G$4)*Annahmen!$B$57 -> 5706.0881 | H32: =H26*INDEX(Annahmen!$B$58:$F$58,1,H$4)*Annahmen!$B$57 -> 5920.543 | I32: =I26*INDEX(Annahmen!$B$58:$F$58,1,I$4)*Annahmen!$B$57 -> 6131.0462 | J32: =J26*INDEX(Annahmen!$B$58:$F$58,1,J$4)*Annahmen!$B$57 -> 6337.6791 | ... Z32: =Z26*INDEX(Annahmen!$B$58:$F$58,1,Z$4)*Annahmen!$B$57 -> 11968.284
A33: Fremdkosten Store-App-Einrichtung | C33: =C15*Annahmen!$B$59 -> 162 | D33: =D15*Annahmen!$B$59 -> 162 | E33: =E15*Annahmen!$B$59 -> 162 | F33: =F15*Annahmen!$B$59 -> 162 | G33: =G15*Annahmen!$B$59 -> 162 | H33: =H15*Annahmen!$B$59 -> 162 | I33: =I15*Annahmen!$B$59 -> 162 | J33: =J15*Annahmen!$B$59 -> 162 | ... Z33: =Z15*Annahmen!$B$59 -> 198
A34: Variable Kosten gesamt | C34: =SUM(C30:C33) -> 6960.2511 | D34: =SUM(D30:D33) -> 7288.6683 | E34: =SUM(E30:E33) -> 7610.9142 | F34: =SUM(F30:F33) -> 7927.1185 | G34: =SUM(G30:G33) -> 8237.4077 | H34: =SUM(H30:H33) -> 8541.9056 | I34: =SUM(I30:I33) -> 8840.733 | J34: =SUM(J30:J33) -> 9134.0079 | ... Z34: =SUM(Z30:Z33) -> 16313.871
A35: Deckungsbeitrag | C35: =C26-C34 -> 69952.676 | D35: =D26-D34 -> 73322.075 | E35: =E26-E34 -> 76628.902 | F35: =F26-F34 -> 79874.455 | G35: =G26-G34 -> 83060.002 | H35: =H26-H34 -> 86186.782 | I35: =I26-I34 -> 89256.007 | J35: =J26-J34 -> 92268.858 | ... Z35: =Z26-Z34 -> 143263.25
A36: Personal
A37: Gründer/Geschäftsführer | C37: =INDEX(Annahmen!$B$90:$F$90,1,C$4)*Annahmen!$B$91 -> 6500 | D37: =INDEX(Annahmen!$B$90:$F$90,1,D$4)*Annahmen!$B$91 -> 6500 | E37: =INDEX(Annahmen!$B$90:$F$90,1,E$4)*Annahmen!$B$91 -> 6500 | F37: =INDEX(Annahmen!$B$90:$F$90,1,F$4)*Annahmen!$B$91 -> 6500 | G37: =INDEX(Annahmen!$B$90:$F$90,1,G$4)*Annahmen!$B$91 -> 6500 | H37: =INDEX(Annahmen!$B$90:$F$90,1,H$4)*Annahmen!$B$91 -> 6500 | I37: =INDEX(Annahmen!$B$90:$F$90,1,I$4)*Annahmen!$B$91 -> 6500 | J37: =INDEX(Annahmen!$B$90:$F$90,1,J$4)*Annahmen!$B$91 -> 6500 | ... Z37: =INDEX(Annahmen!$B$90:$F$90,1,Z$4)*Annahmen!$B$91 -> 7000
A38: Vertrieb & Kundenerfolg 1 (mehrsprachig, Ex-Disposition) | C38: =IF(C$2>=Annahmen!$C$94,Annahmen!$D$94*(1+Annahmen!$B$92)^(C$4-1)*Annahmen!$E$94,0) -> 5024.3587 | D38: =IF(D$2>=Annahmen!$C$94,Annahmen!$D$94*(1+Annahmen!$B$92)^(D$4-1)*Annahmen!$E$94,0) -> 5024.3587 | E38: =IF(E$2>=Annahmen!$C$94,Annahmen!$D$94*(1+Annahmen!$B$92)^(E$4-1)*Annahmen!$E$94,0) -> 5024.3587 | F38: =IF(F$2>=Annahmen!$C$94,Annahmen!$D$94*(1+Annahmen!$B$92)^(F$4-1)*Annahmen!$E$94,0) -> 5024.3587 | G38: =IF(G$2>=Annahmen!$C$94,Annahmen!$D$94*(1+Annahmen!$B$92)^(G$4-1)*Annahmen!$E$94,0) -> 5024.3587 | H38: =IF(H$2>=Annahmen!$C$94,Annahmen!$D$94*(1+Annahmen!$B$92)^(H$4-1)*Annahmen!$E$94,0) -> 5024.3587 | I38: =IF(I$2>=Annahmen!$C$94,Annahmen!$D$94*(1+Annahmen!$B$92)^(I$4-1)*Annahmen!$E$94,0) -> 5024.3587 | J38: =IF(J$2>=Annahmen!$C$94,Annahmen!$D$94*(1+Annahmen!$B$92)^(J$4-1)*Annahmen!$E$94,0) -> 5024.3587 | ... Z38: =IF(Z$2>=Annahmen!$C$94,Annahmen!$D$94*(1+Annahmen!$B$92)^(Z$4-1)*Annahmen!$E$94,0) -> 5175.0895
A39: Softwareentwicklung 1 (Full-Stack) | C39: =IF(C$2>=Annahmen!$C$95,Annahmen!$D$95*(1+Annahmen!$B$92)^(C$4-1)*Annahmen!$E$95,0) -> 6875.4383 | D39: =IF(D$2>=Annahmen!$C$95,Annahmen!$D$95*(1+Annahmen!$B$92)^(D$4-1)*Annahmen!$E$95,0) -> 6875.4383 | E39: =IF(E$2>=Annahmen!$C$95,Annahmen!$D$95*(1+Annahmen!$B$92)^(E$4-1)*Annahmen!$E$95,0) -> 6875.4383 | F39: =IF(F$2>=Annahmen!$C$95,Annahmen!$D$95*(1+Annahmen!$B$92)^(F$4-1)*Annahmen!$E$95,0) -> 6875.4383 | G39: =IF(G$2>=Annahmen!$C$95,Annahmen!$D$95*(1+Annahmen!$B$92)^(G$4-1)*Annahmen!$E$95,0) -> 6875.4383 | H39: =IF(H$2>=Annahmen!$C$95,Annahmen!$D$95*(1+Annahmen!$B$92)^(H$4-1)*Annahmen!$E$95,0) -> 6875.4383 | I39: =IF(I$2>=Annahmen!$C$95,Annahmen!$D$95*(1+Annahmen!$B$92)^(I$4-1)*Annahmen!$E$95,0) -> 6875.4383 | J39: =IF(J$2>=Annahmen!$C$95,Annahmen!$D$95*(1+Annahmen!$B$92)^(J$4-1)*Annahmen!$E$95,0) -> 6875.4383 | ... Z39: =IF(Z$2>=Annahmen!$C$95,Annahmen!$D$95*(1+Annahmen!$B$92)^(Z$4-1)*Annahmen!$E$95,0) -> 7081.7014
A40: Vertrieb 2 / Partnermanagement | C40: =IF(C$2>=Annahmen!$C$96,Annahmen!$D$96*(1+Annahmen!$B$92)^(C$4-1)*Annahmen!$E$96,0) -> 5553.2386 | D40: =IF(D$2>=Annahmen!$C$96,Annahmen!$D$96*(1+Annahmen!$B$92)^(D$4-1)*Annahmen!$E$96,0) -> 5553.2386 | E40: =IF(E$2>=Annahmen!$C$96,Annahmen!$D$96*(1+Annahmen!$B$92)^(E$4-1)*Annahmen!$E$96,0) -> 5553.2386 | F40: =IF(F$2>=Annahmen!$C$96,Annahmen!$D$96*(1+Annahmen!$B$92)^(F$4-1)*Annahmen!$E$96,0) -> 5553.2386 | G40: =IF(G$2>=Annahmen!$C$96,Annahmen!$D$96*(1+Annahmen!$B$92)^(G$4-1)*Annahmen!$E$96,0) -> 5553.2386 | H40: =IF(H$2>=Annahmen!$C$96,Annahmen!$D$96*(1+Annahmen!$B$92)^(H$4-1)*Annahmen!$E$96,0) -> 5553.2386 | I40: =IF(I$2>=Annahmen!$C$96,Annahmen!$D$96*(1+Annahmen!$B$92)^(I$4-1)*Annahmen!$E$96,0) -> 5553.2386 | J40: =IF(J$2>=Annahmen!$C$96,Annahmen!$D$96*(1+Annahmen!$B$92)^(J$4-1)*Annahmen!$E$96,0) -> 5553.2386 | ... Z40: =IF(Z$2>=Annahmen!$C$96,Annahmen!$D$96*(1+Annahmen!$B$92)^(Z$4-1)*Annahmen!$E$96,0) -> 5719.8358
A41: Support Teilzeit (PL/RO/TR) | C41: =IF(C$2>=Annahmen!$C$97,Annahmen!$D$97*(1+Annahmen!$B$92)^(C$4-1)*Annahmen!$E$97,0) -> 2115.5195 | D41: =IF(D$2>=Annahmen!$C$97,Annahmen!$D$97*(1+Annahmen!$B$92)^(D$4-1)*Annahmen!$E$97,0) -> 2115.5195 | E41: =IF(E$2>=Annahmen!$C$97,Annahmen!$D$97*(1+Annahmen!$B$92)^(E$4-1)*Annahmen!$E$97,0) -> 2115.5195 | F41: =IF(F$2>=Annahmen!$C$97,Annahmen!$D$97*(1+Annahmen!$B$92)^(F$4-1)*Annahmen!$E$97,0) -> 2115.5195 | G41: =IF(G$2>=Annahmen!$C$97,Annahmen!$D$97*(1+Annahmen!$B$92)^(G$4-1)*Annahmen!$E$97,0) -> 2115.5195 | H41: =IF(H$2>=Annahmen!$C$97,Annahmen!$D$97*(1+Annahmen!$B$92)^(H$4-1)*Annahmen!$E$97,0) -> 2115.5195 | I41: =IF(I$2>=Annahmen!$C$97,Annahmen!$D$97*(1+Annahmen!$B$92)^(I$4-1)*Annahmen!$E$97,0) -> 2115.5195 | J41: =IF(J$2>=Annahmen!$C$97,Annahmen!$D$97*(1+Annahmen!$B$92)^(J$4-1)*Annahmen!$E$97,0) -> 2115.5195 | ... Z41: =IF(Z$2>=Annahmen!$C$97,Annahmen!$D$97*(1+Annahmen!$B$92)^(Z$4-1)*Annahmen!$E$97,0) -> 2178.9851
A42: Softwareentwicklung 2 | C42: =IF(C$2>=Annahmen!$C$98,Annahmen!$D$98*(1+Annahmen!$B$92)^(C$4-1)*Annahmen!$E$98,0) -> 6875.4383 | D42: =IF(D$2>=Annahmen!$C$98,Annahmen!$D$98*(1+Annahmen!$B$92)^(D$4-1)*Annahmen!$E$98,0) -> 6875.4383 | E42: =IF(E$2>=Annahmen!$C$98,Annahmen!$D$98*(1+Annahmen!$B$92)^(E$4-1)*Annahmen!$E$98,0) -> 6875.4383 | F42: =IF(F$2>=Annahmen!$C$98,Annahmen!$D$98*(1+Annahmen!$B$92)^(F$4-1)*Annahmen!$E$98,0) -> 6875.4383 | G42: =IF(G$2>=Annahmen!$C$98,Annahmen!$D$98*(1+Annahmen!$B$92)^(G$4-1)*Annahmen!$E$98,0) -> 6875.4383 | H42: =IF(H$2>=Annahmen!$C$98,Annahmen!$D$98*(1+Annahmen!$B$92)^(H$4-1)*Annahmen!$E$98,0) -> 6875.4383 | I42: =IF(I$2>=Annahmen!$C$98,Annahmen!$D$98*(1+Annahmen!$B$92)^(I$4-1)*Annahmen!$E$98,0) -> 6875.4383 | J42: =IF(J$2>=Annahmen!$C$98,Annahmen!$D$98*(1+Annahmen!$B$92)^(J$4-1)*Annahmen!$E$98,0) -> 6875.4383 | ... Z42: =IF(Z$2>=Annahmen!$C$98,Annahmen!$D$98*(1+Annahmen!$B$92)^(Z$4-1)*Annahmen!$E$98,0) -> 7081.7014
A43: Kundenerfolg 2 | C43: =IF(C$2>=Annahmen!$C$99,Annahmen!$D$99*(1+Annahmen!$B$92)^(C$4-1)*Annahmen!$E$99,0) -> 5024.3587 | D43: =IF(D$2>=Annahmen!$C$99,Annahmen!$D$99*(1+Annahmen!$B$92)^(D$4-1)*Annahmen!$E$99,0) -> 5024.3587 | E43: =IF(E$2>=Annahmen!$C$99,Annahmen!$D$99*(1+Annahmen!$B$92)^(E$4-1)*Annahmen!$E$99,0) -> 5024.3587 | F43: =IF(F$2>=Annahmen!$C$99,Annahmen!$D$99*(1+Annahmen!$B$92)^(F$4-1)*Annahmen!$E$99,0) -> 5024.3587 | G43: =IF(G$2>=Annahmen!$C$99,Annahmen!$D$99*(1+Annahmen!$B$92)^(G$4-1)*Annahmen!$E$99,0) -> 5024.3587 | H43: =IF(H$2>=Annahmen!$C$99,Annahmen!$D$99*(1+Annahmen!$B$92)^(H$4-1)*Annahmen!$E$99,0) -> 5024.3587 | I43: =IF(I$2>=Annahmen!$C$99,Annahmen!$D$99*(1+Annahmen!$B$92)^(I$4-1)*Annahmen!$E$99,0) -> 5024.3587 | J43: =IF(J$2>=Annahmen!$C$99,Annahmen!$D$99*(1+Annahmen!$B$92)^(J$4-1)*Annahmen!$E$99,0) -> 5024.3587 | ... Z43: =IF(Z$2>=Annahmen!$C$99,Annahmen!$D$99*(1+Annahmen!$B$92)^(Z$4-1)*Annahmen!$E$99,0) -> 5175.0895
A44: Marketing | C44: =IF(C$2>=Annahmen!$C$100,Annahmen!$D$100*(1+Annahmen!$B$92)^(C$4-1)*Annahmen!$E$100,0) -> 5288.7987 | D44: =IF(D$2>=Annahmen!$C$100,Annahmen!$D$100*(1+Annahmen!$B$92)^(D$4-1)*Annahmen!$E$100,0) -> 5288.7987 | E44: =IF(E$2>=Annahmen!$C$100,Annahmen!$D$100*(1+Annahmen!$B$92)^(E$4-1)*Annahmen!$E$100,0) -> 5288.7987 | F44: =IF(F$2>=Annahmen!$C$100,Annahmen!$D$100*(1+Annahmen!$B$92)^(F$4-1)*Annahmen!$E$100,0) -> 5288.7987 | G44: =IF(G$2>=Annahmen!$C$100,Annahmen!$D$100*(1+Annahmen!$B$92)^(G$4-1)*Annahmen!$E$100,0) -> 5288.7987 | H44: =IF(H$2>=Annahmen!$C$100,Annahmen!$D$100*(1+Annahmen!$B$92)^(H$4-1)*Annahmen!$E$100,0) -> 5288.7987 | I44: =IF(I$2>=Annahmen!$C$100,Annahmen!$D$100*(1+Annahmen!$B$92)^(I$4-1)*Annahmen!$E$100,0) -> 5288.7987 | J44: =IF(J$2>=Annahmen!$C$100,Annahmen!$D$100*(1+Annahmen!$B$92)^(J$4-1)*Annahmen!$E$100,0) -> 5288.7987 | ... Z44: =IF(Z$2>=Annahmen!$C$100,Annahmen!$D$100*(1+Annahmen!$B$92)^(Z$4-1)*Annahmen!$E$100,0) -> 5447.4626
A45: Softwareentwicklung 3 | C45: =IF(C$2>=Annahmen!$C$101,Annahmen!$D$101*(1+Annahmen!$B$92)^(C$4-1)*Annahmen!$E$101,0) -> 7139.8782 | D45: =IF(D$2>=Annahmen!$C$101,Annahmen!$D$101*(1+Annahmen!$B$92)^(D$4-1)*Annahmen!$E$101,0) -> 7139.8782 | E45: =IF(E$2>=Annahmen!$C$101,Annahmen!$D$101*(1+Annahmen!$B$92)^(E$4-1)*Annahmen!$E$101,0) -> 7139.8782 | F45: =IF(F$2>=Annahmen!$C$101,Annahmen!$D$101*(1+Annahmen!$B$92)^(F$4-1)*Annahmen!$E$101,0) -> 7139.8782 | G45: =IF(G$2>=Annahmen!$C$101,Annahmen!$D$101*(1+Annahmen!$B$92)^(G$4-1)*Annahmen!$E$101,0) -> 7139.8782 | H45: =IF(H$2>=Annahmen!$C$101,Annahmen!$D$101*(1+Annahmen!$B$92)^(H$4-1)*Annahmen!$E$101,0) -> 7139.8782 | I45: =IF(I$2>=Annahmen!$C$101,Annahmen!$D$101*(1+Annahmen!$B$92)^(I$4-1)*Annahmen!$E$101,0) -> 7139.8782 | J45: =IF(J$2>=Annahmen!$C$101,Annahmen!$D$101*(1+Annahmen!$B$92)^(J$4-1)*Annahmen!$E$101,0) -> 7139.8782 | ... Z45: =IF(Z$2>=Annahmen!$C$101,Annahmen!$D$101*(1+Annahmen!$B$92)^(Z$4-1)*Annahmen!$E$101,0) -> 7354.0746
A46: Vertrieb 3 | C46: =IF(C$2>=Annahmen!$C$102,Annahmen!$D$102*(1+Annahmen!$B$92)^(C$4-1)*Annahmen!$E$102,0) -> 5553.2386 | D46: =IF(D$2>=Annahmen!$C$102,Annahmen!$D$102*(1+Annahmen!$B$92)^(D$4-1)*Annahmen!$E$102,0) -> 5553.2386 | E46: =IF(E$2>=Annahmen!$C$102,Annahmen!$D$102*(1+Annahmen!$B$92)^(E$4-1)*Annahmen!$E$102,0) -> 5553.2386 | F46: =IF(F$2>=Annahmen!$C$102,Annahmen!$D$102*(1+Annahmen!$B$92)^(F$4-1)*Annahmen!$E$102,0) -> 5553.2386 | G46: =IF(G$2>=Annahmen!$C$102,Annahmen!$D$102*(1+Annahmen!$B$92)^(G$4-1)*Annahmen!$E$102,0) -> 5553.2386 | H46: =IF(H$2>=Annahmen!$C$102,Annahmen!$D$102*(1+Annahmen!$B$92)^(H$4-1)*Annahmen!$E$102,0) -> 5553.2386 | I46: =IF(I$2>=Annahmen!$C$102,Annahmen!$D$102*(1+Annahmen!$B$92)^(I$4-1)*Annahmen!$E$102,0) -> 5553.2386 | J46: =IF(J$2>=Annahmen!$C$102,Annahmen!$D$102*(1+Annahmen!$B$92)^(J$4-1)*Annahmen!$E$102,0) -> 5553.2386 | ... Z46: =IF(Z$2>=Annahmen!$C$102,Annahmen!$D$102*(1+Annahmen!$B$92)^(Z$4-1)*Annahmen!$E$102,0) -> 5719.8358
A47: Kundenerfolg 3 | C47: =IF(C$2>=Annahmen!$C$103,Annahmen!$D$103*(1+Annahmen!$B$92)^(C$4-1)*Annahmen!$E$103,0) -> 0 | D47: =IF(D$2>=Annahmen!$C$103,Annahmen!$D$103*(1+Annahmen!$B$92)^(D$4-1)*Annahmen!$E$103,0) -> 0 | E47: =IF(E$2>=Annahmen!$C$103,Annahmen!$D$103*(1+Annahmen!$B$92)^(E$4-1)*Annahmen!$E$103,0) -> 0 | F47: =IF(F$2>=Annahmen!$C$103,Annahmen!$D$103*(1+Annahmen!$B$92)^(F$4-1)*Annahmen!$E$103,0) -> 0 | G47: =IF(G$2>=Annahmen!$C$103,Annahmen!$D$103*(1+Annahmen!$B$92)^(G$4-1)*Annahmen!$E$103,0) -> 0 | H47: =IF(H$2>=Annahmen!$C$103,Annahmen!$D$103*(1+Annahmen!$B$92)^(H$4-1)*Annahmen!$E$103,0) -> 0 | I47: =IF(I$2>=Annahmen!$C$103,Annahmen!$D$103*(1+Annahmen!$B$92)^(I$4-1)*Annahmen!$E$103,0) -> 5024.3587 | J47: =IF(J$2>=Annahmen!$C$103,Annahmen!$D$103*(1+Annahmen!$B$92)^(J$4-1)*Annahmen!$E$103,0) -> 5024.3587 | ... Z47: =IF(Z$2>=Annahmen!$C$103,Annahmen!$D$103*(1+Annahmen!$B$92)^(Z$4-1)*Annahmen!$E$103,0) -> 5175.0895
A48: Vertrieb 4 | C48: =IF(C$2>=Annahmen!$C$104,Annahmen!$D$104*(1+Annahmen!$B$92)^(C$4-1)*Annahmen!$E$104,0) -> 0 | D48: =IF(D$2>=Annahmen!$C$104,Annahmen!$D$104*(1+Annahmen!$B$92)^(D$4-1)*Annahmen!$E$104,0) -> 0 | E48: =IF(E$2>=Annahmen!$C$104,Annahmen!$D$104*(1+Annahmen!$B$92)^(E$4-1)*Annahmen!$E$104,0) -> 0 | F48: =IF(F$2>=Annahmen!$C$104,Annahmen!$D$104*(1+Annahmen!$B$92)^(F$4-1)*Annahmen!$E$104,0) -> 0 | G48: =IF(G$2>=Annahmen!$C$104,Annahmen!$D$104*(1+Annahmen!$B$92)^(G$4-1)*Annahmen!$E$104,0) -> 0 | H48: =IF(H$2>=Annahmen!$C$104,Annahmen!$D$104*(1+Annahmen!$B$92)^(H$4-1)*Annahmen!$E$104,0) -> 0 | I48: =IF(I$2>=Annahmen!$C$104,Annahmen!$D$104*(1+Annahmen!$B$92)^(I$4-1)*Annahmen!$E$104,0) -> 0 | J48: =IF(J$2>=Annahmen!$C$104,Annahmen!$D$104*(1+Annahmen!$B$92)^(J$4-1)*Annahmen!$E$104,0) -> 0 | ... Z48: =IF(Z$2>=Annahmen!$C$104,Annahmen!$D$104*(1+Annahmen!$B$92)^(Z$4-1)*Annahmen!$E$104,0) -> 5719.8358
A49: Support 2 (Vollzeit) | C49: =IF(C$2>=Annahmen!$C$105,Annahmen!$D$105*(1+Annahmen!$B$92)^(C$4-1)*Annahmen!$E$105,0) -> 0 | D49: =IF(D$2>=Annahmen!$C$105,Annahmen!$D$105*(1+Annahmen!$B$92)^(D$4-1)*Annahmen!$E$105,0) -> 0 | E49: =IF(E$2>=Annahmen!$C$105,Annahmen!$D$105*(1+Annahmen!$B$92)^(E$4-1)*Annahmen!$E$105,0) -> 0 | F49: =IF(F$2>=Annahmen!$C$105,Annahmen!$D$105*(1+Annahmen!$B$92)^(F$4-1)*Annahmen!$E$105,0) -> 0 | G49: =IF(G$2>=Annahmen!$C$105,Annahmen!$D$105*(1+Annahmen!$B$92)^(G$4-1)*Annahmen!$E$105,0) -> 0 | H49: =IF(H$2>=Annahmen!$C$105,Annahmen!$D$105*(1+Annahmen!$B$92)^(H$4-1)*Annahmen!$E$105,0) -> 0 | I49: =IF(I$2>=Annahmen!$C$105,Annahmen!$D$105*(1+Annahmen!$B$92)^(I$4-1)*Annahmen!$E$105,0) -> 0 | J49: =IF(J$2>=Annahmen!$C$105,Annahmen!$D$105*(1+Annahmen!$B$92)^(J$4-1)*Annahmen!$E$105,0) -> 0 | ... Z49: =IF(Z$2>=Annahmen!$C$105,Annahmen!$D$105*(1+Annahmen!$B$92)^(Z$4-1)*Annahmen!$E$105,0) -> 4085.597
A50: Personal gesamt | C50: =SUM(C37:C49) -> 55950.268 | D50: =SUM(D37:D49) -> 55950.268 | E50: =SUM(E37:E49) -> 55950.268 | F50: =SUM(F37:F49) -> 55950.268 | G50: =SUM(G37:G49) -> 55950.268 | H50: =SUM(H37:H49) -> 55950.268 | I50: =SUM(I37:I49) -> 60974.626 | J50: =SUM(J37:J49) -> 60974.626 | ... Z50: =SUM(Z37:Z49) -> 72914.298
A51: davon Vertrieb & Marketing | C51: =SUMIF(Annahmen!$B$94:$B$105,"Vertrieb",C38:C49)+SUMIF(Annahmen!$B$94:$B$105,"Marketing",C38:C49) -> 21419.635 | D51: =SUMIF(Annahmen!$B$94:$B$105,"Vertrieb",D38:D49)+SUMIF(Annahmen!$B$94:$B$105,"Marketing",D38:D49) -> 21419.635 | E51: =SUMIF(Annahmen!$B$94:$B$105,"Vertrieb",E38:E49)+SUMIF(Annahmen!$B$94:$B$105,"Marketing",E38:E49) -> 21419.635 | F51: =SUMIF(Annahmen!$B$94:$B$105,"Vertrieb",F38:F49)+SUMIF(Annahmen!$B$94:$B$105,"Marketing",F38:F49) -> 21419.635 | G51: =SUMIF(Annahmen!$B$94:$B$105,"Vertrieb",G38:G49)+SUMIF(Annahmen!$B$94:$B$105,"Marketing",G38:G49) -> 21419.635 | H51: =SUMIF(Annahmen!$B$94:$B$105,"Vertrieb",H38:H49)+SUMIF(Annahmen!$B$94:$B$105,"Marketing",H38:H49) -> 21419.635 | I51: =SUMIF(Annahmen!$B$94:$B$105,"Vertrieb",I38:I49)+SUMIF(Annahmen!$B$94:$B$105,"Marketing",I38:I49) -> 21419.635 | J51: =SUMIF(Annahmen!$B$94:$B$105,"Vertrieb",J38:J49)+SUMIF(Annahmen!$B$94:$B$105,"Marketing",J38:J49) -> 21419.635 | ... Z51: =SUMIF(Annahmen!$B$94:$B$105,"Vertrieb",Z38:Z49)+SUMIF(Annahmen!$B$94:$B$105,"Marketing",Z38:Z49) -> 27782.059
A52: Köpfe (inkl. Gründer) | B52: ='Monat 1–36'!$AL$52 -> 8 | C52: =1+COUNTIF(Annahmen!$C$94:$C$105,"<="&C$2) -> 10 | D52: =1+COUNTIF(Annahmen!$C$94:$C$105,"<="&D$2) -> 10 | E52: =1+COUNTIF(Annahmen!$C$94:$C$105,"<="&E$2) -> 10 | F52: =1+COUNTIF(Annahmen!$C$94:$C$105,"<="&F$2) -> 10 | G52: =1+COUNTIF(Annahmen!$C$94:$C$105,"<="&G$2) -> 10 | H52: =1+COUNTIF(Annahmen!$C$94:$C$105,"<="&H$2) -> 10 | I52: =1+COUNTIF(Annahmen!$C$94:$C$105,"<="&I$2) -> 11 | J52: =1+COUNTIF(Annahmen!$C$94:$C$105,"<="&J$2) -> 11 | ... Z52: =1+COUNTIF(Annahmen!$C$94:$C$105,"<="&Z$2) -> 13
A53: Fixkosten
A54: Marketing laufend | C54: =INDEX(Annahmen!$B$63:$F$63,1,C$4) -> 8000 | D54: =INDEX(Annahmen!$B$63:$F$63,1,D$4) -> 8000 | E54: =INDEX(Annahmen!$B$63:$F$63,1,E$4) -> 8000 | F54: =INDEX(Annahmen!$B$63:$F$63,1,F$4) -> 8000 | G54: =INDEX(Annahmen!$B$63:$F$63,1,G$4) -> 8000 | H54: =INDEX(Annahmen!$B$63:$F$63,1,H$4) -> 8000 | I54: =INDEX(Annahmen!$B$63:$F$63,1,I$4) -> 8000 | J54: =INDEX(Annahmen!$B$63:$F$63,1,J$4) -> 8000 | ... Z54: =INDEX(Annahmen!$B$63:$F$63,1,Z$4) -> 10000
A55: Messen & Veranstaltungen | C55: =SUMIF(Annahmen!$B$76:$B$87,C$2,Annahmen!$C$76:$C$87) -> 0 | D55: =SUMIF(Annahmen!$B$76:$B$87,D$2,Annahmen!$C$76:$C$87) -> 0 | E55: =SUMIF(Annahmen!$B$76:$B$87,E$2,Annahmen!$C$76:$C$87) -> 10000 | F55: =SUMIF(Annahmen!$B$76:$B$87,F$2,Annahmen!$C$76:$C$87) -> 0 | G55: =SUMIF(Annahmen!$B$76:$B$87,G$2,Annahmen!$C$76:$C$87) -> 0 | H55: =SUMIF(Annahmen!$B$76:$B$87,H$2,Annahmen!$C$76:$C$87) -> 0 | I55: =SUMIF(Annahmen!$B$76:$B$87,I$2,Annahmen!$C$76:$C$87) -> 0 | J55: =SUMIF(Annahmen!$B$76:$B$87,J$2,Annahmen!$C$76:$C$87) -> 0 | ... Z55: =SUMIF(Annahmen!$B$76:$B$87,Z$2,Annahmen!$C$76:$C$87) -> 0
A56: Hosting-Grundkosten | C56: =INDEX(Annahmen!$B$62:$F$62,1,C$4) -> 800 | D56: =INDEX(Annahmen!$B$62:$F$62,1,D$4) -> 800 | E56: =INDEX(Annahmen!$B$62:$F$62,1,E$4) -> 800 | F56: =INDEX(Annahmen!$B$62:$F$62,1,F$4) -> 800 | G56: =INDEX(Annahmen!$B$62:$F$62,1,G$4) -> 800 | H56: =INDEX(Annahmen!$B$62:$F$62,1,H$4) -> 800 | I56: =INDEX(Annahmen!$B$62:$F$62,1,I$4) -> 800 | J56: =INDEX(Annahmen!$B$62:$F$62,1,J$4) -> 800 | ... Z56: =INDEX(Annahmen!$B$62:$F$62,1,Z$4) -> 1000
A57: Miete / Coworking | C57: =INDEX(Annahmen!$B$64:$F$64,1,C$4) -> 2200 | D57: =INDEX(Annahmen!$B$64:$F$64,1,D$4) -> 2200 | E57: =INDEX(Annahmen!$B$64:$F$64,1,E$4) -> 2200 | F57: =INDEX(Annahmen!$B$64:$F$64,1,F$4) -> 2200 | G57: =INDEX(Annahmen!$B$64:$F$64,1,G$4) -> 2200 | H57: =INDEX(Annahmen!$B$64:$F$64,1,H$4) -> 2200 | I57: =INDEX(Annahmen!$B$64:$F$64,1,I$4) -> 2200 | J57: =INDEX(Annahmen!$B$64:$F$64,1,J$4) -> 2200 | ... Z57: =INDEX(Annahmen!$B$64:$F$64,1,Z$4) -> 2800
A58: Versicherungen | C58: =INDEX(Annahmen!$B$65:$F$65,1,C$4) -> 300 | D58: =INDEX(Annahmen!$B$65:$F$65,1,D$4) -> 300 | E58: =INDEX(Annahmen!$B$65:$F$65,1,E$4) -> 300 | F58: =INDEX(Annahmen!$B$65:$F$65,1,F$4) -> 300 | G58: =INDEX(Annahmen!$B$65:$F$65,1,G$4) -> 300 | H58: =INDEX(Annahmen!$B$65:$F$65,1,H$4) -> 300 | I58: =INDEX(Annahmen!$B$65:$F$65,1,I$4) -> 300 | J58: =INDEX(Annahmen!$B$65:$F$65,1,J$4) -> 300 | ... Z58: =INDEX(Annahmen!$B$65:$F$65,1,Z$4) -> 380
A59: Steuerberatung/Buchhaltung | C59: =INDEX(Annahmen!$B$66:$F$66,1,C$4) -> 1000 | D59: =INDEX(Annahmen!$B$66:$F$66,1,D$4) -> 1000 | E59: =INDEX(Annahmen!$B$66:$F$66,1,E$4) -> 1000 | F59: =INDEX(Annahmen!$B$66:$F$66,1,F$4) -> 1000 | G59: =INDEX(Annahmen!$B$66:$F$66,1,G$4) -> 1000 | H59: =INDEX(Annahmen!$B$66:$F$66,1,H$4) -> 1000 | I59: =INDEX(Annahmen!$B$66:$F$66,1,I$4) -> 1000 | J59: =INDEX(Annahmen!$B$66:$F$66,1,J$4) -> 1000 | ... Z59: =INDEX(Annahmen!$B$66:$F$66,1,Z$4) -> 1200
A60: Recht & Datenschutz | C60: =INDEX(Annahmen!$B$67:$F$67,1,C$4) -> 550 | D60: =INDEX(Annahmen!$B$67:$F$67,1,D$4) -> 550 | E60: =INDEX(Annahmen!$B$67:$F$67,1,E$4) -> 550 | F60: =INDEX(Annahmen!$B$67:$F$67,1,F$4) -> 550 | G60: =INDEX(Annahmen!$B$67:$F$67,1,G$4) -> 550 | H60: =INDEX(Annahmen!$B$67:$F$67,1,H$4) -> 550 | I60: =INDEX(Annahmen!$B$67:$F$67,1,I$4) -> 550 | J60: =INDEX(Annahmen!$B$67:$F$67,1,J$4) -> 550 | ... Z60: =INDEX(Annahmen!$B$67:$F$67,1,Z$4) -> 600
A61: Reisekosten/Fahrzeug | C61: =INDEX(Annahmen!$B$68:$F$68,1,C$4) -> 1600 | D61: =INDEX(Annahmen!$B$68:$F$68,1,D$4) -> 1600 | E61: =INDEX(Annahmen!$B$68:$F$68,1,E$4) -> 1600 | F61: =INDEX(Annahmen!$B$68:$F$68,1,F$4) -> 1600 | G61: =INDEX(Annahmen!$B$68:$F$68,1,G$4) -> 1600 | H61: =INDEX(Annahmen!$B$68:$F$68,1,H$4) -> 1600 | I61: =INDEX(Annahmen!$B$68:$F$68,1,I$4) -> 1600 | J61: =INDEX(Annahmen!$B$68:$F$68,1,J$4) -> 1600 | ... Z61: =INDEX(Annahmen!$B$68:$F$68,1,Z$4) -> 2000
A62: Sonstiges | C62: =INDEX(Annahmen!$B$69:$F$69,1,C$4) -> 400 | D62: =INDEX(Annahmen!$B$69:$F$69,1,D$4) -> 400 | E62: =INDEX(Annahmen!$B$69:$F$69,1,E$4) -> 400 | F62: =INDEX(Annahmen!$B$69:$F$69,1,F$4) -> 400 | G62: =INDEX(Annahmen!$B$69:$F$69,1,G$4) -> 400 | H62: =INDEX(Annahmen!$B$69:$F$69,1,H$4) -> 400 | I62: =INDEX(Annahmen!$B$69:$F$69,1,I$4) -> 400 | J62: =INDEX(Annahmen!$B$69:$F$69,1,J$4) -> 400 | ... Z62: =INDEX(Annahmen!$B$69:$F$69,1,Z$4) -> 500
A63: Software-Werkzeuge | C63: =Annahmen!$B$70+Annahmen!$B$71*C52 -> 550 | D63: =Annahmen!$B$70+Annahmen!$B$71*D52 -> 550 | E63: =Annahmen!$B$70+Annahmen!$B$71*E52 -> 550 | F63: =Annahmen!$B$70+Annahmen!$B$71*F52 -> 550 | G63: =Annahmen!$B$70+Annahmen!$B$71*G52 -> 550 | H63: =Annahmen!$B$70+Annahmen!$B$71*H52 -> 550 | I63: =Annahmen!$B$70+Annahmen!$B$71*I52 -> 590 | J63: =Annahmen!$B$70+Annahmen!$B$71*J52 -> 590 | ... Z63: =Annahmen!$B$70+Annahmen!$B$71*Z52 -> 670
A64: Ausstattung Neueinstellungen | C64: =MAX(0,C52-B52)*Annahmen!$B$72 -> 3600 | D64: =MAX(0,D52-C52)*Annahmen!$B$72 -> 0 | E64: =MAX(0,E52-D52)*Annahmen!$B$72 -> 0 | F64: =MAX(0,F52-E52)*Annahmen!$B$72 -> 0 | G64: =MAX(0,G52-F52)*Annahmen!$B$72 -> 0 | H64: =MAX(0,H52-G52)*Annahmen!$B$72 -> 0 | I64: =MAX(0,I52-H52)*Annahmen!$B$72 -> 1800 | J64: =MAX(0,J52-I52)*Annahmen!$B$72 -> 0 | ... Z64: =MAX(0,Z52-Y52)*Annahmen!$B$72 -> 0
A65: Einmalkosten Gründung | C65: =IF(C$2=1,Annahmen!$B$73,0) -> 0 | D65: =IF(D$2=1,Annahmen!$B$73,0) -> 0 | E65: =IF(E$2=1,Annahmen!$B$73,0) -> 0 | F65: =IF(F$2=1,Annahmen!$B$73,0) -> 0 | G65: =IF(G$2=1,Annahmen!$B$73,0) -> 0 | H65: =IF(H$2=1,Annahmen!$B$73,0) -> 0 | I65: =IF(I$2=1,Annahmen!$B$73,0) -> 0 | J65: =IF(J$2=1,Annahmen!$B$73,0) -> 0 | ... Z65: =IF(Z$2=1,Annahmen!$B$73,0) -> 0
A66: Fixkosten ohne Personal | C66: =SUM(C54:C65) -> 19000 | D66: =SUM(D54:D65) -> 15400 | E66: =SUM(E54:E65) -> 25400 | F66: =SUM(F54:F65) -> 15400 | G66: =SUM(G54:G65) -> 15400 | H66: =SUM(H54:H65) -> 15400 | I66: =SUM(I54:I65) -> 17240 | J66: =SUM(J54:J65) -> 15440 | ... Z66: =SUM(Z54:Z65) -> 19150
A67: Fixkosten gesamt (inkl. Personal) | C67: =C50+C66 -> 74950.268 | D67: =D50+D66 -> 71350.268 | E67: =E50+E66 -> 81350.268 | F67: =F50+F66 -> 71350.268 | G67: =G50+G66 -> 71350.268 | H67: =H50+H66 -> 71350.268 | I67: =I50+I66 -> 78214.626 | J67: =J50+J66 -> 76414.626 | ... Z67: =Z50+Z66 -> 92064.298
A68: Ergebnis
A69: Kosten gesamt | C69: =C34+C67 -> 81910.519 | D69: =D34+D67 -> 78638.936 | E69: =E34+E67 -> 88961.182 | F69: =F34+F67 -> 79277.386 | G69: =G34+G67 -> 79587.675 | H69: =H34+H67 -> 79892.173 | I69: =I34+I67 -> 87055.359 | J69: =J34+J67 -> 85548.634 | ... Z69: =Z34+Z67 -> 108378.17
A70: EBITDA | C70: =C26-C69 -> -4997.5913 | D70: =D26-D69 -> 1971.8073 | E70: =E26-E69 -> -4721.3656 | F70: =F26-F69 -> 8524.1875 | G70: =G26-G69 -> 11709.735 | H70: =H26-H69 -> 14836.515 | I70: =I26-I69 -> 11041.38 | J70: =J26-J69 -> 15854.232 | ... Z70: =Z26-Z69 -> 51198.954
A71: Finanzierung und Liquidität
A72: Einzahlung Eigenkapital | C72: =IF(C$2=Annahmen!$B$109,Annahmen!$B$108,0) -> 0 | D72: =IF(D$2=Annahmen!$B$109,Annahmen!$B$108,0) -> 0 | E72: =IF(E$2=Annahmen!$B$109,Annahmen!$B$108,0) -> 0 | F72: =IF(F$2=Annahmen!$B$109,Annahmen!$B$108,0) -> 0 | G72: =IF(G$2=Annahmen!$B$109,Annahmen!$B$108,0) -> 0 | H72: =IF(H$2=Annahmen!$B$109,Annahmen!$B$108,0) -> 0 | I72: =IF(I$2=Annahmen!$B$109,Annahmen!$B$108,0) -> 0 | J72: =IF(J$2=Annahmen!$B$109,Annahmen!$B$108,0) -> 0 | ... Z72: =IF(Z$2=Annahmen!$B$109,Annahmen!$B$108,0) -> 0
A73: Auszahlung KfW-Kredit | C73: =IF(C$2=Annahmen!$B$111,Annahmen!$B$110,0) -> 0 | D73: =IF(D$2=Annahmen!$B$111,Annahmen!$B$110,0) -> 0 | E73: =IF(E$2=Annahmen!$B$111,Annahmen!$B$110,0) -> 0 | F73: =IF(F$2=Annahmen!$B$111,Annahmen!$B$110,0) -> 0 | G73: =IF(G$2=Annahmen!$B$111,Annahmen!$B$110,0) -> 0 | H73: =IF(H$2=Annahmen!$B$111,Annahmen!$B$110,0) -> 0 | I73: =IF(I$2=Annahmen!$B$111,Annahmen!$B$110,0) -> 0 | J73: =IF(J$2=Annahmen!$B$111,Annahmen!$B$110,0) -> 0 | ... Z73: =IF(Z$2=Annahmen!$B$111,Annahmen!$B$110,0) -> 0
A74: Business Angel / Pre-Seed | C74: =IF(C$2=Annahmen!$B$116,Annahmen!$B$115,0) -> 0 | D74: =IF(D$2=Annahmen!$B$116,Annahmen!$B$115,0) -> 0 | E74: =IF(E$2=Annahmen!$B$116,Annahmen!$B$115,0) -> 0 | F74: =IF(F$2=Annahmen!$B$116,Annahmen!$B$115,0) -> 0 | G74: =IF(G$2=Annahmen!$B$116,Annahmen!$B$115,0) -> 0 | H74: =IF(H$2=Annahmen!$B$116,Annahmen!$B$115,0) -> 0 | I74: =IF(I$2=Annahmen!$B$116,Annahmen!$B$115,0) -> 0 | J74: =IF(J$2=Annahmen!$B$116,Annahmen!$B$115,0) -> 0 | ... Z74: =IF(Z$2=Annahmen!$B$116,Annahmen!$B$115,0) -> 0
A75: Gründungszuschuss / Förderung | C75: =IF(C$2<=6,Annahmen!$B$117,IF(C$2<=15,Annahmen!$B$118,0)) -> 0 | D75: =IF(D$2<=6,Annahmen!$B$117,IF(D$2<=15,Annahmen!$B$118,0)) -> 0 | E75: =IF(E$2<=6,Annahmen!$B$117,IF(E$2<=15,Annahmen!$B$118,0)) -> 0 | F75: =IF(F$2<=6,Annahmen!$B$117,IF(F$2<=15,Annahmen!$B$118,0)) -> 0 | G75: =IF(G$2<=6,Annahmen!$B$117,IF(G$2<=15,Annahmen!$B$118,0)) -> 0 | H75: =IF(H$2<=6,Annahmen!$B$117,IF(H$2<=15,Annahmen!$B$118,0)) -> 0 | I75: =IF(I$2<=6,Annahmen!$B$117,IF(I$2<=15,Annahmen!$B$118,0)) -> 0 | J75: =IF(J$2<=6,Annahmen!$B$117,IF(J$2<=15,Annahmen!$B$118,0)) -> 0 | ... Z75: =IF(Z$2<=6,Annahmen!$B$117,IF(Z$2<=15,Annahmen!$B$118,0)) -> 0
A76: Zinsen KfW-Kredit | C76: =(B78+C73)*Annahmen!$B$112/12 -> 364.58333 | D76: =(C78+D73)*Annahmen!$B$112/12 -> 360.24306 | E76: =(D78+E73)*Annahmen!$B$112/12 -> 355.90278 | F76: =(E78+F73)*Annahmen!$B$112/12 -> 351.5625 | G76: =(F78+G73)*Annahmen!$B$112/12 -> 347.22222 | H76: =(G78+H73)*Annahmen!$B$112/12 -> 342.88194 | I76: =(H78+I73)*Annahmen!$B$112/12 -> 338.54167 | J76: =(I78+J73)*Annahmen!$B$112/12 -> 334.20139 | ... Z76: =(Y78+Z73)*Annahmen!$B$112/12 -> 264.75694
A77: Tilgung KfW-Kredit | C77: =IF(C$2>Annahmen!$B$111-1+Annahmen!$B$113,MIN(B78,Annahmen!$B$110/(Annahmen!$B$114-Annahmen!$B$113)),0) -> 1302.0833 | D77: =IF(D$2>Annahmen!$B$111-1+Annahmen!$B$113,MIN(C78,Annahmen!$B$110/(Annahmen!$B$114-Annahmen!$B$113)),0) -> 1302.0833 | E77: =IF(E$2>Annahmen!$B$111-1+Annahmen!$B$113,MIN(D78,Annahmen!$B$110/(Annahmen!$B$114-Annahmen!$B$113)),0) -> 1302.0833 | F77: =IF(F$2>Annahmen!$B$111-1+Annahmen!$B$113,MIN(E78,Annahmen!$B$110/(Annahmen!$B$114-Annahmen!$B$113)),0) -> 1302.0833 | G77: =IF(G$2>Annahmen!$B$111-1+Annahmen!$B$113,MIN(F78,Annahmen!$B$110/(Annahmen!$B$114-Annahmen!$B$113)),0) -> 1302.0833 | H77: =IF(H$2>Annahmen!$B$111-1+Annahmen!$B$113,MIN(G78,Annahmen!$B$110/(Annahmen!$B$114-Annahmen!$B$113)),0) -> 1302.0833 | I77: =IF(I$2>Annahmen!$B$111-1+Annahmen!$B$113,MIN(H78,Annahmen!$B$110/(Annahmen!$B$114-Annahmen!$B$113)),0) -> 1302.0833 | J77: =IF(J$2>Annahmen!$B$111-1+Annahmen!$B$113,MIN(I78,Annahmen!$B$110/(Annahmen!$B$114-Annahmen!$B$113)),0) -> 1302.0833 | ... Z77: =IF(Z$2>Annahmen!$B$111-1+Annahmen!$B$113,MIN(Y78,Annahmen!$B$110/(Annahmen!$B$114-Annahmen!$B$113)),0) -> 1302.0833
A78: KfW-Restschuld (Monatsende) | B78: ='Monat 1–36'!$AL$78 -> 109375 | C78: =B78+C73-C77 -> 108072.92 | D78: =C78+D73-D77 -> 106770.83 | E78: =D78+E73-E77 -> 105468.75 | F78: =E78+F73-F77 -> 104166.67 | G78: =F78+G73-G77 -> 102864.58 | H78: =G78+H73-H77 -> 101562.5 | I78: =H78+I73-I77 -> 100260.42 | J78: =I78+J73-J77 -> 98958.333 | ... Z78: =Y78+Z73-Z77 -> 78125
A79: Ergebnis vor Steuern (EBITDA − Zinsen) | C79: =C70-C76 -> -5362.1747 | D79: =D70-D76 -> 1611.5642 | E79: =E70-E76 -> -5077.2684 | F79: =F70-F76 -> 8172.625 | G79: =G70-G76 -> 11362.512 | H79: =H70-H76 -> 14493.633 | I79: =I70-I76 -> 10702.838 | J79: =J70-J76 -> 15520.03 | ... Z79: =Z70-Z76 -> 50934.197
A80: Steuerzahlung (Vorjahressteuer im Juni) | C80: =IF(AND(MOD(C$2,12)=6,C$2>12),INDEX('5 Jahre'!$B$46:$F$46,1,C$4-1),0) -> 0 | D80: =IF(AND(MOD(D$2,12)=6,D$2>12),INDEX('5 Jahre'!$B$46:$F$46,1,D$4-1),0) -> 0 | E80: =IF(AND(MOD(E$2,12)=6,E$2>12),INDEX('5 Jahre'!$B$46:$F$46,1,E$4-1),0) -> 0 | F80: =IF(AND(MOD(F$2,12)=6,F$2>12),INDEX('5 Jahre'!$B$46:$F$46,1,F$4-1),0) -> 0 | G80: =IF(AND(MOD(G$2,12)=6,G$2>12),INDEX('5 Jahre'!$B$46:$F$46,1,G$4-1),0) -> 0 | H80: =IF(AND(MOD(H$2,12)=6,H$2>12),INDEX('5 Jahre'!$B$46:$F$46,1,H$4-1),0) -> 0 | I80: =IF(AND(MOD(I$2,12)=6,I$2>12),INDEX('5 Jahre'!$B$46:$F$46,1,I$4-1),0) -> 0 | J80: =IF(AND(MOD(J$2,12)=6,J$2>12),INDEX('5 Jahre'!$B$46:$F$46,1,J$4-1),0) -> 0 | ... Z80: =IF(AND(MOD(Z$2,12)=6,Z$2>12),INDEX('5 Jahre'!$B$46:$F$46,1,Z$4-1),0) -> 0
A81: Cashflow gesamt | C81: =C70-C76-C77-C80+C72+C73+C74+C75 -> -6664.258 | D81: =D70-D76-D77-D80+D72+D73+D74+D75 -> 309.48091 | E81: =E70-E76-E77-E80+E72+E73+E74+E75 -> -6379.3517 | F81: =F70-F76-F77-F80+F72+F73+F74+F75 -> 6870.5417 | G81: =G70-G76-G77-G80+G72+G73+G74+G75 -> 10060.429 | H81: =H70-H76-H77-H80+H72+H73+H74+H75 -> 13191.549 | I81: =I70-I76-I77-I80+I72+I73+I74+I75 -> 9400.7551 | J81: =J70-J76-J77-J80+J72+J73+J74+J75 -> 14217.947 | ... Z81: =Z70-Z76-Z77-Z80+Z72+Z73+Z74+Z75 -> 49632.114
A82: Kasse (Monatsende) | B82: ='Monat 1–36'!$AL$82 -> 82140.558 | C82: =B82+C81 -> 75476.3 | D82: =C82+D81 -> 75785.781 | E82: =D82+E81 -> 69406.429 | F82: =E82+F81 -> 76276.971 | G82: =F82+G81 -> 86337.4 | H82: =G82+H81 -> 99528.949 | I82: =H82+I81 -> 108929.7 | J82: =I82+J81 -> 123147.65 | ... Z82: =Y82+Z81 -> 545886.07
A83: Kumulierter Cashflow ohne Finanzierung | B83: ='Monat 1–36'!$AL$83 -> -267859.44 | C83: =B83+C70-C76-C77-C80 -> -274523.7 | D83: =C83+D70-D76-D77-D80 -> -274214.22 | E83: =D83+E70-E76-E77-E80 -> -280593.57 | F83: =E83+F70-F76-F77-F80 -> -273723.03 | G83: =F83+G70-G76-G77-G80 -> -263662.6 | H83: =G83+H70-H76-H77-H80 -> -250471.05 | I83: =H83+I70-I76-I77-I80 -> -241070.3 | J83: =I83+J70-J76-J77-J80 -> -226852.35 | ... Z83: =Y83+Z70-Z76-Z77-Z80 -> 195886.07
A84: Hilfszeile: Monat mit EBITDA ≥ 0 (sonst 999) | C84: =IF(C70>=0,C$2,999) -> 999 | D84: =IF(D70>=0,D$2,999) -> 38 | E84: =IF(E70>=0,E$2,999) -> 999 | F84: =IF(F70>=0,F$2,999) -> 40 | G84: =IF(G70>=0,G$2,999) -> 41 | H84: =IF(H70>=0,H$2,999) -> 42 | I84: =IF(I70>=0,I$2,999) -> 43 | J84: =IF(J70>=0,J$2,999) -> 44 | ... Z84: =IF(Z70>=0,Z$2,999) -> 60
A85: Hilfszeile: Monat mit EBITDA < 0 (sonst 0) | C85: =IF(C70<0,C$2,0) -> 37 | D85: =IF(D70<0,D$2,0) -> 0 | E85: =IF(E70<0,E$2,0) -> 39 | F85: =IF(F70<0,F$2,0) -> 0 | G85: =IF(G70<0,G$2,0) -> 0 | H85: =IF(H70<0,H$2,0) -> 0 | I85: =IF(I70<0,I$2,0) -> 0 | J85: =IF(J70<0,J$2,0) -> 0 | ... Z85: =IF(Z70<0,Z$2,0) -> 0
A86: Hilfszeile: kum. Cashflow ≥ 0 nach Tiefpunkt (sonst 999) | C86: =IF(AND(C83>=0,C$2>1),C$2,999) -> 999 | D86: =IF(AND(D83>=0,D$2>1),D$2,999) -> 999 | E86: =IF(AND(E83>=0,E$2>1),E$2,999) -> 999 | F86: =IF(AND(F83>=0,F$2>1),F$2,999) -> 999 | G86: =IF(AND(G83>=0,G$2>1),G$2,999) -> 999 | H86: =IF(AND(H83>=0,H$2>1),H$2,999) -> 999 | I86: =IF(AND(I83>=0,I$2>1),I$2,999) -> 999 | J86: =IF(AND(J83>=0,J$2>1),J$2,999) -> 999 | ... Z86: =IF(AND(Z83>=0,Z$2>1),Z$2,999) -> 60

Sheet 5 Jahre
A1: LADEKLAR – GuV-Übersicht 5 Jahre
A3: Kennzahl | B3: Jahr 1 | C3: Jahr 2 | D3: Jahr 3 | E3: Jahr 4 | F3: Jahr 5
A4: Kalenderjahr | B4: =YEAR(Annahmen!$B$6)+0 -> 2027 | C4: =YEAR(Annahmen!$B$6)+1 -> 2028 | D4: =YEAR(Annahmen!$B$6)+2 -> 2029 | E4: =YEAR(Annahmen!$B$6)+3 -> 2030 | F4: =YEAR(Annahmen!$B$6)+4 -> 2031
A5: Modelljahr | B5: 1 | C5: 2 | D5: 3 | E5: 4 | F5: 5
A6: Kunden
A7: Kunden Start (Jahresende) | B7: =IF(B$5<=3,INDEX('Monat 1–36'!$C$10:$AL$10,1,B$5*12),INDEX('Monat 37–60'!$C$10:$Z$10,1,B$5*12-36)) -> 41.748685 | C7: =IF(C$5<=3,INDEX('Monat 1–36'!$C$10:$AL$10,1,C$5*12),INDEX('Monat 37–60'!$C$10:$Z$10,1,C$5*12-36)) -> 143.55064 | D7: =IF(D$5<=3,INDEX('Monat 1–36'!$C$10:$AL$10,1,D$5*12),INDEX('Monat 37–60'!$C$10:$Z$10,1,D$5*12-36)) -> 278.84198 | E7: =IF(E$5<=3,INDEX('Monat 1–36'!$C$10:$AL$10,1,E$5*12),INDEX('Monat 37–60'!$C$10:$Z$10,1,E$5*12-36)) -> 423.09061 | F7: =IF(F$5<=3,INDEX('Monat 1–36'!$C$10:$AL$10,1,F$5*12),INDEX('Monat 37–60'!$C$10:$Z$10,1,F$5*12-36)) -> 574.20269
A8: Kunden Flotte (Jahresende) | B8: =IF(B$5<=3,INDEX('Monat 1–36'!$C$11:$AL$11,1,B$5*12),INDEX('Monat 37–60'!$C$11:$Z$11,1,B$5*12-36)) -> 33.097526 | C8: =IF(C$5<=3,INDEX('Monat 1–36'!$C$11:$AL$11,1,C$5*12),INDEX('Monat 37–60'!$C$11:$Z$11,1,C$5*12-36)) -> 117.19886 | D8: =IF(D$5<=3,INDEX('Monat 1–36'!$C$11:$AL$11,1,D$5*12),INDEX('Monat 37–60'!$C$11:$Z$11,1,D$5*12-36)) -> 235.13214 | E8: =IF(E$5<=3,INDEX('Monat 1–36'!$C$11:$AL$11,1,E$5*12),INDEX('Monat 37–60'!$C$11:$Z$11,1,E$5*12-36)) -> 368.57932 | F8: =IF(F$5<=3,INDEX('Monat 1–36'!$C$11:$AL$11,1,F$5*12),INDEX('Monat 37–60'!$C$11:$Z$11,1,F$5*12-36)) -> 514.20138
A9: Kunden Premium (Jahresende) | B9: =IF(B$5<=3,INDEX('Monat 1–36'!$C$12:$AL$12,1,B$5*12),INDEX('Monat 37–60'!$C$12:$Z$12,1,B$5*12-36)) -> 10.81714 | C9: =IF(C$5<=3,INDEX('Monat 1–36'!$C$12:$AL$12,1,C$5*12),INDEX('Monat 37–60'!$C$12:$Z$12,1,C$5*12-36)) -> 39.272951 | D9: =IF(D$5<=3,INDEX('Monat 1–36'!$C$12:$AL$12,1,D$5*12),INDEX('Monat 37–60'!$C$12:$Z$12,1,D$5*12-36)) -> 81.043962 | E9: =IF(E$5<=3,INDEX('Monat 1–36'!$C$12:$AL$12,1,E$5*12),INDEX('Monat 37–60'!$C$12:$Z$12,1,E$5*12-36)) -> 130.80362 | F9: =IF(F$5<=3,INDEX('Monat 1–36'!$C$12:$AL$12,1,F$5*12),INDEX('Monat 37–60'!$C$12:$Z$12,1,F$5*12-36)) -> 187.339
A10: Kunden gesamt (Jahresende) | B10: =IF(B$5<=3,INDEX('Monat 1–36'!$C$13:$AL$13,1,B$5*12),INDEX('Monat 37–60'!$C$13:$Z$13,1,B$5*12-36)) -> 85.663351 | C10: =IF(C$5<=3,INDEX('Monat 1–36'!$C$13:$AL$13,1,C$5*12),INDEX('Monat 37–60'!$C$13:$Z$13,1,C$5*12-36)) -> 300.02244 | D10: =IF(D$5<=3,INDEX('Monat 1–36'!$C$13:$AL$13,1,D$5*12),INDEX('Monat 37–60'!$C$13:$Z$13,1,D$5*12-36)) -> 595.01808 | E10: =IF(E$5<=3,INDEX('Monat 1–36'!$C$13:$AL$13,1,E$5*12),INDEX('Monat 37–60'!$C$13:$Z$13,1,E$5*12-36)) -> 922.47355 | F10: =IF(F$5<=3,INDEX('Monat 1–36'!$C$13:$AL$13,1,F$5*12),INDEX('Monat 37–60'!$C$13:$Z$13,1,F$5*12-36)) -> 1275.7431
A11: Neukunden im Jahr | B11: =SUMIF('Monat 1–36'!$C$4:$AL$4,B$5,'Monat 1–36'!$C$6:$AL$6)+SUMIF('Monat 37–60'!$C$4:$Z$4,B$5,'Monat 37–60'!$C$6:$Z$6) -> 90 | C11: =SUMIF('Monat 1–36'!$C$4:$AL$4,C$5,'Monat 1–36'!$C$6:$AL$6)+SUMIF('Monat 37–60'!$C$4:$Z$4,C$5,'Monat 37–60'!$C$6:$Z$6) -> 264 | D11: =SUMIF('Monat 1–36'!$C$4:$AL$4,D$5,'Monat 1–36'!$C$6:$AL$6)+SUMIF('Monat 37–60'!$C$4:$Z$4,D$5,'Monat 37–60'!$C$6:$Z$6) -> 417 | E11: =SUMIF('Monat 1–36'!$C$4:$AL$4,E$5,'Monat 1–36'!$C$6:$AL$6)+SUMIF('Monat 37–60'!$C$4:$Z$4,E$5,'Monat 37–60'!$C$6:$Z$6) -> 540 | F11: =SUMIF('Monat 1–36'!$C$4:$AL$4,F$5,'Monat 1–36'!$C$6:$AL$6)+SUMIF('Monat 37–60'!$C$4:$Z$4,F$5,'Monat 37–60'!$C$6:$Z$6) -> 660
A12: Kündigungen im Jahr | B12: =SUMIF('Monat 1–36'!$C$4:$AL$4,B$5,'Monat 1–36'!$C$14:$AL$14)+SUMIF('Monat 37–60'!$C$4:$Z$4,B$5,'Monat 37–60'!$C$14:$Z$14) -> 9.3366494 | C12: =SUMIF('Monat 1–36'!$C$4:$AL$4,C$5,'Monat 1–36'!$C$14:$AL$14)+SUMIF('Monat 37–60'!$C$4:$Z$4,C$5,'Monat 37–60'!$C$14:$Z$14) -> 49.640906 | D12: =SUMIF('Monat 1–36'!$C$4:$AL$4,D$5,'Monat 1–36'!$C$14:$AL$14)+SUMIF('Monat 37–60'!$C$4:$Z$4,D$5,'Monat 37–60'!$C$14:$Z$14) -> 122.00436 | E12: =SUMIF('Monat 1–36'!$C$4:$AL$4,E$5,'Monat 1–36'!$C$14:$AL$14)+SUMIF('Monat 37–60'!$C$4:$Z$4,E$5,'Monat 37–60'!$C$14:$Z$14) -> 212.54453 | F12: =SUMIF('Monat 1–36'!$C$4:$AL$4,F$5,'Monat 1–36'!$C$14:$AL$14)+SUMIF('Monat 37–60'!$C$4:$Z$4,F$5,'Monat 37–60'!$C$14:$Z$14) -> 306.73048
A13: Jahres-Churn (Kündigungen / Ø Kunden) | B13: =IF((B10+'Monat 1–36'!$B$13)>0,B12/((B10+'Monat 1–36'!$B$13)/2),0) -> 0.20596304 | C13: =IF((C10+B10)>0,C12/((C10+B10)/2),0) -> 0.2574163 | D13: =IF((D10+C10)>0,D12/((D10+C10)/2),0) -> 0.2726231 | E13: =IF((E10+D10)>0,E12/((E10+D10)/2),0) -> 0.28012613 | F13: =IF((F10+E10)>0,F12/((F10+E10)/2),0) -> 0.27907212
A14: Store-Apps aktiv (Jahresende) | B14: =IF(B$5<=3,INDEX('Monat 1–36'!$C$16:$AL$16,1,B$5*12),INDEX('Monat 37–60'!$C$16:$Z$16,1,B$5*12-36)) -> 2.1634279 | C14: =IF(C$5<=3,INDEX('Monat 1–36'!$C$16:$AL$16,1,C$5*12),INDEX('Monat 37–60'!$C$16:$Z$16,1,C$5*12-36)) -> 7.8545901 | D14: =IF(D$5<=3,INDEX('Monat 1–36'!$C$16:$AL$16,1,D$5*12),INDEX('Monat 37–60'!$C$16:$Z$16,1,D$5*12-36)) -> 16.208792 | E14: =IF(E$5<=3,INDEX('Monat 1–36'!$C$16:$AL$16,1,E$5*12),INDEX('Monat 37–60'!$C$16:$Z$16,1,E$5*12-36)) -> 26.160724 | F14: =IF(F$5<=3,INDEX('Monat 1–36'!$C$16:$AL$16,1,F$5*12),INDEX('Monat 37–60'!$C$16:$Z$16,1,F$5*12-36)) -> 37.467799
A15: Nötige Testzugänge im Jahr | B15: =SUMIF('Monat 1–36'!$C$4:$AL$4,B$5,'Monat 1–36'!$C$17:$AL$17)+SUMIF('Monat 37–60'!$C$4:$Z$4,B$5,'Monat 37–60'!$C$17:$Z$17) -> 257.14286 | C15: =SUMIF('Monat 1–36'!$C$4:$AL$4,C$5,'Monat 1–36'!$C$17:$AL$17)+SUMIF('Monat 37–60'!$C$4:$Z$4,C$5,'Monat 37–60'!$C$17:$Z$17) -> 754.28571 | D15: =SUMIF('Monat 1–36'!$C$4:$AL$4,D$5,'Monat 1–36'!$C$17:$AL$17)+SUMIF('Monat 37–60'!$C$4:$Z$4,D$5,'Monat 37–60'!$C$17:$Z$17) -> 1191.4286 | E15: =SUMIF('Monat 1–36'!$C$4:$AL$4,E$5,'Monat 1–36'!$C$17:$AL$17)+SUMIF('Monat 37–60'!$C$4:$Z$4,E$5,'Monat 37–60'!$C$17:$Z$17) -> 1542.8571 | F15: =SUMIF('Monat 1–36'!$C$4:$AL$4,F$5,'Monat 1–36'!$C$17:$AL$17)+SUMIF('Monat 37–60'!$C$4:$Z$4,F$5,'Monat 37–60'!$C$17:$Z$17) -> 1885.7143
A16: Umsatz
A17: MRR im Dezember | B17: =IF(B$5<=3,INDEX('Monat 1–36'!$C$23:$AL$23,1,B$5*12),INDEX('Monat 37–60'!$C$23:$Z$23,1,B$5*12-36)) -> 10435.809 | C17: =IF(C$5<=3,INDEX('Monat 1–36'!$C$23:$AL$23,1,C$5*12),INDEX('Monat 37–60'!$C$23:$Z$23,1,C$5*12-36)) -> 37081.627 | D17: =IF(D$5<=3,INDEX('Monat 1–36'!$C$23:$AL$23,1,D$5*12),INDEX('Monat 37–60'!$C$23:$Z$23,1,D$5*12-36)) -> 74732.324 | E17: =IF(E$5<=3,INDEX('Monat 1–36'!$C$23:$AL$23,1,E$5*12),INDEX('Monat 37–60'!$C$23:$Z$23,1,E$5*12-36)) -> 117772.56 | F17: =IF(F$5<=3,INDEX('Monat 1–36'!$C$23:$AL$23,1,F$5*12),INDEX('Monat 37–60'!$C$23:$Z$23,1,F$5*12-36)) -> 165210.87
A18: ARR zum Jahresende (MRR Dez. × 12) | B18: =IF(B$5<=3,INDEX('Monat 1–36'!$C$27:$AL$27,1,B$5*12),INDEX('Monat 37–60'!$C$27:$Z$27,1,B$5*12-36)) -> 125229.7 | C18: =IF(C$5<=3,INDEX('Monat 1–36'!$C$27:$AL$27,1,C$5*12),INDEX('Monat 37–60'!$C$27:$Z$27,1,C$5*12-36)) -> 444979.52 | D18: =IF(D$5<=3,INDEX('Monat 1–36'!$C$27:$AL$27,1,D$5*12),INDEX('Monat 37–60'!$C$27:$Z$27,1,D$5*12-36)) -> 896787.89 | E18: =IF(E$5<=3,INDEX('Monat 1–36'!$C$27:$AL$27,1,E$5*12),INDEX('Monat 37–60'!$C$27:$Z$27,1,E$5*12-36)) -> 1413270.7 | F18: =IF(F$5<=3,INDEX('Monat 1–36'!$C$27:$AL$27,1,F$5*12),INDEX('Monat 37–60'!$C$27:$Z$27,1,F$5*12-36)) -> 1982530.4
A19: ARPA im Dezember | B19: =IF(B$5<=3,INDEX('Monat 1–36'!$C$28:$AL$28,1,B$5*12),INDEX('Monat 37–60'!$C$28:$Z$28,1,B$5*12-36)) -> 121.82349 | C19: =IF(C$5<=3,INDEX('Monat 1–36'!$C$28:$AL$28,1,C$5*12),INDEX('Monat 37–60'!$C$28:$Z$28,1,C$5*12-36)) -> 123.59618 | D19: =IF(D$5<=3,INDEX('Monat 1–36'!$C$28:$AL$28,1,D$5*12),INDEX('Monat 37–60'!$C$28:$Z$28,1,D$5*12-36)) -> 125.59673 | E19: =IF(E$5<=3,INDEX('Monat 1–36'!$C$28:$AL$28,1,E$5*12),INDEX('Monat 37–60'!$C$28:$Z$28,1,E$5*12-36)) -> 127.67039 | F19: =IF(F$5<=3,INDEX('Monat 1–36'!$C$28:$AL$28,1,F$5*12),INDEX('Monat 37–60'!$C$28:$Z$28,1,F$5*12-36)) -> 129.50168
A20: Abo-Umsatz (nach Jahreszahler-Rabatt) | B20: =SUMIF('Monat 1–36'!$C$4:$AL$4,B$5,'Monat 1–36'!$C$23:$AL$23)+SUMIF('Monat 37–60'!$C$4:$Z$4,B$5,'Monat 37–60'!$C$23:$Z$23)+SUMIF('Monat 1–36'!$C$4:$AL$4,B$5,'Monat 1–36'!$C$24:$AL$24)+SUMIF('Monat 37–60'!$C$4:$Z$4,B$5,'Monat 37–60'!$C$24:$Z$24) -> 54261.016 | C20: =SUMIF('Monat 1–36'!$C$4:$AL$4,C$5,'Monat 1–36'!$C$23:$AL$23)+SUMIF('Monat 37–60'!$C$4:$Z$4,C$5,'Monat 37–60'!$C$23:$Z$23)+SUMIF('Monat 1–36'!$C$4:$AL$4,C$5,'Monat 1–36'!$C$24:$AL$24)+SUMIF('Monat 37–60'!$C$4:$Z$4,C$5,'Monat 37–60'!$C$24:$Z$24) -> 268670.4 | D20: =SUMIF('Monat 1–36'!$C$4:$AL$4,D$5,'Monat 1–36'!$C$23:$AL$23)+SUMIF('Monat 37–60'!$C$4:$Z$4,D$5,'Monat 37–60'!$C$23:$Z$23)+SUMIF('Monat 1–36'!$C$4:$AL$4,D$5,'Monat 1–36'!$C$24:$AL$24)+SUMIF('Monat 37–60'!$C$4:$Z$4,D$5,'Monat 37–60'!$C$24:$Z$24) -> 646238.09 | E20: =SUMIF('Monat 1–36'!$C$4:$AL$4,E$5,'Monat 1–36'!$C$23:$AL$23)+SUMIF('Monat 37–60'!$C$4:$Z$4,E$5,'Monat 37–60'!$C$23:$Z$23)+SUMIF('Monat 1–36'!$C$4:$AL$4,E$5,'Monat 1–36'!$C$24:$AL$24)+SUMIF('Monat 37–60'!$C$4:$Z$4,E$5,'Monat 37–60'!$C$24:$Z$24) -> 1126778.5 | F20: =SUMIF('Monat 1–36'!$C$4:$AL$4,F$5,'Monat 1–36'!$C$23:$AL$23)+SUMIF('Monat 37–60'!$C$4:$Z$4,F$5,'Monat 37–60'!$C$23:$Z$23)+SUMIF('Monat 1–36'!$C$4:$AL$4,F$5,'Monat 1–36'!$C$24:$AL$24)+SUMIF('Monat 37–60'!$C$4:$Z$4,F$5,'Monat 37–60'!$C$24:$Z$24) -> 1645421.9
A21: Einrichtung Store-Apps | B21: =SUMIF('Monat 1–36'!$C$4:$AL$4,B$5,'Monat 1–36'!$C$25:$AL$25)+SUMIF('Monat 37–60'!$C$4:$Z$4,B$5,'Monat 37–60'!$C$25:$Z$25) -> 4298.4 | C21: =SUMIF('Monat 1–36'!$C$4:$AL$4,C$5,'Monat 1–36'!$C$25:$AL$25)+SUMIF('Monat 37–60'!$C$4:$Z$4,C$5,'Monat 37–60'!$C$25:$Z$25) -> 12608.64 | D21: =SUMIF('Monat 1–36'!$C$4:$AL$4,D$5,'Monat 1–36'!$C$25:$AL$25)+SUMIF('Monat 37–60'!$C$4:$Z$4,D$5,'Monat 37–60'!$C$25:$Z$25) -> 19915.92 | E21: =SUMIF('Monat 1–36'!$C$4:$AL$4,E$5,'Monat 1–36'!$C$25:$AL$25)+SUMIF('Monat 37–60'!$C$4:$Z$4,E$5,'Monat 37–60'!$C$25:$Z$25) -> 25790.4 | F21: =SUMIF('Monat 1–36'!$C$4:$AL$4,F$5,'Monat 1–36'!$C$25:$AL$25)+SUMIF('Monat 37–60'!$C$4:$Z$4,F$5,'Monat 37–60'!$C$25:$Z$25) -> 31521.6
A22: Umsatz gesamt | B22: =SUMIF('Monat 1–36'!$C$4:$AL$4,B$5,'Monat 1–36'!$C$26:$AL$26)+SUMIF('Monat 37–60'!$C$4:$Z$4,B$5,'Monat 37–60'!$C$26:$Z$26) -> 58559.416 | C22: =SUMIF('Monat 1–36'!$C$4:$AL$4,C$5,'Monat 1–36'!$C$26:$AL$26)+SUMIF('Monat 37–60'!$C$4:$Z$4,C$5,'Monat 37–60'!$C$26:$Z$26) -> 281279.04 | D22: =SUMIF('Monat 1–36'!$C$4:$AL$4,D$5,'Monat 1–36'!$C$26:$AL$26)+SUMIF('Monat 37–60'!$C$4:$Z$4,D$5,'Monat 37–60'!$C$26:$Z$26) -> 666154.01 | E22: =SUMIF('Monat 1–36'!$C$4:$AL$4,E$5,'Monat 1–36'!$C$26:$AL$26)+SUMIF('Monat 37–60'!$C$4:$Z$4,E$5,'Monat 37–60'!$C$26:$Z$26) -> 1152568.9 | F22: =SUMIF('Monat 1–36'!$C$4:$AL$4,F$5,'Monat 1–36'!$C$26:$AL$26)+SUMIF('Monat 37–60'!$C$4:$Z$4,F$5,'Monat 37–60'!$C$26:$Z$26) -> 1676943.5
A23: Umsatzwachstum ggü. Vorjahr | B23: ="–" -> – | C23: =IF(B22>0,C22/B22-1,0) -> 3.8033102 | D23: =IF(C22>0,D22/C22-1,0) -> 1.368303 | E23: =IF(D22>0,E22/D22-1,0) -> 0.73018385 | F23: =IF(E22>0,F22/E22-1,0) -> 0.45496164
A24: Kosten
A25: Variable Kosten | B25: =SUMIF('Monat 1–36'!$C$4:$AL$4,B$5,'Monat 1–36'!$C$34:$AL$34)+SUMIF('Monat 37–60'!$C$4:$Z$4,B$5,'Monat 37–60'!$C$34:$Z$34) -> 1798.7036 | C25: =SUMIF('Monat 1–36'!$C$4:$AL$4,C$5,'Monat 1–36'!$C$34:$AL$34)+SUMIF('Monat 37–60'!$C$4:$Z$4,C$5,'Monat 37–60'!$C$34:$Z$34) -> 15200.294 | D25: =SUMIF('Monat 1–36'!$C$4:$AL$4,D$5,'Monat 1–36'!$C$34:$AL$34)+SUMIF('Monat 37–60'!$C$4:$Z$4,D$5,'Monat 37–60'!$C$34:$Z$34) -> 52049.147 | E25: =SUMIF('Monat 1–36'!$C$4:$AL$4,E$5,'Monat 1–36'!$C$34:$AL$34)+SUMIF('Monat 37–60'!$C$4:$Z$4,E$5,'Monat 37–60'!$C$34:$Z$34) -> 103902.72 | F25: =SUMIF('Monat 1–36'!$C$4:$AL$4,F$5,'Monat 1–36'!$C$34:$AL$34)+SUMIF('Monat 37–60'!$C$4:$Z$4,F$5,'Monat 37–60'!$C$34:$Z$34) -> 171701.19
A26: Deckungsbeitrag | B26: =SUMIF('Monat 1–36'!$C$4:$AL$4,B$5,'Monat 1–36'!$C$35:$AL$35)+SUMIF('Monat 37–60'!$C$4:$Z$4,B$5,'Monat 37–60'!$C$35:$Z$35) -> 56760.712 | C26: =SUMIF('Monat 1–36'!$C$4:$AL$4,C$5,'Monat 1–36'!$C$35:$AL$35)+SUMIF('Monat 37–60'!$C$4:$Z$4,C$5,'Monat 37–60'!$C$35:$Z$35) -> 266078.75 | D26: =SUMIF('Monat 1–36'!$C$4:$AL$4,D$5,'Monat 1–36'!$C$35:$AL$35)+SUMIF('Monat 37–60'!$C$4:$Z$4,D$5,'Monat 37–60'!$C$35:$Z$35) -> 614104.86 | E26: =SUMIF('Monat 1–36'!$C$4:$AL$4,E$5,'Monat 1–36'!$C$35:$AL$35)+SUMIF('Monat 37–60'!$C$4:$Z$4,E$5,'Monat 37–60'!$C$35:$Z$35) -> 1048666.2 | F26: =SUMIF('Monat 1–36'!$C$4:$AL$4,F$5,'Monat 1–36'!$C$35:$AL$35)+SUMIF('Monat 37–60'!$C$4:$Z$4,F$5,'Monat 37–60'!$C$35:$Z$35) -> 1505242.3
A27: Deckungsbeitragsmarge | B27: =IF(B22>0,B26/B22,0) -> 0.96928413 | C27: =IF(C22>0,C26/C22,0) -> 0.94596009 | D27: =IF(D22>0,D26/D22,0) -> 0.92186619 | E27: =IF(E22>0,E26/E22,0) -> 0.90985119 | F27: =IF(F22>0,F26/F22,0) -> 0.89761063
A28: Personal | B28: =SUMIF('Monat 1–36'!$C$4:$AL$4,B$5,'Monat 1–36'!$C$50:$AL$50)+SUMIF('Monat 37–60'!$C$4:$Z$4,B$5,'Monat 37–60'!$C$50:$Z$50) -> 76464 | C28: =SUMIF('Monat 1–36'!$C$4:$AL$4,C$5,'Monat 1–36'!$C$50:$AL$50)+SUMIF('Monat 37–60'!$C$4:$Z$4,C$5,'Monat 37–60'!$C$50:$Z$50) -> 288785.16 | D28: =SUMIF('Monat 1–36'!$C$4:$AL$4,D$5,'Monat 1–36'!$C$50:$AL$50)+SUMIF('Monat 37–60'!$C$4:$Z$4,D$5,'Monat 37–60'!$C$50:$Z$50) -> 448796.06 | E28: =SUMIF('Monat 1–36'!$C$4:$AL$4,E$5,'Monat 1–36'!$C$50:$AL$50)+SUMIF('Monat 37–60'!$C$4:$Z$4,E$5,'Monat 37–60'!$C$50:$Z$50) -> 701549.36 | F28: =SUMIF('Monat 1–36'!$C$4:$AL$4,F$5,'Monat 1–36'!$C$50:$AL$50)+SUMIF('Monat 37–60'!$C$4:$Z$4,F$5,'Monat 37–60'!$C$50:$Z$50) -> 874971.58
A29: davon Vertrieb & Marketing | B29: =SUMIF('Monat 1–36'!$C$4:$AL$4,B$5,'Monat 1–36'!$C$51:$AL$51)+SUMIF('Monat 37–60'!$C$4:$Z$4,B$5,'Monat 37–60'!$C$51:$Z$51) -> 27588 | C29: =SUMIF('Monat 1–36'!$C$4:$AL$4,C$5,'Monat 1–36'!$C$51:$AL$51)+SUMIF('Monat 37–60'!$C$4:$Z$4,C$5,'Monat 37–60'!$C$51:$Z$51) -> 119644.8 | D29: =SUMIF('Monat 1–36'!$C$4:$AL$4,D$5,'Monat 1–36'!$C$51:$AL$51)+SUMIF('Monat 37–60'!$C$4:$Z$4,D$5,'Monat 37–60'!$C$51:$Z$51) -> 154042.68 | E29: =SUMIF('Monat 1–36'!$C$4:$AL$4,E$5,'Monat 1–36'!$C$51:$AL$51)+SUMIF('Monat 37–60'!$C$4:$Z$4,E$5,'Monat 37–60'!$C$51:$Z$51) -> 257035.62 | F29: =SUMIF('Monat 1–36'!$C$4:$AL$4,F$5,'Monat 1–36'!$C$51:$AL$51)+SUMIF('Monat 37–60'!$C$4:$Z$4,F$5,'Monat 37–60'!$C$51:$Z$51) -> 333384.71
A30: Marketing laufend | B30: =SUMIF('Monat 1–36'!$C$4:$AL$4,B$5,'Monat 1–36'!$C$54:$AL$54)+SUMIF('Monat 37–60'!$C$4:$Z$4,B$5,'Monat 37–60'!$C$54:$Z$54) -> 30000 | C30: =SUMIF('Monat 1–36'!$C$4:$AL$4,C$5,'Monat 1–36'!$C$54:$AL$54)+SUMIF('Monat 37–60'!$C$4:$Z$4,C$5,'Monat 37–60'!$C$54:$Z$54) -> 48000 | D30: =SUMIF('Monat 1–36'!$C$4:$AL$4,D$5,'Monat 1–36'!$C$54:$AL$54)+SUMIF('Monat 37–60'!$C$4:$Z$4,D$5,'Monat 37–60'!$C$54:$Z$54) -> 72000 | E30: =SUMIF('Monat 1–36'!$C$4:$AL$4,E$5,'Monat 1–36'!$C$54:$AL$54)+SUMIF('Monat 37–60'!$C$4:$Z$4,E$5,'Monat 37–60'!$C$54:$Z$54) -> 96000 | F30: =SUMIF('Monat 1–36'!$C$4:$AL$4,F$5,'Monat 1–36'!$C$54:$AL$54)+SUMIF('Monat 37–60'!$C$4:$Z$4,F$5,'Monat 37–60'!$C$54:$Z$54) -> 120000
A31: Messen & Veranstaltungen | B31: =SUMIF('Monat 1–36'!$C$4:$AL$4,B$5,'Monat 1–36'!$C$55:$AL$55)+SUMIF('Monat 37–60'!$C$4:$Z$4,B$5,'Monat 37–60'!$C$55:$Z$55) -> 12300 | C31: =SUMIF('Monat 1–36'!$C$4:$AL$4,C$5,'Monat 1–36'!$C$55:$AL$55)+SUMIF('Monat 37–60'!$C$4:$Z$4,C$5,'Monat 37–60'!$C$55:$Z$55) -> 24000 | D31: =SUMIF('Monat 1–36'!$C$4:$AL$4,D$5,'Monat 1–36'!$C$55:$AL$55)+SUMIF('Monat 37–60'!$C$4:$Z$4,D$5,'Monat 37–60'!$C$55:$Z$55) -> 19000 | E31: =SUMIF('Monat 1–36'!$C$4:$AL$4,E$5,'Monat 1–36'!$C$55:$AL$55)+SUMIF('Monat 37–60'!$C$4:$Z$4,E$5,'Monat 37–60'!$C$55:$Z$55) -> 28000 | F31: =SUMIF('Monat 1–36'!$C$4:$AL$4,F$5,'Monat 1–36'!$C$55:$AL$55)+SUMIF('Monat 37–60'!$C$4:$Z$4,F$5,'Monat 37–60'!$C$55:$Z$55) -> 23000
A32: Übrige Fixkosten (Hosting, Miete, Beratung, Reisen …) | B32: =SUMIF('Monat 1–36'!$C$4:$AL$4,B$5,'Monat 1–36'!$C$66:$AL$66)+SUMIF('Monat 37–60'!$C$4:$Z$4,B$5,'Monat 37–60'!$C$66:$Z$66)-B30-B31 -> 39680 | C32: =SUMIF('Monat 1–36'!$C$4:$AL$4,C$5,'Monat 1–36'!$C$66:$AL$66)+SUMIF('Monat 37–60'!$C$4:$Z$4,C$5,'Monat 37–60'!$C$66:$Z$66)-C30-C31 -> 45720 | D32: =SUMIF('Monat 1–36'!$C$4:$AL$4,D$5,'Monat 1–36'!$C$66:$AL$66)+SUMIF('Monat 37–60'!$C$4:$Z$4,D$5,'Monat 37–60'!$C$66:$Z$66)-D30-D31 -> 69720 | E32: =SUMIF('Monat 1–36'!$C$4:$AL$4,E$5,'Monat 1–36'!$C$66:$AL$66)+SUMIF('Monat 37–60'!$C$4:$Z$4,E$5,'Monat 37–60'!$C$66:$Z$66)-E30-E31 -> 94440 | F32: =SUMIF('Monat 1–36'!$C$4:$AL$4,F$5,'Monat 1–36'!$C$66:$AL$66)+SUMIF('Monat 37–60'!$C$4:$Z$4,F$5,'Monat 37–60'!$C$66:$Z$66)-F30-F31 -> 113400
A33: Fixkosten gesamt | B33: =SUMIF('Monat 1–36'!$C$4:$AL$4,B$5,'Monat 1–36'!$C$67:$AL$67)+SUMIF('Monat 37–60'!$C$4:$Z$4,B$5,'Monat 37–60'!$C$67:$Z$67) -> 158444 | C33: =SUMIF('Monat 1–36'!$C$4:$AL$4,C$5,'Monat 1–36'!$C$67:$AL$67)+SUMIF('Monat 37–60'!$C$4:$Z$4,C$5,'Monat 37–60'!$C$67:$Z$67) -> 406505.16 | D33: =SUMIF('Monat 1–36'!$C$4:$AL$4,D$5,'Monat 1–36'!$C$67:$AL$67)+SUMIF('Monat 37–60'!$C$4:$Z$4,D$5,'Monat 37–60'!$C$67:$Z$67) -> 609516.06 | E33: =SUMIF('Monat 1–36'!$C$4:$AL$4,E$5,'Monat 1–36'!$C$67:$AL$67)+SUMIF('Monat 37–60'!$C$4:$Z$4,E$5,'Monat 37–60'!$C$67:$Z$67) -> 919989.36 | F33: =SUMIF('Monat 1–36'!$C$4:$AL$4,F$5,'Monat 1–36'!$C$67:$AL$67)+SUMIF('Monat 37–60'!$C$4:$Z$4,F$5,'Monat 37–60'!$C$67:$Z$67) -> 1131371.6
A34: Kosten gesamt | B34: =SUMIF('Monat 1–36'!$C$4:$AL$4,B$5,'Monat 1–36'!$C$69:$AL$69)+SUMIF('Monat 37–60'!$C$4:$Z$4,B$5,'Monat 37–60'!$C$69:$Z$69) -> 160242.7 | C34: =SUMIF('Monat 1–36'!$C$4:$AL$4,C$5,'Monat 1–36'!$C$69:$AL$69)+SUMIF('Monat 37–60'!$C$4:$Z$4,C$5,'Monat 37–60'!$C$69:$Z$69) -> 421705.45 | D34: =SUMIF('Monat 1–36'!$C$4:$AL$4,D$5,'Monat 1–36'!$C$69:$AL$69)+SUMIF('Monat 37–60'!$C$4:$Z$4,D$5,'Monat 37–60'!$C$69:$Z$69) -> 661565.21 | E34: =SUMIF('Monat 1–36'!$C$4:$AL$4,E$5,'Monat 1–36'!$C$69:$AL$69)+SUMIF('Monat 37–60'!$C$4:$Z$4,E$5,'Monat 37–60'!$C$69:$Z$69) -> 1023892.1 | F34: =SUMIF('Monat 1–36'!$C$4:$AL$4,F$5,'Monat 1–36'!$C$69:$AL$69)+SUMIF('Monat 37–60'!$C$4:$Z$4,F$5,'Monat 37–60'!$C$69:$Z$69) -> 1303072.8
A35: Ergebnis
A36: EBITDA | B36: =SUMIF('Monat 1–36'!$C$4:$AL$4,B$5,'Monat 1–36'!$C$70:$AL$70)+SUMIF('Monat 37–60'!$C$4:$Z$4,B$5,'Monat 37–60'!$C$70:$Z$70) -> -101683.29 | C36: =SUMIF('Monat 1–36'!$C$4:$AL$4,C$5,'Monat 1–36'!$C$70:$AL$70)+SUMIF('Monat 37–60'!$C$4:$Z$4,C$5,'Monat 37–60'!$C$70:$Z$70) -> -140426.41 | D36: =SUMIF('Monat 1–36'!$C$4:$AL$4,D$5,'Monat 1–36'!$C$70:$AL$70)+SUMIF('Monat 37–60'!$C$4:$Z$4,D$5,'Monat 37–60'!$C$70:$Z$70) -> 4588.8008 | E36: =SUMIF('Monat 1–36'!$C$4:$AL$4,E$5,'Monat 1–36'!$C$70:$AL$70)+SUMIF('Monat 37–60'!$C$4:$Z$4,E$5,'Monat 37–60'!$C$70:$Z$70) -> 128676.82 | F36: =SUMIF('Monat 1–36'!$C$4:$AL$4,F$5,'Monat 1–36'!$C$70:$AL$70)+SUMIF('Monat 37–60'!$C$4:$Z$4,F$5,'Monat 37–60'!$C$70:$Z$70) -> 373870.77
A37: EBITDA-Marge | B37: =IF(B22>0,B36/B22,0) -> -1.7364123 | C37: =IF(C22>0,C36/C22,0) -> -0.49924237 | D37: =IF(D22>0,D36/D22,0) -> 0.0068884984 | E37: =IF(E22>0,E36/E22,0) -> 0.11164349 | F37: =IF(F22>0,F36/F22,0) -> 0.22294774
A38: Abschreibungen | B38: =0 -> 0 | C38: =0 -> 0 | D38: =0 -> 0 | E38: =0 -> 0 | F38: =0 -> 0 | G38: keine wesentlichen Investitionen; Hardware sofort Aufwand
A39: Zinsen | B39: =SUMIF('Monat 1–36'!$C$4:$AL$4,B$5,'Monat 1–36'!$C$76:$AL$76)+SUMIF('Monat 37–60'!$C$4:$Z$4,B$5,'Monat 37–60'!$C$76:$Z$76) -> 5000 | C39: =SUMIF('Monat 1–36'!$C$4:$AL$4,C$5,'Monat 1–36'!$C$76:$AL$76)+SUMIF('Monat 37–60'!$C$4:$Z$4,C$5,'Monat 37–60'!$C$76:$Z$76) -> 5000 | D39: =SUMIF('Monat 1–36'!$C$4:$AL$4,D$5,'Monat 1–36'!$C$76:$AL$76)+SUMIF('Monat 37–60'!$C$4:$Z$4,D$5,'Monat 37–60'!$C$76:$Z$76) -> 4713.5417 | E39: =SUMIF('Monat 1–36'!$C$4:$AL$4,E$5,'Monat 1–36'!$C$76:$AL$76)+SUMIF('Monat 37–60'!$C$4:$Z$4,E$5,'Monat 37–60'!$C$76:$Z$76) -> 4088.5417 | F39: =SUMIF('Monat 1–36'!$C$4:$AL$4,F$5,'Monat 1–36'!$C$76:$AL$76)+SUMIF('Monat 37–60'!$C$4:$Z$4,F$5,'Monat 37–60'!$C$76:$Z$76) -> 3463.5417
A40: Ergebnis vor Steuern (EBT) | B40: =B36-B38-B39 -> -106683.29 | C40: =C36-C38-C39 -> -145426.41 | D40: =D36-D38-D39 -> -124.74085 | E40: =E36-E38-E39 -> 124588.28 | F40: =F36-F38-F39 -> 370407.23
A41: Verlustvortrag Jahresanfang | B41: =0 -> 0 | C41: =B43 -> 106683.29 | D41: =C43 -> 252109.7 | E41: =D43 -> 252234.44 | F41: =E43 -> 127646.16
A42: Zu versteuerndes Einkommen | B42: =MAX(0,B40-B41) -> 0 | C42: =MAX(0,C40-C41) -> 0 | D42: =MAX(0,D40-D41) -> 0 | E42: =MAX(0,E40-E41) -> 0 | F42: =MAX(0,F40-F41) -> 242761.07
A43: Verlustvortrag Jahresende | B43: =MAX(0,B41-B40) -> 106683.29 | C43: =MAX(0,C41-C40) -> 252109.7 | D43: =MAX(0,D41-D40) -> 252234.44 | E43: =MAX(0,E41-E40) -> 127646.16 | F43: =MAX(0,F41-F40) -> 0
A44: Körperschaftsteuer + Soli | B44: =B42*INDEX(Annahmen!$B$122:$F$122,1,B$5)*(1+Annahmen!$B$123) -> 0 | C44: =C42*INDEX(Annahmen!$B$122:$F$122,1,C$5)*(1+Annahmen!$B$123) -> 0 | D44: =D42*INDEX(Annahmen!$B$122:$F$122,1,D$5)*(1+Annahmen!$B$123) -> 0 | E44: =E42*INDEX(Annahmen!$B$122:$F$122,1,E$5)*(1+Annahmen!$B$123) -> 0 | F44: =F42*INDEX(Annahmen!$B$122:$F$122,1,F$5)*(1+Annahmen!$B$123) -> 28172.422
A45: Gewerbesteuer | B45: =B42*Annahmen!$B$125*Annahmen!$B$124 -> 0 | C45: =C42*Annahmen!$B$125*Annahmen!$B$124 -> 0 | D45: =D42*Annahmen!$B$125*Annahmen!$B$124 -> 0 | E45: =E42*Annahmen!$B$125*Annahmen!$B$124 -> 0 | F45: =F42*Annahmen!$B$125*Annahmen!$B$124 -> 33986.55
A46: Steuern gesamt | B46: =B44+B45 -> 0 | C46: =C44+C45 -> 0 | D46: =D44+D45 -> 0 | E46: =E44+E45 -> 0 | F46: =F44+F45 -> 62158.972
A47: Jahresergebnis nach Steuern | B47: =B40-B46 -> -106683.29 | C47: =C40-C46 -> -145426.41 | D47: =D40-D46 -> -124.74085 | E47: =E40-E46 -> 124588.28 | F47: =F40-F46 -> 308248.26
A48: Liquidität und Kennzahlen
A49: Kasse zum Jahresende | B49: =IF(B$5<=3,INDEX('Monat 1–36'!$C$82:$AL$82,1,B$5*12),INDEX('Monat 37–60'!$C$82:$Z$82,1,B$5*12-36)) -> 243316.71 | C49: =IF(C$5<=3,INDEX('Monat 1–36'!$C$82:$AL$82,1,C$5*12),INDEX('Monat 37–60'!$C$82:$Z$82,1,C$5*12-36)) -> 97890.299 | D49: =IF(D$5<=3,INDEX('Monat 1–36'!$C$82:$AL$82,1,D$5*12),INDEX('Monat 37–60'!$C$82:$Z$82,1,D$5*12-36)) -> 82140.558 | E49: =IF(E$5<=3,INDEX('Monat 1–36'!$C$82:$AL$82,1,E$5*12),INDEX('Monat 37–60'!$C$82:$Z$82,1,E$5*12-36)) -> 191103.84 | F49: =IF(F$5<=3,INDEX('Monat 1–36'!$C$82:$AL$82,1,F$5*12),INDEX('Monat 37–60'!$C$82:$Z$82,1,F$5*12-36)) -> 545886.07
A50: KfW-Restschuld zum Jahresende | B50: =IF(B$5<=3,INDEX('Monat 1–36'!$C$78:$AL$78,1,B$5*12),INDEX('Monat 37–60'!$C$78:$Z$78,1,B$5*12-36)) -> 125000 | C50: =IF(C$5<=3,INDEX('Monat 1–36'!$C$78:$AL$78,1,C$5*12),INDEX('Monat 37–60'!$C$78:$Z$78,1,C$5*12-36)) -> 125000 | D50: =IF(D$5<=3,INDEX('Monat 1–36'!$C$78:$AL$78,1,D$5*12),INDEX('Monat 37–60'!$C$78:$Z$78,1,D$5*12-36)) -> 109375 | E50: =IF(E$5<=3,INDEX('Monat 1–36'!$C$78:$AL$78,1,E$5*12),INDEX('Monat 37–60'!$C$78:$Z$78,1,E$5*12-36)) -> 93750 | F50: =IF(F$5<=3,INDEX('Monat 1–36'!$C$78:$AL$78,1,F$5*12),INDEX('Monat 37–60'!$C$78:$Z$78,1,F$5*12-36)) -> 78125
A51: Köpfe zum Jahresende (inkl. Gründer) | B51: =IF(B$5<=3,INDEX('Monat 1–36'!$C$52:$AL$52,1,B$5*12),INDEX('Monat 37–60'!$C$52:$Z$52,1,B$5*12-36)) -> 3 | C51: =IF(C$5<=3,INDEX('Monat 1–36'!$C$52:$AL$52,1,C$5*12),INDEX('Monat 37–60'!$C$52:$Z$52,1,C$5*12-36)) -> 6 | D51: =IF(D$5<=3,INDEX('Monat 1–36'!$C$52:$AL$52,1,D$5*12),INDEX('Monat 37–60'!$C$52:$Z$52,1,D$5*12-36)) -> 8 | E51: =IF(E$5<=3,INDEX('Monat 1–36'!$C$52:$AL$52,1,E$5*12),INDEX('Monat 37–60'!$C$52:$Z$52,1,E$5*12-36)) -> 11 | F51: =IF(F$5<=3,INDEX('Monat 1–36'!$C$52:$AL$52,1,F$5*12),INDEX('Monat 37–60'!$C$52:$Z$52,1,F$5*12-36)) -> 13
A52: Umsatz je Kopf | B52: =IF(B51>0,B22/B51,0) -> 19519.805 | C52: =IF(C51>0,C22/C51,0) -> 46879.84 | D52: =IF(D51>0,D22/D51,0) -> 83269.251 | E52: =IF(E51>0,E22/E51,0) -> 104778.99 | F52: =IF(F51>0,F22/F51,0) -> 128995.66
A53: CAC (Vertrieb+Marketing+Messen+Provision je Neukunde) | B53: =IF(B11>0,(B29+B30+B31+SUMIF('Monat 1–36'!$C$4:$AL$4,B$5,'Monat 1–36'!$C$32:$AL$32)+SUMIF('Monat 37–60'!$C$4:$Z$4,B$5,'Monat 37–60'!$C$32:$Z$32))/B11,0) -> 776.53333 | C53: =IF(C11>0,(C29+C30+C31+SUMIF('Monat 1–36'!$C$4:$AL$4,C$5,'Monat 1–36'!$C$32:$AL$32)+SUMIF('Monat 37–60'!$C$4:$Z$4,C$5,'Monat 37–60'!$C$32:$Z$32))/C11,0) -> 752.56355 | D53: =IF(D11>0,(D29+D30+D31+SUMIF('Monat 1–36'!$C$4:$AL$4,D$5,'Monat 1–36'!$C$32:$AL$32)+SUMIF('Monat 37–60'!$C$4:$Z$4,D$5,'Monat 37–60'!$C$32:$Z$32))/D11,0) -> 667.50691 | E53: =IF(E11>0,(E29+E30+E31+SUMIF('Monat 1–36'!$C$4:$AL$4,E$5,'Monat 1–36'!$C$32:$AL$32)+SUMIF('Monat 37–60'!$C$4:$Z$4,E$5,'Monat 37–60'!$C$32:$Z$32))/E11,0) -> 839.02069 | F53: =IF(F11>0,(F29+F30+F31+SUMIF('Monat 1–36'!$C$4:$AL$4,F$5,'Monat 1–36'!$C$32:$AL$32)+SUMIF('Monat 37–60'!$C$4:$Z$4,F$5,'Monat 37–60'!$C$32:$Z$32))/F11,0) -> 912.35679
A54: LTV (ARPA × DB-Marge / Monats-Churn) | B54: =IF(B13>0,B19*B27/(B13/12),0) -> 6879.7731 | C54: =IF(C13>0,C19*C27/(C13/12),0) -> 5450.3331 | D54: =IF(D13>0,D19*D27/(D13/12),0) -> 5096.4152 | E54: =IF(E13>0,E19*E27/(E13/12),0) -> 4976.0894 | F54: =IF(F13>0,F19*F27/(F13/12),0) -> 4998.3674
A55: LTV / CAC | B55: =IF(B53>0,B54/B53,0) -> 8.859598 | C55: =IF(C53>0,C54/C53,0) -> 7.242356 | D55: =IF(D53>0,D54/D53,0) -> 7.635 | E55: =IF(E53>0,E54/E53,0) -> 5.9308304 | F55: =IF(F53>0,F54/F53,0) -> 5.4785228
A56: CAC-Amortisation in Monaten (CAC / (ARPA × DB-Marge)) | B56: =IF(B19*B27>0,B53/(B19*B27),0) -> 6.5762444 | C56: =IF(C19*C27>0,C53/(C19*C27),0) -> 6.4367306 | D56: =IF(D19*D27>0,D53/(D19*D27),0) -> 5.7651359 | E56: =IF(E19*E27>0,E53/(E19*E27),0) -> 7.2229086 | F56: =IF(F19*F27>0,F53/(F19*F27),0) -> 7.848765

Sheet Break-even
A1: LADEKLAR – Break-even und Kapitalbedarf
A3: EBITDA-Break-even
A4: Erster Monat mit EBITDA ≥ 0 (Monat-Nr.) | B4: =MIN('Monat 1–36'!$C$84:$AL$84,'Monat 37–60'!$C$84:$Z$84) -> 30
A5: … als Kalendermonat | B5: =IF(B4<999,EDATE(Annahmen!$B$6,B4-1),"nicht erreicht") -> 47270
A6: Dauerhaft positives EBITDA ab Monat-Nr. | B6: =MAX('Monat 1–36'!$C$85:$AL$85,'Monat 37–60'!$C$85:$Z$85)+1 -> 40 | C6: Monat nach dem letzten Monat mit negativem EBITDA
A7: … als Kalendermonat | B7: =IF(B6<=60,EDATE(Annahmen!$B$6,B6-1),"nach Monat 60") -> 47574
A8: Kunden im ersten Break-even-Monat | B8: =IF(B4<=36,INDEX('Monat 1–36'!$C$13:$AL$13,1,B4),IF(B4<=60,INDEX('Monat 37–60'!$C$13:$Z$13,1,B4-36),0)) -> 438.25377
A9: MRR im ersten Break-even-Monat | B9: =IF(B4<=36,INDEX('Monat 1–36'!$C$23:$AL$23,1,B4),IF(B4<=60,INDEX('Monat 37–60'!$C$23:$Z$23,1,B4-36),0)) -> 54618.034
A11: Liquidität und Kapitalbedarf
A12: Tiefster kumulierter Cashflow ohne Finanzierung | B12: =MIN('Monat 1–36'!$C$83:$AL$83,'Monat 37–60'!$C$83:$Z$83) -> -297354.15 | C12: entspricht dem Finanzierungsbedarf vor Puffer
A13: … erreicht im Monat-Nr. | B13: =IFERROR(MATCH(B12,'Monat 1–36'!$C$83:$AL$83,0),36+MATCH(B12,'Monat 37–60'!$C$83:$Z$83,0)) -> 31
A14: … als Kalendermonat | B14: =EDATE(Annahmen!$B$6,B13-1) -> 47300
A15: Sicherheitspuffer | B15: =Annahmen!$B$119 -> 50000
A16: Kapitalbedarf (inkl. Puffer) | B16: =-B12+B15 -> 347354.15
A17: Geplante Finanzierung (EK + KfW + Angel + Förderung) | B17: =Annahmen!$B$108+Annahmen!$B$110+Annahmen!$B$115+SUM('Monat 1–36'!$C$75:$AL$75) -> 350000
A18: Über-/Unterdeckung | B18: =B17-B16 -> 2645.8524
A19: Tiefster Kassenstand (mit Finanzierung) | B19: =MIN('Monat 1–36'!$C$82:$AL$82,'Monat 37–60'!$C$82:$Z$82) -> 52645.852
A20: Kumulierter Cashflow wieder ≥ 0 ab Monat-Nr. | B20: =MIN('Monat 1–36'!$C$86:$AL$86,'Monat 37–60'!$C$86:$Z$86) -> 56 | C20: 999 = innerhalb von 60 Monaten nicht erreicht
A22: Break-even-Kunden (Fixkosten / Deckungsbeitrag je Kunde)
B23: Monat 12 | C23: Monat 24 | D23: Monat 36 | E23: Monat 48 | F23: Monat 60
A24: Fixkosten im Monat | B24: ='Monat 1–36'!N67 -> 18130 | C24: ='Monat 1–36'!Z67 -> 36316 | D24: ='Monat 1–36'!AL67 -> 52726.554 | E24: ='Monat 37–60'!N67 -> 76414.626 | F24: ='Monat 37–60'!Z67 -> 92064.298
A25: Kunden | B25: ='Monat 1–36'!N13 -> 85.663351 | C25: ='Monat 1–36'!Z13 -> 300.02244 | D25: ='Monat 1–36'!AL13 -> 595.01808 | E25: ='Monat 37–60'!N13 -> 922.47355 | F25: ='Monat 37–60'!Z13 -> 1275.7431
A26: Umsatz im Monat | B26: ='Monat 1–36'!N26 -> 10487.138 | C26: ='Monat 1–36'!Z26 -> 36564.825 | D26: ='Monat 1–36'!AL26 -> 72906.108 | E26: ='Monat 37–60'!N26 -> 114033.13 | F26: ='Monat 37–60'!Z26 -> 159577.12
A27: Variable Kosten im Monat | B27: ='Monat 1–36'!N34 -> 310.75898 | C27: ='Monat 1–36'!Z34 -> 1958.0501 | D27: ='Monat 1–36'!AL34 -> 5679.3683 | E27: ='Monat 37–60'!N34 -> 10253.851 | F27: ='Monat 37–60'!Z34 -> 16313.871
A28: Deckungsbeitrag je Kunde und Monat | B28: =IF(B25>0,(B26-B27)/B25,0) -> 118.79502 | C28: =IF(C25>0,(C26-C27)/C25,0) -> 115.34729 | D28: =IF(D25>0,(D26-D27)/D25,0) -> 112.98268 | E28: =IF(E25>0,(E26-E27)/E25,0) -> 112.50109 | F28: =IF(F25>0,(F26-F27)/F25,0) -> 112.29789
A29: Nötige Kunden für EBITDA = 0 | B29: =IF(B28>0,B24/B28,0) -> 152.61583 | C29: =IF(C28>0,C24/C28,0) -> 314.84052 | D29: =IF(D28>0,D24/D28,0) -> 466.67819 | E29: =IF(E28>0,E24/E28,0) -> 679.23455 | F29: =IF(F28>0,F24/F28,0) -> 819.82217
A30: Abstand tatsächliche zu nötigen Kunden | B30: =B25-B29 -> -66.952476 | C30: =C25-C29 -> -14.818074 | D30: =D25-D29 -> 128.33989 | E30: =E25-E29 -> 243.23901 | F30: =F25-F29 -> 455.9209
A32: Hinweis: Der Break-even je Kunde steigt mit dem Team. Die Fixkosten wachsen stufenweise (Einstellungen), der Deckungsbeitrag je Kunde steigt leicht durch den höheren Anteil Flotte/Premium im Bestand.

Sheet Sensitivität
A1: LADEKLAR – Sensitivität (Churn, Preis, Wachstum)
A2: Jedes Szenario rechnet das Kundenmodell über 60 Monate neu (Rechenblöcke unten). Fixkosten, Zinsen und Tilgung wie im Basisplan; Steuern nicht berücksichtigt (vor Steuern). Faktoren in Blau sind änderbar.
A4: Nr. | B4: Szenario | C4: Churn-Faktor | D4: Preis-Faktor | E4: Wachstums-Faktor | F4: Kunden M36 | G4: ARR M36 | H4: Kunden M60 | I4: ARR M60 | J4: Umsatz J3 | K4: Umsatz J5 | L4: EBITDA J3 | M4: EBITDA J5 | N4: Break-even (Monat) | O4: Finanzbedarf vor Puffer | P4: Δ Finanzbedarf ggü. Basis
A5: 1 | B5: Basisplan | C5: 1 | D5: 1 | E5: 1 | F5: =AL33 -> 595.01808 | G5: =AL34*12 -> 896787.89 | H5: =BJ33 -> 1275.7431 | I5: =BJ34*12 -> 1982530.4 | J5: =SUM(AA35:AL35) -> 666154.01 | K5: =SUM(AY35:BJ35) -> 1676943.5 | L5: =SUM(AA37:AL37) -> 4588.8008 | M5: =SUM(AY37:BJ37) -> 373870.77 | N5: =IF(MIN(C39:BJ39)=999,"> 60",MIN(C39:BJ39)) -> 30 | O5: =MAX(0,-MIN(C38:BJ38)) -> 297354.15 | P5: =O5-$O$5 -> 0
A6: 2 | B6: Churn +50 % | C6: 1.5 | D6: 1 | E6: 1 | F6: =AL45 -> 528.95784 | G6: =AL46*12 -> 814110.28 | H6: =BJ45 -> 1065.9578 | I6: =BJ46*12 -> 1705530.7 | J6: =SUM(AA47:AL47) -> 613413.63 | K6: =SUM(AY47:BJ47) -> 1463457.1 | L6: =SUM(AA49:AL49) -> -44078.24 | M6: =SUM(AY49:BJ49) -> 182157.67 | N6: =IF(MIN(C51:BJ51)=999,"> 60",MIN(C51:BJ51)) -> 33 | O6: =MAX(0,-MIN(C50:BJ50)) -> 366820.46 | P6: =O6-$O$5 -> 69466.317
A7: 3 | B7: Churn doppelt | C7: 2 | D7: 1 | E7: 1 | F7: =AL57 -> 474.39053 | G7: =AL58*12 -> 743640.89 | H7: =BJ57 -> 909.2531 | I7: =BJ58*12 -> 1488932.5 | J7: =SUM(AA59:AL59) -> 567651.29 | K7: =SUM(AY59:BJ59) -> 1293642.8 | L7: =SUM(AA61:AL61) -> -86312.147 | M7: =SUM(AY61:BJ61) -> 29630.668 | N7: =IF(MIN(C63:BJ63)=999,"> 60",MIN(C63:BJ63)) -> 35 | O7: =MAX(0,-MIN(C62:BJ62)) -> 525116.71 | P7: =O7-$O$5 -> 227762.56
A8: 4 | B8: Churn −30 % | C8: 0.7 | D8: 1 | E8: 1 | F8: =AL69 -> 641.50393 | G8: =AL70*12 -> 953454.27 | H8: =BJ69 -> 1437.4314 | I8: =BJ70*12 -> 2187571.5 | J8: =SUM(AA71:AL71) -> 701754.87 | K8: =SUM(AY71:BJ71) -> 1832545.1 | L8: =SUM(AA73:AL73) -> 37436.071 | M8: =SUM(AY73:BJ73) -> 513575.91 | N8: =IF(MIN(C75:BJ75)=999,"> 60",MIN(C75:BJ75)) -> 27 | O8: =MAX(0,-MIN(C74:BJ74)) -> 273609.55 | P8: =O8-$O$5 -> -23744.595
A9: 5 | B9: Preise −15 % | C9: 1 | D9: 0.85 | E9: 1 | F9: =AL81 -> 595.01808 | G9: =AL82*12 -> 762269.71 | H9: =BJ81 -> 1275.7431 | I9: =BJ82*12 -> 1685150.8 | J9: =SUM(AA83:AL83) -> 566230.91 | K9: =SUM(AY83:BJ83) -> 1425402 | L9: =SUM(AA85:AL85) -> -89538.761 | M9: =SUM(AY85:BJ85) -> 143207.19 | N9: =IF(MIN(C87:BJ87)=999,"> 60",MIN(C87:BJ87)) -> 35 | O9: =MAX(0,-MIN(C86:BJ86)) -> 485605.28 | P9: =O9-$O$5 -> 188251.13
A10: 6 | B10: Preise +10 % | C10: 1 | D10: 1.1 | E10: 1 | F10: =AL93 -> 595.01808 | G10: =AL94*12 -> 986466.68 | H10: =BJ93 -> 1275.7431 | I10: =BJ94*12 -> 2180783.4 | J10: =SUM(AA95:AL95) -> 732769.41 | K10: =SUM(AY95:BJ95) -> 1844637.9 | L10: =SUM(AA97:AL97) -> 67340.508 | M10: =SUM(AY97:BJ97) -> 527646.5 | N10: =IF(MIN(C99:BJ99)=999,"> 60",MIN(C99:BJ99)) -> 24 | O10: =MAX(0,-MIN(C98:BJ98)) -> 241487.37 | P10: =O10-$O$5 -> -55866.78
A11: 7 | B11: Wachstum −30 % | C11: 1 | D11: 1 | E11: 0.7 | F11: =AL105 -> 417.15516 | G11: =AL106*12 -> 628847.75 | H11: =BJ105 -> 893.39759 | I11: =BJ106*12 -> 1388491.2 | J11: =SUM(AA107:AL107) -> 467460.57 | K11: =SUM(AY107:BJ107) -> 1174613.7 | L11: =SUM(AA109:AL109) -> -178577.57 | M11: =SUM(AY109:BJ109) -> -77024.516 | N11: =IF(MIN(C111:BJ111)=999,"> 60",MIN(C111:BJ111)) -> 57 | O11: =MAX(0,-MIN(C110:BJ110)) -> 856932.06 | P11: =O11-$O$5 -> 559577.91
A12: 8 | B12: Wachstum −50 % | C12: 1 | D12: 1 | E12: 0.5 | F12: =AL117 -> 298.57988 | G12: =AL118*12 -> 450220.98 | H12: =BJ117 -> 638.50061 | I12: =BJ118*12 -> 992465.14 | J12: =SUM(AA119:AL119) -> 334998.28 | K12: =SUM(AY119:BJ119) -> 839727.21 | L12: =SUM(AA121:AL121) -> -300688.48 | M12: =SUM(AY121:BJ121) -> -377621.38 | N12: =IF(MIN(C123:BJ123)=999,"> 60",MIN(C123:BJ123)) -> > 60 | O12: =MAX(0,-MIN(C122:BJ122)) -> 1540022 | P12: =O12-$O$5 -> 1242667.8
A13: 9 | B13: Wachstum +30 % | C13: 1 | D13: 1 | E13: 1.3 | F13: =AL129 -> 772.881 | G13: =AL130*12 -> 1164728 | H13: =BJ129 -> 1658.0885 | I13: =BJ130*12 -> 2576569.6 | J13: =SUM(AA131:AL131) -> 864847.45 | K13: =SUM(AY131:BJ131) -> 2179273.3 | L13: =SUM(AA133:AL133) -> 187755.17 | M13: =SUM(AY133:BJ133) -> 824766.06 | N13: =IF(MIN(C135:BJ135)=999,"> 60",MIN(C135:BJ135)) -> 20 | O13: =MAX(0,-MIN(C134:BJ134)) -> 171532.79 | P13: =O13-$O$5 -> -125821.36
A14: 10 | B14: Pessimistisch (Churn ×1,5, Preis ×0,9, Wachstum ×0,7) | C14: 1.5 | D14: 0.9 | E14: 0.7 | F14: =AL141 -> 370.69744 | G14: =AL142*12 -> 513604.58 | H14: =BJ141 -> 746.37001 | I14: =BJ142*12 -> 1074875.5 | J14: =SUM(AA143:AL143) -> 387239.22 | K14: =SUM(AY143:BJ143) -> 922404.87 | L14: =SUM(AA145:AL145) -> -253430.8 | M14: =SUM(AY145:BJ145) -> -305457.21 | N14: =IF(MIN(C147:BJ147)=999,"> 60",MIN(C147:BJ147)) -> > 60 | O14: =MAX(0,-MIN(C146:BJ146)) -> 1326497.5 | P14: =O14-$O$5 -> 1029143.3
A15: 11 | B15: Optimistisch (Churn ×0,8, Preis ×1,0, Wachstum ×1,2) | C15: 0.8 | D15: 1 | E15: 1.2 | F15: =AL153 -> 749.93426 | G15: =AL154*12 -> 1119863.9 | H15: =BJ153 -> 1655.6019 | I15: =BJ154*12 -> 2537918.6 | J15: =SUM(AA155:AL155) -> 826572.9 | K15: =SUM(AY155:BJ155) -> 2133013 | L15: =SUM(AA157:AL157) -> 152494.38 | M15: =SUM(AY157:BJ157) -> 783273.34 | N15: =IF(MIN(C159:BJ159)=999,"> 60",MIN(C159:BJ159)) -> 20 | O15: =MAX(0,-MIN(C158:BJ158)) -> 190311.72 | P15: =O15-$O$5 -> -107042.42
B16: Kontrolle: EBITDA J5 Basis − Hauptmodell (muss 0 sein) | I16: =ROUND(I5-'5 Jahre'!F18,2) -> 0 | M16: =ROUND(M5-'5 Jahre'!F36,2) -> 0
A18: Basisdaten aus dem Monatsplan
B19: Monat-Nr. | C19: ='Monat 1–36'!C2 -> 1 | D19: ='Monat 1–36'!D2 -> 2 | E19: ='Monat 1–36'!E2 -> 3 | F19: ='Monat 1–36'!F2 -> 4 | G19: ='Monat 1–36'!G2 -> 5 | H19: ='Monat 1–36'!H2 -> 6 | I19: ='Monat 1–36'!I2 -> 7 | J19: ='Monat 1–36'!J2 -> 8 | ... AL19: ='Monat 1–36'!AL2 -> 36 | AM19: ='Monat 37–60'!C2 -> 37 | AN19: ='Monat 37–60'!D2 -> 38 | AO19: ='Monat 37–60'!E2 -> 39 | AP19: ='Monat 37–60'!F2 -> 40 | AQ19: ='Monat 37–60'!G2 -> 41 | AR19: ='Monat 37–60'!H2 -> 42 | AS19: ='Monat 37–60'!I2 -> 43 | AT19: ='Monat 37–60'!J2 -> 44 | ... BJ19: ='Monat 37–60'!Z2 -> 60
B20: Modelljahr | C20: ='Monat 1–36'!C4 -> 1 | D20: ='Monat 1–36'!D4 -> 1 | E20: ='Monat 1–36'!E4 -> 1 | F20: ='Monat 1–36'!F4 -> 1 | G20: ='Monat 1–36'!G4 -> 1 | H20: ='Monat 1–36'!H4 -> 1 | I20: ='Monat 1–36'!I4 -> 1 | J20: ='Monat 1–36'!J4 -> 1 | ... AL20: ='Monat 1–36'!AL4 -> 3 | AM20: ='Monat 37–60'!C4 -> 4 | AN20: ='Monat 37–60'!D4 -> 4 | AO20: ='Monat 37–60'!E4 -> 4 | AP20: ='Monat 37–60'!F4 -> 4 | AQ20: ='Monat 37–60'!G4 -> 4 | AR20: ='Monat 37–60'!H4 -> 4 | AS20: ='Monat 37–60'!I4 -> 4 | AT20: ='Monat 37–60'!J4 -> 4 | ... BJ20: ='Monat 37–60'!Z4 -> 5
B21: Neukunden Basis | C21: ='Monat 1–36'!C6 -> 3 | D21: ='Monat 1–36'!D6 -> 3 | E21: ='Monat 1–36'!E6 -> 3 | F21: ='Monat 1–36'!F6 -> 6 | G21: ='Monat 1–36'!G6 -> 6 | H21: ='Monat 1–36'!H6 -> 6 | I21: ='Monat 1–36'!I6 -> 9 | J21: ='Monat 1–36'!J6 -> 9 | ... AL21: ='Monat 1–36'!AL6 -> 40 | AM21: ='Monat 37–60'!C6 -> 45 | AN21: ='Monat 37–60'!D6 -> 45 | AO21: ='Monat 37–60'!E6 -> 45 | AP21: ='Monat 37–60'!F6 -> 45 | AQ21: ='Monat 37–60'!G6 -> 45 | AR21: ='Monat 37–60'!H6 -> 45 | AS21: ='Monat 37–60'!I6 -> 45 | AT21: ='Monat 37–60'!J6 -> 45 | ... BJ21: ='Monat 37–60'!Z6 -> 55
B22: Fixkosten Basis | C22: ='Monat 1–36'!C67 -> 16960 | D22: ='Monat 1–36'!D67 -> 7160 | E22: ='Monat 1–36'!E67 -> 7960 | F22: ='Monat 1–36'!F67 -> 16160 | G22: ='Monat 1–36'!G67 -> 7160 | H22: ='Monat 1–36'!H67 -> 7160 | I22: ='Monat 1–36'!I67 -> 13598 | J22: ='Monat 1–36'!J67 -> 11798 | ... AL22: ='Monat 1–36'!AL67 -> 52726.554 | AM22: ='Monat 37–60'!C67 -> 74950.268 | AN22: ='Monat 37–60'!D67 -> 71350.268 | AO22: ='Monat 37–60'!E67 -> 81350.268 | AP22: ='Monat 37–60'!F67 -> 71350.268 | AQ22: ='Monat 37–60'!G67 -> 71350.268 | AR22: ='Monat 37–60'!H67 -> 71350.268 | AS22: ='Monat 37–60'!I67 -> 78214.626 | AT22: ='Monat 37–60'!J67 -> 76414.626 | ... BJ22: ='Monat 37–60'!Z67 -> 92064.298
B23: Zinsen Basis | C23: ='Monat 1–36'!C76 -> 416.66667 | D23: ='Monat 1–36'!D76 -> 416.66667 | E23: ='Monat 1–36'!E76 -> 416.66667 | F23: ='Monat 1–36'!F76 -> 416.66667 | G23: ='Monat 1–36'!G76 -> 416.66667 | H23: ='Monat 1–36'!H76 -> 416.66667 | I23: ='Monat 1–36'!I76 -> 416.66667 | J23: ='Monat 1–36'!J76 -> 416.66667 | ... AL23: ='Monat 1–36'!AL76 -> 368.92361 | AM23: ='Monat 37–60'!C76 -> 364.58333 | AN23: ='Monat 37–60'!D76 -> 360.24306 | AO23: ='Monat 37–60'!E76 -> 355.90278 | AP23: ='Monat 37–60'!F76 -> 351.5625 | AQ23: ='Monat 37–60'!G76 -> 347.22222 | AR23: ='Monat 37–60'!H76 -> 342.88194 | AS23: ='Monat 37–60'!I76 -> 338.54167 | AT23: ='Monat 37–60'!J76 -> 334.20139 | ... BJ23: ='Monat 37–60'!Z76 -> 264.75694
B24: Tilgung Basis | C24: ='Monat 1–36'!C77 -> 0 | D24: ='Monat 1–36'!D77 -> 0 | E24: ='Monat 1–36'!E77 -> 0 | F24: ='Monat 1–36'!F77 -> 0 | G24: ='Monat 1–36'!G77 -> 0 | H24: ='Monat 1–36'!H77 -> 0 | I24: ='Monat 1–36'!I77 -> 0 | J24: ='Monat 1–36'!J77 -> 0 | ... AL24: ='Monat 1–36'!AL77 -> 1302.0833 | AM24: ='Monat 37–60'!C77 -> 1302.0833 | AN24: ='Monat 37–60'!D77 -> 1302.0833 | AO24: ='Monat 37–60'!E77 -> 1302.0833 | AP24: ='Monat 37–60'!F77 -> 1302.0833 | AQ24: ='Monat 37–60'!G77 -> 1302.0833 | AR24: ='Monat 37–60'!H77 -> 1302.0833 | AS24: ='Monat 37–60'!I77 -> 1302.0833 | AT24: ='Monat 37–60'!J77 -> 1302.0833 | ... BJ24: ='Monat 37–60'!Z77 -> 1302.0833
B25: EBITDA Basis (Kontrolle) | C25: ='Monat 1–36'!C70 -> -15956.234 | D25: ='Monat 1–36'!D70 -> -5841.8434 | E25: ='Monat 1–36'!E70 -> -6333.4615 | F25: ='Monat 1–36'!F70 -> -13768.485 | G25: ='Monat 1–36'!G70 -> -4146.9644 | H25: ='Monat 1–36'!H70 -> -3537.3078 | I25: ='Monat 1–36'!I70 -> -8914.7872 | J25: ='Monat 1–36'!J70 -> -6203.3322 | ... AL25: ='Monat 1–36'!AL70 -> 14500.186 | AM25: ='Monat 37–60'!C70 -> -4997.5913 | AN25: ='Monat 37–60'!D70 -> 1971.8073 | AO25: ='Monat 37–60'!E70 -> -4721.3656 | AP25: ='Monat 37–60'!F70 -> 8524.1875 | AQ25: ='Monat 37–60'!G70 -> 11709.735 | AR25: ='Monat 37–60'!H70 -> 14836.515 | AS25: ='Monat 37–60'!I70 -> 11041.38 | AT25: ='Monat 37–60'!J70 -> 15854.232 | ... BJ25: ='Monat 37–60'!Z70 -> 51198.954
B28: ="Szenario "&A5&": "&B5 -> Szenario 1: Basisplan
B29: Kunden Start | C29: =Annahmen!$B$7*Annahmen!$B$19*(1-Annahmen!$B$31*$C$5)+C$21*$E$5*Annahmen!$B$19 -> 3.925 | D29: =C29*(1-Annahmen!$B$31*$C$5)+D$21*$E$5*Annahmen!$B$19 -> 5.30725 | E29: =D29*(1-Annahmen!$B$31*$C$5)+E$21*$E$5*Annahmen!$B$19 -> 6.6480325 | F29: =E29*(1-Annahmen!$B$31*$C$5)+F$21*$E$5*Annahmen!$B$19 -> 9.4485915 | G29: =F29*(1-Annahmen!$B$31*$C$5)+G$21*$E$5*Annahmen!$B$19 -> 12.165134 | H29: =G29*(1-Annahmen!$B$31*$C$5)+H$21*$E$5*Annahmen!$B$19 -> 14.80018 | I29: =H29*(1-Annahmen!$B$31*$C$5)+I$21*$E$5*Annahmen!$B$19 -> 18.856174 | J29: =I29*(1-Annahmen!$B$31*$C$5)+J$21*$E$5*Annahmen!$B$19 -> 22.790489 | K29: =J29*(1-Annahmen!$B$31*$C$5)+K$21*$E$5*Annahmen!$B$19 -> 26.606774 | ... BJ29: =BI29*(1-Annahmen!$B$31*$C$5)+BJ$21*$E$5*Annahmen!$B$19 -> 574.20269
B30: Kunden Flotte | C30: =Annahmen!$B$7*Annahmen!$B$20*(1-Annahmen!$B$32*$C$5)+C$21*$E$5*Annahmen!$B$20 -> 3.002 | D30: =C30*(1-Annahmen!$B$32*$C$5)+D$21*$E$5*Annahmen!$B$20 -> 4.08196 | E30: =D30*(1-Annahmen!$B$32*$C$5)+E$21*$E$5*Annahmen!$B$20 -> 5.1403208 | F30: =E30*(1-Annahmen!$B$32*$C$5)+F$21*$E$5*Annahmen!$B$20 -> 7.3175144 | G30: =F30*(1-Annahmen!$B$32*$C$5)+G$21*$E$5*Annahmen!$B$20 -> 9.4511641 | H30: =G30*(1-Annahmen!$B$32*$C$5)+H$21*$E$5*Annahmen!$B$20 -> 11.542141 | I30: =H30*(1-Annahmen!$B$32*$C$5)+I$21*$E$5*Annahmen!$B$20 -> 14.731298 | J30: =I30*(1-Annahmen!$B$32*$C$5)+J$21*$E$5*Annahmen!$B$20 -> 17.856672 | K30: =J30*(1-Annahmen!$B$32*$C$5)+K$21*$E$5*Annahmen!$B$20 -> 20.919539 | ... BJ30: =BI30*(1-Annahmen!$B$32*$C$5)+BJ$21*$E$5*Annahmen!$B$20 -> 514.20138
B31: Kunden Premium | C31: =Annahmen!$B$7*Annahmen!$B$21*(1-Annahmen!$B$33*$C$5)+C$21*$E$5*Annahmen!$B$21 -> 0.9528 | D31: =C31*(1-Annahmen!$B$33*$C$5)+D$21*$E$5*Annahmen!$B$21 -> 1.3013664 | E31: =D31*(1-Annahmen!$B$33*$C$5)+E$21*$E$5*Annahmen!$B$21 -> 1.64575 | F31: =E31*(1-Annahmen!$B$33*$C$5)+F$21*$E$5*Annahmen!$B$21 -> 2.346001 | G31: =F31*(1-Annahmen!$B$33*$C$5)+G$21*$E$5*Annahmen!$B$21 -> 3.037849 | H31: =G31*(1-Annahmen!$B$33*$C$5)+H$21*$E$5*Annahmen!$B$21 -> 3.7213948 | I31: =H31*(1-Annahmen!$B$33*$C$5)+I$21*$E$5*Annahmen!$B$21 -> 4.7567381 | J31: =I31*(1-Annahmen!$B$33*$C$5)+J$21*$E$5*Annahmen!$B$21 -> 5.7796572 | K31: =J31*(1-Annahmen!$B$33*$C$5)+K$21*$E$5*Annahmen!$B$21 -> 6.7903013 | ... BJ31: =BI31*(1-Annahmen!$B$33*$C$5)+BJ$21*$E$5*Annahmen!$B$21 -> 187.339
B32: Store-Apps | C32: =Annahmen!$B$7*Annahmen!$B$21*Annahmen!$B$24*(1-Annahmen!$B$33*$C$5)+C$21*$E$5*Annahmen!$B$21*Annahmen!$B$24 -> 0.19056 | D32: =C32*(1-Annahmen!$B$33*$C$5)+D$21*$E$5*Annahmen!$B$21*Annahmen!$B$24 -> 0.26027328 | E32: =D32*(1-Annahmen!$B$33*$C$5)+E$21*$E$5*Annahmen!$B$21*Annahmen!$B$24 -> 0.32915 | F32: =E32*(1-Annahmen!$B$33*$C$5)+F$21*$E$5*Annahmen!$B$21*Annahmen!$B$24 -> 0.4692002 | G32: =F32*(1-Annahmen!$B$33*$C$5)+G$21*$E$5*Annahmen!$B$21*Annahmen!$B$24 -> 0.6075698 | H32: =G32*(1-Annahmen!$B$33*$C$5)+H$21*$E$5*Annahmen!$B$21*Annahmen!$B$24 -> 0.74427896 | I32: =H32*(1-Annahmen!$B$33*$C$5)+I$21*$E$5*Annahmen!$B$21*Annahmen!$B$24 -> 0.95134761 | J32: =I32*(1-Annahmen!$B$33*$C$5)+J$21*$E$5*Annahmen!$B$21*Annahmen!$B$24 -> 1.1559314 | K32: =J32*(1-Annahmen!$B$33*$C$5)+K$21*$E$5*Annahmen!$B$21*Annahmen!$B$24 -> 1.3580603 | ... BJ32: =BI32*(1-Annahmen!$B$33*$C$5)+BJ$21*$E$5*Annahmen!$B$21*Annahmen!$B$24 -> 37.467799
B33: Kunden gesamt | C33: =C29+C30+C31 -> 7.8798 | D33: =D29+D30+D31 -> 10.690576 | E33: =E29+E30+E31 -> 13.434103 | F33: =F29+F30+F31 -> 19.112107 | G33: =G29+G30+G31 -> 24.654147 | H33: =H29+H30+H31 -> 30.063715 | I33: =I29+I30+I31 -> 38.34421 | J33: =J29+J30+J31 -> 46.426818 | ... BJ33: =BJ29+BJ30+BJ31 -> 1275.7431
B34: MRR | C34: =(C29*Annahmen!$B$10+C30*(Annahmen!$B$11+Annahmen!$B$13*Annahmen!$B$22)+C31*(Annahmen!$B$12+Annahmen!$B$14*Annahmen!$B$23)+C32*Annahmen!$B$16)*$D$5 -> 943.44064 | D34: =(D29*Annahmen!$B$10+D30*(Annahmen!$B$11+Annahmen!$B$13*Annahmen!$B$22)+D31*(Annahmen!$B$12+Annahmen!$B$14*Annahmen!$B$23)+D32*Annahmen!$B$16)*$D$5 -> 1283.4053 | E34: =(E29*Annahmen!$B$10+E30*(Annahmen!$B$11+Annahmen!$B$13*Annahmen!$B$22)+E31*(Annahmen!$B$12+Annahmen!$B$14*Annahmen!$B$23)+E32*Annahmen!$B$16)*$D$5 -> 1616.8659 | F34: =(F29*Annahmen!$B$10+F30*(Annahmen!$B$11+Annahmen!$B$13*Annahmen!$B$22)+F31*(Annahmen!$B$12+Annahmen!$B$14*Annahmen!$B$23)+F32*Annahmen!$B$16)*$D$5 -> 2302.0594 | G34: =(G29*Annahmen!$B$10+G30*(Annahmen!$B$11+Annahmen!$B$13*Annahmen!$B$22)+G31*(Annahmen!$B$12+Annahmen!$B$14*Annahmen!$B$23)+G32*Annahmen!$B$16)*$D$5 -> 2974.1307 | H34: =(H29*Annahmen!$B$10+H30*(Annahmen!$B$11+Annahmen!$B$13*Annahmen!$B$22)+H31*(Annahmen!$B$12+Annahmen!$B$14*Annahmen!$B$23)+H32*Annahmen!$B$16)*$D$5 -> 3633.36 | I34: =(I29*Annahmen!$B$10+I30*(Annahmen!$B$11+Annahmen!$B$13*Annahmen!$B$22)+I31*(Annahmen!$B$12+Annahmen!$B$14*Annahmen!$B$23)+I32*Annahmen!$B$16)*$D$5 -> 4638.1189 | J34: =(J29*Annahmen!$B$10+J30*(Annahmen!$B$11+Annahmen!$B$13*Annahmen!$B$22)+J31*(Annahmen!$B$12+Annahmen!$B$14*Annahmen!$B$23)+J32*Annahmen!$B$16)*$D$5 -> 5623.6842 | ... BJ34: =(BJ29*Annahmen!$B$10+BJ30*(Annahmen!$B$11+Annahmen!$B$13*Annahmen!$B$22)+BJ31*(Annahmen!$B$12+Annahmen!$B$14*Annahmen!$B$23)+BJ32*Annahmen!$B$16)*$D$5 -> 165210.87
B35: Umsatz | C35: =C34*(1-Annahmen!$B$27)+C$21*$E$5*Annahmen!$B$21*Annahmen!$B$24*Annahmen!$B$15*$D$5 -> 1039.5486 | D35: =D34*(1-Annahmen!$B$27)+D$21*$E$5*Annahmen!$B$21*Annahmen!$B$24*Annahmen!$B$15*$D$5 -> 1362.515 | E35: =E34*(1-Annahmen!$B$27)+E$21*$E$5*Annahmen!$B$21*Annahmen!$B$24*Annahmen!$B$15*$D$5 -> 1679.3026 | F35: =F34*(1-Annahmen!$B$27)+F$21*$E$5*Annahmen!$B$21*Annahmen!$B$24*Annahmen!$B$15*$D$5 -> 2473.5164 | G35: =G34*(1-Annahmen!$B$27)+G$21*$E$5*Annahmen!$B$21*Annahmen!$B$24*Annahmen!$B$15*$D$5 -> 3111.9841 | H35: =H34*(1-Annahmen!$B$27)+H$21*$E$5*Annahmen!$B$21*Annahmen!$B$24*Annahmen!$B$15*$D$5 -> 3738.252 | I35: =I34*(1-Annahmen!$B$27)+I$21*$E$5*Annahmen!$B$21*Annahmen!$B$24*Annahmen!$B$15*$D$5 -> 4836.0529 | J35: =J34*(1-Annahmen!$B$27)+J$21*$E$5*Annahmen!$B$21*Annahmen!$B$24*Annahmen!$B$15*$D$5 -> 5772.3399 | ... BJ35: =BJ34*(1-Annahmen!$B$27)+BJ$21*$E$5*Annahmen!$B$21*Annahmen!$B$24*Annahmen!$B$15*$D$5 -> 159577.12
B36: Variable Kosten | C36: =C29*Annahmen!$B$52+C30*Annahmen!$B$53+C31*Annahmen!$B$54+C35*Annahmen!$B$55+C33*Annahmen!$B$56+C35*INDEX(Annahmen!$B$58:$F$58,1,C$20)*Annahmen!$B$57+C$21*$E$5*Annahmen!$B$21*Annahmen!$B$24*Annahmen!$B$59 -> 35.782319 | D36: =D29*Annahmen!$B$52+D30*Annahmen!$B$53+D31*Annahmen!$B$54+D35*Annahmen!$B$55+D33*Annahmen!$B$56+D35*INDEX(Annahmen!$B$58:$F$58,1,D$20)*Annahmen!$B$57+D$21*$E$5*Annahmen!$B$21*Annahmen!$B$24*Annahmen!$B$59 -> 44.358374 | E36: =E29*Annahmen!$B$52+E30*Annahmen!$B$53+E31*Annahmen!$B$54+E35*Annahmen!$B$55+E33*Annahmen!$B$56+E35*INDEX(Annahmen!$B$58:$F$58,1,E$20)*Annahmen!$B$57+E$21*$E$5*Annahmen!$B$21*Annahmen!$B$24*Annahmen!$B$59 -> 52.764175 | F36: =F29*Annahmen!$B$52+F30*Annahmen!$B$53+F31*Annahmen!$B$54+F35*Annahmen!$B$55+F33*Annahmen!$B$56+F35*INDEX(Annahmen!$B$58:$F$58,1,F$20)*Annahmen!$B$57+F$21*$E$5*Annahmen!$B$21*Annahmen!$B$24*Annahmen!$B$59 -> 82.001276 | G36: =G29*Annahmen!$B$52+G30*Annahmen!$B$53+G31*Annahmen!$B$54+G35*Annahmen!$B$55+G33*Annahmen!$B$56+G35*INDEX(Annahmen!$B$58:$F$58,1,G$20)*Annahmen!$B$57+G$21*$E$5*Annahmen!$B$21*Annahmen!$B$24*Annahmen!$B$59 -> 98.948505 | H36: =H29*Annahmen!$B$52+H30*Annahmen!$B$53+H31*Annahmen!$B$54+H35*Annahmen!$B$55+H33*Annahmen!$B$56+H35*INDEX(Annahmen!$B$58:$F$58,1,H$20)*Annahmen!$B$57+H$21*$E$5*Annahmen!$B$21*Annahmen!$B$24*Annahmen!$B$59 -> 115.55972 | I36: =I29*Annahmen!$B$52+I30*Annahmen!$B$53+I31*Annahmen!$B$54+I35*Annahmen!$B$55+I33*Annahmen!$B$56+I35*INDEX(Annahmen!$B$58:$F$58,1,I$20)*Annahmen!$B$57+I$21*$E$5*Annahmen!$B$21*Annahmen!$B$24*Annahmen!$B$59 -> 152.84012 | J36: =J29*Annahmen!$B$52+J30*Annahmen!$B$53+J31*Annahmen!$B$54+J35*Annahmen!$B$55+J33*Annahmen!$B$56+J35*INDEX(Annahmen!$B$58:$F$58,1,J$20)*Annahmen!$B$57+J$21*$E$5*Annahmen!$B$21*Annahmen!$B$24*Annahmen!$B$59 -> 177.67213 | ... BJ36: =BJ29*Annahmen!$B$52+BJ30*Annahmen!$B$53+BJ31*Annahmen!$B$54+BJ35*Annahmen!$B$55+BJ33*Annahmen!$B$56+BJ35*INDEX(Annahmen!$B$58:$F$58,1,BJ$20)*Annahmen!$B$57+BJ$21*$E$5*Annahmen!$B$21*Annahmen!$B$24*Annahmen!$B$59 -> 16313.871
B37: EBITDA | C37: =C35-C36-C$22 -> -15956.234 | D37: =D35-D36-D$22 -> -5841.8434 | E37: =E35-E36-E$22 -> -6333.4615 | F37: =F35-F36-F$22 -> -13768.485 | G37: =G35-G36-G$22 -> -4146.9644 | H37: =H35-H36-H$22 -> -3537.3078 | I37: =I35-I36-I$22 -> -8914.7872 | J37: =J35-J36-J$22 -> -6203.3322 | ... BJ37: =BJ35-BJ36-BJ$22 -> 51198.954
B38: Kum. Cashflow vor Steuern | C38: =0+C37-C$23-C$24 -> -16372.9 | D38: =C38+D37-D$23-D$24 -> -22631.41 | E38: =D38+E37-E$23-E$24 -> -29381.539 | F38: =E38+F37-F$23-F$24 -> -43566.69 | G38: =F38+G37-G$23-G$24 -> -48130.321 | H38: =G38+H37-H$23-H$24 -> -52084.296 | I38: =H38+I37-I$23-I$24 -> -61415.749 | J38: =I38+J37-J$23-J$24 -> -68035.748 | K38: =J38+K37-K$23-K$24 -> -73761.647 | ... BJ38: =BI38+BJ37-BJ$23-BJ$24 -> 195886.07
B39: Hilfszeile Break-even | C39: =IF(C37>=0,C$19,999) -> 999 | D39: =IF(D37>=0,D$19,999) -> 999 | E39: =IF(E37>=0,E$19,999) -> 999 | F39: =IF(F37>=0,F$19,999) -> 999 | G39: =IF(G37>=0,G$19,999) -> 999 | H39: =IF(H37>=0,H$19,999) -> 999 | I39: =IF(I37>=0,I$19,999) -> 999 | J39: =IF(J37>=0,J$19,999) -> 999 | ... BJ39: =IF(BJ37>=0,BJ$19,999) -> 60
B40: ="Szenario "&A6&": "&B6 -> Szenario 2: Churn +50 %
B41: Kunden Start | C41: =Annahmen!$B$7*Annahmen!$B$19*(1-Annahmen!$B$31*$C$6)+C$21*$E$6*Annahmen!$B$19 -> 3.8875 | D41: =C41*(1-Annahmen!$B$31*$C$6)+D$21*$E$6*Annahmen!$B$19 -> 5.2125625 | E41: =D41*(1-Annahmen!$B$31*$C$6)+E$21*$E$6*Annahmen!$B$19 -> 6.4779972 | F41: =E41*(1-Annahmen!$B$31*$C$6)+F$21*$E$6*Annahmen!$B$19 -> 9.1864873 | G41: =F41*(1-Annahmen!$B$31*$C$6)+G$21*$E$6*Annahmen!$B$19 -> 11.773095 | H41: =G41*(1-Annahmen!$B$31*$C$6)+H$21*$E$6*Annahmen!$B$19 -> 14.243306 | I41: =H41*(1-Annahmen!$B$31*$C$6)+I$21*$E$6*Annahmen!$B$19 -> 18.102357 | J41: =I41*(1-Annahmen!$B$31*$C$6)+J$21*$E$6*Annahmen!$B$19 -> 21.787751 | K41: =J41*(1-Annahmen!$B$31*$C$6)+K$21*$E$6*Annahmen!$B$19 -> 25.307302 | ... BJ41: =BI41*(1-Annahmen!$B$31*$C$6)+BJ$21*$E$6*Annahmen!$B$19 -> 461.44515
B42: Kunden Flotte | C42: =Annahmen!$B$7*Annahmen!$B$20*(1-Annahmen!$B$32*$C$6)+C$21*$E$6*Annahmen!$B$20 -> 2.983 | D42: =C42*(1-Annahmen!$B$32*$C$6)+D$21*$E$6*Annahmen!$B$20 -> 4.03351 | E42: =D42*(1-Annahmen!$B$32*$C$6)+E$21*$E$6*Annahmen!$B$20 -> 5.0525047 | F42: =E42*(1-Annahmen!$B$32*$C$6)+F$21*$E$6*Annahmen!$B$20 -> 7.1809296 | G42: =F42*(1-Annahmen!$B$32*$C$6)+G$21*$E$6*Annahmen!$B$20 -> 9.2455017 | H42: =G42*(1-Annahmen!$B$32*$C$6)+H$21*$E$6*Annahmen!$B$20 -> 11.248137 | I42: =H42*(1-Annahmen!$B$32*$C$6)+I$21*$E$6*Annahmen!$B$20 -> 14.330693 | J42: =I42*(1-Annahmen!$B$32*$C$6)+J$21*$E$6*Annahmen!$B$20 -> 17.320772 | K42: =J42*(1-Annahmen!$B$32*$C$6)+K$21*$E$6*Annahmen!$B$20 -> 20.221149 | ... BJ42: =BI42*(1-Annahmen!$B$32*$C$6)+BJ$21*$E$6*Annahmen!$B$20 -> 436.39404
B43: Kunden Premium | C43: =Annahmen!$B$7*Annahmen!$B$21*(1-Annahmen!$B$33*$C$6)+C$21*$E$6*Annahmen!$B$21 -> 0.9492 | D43: =C43*(1-Annahmen!$B$33*$C$6)+D$21*$E$6*Annahmen!$B$21 -> 1.2921144 | E43: =D43*(1-Annahmen!$B$33*$C$6)+E$21*$E$6*Annahmen!$B$21 -> 1.6288563 | F43: =E43*(1-Annahmen!$B$33*$C$6)+F$21*$E$6*Annahmen!$B$21 -> 2.3195369 | G43: =F43*(1-Annahmen!$B$33*$C$6)+G$21*$E$6*Annahmen!$B$21 -> 2.9977853 | H43: =G43*(1-Annahmen!$B$33*$C$6)+H$21*$E$6*Annahmen!$B$21 -> 3.6638251 | I43: =H43*(1-Annahmen!$B$33*$C$6)+I$21*$E$6*Annahmen!$B$21 -> 4.6778763 | J43: =I43*(1-Annahmen!$B$33*$C$6)+J$21*$E$6*Annahmen!$B$21 -> 5.6736745 | K43: =J43*(1-Annahmen!$B$33*$C$6)+K$21*$E$6*Annahmen!$B$21 -> 6.6515484 | ... BJ43: =BI43*(1-Annahmen!$B$33*$C$6)+BJ$21*$E$6*Annahmen!$B$21 -> 168.11863
B44: Store-Apps | C44: =Annahmen!$B$7*Annahmen!$B$21*Annahmen!$B$24*(1-Annahmen!$B$33*$C$6)+C$21*$E$6*Annahmen!$B$21*Annahmen!$B$24 -> 0.18984 | D44: =C44*(1-Annahmen!$B$33*$C$6)+D$21*$E$6*Annahmen!$B$21*Annahmen!$B$24 -> 0.25842288 | E44: =D44*(1-Annahmen!$B$33*$C$6)+E$21*$E$6*Annahmen!$B$21*Annahmen!$B$24 -> 0.32577127 | F44: =E44*(1-Annahmen!$B$33*$C$6)+F$21*$E$6*Annahmen!$B$21*Annahmen!$B$24 -> 0.46390739 | G44: =F44*(1-Annahmen!$B$33*$C$6)+G$21*$E$6*Annahmen!$B$21*Annahmen!$B$24 -> 0.59955705 | H44: =G44*(1-Annahmen!$B$33*$C$6)+H$21*$E$6*Annahmen!$B$21*Annahmen!$B$24 -> 0.73276503 | I44: =H44*(1-Annahmen!$B$33*$C$6)+I$21*$E$6*Annahmen!$B$21*Annahmen!$B$24 -> 0.93557525 | J44: =I44*(1-Annahmen!$B$33*$C$6)+J$21*$E$6*Annahmen!$B$21*Annahmen!$B$24 -> 1.1347349 | K44: =J44*(1-Annahmen!$B$33*$C$6)+K$21*$E$6*Annahmen!$B$21*Annahmen!$B$24 -> 1.3303097 | ... BJ44: =BI44*(1-Annahmen!$B$33*$C$6)+BJ$21*$E$6*Annahmen!$B$21*Annahmen!$B$24 -> 33.623726
B45: Kunden gesamt | C45: =C41+C42+C43 -> 7.8197 | D45: =D41+D42+D43 -> 10.538187 | E45: =E41+E42+E43 -> 13.159358 | F45: =F41+F42+F43 -> 18.686954 | G45: =G41+G42+G43 -> 24.016382 | H45: =H41+H42+H43 -> 29.155268 | I45: =I41+I42+I43 -> 37.110926 | J45: =J41+J42+J43 -> 44.782197 | ... BJ45: =BJ41+BJ42+BJ43 -> 1065.9578
B46: MRR | C46: =(C41*Annahmen!$B$10+C42*(Annahmen!$B$11+Annahmen!$B$13*Annahmen!$B$22)+C43*(Annahmen!$B$12+Annahmen!$B$14*Annahmen!$B$23)+C44*Annahmen!$B$16)*$D$6 -> 937.69696 | D46: =(D41*Annahmen!$B$10+D42*(Annahmen!$B$11+Annahmen!$B$13*Annahmen!$B$22)+D43*(Annahmen!$B$12+Annahmen!$B$14*Annahmen!$B$23)+D44*Annahmen!$B$16)*$D$6 -> 1268.7797 | E46: =(E41*Annahmen!$B$10+E42*(Annahmen!$B$11+Annahmen!$B$13*Annahmen!$B$22)+E43*(Annahmen!$B$12+Annahmen!$B$14*Annahmen!$B$23)+E44*Annahmen!$B$16)*$D$6 -> 1590.3914 | F46: =(F41*Annahmen!$B$10+F42*(Annahmen!$B$11+Annahmen!$B$13*Annahmen!$B$22)+F43*(Annahmen!$B$12+Annahmen!$B$14*Annahmen!$B$23)+F44*Annahmen!$B$16)*$D$6 -> 2260.932 | G46: =(G41*Annahmen!$B$10+G42*(Annahmen!$B$11+Annahmen!$B$13*Annahmen!$B$22)+G43*(Annahmen!$B$12+Annahmen!$B$14*Annahmen!$B$23)+G44*Annahmen!$B$16)*$D$6 -> 2912.2567 | H46: =(H41*Annahmen!$B$10+H42*(Annahmen!$B$11+Annahmen!$B$13*Annahmen!$B$22)+H43*(Annahmen!$B$12+Annahmen!$B$14*Annahmen!$B$23)+H44*Annahmen!$B$16)*$D$6 -> 3544.9793 | I46: =(I41*Annahmen!$B$10+I42*(Annahmen!$B$11+Annahmen!$B$13*Annahmen!$B$22)+I43*(Annahmen!$B$12+Annahmen!$B$14*Annahmen!$B$23)+I44*Annahmen!$B$16)*$D$6 -> 4517.7904 | J46: =(J41*Annahmen!$B$10+J42*(Annahmen!$B$11+Annahmen!$B$13*Annahmen!$B$22)+J43*(Annahmen!$B$12+Annahmen!$B$14*Annahmen!$B$23)+J44*Annahmen!$B$16)*$D$6 -> 5462.8251 | ... BJ46: =(BJ41*Annahmen!$B$10+BJ42*(Annahmen!$B$11+Annahmen!$B$13*Annahmen!$B$22)+BJ43*(Annahmen!$B$12+Annahmen!$B$14*Annahmen!$B$23)+BJ44*Annahmen!$B$16)*$D$6 -> 142127.56
B47: Umsatz | C47: =C46*(1-Annahmen!$B$27)+C$21*$E$6*Annahmen!$B$21*Annahmen!$B$24*Annahmen!$B$15*$D$6 -> 1034.0921 | D47: =D46*(1-Annahmen!$B$27)+D$21*$E$6*Annahmen!$B$21*Annahmen!$B$24*Annahmen!$B$15*$D$6 -> 1348.6207 | E47: =E46*(1-Annahmen!$B$27)+E$21*$E$6*Annahmen!$B$21*Annahmen!$B$24*Annahmen!$B$15*$D$6 -> 1654.1518 | F47: =F46*(1-Annahmen!$B$27)+F$21*$E$6*Annahmen!$B$21*Annahmen!$B$24*Annahmen!$B$15*$D$6 -> 2434.4454 | G47: =G46*(1-Annahmen!$B$27)+G$21*$E$6*Annahmen!$B$21*Annahmen!$B$24*Annahmen!$B$15*$D$6 -> 3053.2038 | H47: =H46*(1-Annahmen!$B$27)+H$21*$E$6*Annahmen!$B$21*Annahmen!$B$24*Annahmen!$B$15*$D$6 -> 3654.2903 | I47: =I46*(1-Annahmen!$B$27)+I$21*$E$6*Annahmen!$B$21*Annahmen!$B$24*Annahmen!$B$15*$D$6 -> 4721.7408 | J47: =J46*(1-Annahmen!$B$27)+J$21*$E$6*Annahmen!$B$21*Annahmen!$B$24*Annahmen!$B$15*$D$6 -> 5619.5239 | ... BJ47: =BJ46*(1-Annahmen!$B$27)+BJ$21*$E$6*Annahmen!$B$21*Annahmen!$B$24*Annahmen!$B$15*$D$6 -> 137647.98
B48: Variable Kosten | C48: =C41*Annahmen!$B$52+C42*Annahmen!$B$53+C43*Annahmen!$B$54+C47*Annahmen!$B$55+C45*Annahmen!$B$56+C47*INDEX(Annahmen!$B$58:$F$58,1,C$20)*Annahmen!$B$57+C$21*$E$6*Annahmen!$B$21*Annahmen!$B$24*Annahmen!$B$59 -> 35.631632 | D48: =D41*Annahmen!$B$52+D42*Annahmen!$B$53+D43*Annahmen!$B$54+D47*Annahmen!$B$55+D45*Annahmen!$B$56+D47*INDEX(Annahmen!$B$58:$F$58,1,D$20)*Annahmen!$B$57+D$21*$E$6*Annahmen!$B$21*Annahmen!$B$24*Annahmen!$B$59 -> 43.974973 | E48: =E41*Annahmen!$B$52+E42*Annahmen!$B$53+E43*Annahmen!$B$54+E47*Annahmen!$B$55+E45*Annahmen!$B$56+E47*INDEX(Annahmen!$B$58:$F$58,1,E$20)*Annahmen!$B$57+E$21*$E$6*Annahmen!$B$21*Annahmen!$B$24*Annahmen!$B$59 -> 52.070679 | F48: =F41*Annahmen!$B$52+F42*Annahmen!$B$53+F43*Annahmen!$B$54+F47*Annahmen!$B$55+F45*Annahmen!$B$56+F47*INDEX(Annahmen!$B$58:$F$58,1,F$20)*Annahmen!$B$57+F$21*$E$6*Annahmen!$B$21*Annahmen!$B$24*Annahmen!$B$59 -> 80.924731 | G48: =G41*Annahmen!$B$52+G42*Annahmen!$B$53+G43*Annahmen!$B$54+G47*Annahmen!$B$55+G45*Annahmen!$B$56+G47*INDEX(Annahmen!$B$58:$F$58,1,G$20)*Annahmen!$B$57+G$21*$E$6*Annahmen!$B$21*Annahmen!$B$24*Annahmen!$B$59 -> 97.32977 | H48: =H41*Annahmen!$B$52+H42*Annahmen!$B$53+H43*Annahmen!$B$54+H47*Annahmen!$B$55+H45*Annahmen!$B$56+H47*INDEX(Annahmen!$B$58:$F$58,1,H$20)*Annahmen!$B$57+H$21*$E$6*Annahmen!$B$21*Annahmen!$B$24*Annahmen!$B$59 -> 113.24871 | I48: =I41*Annahmen!$B$52+I42*Annahmen!$B$53+I43*Annahmen!$B$54+I47*Annahmen!$B$55+I45*Annahmen!$B$56+I47*INDEX(Annahmen!$B$58:$F$58,1,I$20)*Annahmen!$B$57+I$21*$E$6*Annahmen!$B$21*Annahmen!$B$24*Annahmen!$B$59 -> 149.6954 | J48: =J41*Annahmen!$B$52+J42*Annahmen!$B$53+J43*Annahmen!$B$54+J47*Annahmen!$B$55+J45*Annahmen!$B$56+J47*INDEX(Annahmen!$B$58:$F$58,1,J$20)*Annahmen!$B$57+J$21*$E$6*Annahmen!$B$21*Annahmen!$B$24*Annahmen!$B$59 -> 173.47008 | ... BJ48: =BJ41*Annahmen!$B$52+BJ42*Annahmen!$B$53+BJ43*Annahmen!$B$54+BJ47*Annahmen!$B$55+BJ45*Annahmen!$B$56+BJ47*INDEX(Annahmen!$B$58:$F$58,1,BJ$20)*Annahmen!$B$57+BJ$21*$E$6*Annahmen!$B$21*Annahmen!$B$24*Annahmen!$B$59 -> 14078.405
B49: EBITDA | C49: =C47-C48-C$22 -> -15961.54 | D49: =D47-D48-D$22 -> -5855.3542 | E49: =E47-E48-E$22 -> -6357.9189 | F49: =F47-F48-F$22 -> -13806.479 | G49: =G47-G48-G$22 -> -4204.1259 | H49: =H47-H48-H$22 -> -3618.9584 | I49: =I47-I48-I$22 -> -9025.9546 | J49: =J47-J48-J$22 -> -6351.9462 | ... BJ49: =BJ47-BJ48-BJ$22 -> 31505.278
B50: Kum. Cashflow vor Steuern | C50: =0+C49-C$23-C$24 -> -16378.206 | D50: =C50+D49-D$23-D$24 -> -22650.227 | E50: =D50+E49-E$23-E$24 -> -29424.813 | F50: =E50+F49-F$23-F$24 -> -43647.959 | G50: =F50+G49-G$23-G$24 -> -48268.751 | H50: =G50+H49-H$23-H$24 -> -52304.376 | I50: =H50+I49-I$23-I$24 -> -61746.998 | J50: =I50+J49-J$23-J$24 -> -68515.61 | K50: =J50+K49-K$23-K$24 -> -74435.06 | ... BJ50: =BI50+BJ49-BJ$23-BJ$24 -> -169436.03
B51: Hilfszeile Break-even | C51: =IF(C49>=0,C$19,999) -> 999 | D51: =IF(D49>=0,D$19,999) -> 999 | E51: =IF(E49>=0,E$19,999) -> 999 | F51: =IF(F49>=0,F$19,999) -> 999 | G51: =IF(G49>=0,G$19,999) -> 999 | H51: =IF(H49>=0,H$19,999) -> 999 | I51: =IF(I49>=0,I$19,999) -> 999 | J51: =IF(J49>=0,J$19,999) -> 999 | ... BJ51: =IF(BJ49>=0,BJ$19,999) -> 60
B52: ="Szenario "&A7&": "&B7 -> Szenario 3: Churn doppelt
B53: Kunden Start | C53: =Annahmen!$B$7*Annahmen!$B$19*(1-Annahmen!$B$31*$C$7)+C$21*$E$7*Annahmen!$B$19 -> 3.85 | D53: =C53*(1-Annahmen!$B$31*$C$7)+D$21*$E$7*Annahmen!$B$19 -> 5.119 | E53: =D53*(1-Annahmen!$B$31*$C$7)+E$21*$E$7*Annahmen!$B$19 -> 6.31186 | F53: =E53*(1-Annahmen!$B$31*$C$7)+F$21*$E$7*Annahmen!$B$19 -> 8.9331484 | G53: =F53*(1-Annahmen!$B$31*$C$7)+G$21*$E$7*Annahmen!$B$19 -> 11.397159 | H53: =G53*(1-Annahmen!$B$31*$C$7)+H$21*$E$7*Annahmen!$B$19 -> 13.71333 | I53: =H53*(1-Annahmen!$B$31*$C$7)+I$21*$E$7*Annahmen!$B$19 -> 17.39053 | J53: =I53*(1-Annahmen!$B$31*$C$7)+J$21*$E$7*Annahmen!$B$19 -> 20.847098 | K53: =J53*(1-Annahmen!$B$31*$C$7)+K$21*$E$7*Annahmen!$B$19 -> 24.096272 | ... BJ53: =BI53*(1-Annahmen!$B$31*$C$7)+BJ$21*$E$7*Annahmen!$B$19 -> 381.55073
B54: Kunden Flotte | C54: =Annahmen!$B$7*Annahmen!$B$20*(1-Annahmen!$B$32*$C$7)+C$21*$E$7*Annahmen!$B$20 -> 2.964 | D54: =C54*(1-Annahmen!$B$32*$C$7)+D$21*$E$7*Annahmen!$B$20 -> 3.98544 | E54: =D54*(1-Annahmen!$B$32*$C$7)+E$21*$E$7*Annahmen!$B$20 -> 4.9660224 | F54: =E54*(1-Annahmen!$B$32*$C$7)+F$21*$E$7*Annahmen!$B$20 -> 7.0473815 | G54: =F54*(1-Annahmen!$B$32*$C$7)+G$21*$E$7*Annahmen!$B$20 -> 9.0454862 | H54: =G54*(1-Annahmen!$B$32*$C$7)+H$21*$E$7*Annahmen!$B$20 -> 10.963667 | I54: =H54*(1-Annahmen!$B$32*$C$7)+I$21*$E$7*Annahmen!$B$20 -> 13.94512 | J54: =I54*(1-Annahmen!$B$32*$C$7)+J$21*$E$7*Annahmen!$B$20 -> 16.807315 | K54: =J54*(1-Annahmen!$B$32*$C$7)+K$21*$E$7*Annahmen!$B$20 -> 19.555023 | ... BJ54: =BI54*(1-Annahmen!$B$32*$C$7)+BJ$21*$E$7*Annahmen!$B$20 -> 375.92385
B55: Kunden Premium | C55: =Annahmen!$B$7*Annahmen!$B$21*(1-Annahmen!$B$33*$C$7)+C$21*$E$7*Annahmen!$B$21 -> 0.9456 | D55: =C55*(1-Annahmen!$B$33*$C$7)+D$21*$E$7*Annahmen!$B$21 -> 1.2829056 | E55: =D55*(1-Annahmen!$B$33*$C$7)+E$21*$E$7*Annahmen!$B$21 -> 1.6121159 | F55: =E55*(1-Annahmen!$B$33*$C$7)+F$21*$E$7*Annahmen!$B$21 -> 2.2934251 | G55: =F55*(1-Annahmen!$B$33*$C$7)+G$21*$E$7*Annahmen!$B$21 -> 2.9583829 | H55: =G55*(1-Annahmen!$B$33*$C$7)+H$21*$E$7*Annahmen!$B$21 -> 3.6073817 | I55: =H55*(1-Annahmen!$B$33*$C$7)+I$21*$E$7*Annahmen!$B$21 -> 4.6008045 | J55: =I55*(1-Annahmen!$B$33*$C$7)+J$21*$E$7*Annahmen!$B$21 -> 5.5703852 | K55: =J55*(1-Annahmen!$B$33*$C$7)+K$21*$E$7*Annahmen!$B$21 -> 6.516696 | ... BJ55: =BI55*(1-Annahmen!$B$33*$C$7)+BJ$21*$E$7*Annahmen!$B$21 -> 151.77853
B56: Store-Apps | C56: =Annahmen!$B$7*Annahmen!$B$21*Annahmen!$B$24*(1-Annahmen!$B$33*$C$7)+C$21*$E$7*Annahmen!$B$21*Annahmen!$B$24 -> 0.18912 | D56: =C56*(1-Annahmen!$B$33*$C$7)+D$21*$E$7*Annahmen!$B$21*Annahmen!$B$24 -> 0.25658112 | E56: =D56*(1-Annahmen!$B$33*$C$7)+E$21*$E$7*Annahmen!$B$21*Annahmen!$B$24 -> 0.32242317 | F56: =E56*(1-Annahmen!$B$33*$C$7)+F$21*$E$7*Annahmen!$B$21*Annahmen!$B$24 -> 0.45868502 | G56: =F56*(1-Annahmen!$B$33*$C$7)+G$21*$E$7*Annahmen!$B$21*Annahmen!$B$24 -> 0.59167658 | H56: =G56*(1-Annahmen!$B$33*$C$7)+H$21*$E$7*Annahmen!$B$21*Annahmen!$B$24 -> 0.72147634 | I56: =H56*(1-Annahmen!$B$33*$C$7)+I$21*$E$7*Annahmen!$B$21*Annahmen!$B$24 -> 0.92016091 | J56: =I56*(1-Annahmen!$B$33*$C$7)+J$21*$E$7*Annahmen!$B$21*Annahmen!$B$24 -> 1.114077 | K56: =J56*(1-Annahmen!$B$33*$C$7)+K$21*$E$7*Annahmen!$B$21*Annahmen!$B$24 -> 1.3033392 | ... BJ56: =BI56*(1-Annahmen!$B$33*$C$7)+BJ$21*$E$7*Annahmen!$B$21*Annahmen!$B$24 -> 30.355705
B57: Kunden gesamt | C57: =C53+C54+C55 -> 7.7596 | D57: =D53+D54+D55 -> 10.387346 | E57: =E53+E54+E55 -> 12.889998 | F57: =F53+F54+F55 -> 18.273955 | G57: =G53+G54+G55 -> 23.401029 | H57: =H53+H54+H55 -> 28.284378 | I57: =I53+I54+I55 -> 35.936455 | J57: =J53+J54+J55 -> 43.224799 | ... BJ57: =BJ53+BJ54+BJ55 -> 909.2531
B58: MRR | C58: =(C53*Annahmen!$B$10+C54*(Annahmen!$B$11+Annahmen!$B$13*Annahmen!$B$22)+C55*(Annahmen!$B$12+Annahmen!$B$14*Annahmen!$B$23)+C56*Annahmen!$B$16)*$D$7 -> 931.95328 | D58: =(D53*Annahmen!$B$10+D54*(Annahmen!$B$11+Annahmen!$B$13*Annahmen!$B$22)+D55*(Annahmen!$B$12+Annahmen!$B$14*Annahmen!$B$23)+D56*Annahmen!$B$16)*$D$7 -> 1254.2774 | E58: =(E53*Annahmen!$B$10+E54*(Annahmen!$B$11+Annahmen!$B$13*Annahmen!$B$22)+E55*(Annahmen!$B$12+Annahmen!$B$14*Annahmen!$B$23)+E56*Annahmen!$B$16)*$D$7 -> 1564.3473 | F58: =(F53*Annahmen!$B$10+F54*(Annahmen!$B$11+Annahmen!$B$13*Annahmen!$B$22)+F55*(Annahmen!$B$12+Annahmen!$B$14*Annahmen!$B$23)+F56*Annahmen!$B$16)*$D$7 -> 2220.7807 | G58: =(G53*Annahmen!$B$10+G54*(Annahmen!$B$11+Annahmen!$B$13*Annahmen!$B$22)+G55*(Annahmen!$B$12+Annahmen!$B$14*Annahmen!$B$23)+G56*Annahmen!$B$16)*$D$7 -> 2852.1901 | H58: =(H53*Annahmen!$B$10+H54*(Annahmen!$B$11+Annahmen!$B$13*Annahmen!$B$22)+H55*(Annahmen!$B$12+Annahmen!$B$14*Annahmen!$B$23)+H56*Annahmen!$B$16)*$D$7 -> 3459.6394 | I58: =(I53*Annahmen!$B$10+I54*(Annahmen!$B$11+Annahmen!$B$13*Annahmen!$B$22)+I55*(Annahmen!$B$12+Annahmen!$B$14*Annahmen!$B$23)+I56*Annahmen!$B$16)*$D$7 -> 4402.2409 | J58: =(J53*Annahmen!$B$10+J54*(Annahmen!$B$11+Annahmen!$B$13*Annahmen!$B$22)+J55*(Annahmen!$B$12+Annahmen!$B$14*Annahmen!$B$23)+J56*Annahmen!$B$16)*$D$7 -> 5309.0787 | ... BJ58: =(BJ53*Annahmen!$B$10+BJ54*(Annahmen!$B$11+Annahmen!$B$13*Annahmen!$B$22)+BJ55*(Annahmen!$B$12+Annahmen!$B$14*Annahmen!$B$23)+BJ56*Annahmen!$B$16)*$D$7 -> 124077.71
B59: Umsatz | C59: =C58*(1-Annahmen!$B$27)+C$21*$E$7*Annahmen!$B$21*Annahmen!$B$24*Annahmen!$B$15*$D$7 -> 1028.6356 | D59: =D58*(1-Annahmen!$B$27)+D$21*$E$7*Annahmen!$B$21*Annahmen!$B$24*Annahmen!$B$15*$D$7 -> 1334.8435 | E59: =E58*(1-Annahmen!$B$27)+E$21*$E$7*Annahmen!$B$21*Annahmen!$B$24*Annahmen!$B$15*$D$7 -> 1629.4099 | F59: =F58*(1-Annahmen!$B$27)+F$21*$E$7*Annahmen!$B$21*Annahmen!$B$24*Annahmen!$B$15*$D$7 -> 2396.3016 | G59: =G58*(1-Annahmen!$B$27)+G$21*$E$7*Annahmen!$B$21*Annahmen!$B$24*Annahmen!$B$15*$D$7 -> 2996.1406 | H59: =H58*(1-Annahmen!$B$27)+H$21*$E$7*Annahmen!$B$21*Annahmen!$B$24*Annahmen!$B$15*$D$7 -> 3573.2174 | I59: =I58*(1-Annahmen!$B$27)+I$21*$E$7*Annahmen!$B$21*Annahmen!$B$24*Annahmen!$B$15*$D$7 -> 4611.9688 | J59: =J58*(1-Annahmen!$B$27)+J$21*$E$7*Annahmen!$B$21*Annahmen!$B$24*Annahmen!$B$15*$D$7 -> 5473.4647 | ... BJ59: =BJ58*(1-Annahmen!$B$27)+BJ$21*$E$7*Annahmen!$B$21*Annahmen!$B$24*Annahmen!$B$15*$D$7 -> 120500.63
B60: Variable Kosten | C60: =C53*Annahmen!$B$52+C54*Annahmen!$B$53+C55*Annahmen!$B$54+C59*Annahmen!$B$55+C57*Annahmen!$B$56+C59*INDEX(Annahmen!$B$58:$F$58,1,C$20)*Annahmen!$B$57+C$21*$E$7*Annahmen!$B$21*Annahmen!$B$24*Annahmen!$B$59 -> 35.480945 | D60: =D53*Annahmen!$B$52+D54*Annahmen!$B$53+D55*Annahmen!$B$54+D59*Annahmen!$B$55+D57*Annahmen!$B$56+D59*INDEX(Annahmen!$B$58:$F$58,1,D$20)*Annahmen!$B$57+D$21*$E$7*Annahmen!$B$21*Annahmen!$B$24*Annahmen!$B$59 -> 43.594927 | E60: =E53*Annahmen!$B$52+E54*Annahmen!$B$53+E55*Annahmen!$B$54+E59*Annahmen!$B$55+E57*Annahmen!$B$56+E59*INDEX(Annahmen!$B$58:$F$58,1,E$20)*Annahmen!$B$57+E$21*$E$7*Annahmen!$B$21*Annahmen!$B$24*Annahmen!$B$59 -> 51.388891 | F60: =F53*Annahmen!$B$52+F54*Annahmen!$B$53+F55*Annahmen!$B$54+F59*Annahmen!$B$55+F57*Annahmen!$B$56+F59*INDEX(Annahmen!$B$58:$F$58,1,F$20)*Annahmen!$B$57+F$21*$E$7*Annahmen!$B$21*Annahmen!$B$24*Annahmen!$B$59 -> 79.874704 | G60: =G53*Annahmen!$B$52+G54*Annahmen!$B$53+G55*Annahmen!$B$54+G59*Annahmen!$B$55+G57*Annahmen!$B$56+G59*INDEX(Annahmen!$B$58:$F$58,1,G$20)*Annahmen!$B$57+G$21*$E$7*Annahmen!$B$21*Annahmen!$B$24*Annahmen!$B$59 -> 95.760099 | H60: =H53*Annahmen!$B$52+H54*Annahmen!$B$53+H55*Annahmen!$B$54+H59*Annahmen!$B$55+H57*Annahmen!$B$56+H59*INDEX(Annahmen!$B$58:$F$58,1,H$20)*Annahmen!$B$57+H$21*$E$7*Annahmen!$B$21*Annahmen!$B$24*Annahmen!$B$59 -> 111.02018 | I60: =I53*Annahmen!$B$52+I54*Annahmen!$B$53+I55*Annahmen!$B$54+I59*Annahmen!$B$55+I57*Annahmen!$B$56+I59*INDEX(Annahmen!$B$58:$F$58,1,I$20)*Annahmen!$B$57+I$21*$E$7*Annahmen!$B$21*Annahmen!$B$24*Annahmen!$B$59 -> 146.6802 | J60: =J53*Annahmen!$B$52+J54*Annahmen!$B$53+J55*Annahmen!$B$54+J59*Annahmen!$B$55+J57*Annahmen!$B$56+J59*INDEX(Annahmen!$B$58:$F$58,1,J$20)*Annahmen!$B$57+J$21*$E$7*Annahmen!$B$21*Annahmen!$B$24*Annahmen!$B$59 -> 169.46063 | ... BJ60: =BJ53*Annahmen!$B$52+BJ54*Annahmen!$B$53+BJ55*Annahmen!$B$54+BJ59*Annahmen!$B$55+BJ57*Annahmen!$B$56+BJ59*INDEX(Annahmen!$B$58:$F$58,1,BJ$20)*Annahmen!$B$57+BJ$21*$E$7*Annahmen!$B$21*Annahmen!$B$24*Annahmen!$B$59 -> 12333.772
B61: EBITDA | C61: =C59-C60-C$22 -> -15966.845 | D61: =D59-D60-D$22 -> -5868.7514 | E61: =E59-E60-E$22 -> -6381.979 | F61: =F59-F60-F$22 -> -13843.573 | G61: =G59-G60-G$22 -> -4259.6195 | H61: =H59-H60-H$22 -> -3697.8027 | I61: =I59-I60-I$22 -> -9132.7114 | J61: =J59-J60-J$22 -> -6493.9959 | ... BJ61: =BJ59-BJ60-BJ$22 -> 16102.557
B62: Kum. Cashflow vor Steuern | C62: =0+C61-C$23-C$24 -> -16383.512 | D62: =C62+D61-D$23-D$24 -> -22668.93 | E62: =D62+E61-E$23-E$24 -> -29467.576 | F62: =E62+F61-F$23-F$24 -> -43727.815 | G62: =F62+G61-G$23-G$24 -> -48404.102 | H62: =G62+H61-H$23-H$24 -> -52518.571 | I62: =H62+I61-I$23-I$24 -> -62067.949 | J62: =I62+J61-J$23-J$24 -> -68978.612 | K62: =J62+K61-K$23-K$24 -> -75082.204 | ... BJ62: =BI62+BJ61-BJ$23-BJ$24 -> -469220.89
B63: Hilfszeile Break-even | C63: =IF(C61>=0,C$19,999) -> 999 | D63: =IF(D61>=0,D$19,999) -> 999 | E63: =IF(E61>=0,E$19,999) -> 999 | F63: =IF(F61>=0,F$19,999) -> 999 | G63: =IF(G61>=0,G$19,999) -> 999 | H63: =IF(H61>=0,H$19,999) -> 999 | I63: =IF(I61>=0,I$19,999) -> 999 | J63: =IF(J61>=0,J$19,999) -> 999 | ... BJ63: =IF(BJ61>=0,BJ$19,999) -> 60
B64: ="Szenario "&A8&": "&B8 -> Szenario 4: Churn −30 %
B65: Kunden Start | C65: =Annahmen!$B$7*Annahmen!$B$19*(1-Annahmen!$B$31*$C$8)+C$21*$E$8*Annahmen!$B$19 -> 3.9475 | D65: =C65*(1-Annahmen!$B$31*$C$8)+D$21*$E$8*Annahmen!$B$19 -> 5.3646025 | E65: =D65*(1-Annahmen!$B$31*$C$8)+E$21*$E$8*Annahmen!$B$19 -> 6.7519458 | F65: =E65*(1-Annahmen!$B$31*$C$8)+F$21*$E$8*Annahmen!$B$19 -> 9.610155 | G65: =F65*(1-Annahmen!$B$31*$C$8)+G$21*$E$8*Annahmen!$B$19 -> 12.408342 | H65: =G65*(1-Annahmen!$B$31*$C$8)+H$21*$E$8*Annahmen!$B$19 -> 15.147767 | I65: =H65*(1-Annahmen!$B$31*$C$8)+I$21*$E$8*Annahmen!$B$19 -> 19.329663 | J65: =I65*(1-Annahmen!$B$31*$C$8)+J$21*$E$8*Annahmen!$B$19 -> 23.423741 | K65: =J65*(1-Annahmen!$B$31*$C$8)+K$21*$E$8*Annahmen!$B$19 -> 27.431842 | ... BJ65: =BI65*(1-Annahmen!$B$31*$C$8)+BJ$21*$E$8*Annahmen!$B$19 -> 665.09592
B66: Kunden Flotte | C66: =Annahmen!$B$7*Annahmen!$B$20*(1-Annahmen!$B$32*$C$8)+C$21*$E$8*Annahmen!$B$20 -> 3.0134 | D66: =C66*(1-Annahmen!$B$32*$C$8)+D$21*$E$8*Annahmen!$B$20 -> 4.1112124 | E66: =D66*(1-Annahmen!$B$32*$C$8)+E$21*$E$8*Annahmen!$B$20 -> 5.1936554 | F66: =E66*(1-Annahmen!$B$32*$C$8)+F$21*$E$8*Annahmen!$B$20 -> 7.4009443 | G66: =F66*(1-Annahmen!$B$32*$C$8)+G$21*$E$8*Annahmen!$B$20 -> 9.577331 | H66: =G66*(1-Annahmen!$B$32*$C$8)+H$21*$E$8*Annahmen!$B$20 -> 11.723248 | I66: =H66*(1-Annahmen!$B$32*$C$8)+I$21*$E$8*Annahmen!$B$20 -> 14.979123 | J66: =I66*(1-Annahmen!$B$32*$C$8)+J$21*$E$8*Annahmen!$B$20 -> 18.189415 | K66: =J66*(1-Annahmen!$B$32*$C$8)+K$21*$E$8*Annahmen!$B$20 -> 21.354763 | ... BJ66: =BI66*(1-Annahmen!$B$32*$C$8)+BJ$21*$E$8*Annahmen!$B$20 -> 571.82359
B67: Kunden Premium | C67: =Annahmen!$B$7*Annahmen!$B$21*(1-Annahmen!$B$33*$C$8)+C$21*$E$8*Annahmen!$B$21 -> 0.95496 | D67: =C67*(1-Annahmen!$B$33*$C$8)+D$21*$E$8*Annahmen!$B$21 -> 1.3069383 | E67: =D67*(1-Annahmen!$B$33*$C$8)+E$21*$E$8*Annahmen!$B$21 -> 1.6559601 | F67: =E67*(1-Annahmen!$B$33*$C$8)+F$21*$E$8*Annahmen!$B$21 -> 2.36205 | G67: =F67*(1-Annahmen!$B$33*$C$8)+G$21*$E$8*Annahmen!$B$21 -> 3.0622088 | H67: =G67*(1-Annahmen!$B$33*$C$8)+H$21*$E$8*Annahmen!$B$21 -> 3.7564862 | I67: =H67*(1-Annahmen!$B$33*$C$8)+I$21*$E$8*Annahmen!$B$21 -> 4.8049317 | J67: =I67*(1-Annahmen!$B$33*$C$8)+J$21*$E$8*Annahmen!$B$21 -> 5.8445703 | K67: =J67*(1-Annahmen!$B$33*$C$8)+K$21*$E$8*Annahmen!$B$21 -> 6.8754759 | ... BJ67: =BI67*(1-Annahmen!$B$33*$C$8)+BJ$21*$E$8*Annahmen!$B$21 -> 200.51186
B68: Store-Apps | C68: =Annahmen!$B$7*Annahmen!$B$21*Annahmen!$B$24*(1-Annahmen!$B$33*$C$8)+C$21*$E$8*Annahmen!$B$21*Annahmen!$B$24 -> 0.190992 | D68: =C68*(1-Annahmen!$B$33*$C$8)+D$21*$E$8*Annahmen!$B$21*Annahmen!$B$24 -> 0.26138767 | E68: =D68*(1-Annahmen!$B$33*$C$8)+E$21*$E$8*Annahmen!$B$21*Annahmen!$B$24 -> 0.33119201 | F68: =E68*(1-Annahmen!$B$33*$C$8)+F$21*$E$8*Annahmen!$B$21*Annahmen!$B$24 -> 0.47241 | G68: =F68*(1-Annahmen!$B$33*$C$8)+G$21*$E$8*Annahmen!$B$21*Annahmen!$B$24 -> 0.61244175 | H68: =G68*(1-Annahmen!$B$33*$C$8)+H$21*$E$8*Annahmen!$B$21*Annahmen!$B$24 -> 0.75129724 | I68: =H68*(1-Annahmen!$B$33*$C$8)+I$21*$E$8*Annahmen!$B$21*Annahmen!$B$24 -> 0.96098635 | J68: =I68*(1-Annahmen!$B$33*$C$8)+J$21*$E$8*Annahmen!$B$21*Annahmen!$B$24 -> 1.1689141 | K68: =J68*(1-Annahmen!$B$33*$C$8)+K$21*$E$8*Annahmen!$B$21*Annahmen!$B$24 -> 1.3750952 | ... BJ68: =BI68*(1-Annahmen!$B$33*$C$8)+BJ$21*$E$8*Annahmen!$B$21*Annahmen!$B$24 -> 40.102373
B69: Kunden gesamt | C69: =C65+C66+C67 -> 7.91586 | D69: =D65+D66+D67 -> 10.782753 | E69: =E65+E66+E67 -> 13.601561 | F69: =F65+F66+F67 -> 19.373149 | G69: =G65+G66+G67 -> 25.047882 | H69: =H65+H66+H67 -> 30.627501 | I69: =I65+I66+I67 -> 39.113718 | J69: =J65+J66+J67 -> 47.457726 | ... BJ69: =BJ65+BJ66+BJ67 -> 1437.4314
B70: MRR | C70: =(C65*Annahmen!$B$10+C66*(Annahmen!$B$11+Annahmen!$B$13*Annahmen!$B$22)+C67*(Annahmen!$B$12+Annahmen!$B$14*Annahmen!$B$23)+C68*Annahmen!$B$16)*$D$8 -> 946.88685 | D70: =(D65*Annahmen!$B$10+D66*(Annahmen!$B$11+Annahmen!$B$13*Annahmen!$B$22)+D67*(Annahmen!$B$12+Annahmen!$B$14*Annahmen!$B$23)+D68*Annahmen!$B$16)*$D$8 -> 1292.2397 | E70: =(E65*Annahmen!$B$10+E66*(Annahmen!$B$11+Annahmen!$B$13*Annahmen!$B$22)+E67*(Annahmen!$B$12+Annahmen!$B$14*Annahmen!$B$23)+E68*Annahmen!$B$16)*$D$8 -> 1632.9591 | F70: =(F65*Annahmen!$B$10+F66*(Annahmen!$B$11+Annahmen!$B$13*Annahmen!$B$22)+F67*(Annahmen!$B$12+Annahmen!$B$14*Annahmen!$B$23)+F68*Annahmen!$B$16)*$D$8 -> 2327.2124 | G70: =(G65*Annahmen!$B$10+G66*(Annahmen!$B$11+Annahmen!$B$13*Annahmen!$B$22)+G67*(Annahmen!$B$12+Annahmen!$B$14*Annahmen!$B$23)+G68*Annahmen!$B$16)*$D$8 -> 3012.1448 | H70: =(H65*Annahmen!$B$10+H66*(Annahmen!$B$11+Annahmen!$B$13*Annahmen!$B$22)+H67*(Annahmen!$B$12+Annahmen!$B$14*Annahmen!$B$23)+H68*Annahmen!$B$16)*$D$8 -> 3687.8961 | I70: =(I65*Annahmen!$B$10+I66*(Annahmen!$B$11+Annahmen!$B$13*Annahmen!$B$22)+I67*(Annahmen!$B$12+Annahmen!$B$14*Annahmen!$B$23)+I68*Annahmen!$B$16)*$D$8 -> 4712.7013 | J70: =(J65*Annahmen!$B$10+J66*(Annahmen!$B$11+Annahmen!$B$13*Annahmen!$B$22)+J67*(Annahmen!$B$12+Annahmen!$B$14*Annahmen!$B$23)+J68*Annahmen!$B$16)*$D$8 -> 5723.7728 | ... BJ70: =(BJ65*Annahmen!$B$10+BJ66*(Annahmen!$B$11+Annahmen!$B$13*Annahmen!$B$22)+BJ67*(Annahmen!$B$12+Annahmen!$B$14*Annahmen!$B$23)+BJ68*Annahmen!$B$16)*$D$8 -> 182297.63
B71: Umsatz | C71: =C70*(1-Annahmen!$B$27)+C$21*$E$8*Annahmen!$B$21*Annahmen!$B$24*Annahmen!$B$15*$D$8 -> 1042.8225 | D71: =D70*(1-Annahmen!$B$27)+D$21*$E$8*Annahmen!$B$21*Annahmen!$B$24*Annahmen!$B$15*$D$8 -> 1370.9078 | E71: =E70*(1-Annahmen!$B$27)+E$21*$E$8*Annahmen!$B$21*Annahmen!$B$24*Annahmen!$B$15*$D$8 -> 1694.5912 | F71: =F70*(1-Annahmen!$B$27)+F$21*$E$8*Annahmen!$B$21*Annahmen!$B$24*Annahmen!$B$15*$D$8 -> 2497.4117 | G71: =G70*(1-Annahmen!$B$27)+G$21*$E$8*Annahmen!$B$21*Annahmen!$B$24*Annahmen!$B$15*$D$8 -> 3148.0976 | H71: =H70*(1-Annahmen!$B$27)+H$21*$E$8*Annahmen!$B$21*Annahmen!$B$24*Annahmen!$B$15*$D$8 -> 3790.0613 | I71: =I70*(1-Annahmen!$B$27)+I$21*$E$8*Annahmen!$B$21*Annahmen!$B$24*Annahmen!$B$15*$D$8 -> 4906.9063 | J71: =J70*(1-Annahmen!$B$27)+J$21*$E$8*Annahmen!$B$21*Annahmen!$B$24*Annahmen!$B$15*$D$8 -> 5867.4242 | ... BJ71: =BJ70*(1-Annahmen!$B$27)+BJ$21*$E$8*Annahmen!$B$21*Annahmen!$B$24*Annahmen!$B$15*$D$8 -> 175809.55
B72: Variable Kosten | C72: =C65*Annahmen!$B$52+C66*Annahmen!$B$53+C67*Annahmen!$B$54+C71*Annahmen!$B$55+C69*Annahmen!$B$56+C71*INDEX(Annahmen!$B$58:$F$58,1,C$20)*Annahmen!$B$57+C$21*$E$8*Annahmen!$B$21*Annahmen!$B$24*Annahmen!$B$59 -> 35.872731 | D72: =D65*Annahmen!$B$52+D66*Annahmen!$B$53+D67*Annahmen!$B$54+D71*Annahmen!$B$55+D69*Annahmen!$B$56+D71*INDEX(Annahmen!$B$58:$F$58,1,D$20)*Annahmen!$B$57+D$21*$E$8*Annahmen!$B$21*Annahmen!$B$24*Annahmen!$B$59 -> 44.590024 | E72: =E65*Annahmen!$B$52+E66*Annahmen!$B$53+E67*Annahmen!$B$54+E71*Annahmen!$B$55+E69*Annahmen!$B$56+E71*INDEX(Annahmen!$B$58:$F$58,1,E$20)*Annahmen!$B$57+E$21*$E$8*Annahmen!$B$21*Annahmen!$B$24*Annahmen!$B$59 -> 53.185944 | F72: =F65*Annahmen!$B$52+F66*Annahmen!$B$53+F67*Annahmen!$B$54+F71*Annahmen!$B$55+F69*Annahmen!$B$56+F71*INDEX(Annahmen!$B$58:$F$58,1,F$20)*Annahmen!$B$57+F$21*$E$8*Annahmen!$B$21*Annahmen!$B$24*Annahmen!$B$59 -> 82.660159 | G72: =G65*Annahmen!$B$52+G66*Annahmen!$B$53+G67*Annahmen!$B$54+G71*Annahmen!$B$55+G69*Annahmen!$B$56+G71*INDEX(Annahmen!$B$58:$F$58,1,G$20)*Annahmen!$B$57+G$21*$E$8*Annahmen!$B$21*Annahmen!$B$24*Annahmen!$B$59 -> 99.943919 | H72: =H65*Annahmen!$B$52+H66*Annahmen!$B$53+H67*Annahmen!$B$54+H71*Annahmen!$B$55+H69*Annahmen!$B$56+H71*INDEX(Annahmen!$B$58:$F$58,1,H$20)*Annahmen!$B$57+H$21*$E$8*Annahmen!$B$21*Annahmen!$B$24*Annahmen!$B$59 -> 116.98726 | I72: =I65*Annahmen!$B$52+I66*Annahmen!$B$53+I67*Annahmen!$B$54+I71*Annahmen!$B$55+I69*Annahmen!$B$56+I71*INDEX(Annahmen!$B$58:$F$58,1,I$20)*Annahmen!$B$57+I$21*$E$8*Annahmen!$B$21*Annahmen!$B$24*Annahmen!$B$59 -> 154.79169 | J72: =J65*Annahmen!$B$52+J66*Annahmen!$B$53+J67*Annahmen!$B$54+J71*Annahmen!$B$55+J69*Annahmen!$B$56+J71*INDEX(Annahmen!$B$58:$F$58,1,J$20)*Annahmen!$B$57+J$21*$E$8*Annahmen!$B$21*Annahmen!$B$24*Annahmen!$B$59 -> 180.29027 | ... BJ72: =BJ65*Annahmen!$B$52+BJ66*Annahmen!$B$53+BJ67*Annahmen!$B$54+BJ71*Annahmen!$B$55+BJ69*Annahmen!$B$56+BJ71*INDEX(Annahmen!$B$58:$F$58,1,BJ$20)*Annahmen!$B$57+BJ$21*$E$8*Annahmen!$B$21*Annahmen!$B$24*Annahmen!$B$59 -> 17971.577
B73: EBITDA | C73: =C71-C72-C$22 -> -15953.05 | D73: =D71-D72-D$22 -> -5833.6823 | E73: =E71-E72-E$22 -> -6318.5948 | F73: =F71-F72-F$22 -> -13745.248 | G73: =G71-G72-G$22 -> -4111.8463 | H73: =H71-H72-H$22 -> -3486.926 | I73: =I71-I72-I$22 -> -8845.8854 | J73: =J71-J72-J$22 -> -6110.8661 | ... BJ73: =BJ71-BJ72-BJ$22 -> 65773.673
B74: Kum. Cashflow vor Steuern | C74: =0+C73-C$23-C$24 -> -16369.717 | D74: =C74+D73-D$23-D$24 -> -22620.066 | E74: =D74+E73-E$23-E$24 -> -29355.327 | F74: =E74+F73-F$23-F$24 -> -43517.242 | G74: =F74+G73-G$23-G$24 -> -48045.755 | H74: =G74+H73-H$23-H$24 -> -51949.348 | I74: =H74+I73-I$23-I$24 -> -61211.9 | J74: =I74+J73-J$23-J$24 -> -67739.433 | K74: =J74+K73-K$23-K$24 -> -73344.444 | ... BJ74: =BI74+BJ73-BJ$23-BJ$24 -> 455227.39
B75: Hilfszeile Break-even | C75: =IF(C73>=0,C$19,999) -> 999 | D75: =IF(D73>=0,D$19,999) -> 999 | E75: =IF(E73>=0,E$19,999) -> 999 | F75: =IF(F73>=0,F$19,999) -> 999 | G75: =IF(G73>=0,G$19,999) -> 999 | H75: =IF(H73>=0,H$19,999) -> 999 | I75: =IF(I73>=0,I$19,999) -> 999 | J75: =IF(J73>=0,J$19,999) -> 999 | ... BJ75: =IF(BJ73>=0,BJ$19,999) -> 60
B76: ="Szenario "&A9&": "&B9 -> Szenario 5: Preise −15 %
B77: Kunden Start | C77: =Annahmen!$B$7*Annahmen!$B$19*(1-Annahmen!$B$31*$C$9)+C$21*$E$9*Annahmen!$B$19 -> 3.925 | D77: =C77*(1-Annahmen!$B$31*$C$9)+D$21*$E$9*Annahmen!$B$19 -> 5.30725 | E77: =D77*(1-Annahmen!$B$31*$C$9)+E$21*$E$9*Annahmen!$B$19 -> 6.6480325 | F77: =E77*(1-Annahmen!$B$31*$C$9)+F$21*$E$9*Annahmen!$B$19 -> 9.4485915 | G77: =F77*(1-Annahmen!$B$31*$C$9)+G$21*$E$9*Annahmen!$B$19 -> 12.165134 | H77: =G77*(1-Annahmen!$B$31*$C$9)+H$21*$E$9*Annahmen!$B$19 -> 14.80018 | I77: =H77*(1-Annahmen!$B$31*$C$9)+I$21*$E$9*Annahmen!$B$19 -> 18.856174 | J77: =I77*(1-Annahmen!$B$31*$C$9)+J$21*$E$9*Annahmen!$B$19 -> 22.790489 | K77: =J77*(1-Annahmen!$B$31*$C$9)+K$21*$E$9*Annahmen!$B$19 -> 26.606774 | ... BJ77: =BI77*(1-Annahmen!$B$31*$C$9)+BJ$21*$E$9*Annahmen!$B$19 -> 574.20269
B78: Kunden Flotte | C78: =Annahmen!$B$7*Annahmen!$B$20*(1-Annahmen!$B$32*$C$9)+C$21*$E$9*Annahmen!$B$20 -> 3.002 | D78: =C78*(1-Annahmen!$B$32*$C$9)+D$21*$E$9*Annahmen!$B$20 -> 4.08196 | E78: =D78*(1-Annahmen!$B$32*$C$9)+E$21*$E$9*Annahmen!$B$20 -> 5.1403208 | F78: =E78*(1-Annahmen!$B$32*$C$9)+F$21*$E$9*Annahmen!$B$20 -> 7.3175144 | G78: =F78*(1-Annahmen!$B$32*$C$9)+G$21*$E$9*Annahmen!$B$20 -> 9.4511641 | H78: =G78*(1-Annahmen!$B$32*$C$9)+H$21*$E$9*Annahmen!$B$20 -> 11.542141 | I78: =H78*(1-Annahmen!$B$32*$C$9)+I$21*$E$9*Annahmen!$B$20 -> 14.731298 | J78: =I78*(1-Annahmen!$B$32*$C$9)+J$21*$E$9*Annahmen!$B$20 -> 17.856672 | K78: =J78*(1-Annahmen!$B$32*$C$9)+K$21*$E$9*Annahmen!$B$20 -> 20.919539 | ... BJ78: =BI78*(1-Annahmen!$B$32*$C$9)+BJ$21*$E$9*Annahmen!$B$20 -> 514.20138
B79: Kunden Premium | C79: =Annahmen!$B$7*Annahmen!$B$21*(1-Annahmen!$B$33*$C$9)+C$21*$E$9*Annahmen!$B$21 -> 0.9528 | D79: =C79*(1-Annahmen!$B$33*$C$9)+D$21*$E$9*Annahmen!$B$21 -> 1.3013664 | E79: =D79*(1-Annahmen!$B$33*$C$9)+E$21*$E$9*Annahmen!$B$21 -> 1.64575 | F79: =E79*(1-Annahmen!$B$33*$C$9)+F$21*$E$9*Annahmen!$B$21 -> 2.346001 | G79: =F79*(1-Annahmen!$B$33*$C$9)+G$21*$E$9*Annahmen!$B$21 -> 3.037849 | H79: =G79*(1-Annahmen!$B$33*$C$9)+H$21*$E$9*Annahmen!$B$21 -> 3.7213948 | I79: =H79*(1-Annahmen!$B$33*$C$9)+I$21*$E$9*Annahmen!$B$21 -> 4.7567381 | J79: =I79*(1-Annahmen!$B$33*$C$9)+J$21*$E$9*Annahmen!$B$21 -> 5.7796572 | K79: =J79*(1-Annahmen!$B$33*$C$9)+K$21*$E$9*Annahmen!$B$21 -> 6.7903013 | ... BJ79: =BI79*(1-Annahmen!$B$33*$C$9)+BJ$21*$E$9*Annahmen!$B$21 -> 187.339
B80: Store-Apps | C80: =Annahmen!$B$7*Annahmen!$B$21*Annahmen!$B$24*(1-Annahmen!$B$33*$C$9)+C$21*$E$9*Annahmen!$B$21*Annahmen!$B$24 -> 0.19056 | D80: =C80*(1-Annahmen!$B$33*$C$9)+D$21*$E$9*Annahmen!$B$21*Annahmen!$B$24 -> 0.26027328 | E80: =D80*(1-Annahmen!$B$33*$C$9)+E$21*$E$9*Annahmen!$B$21*Annahmen!$B$24 -> 0.32915 | F80: =E80*(1-Annahmen!$B$33*$C$9)+F$21*$E$9*Annahmen!$B$21*Annahmen!$B$24 -> 0.4692002 | G80: =F80*(1-Annahmen!$B$33*$C$9)+G$21*$E$9*Annahmen!$B$21*Annahmen!$B$24 -> 0.6075698 | H80: =G80*(1-Annahmen!$B$33*$C$9)+H$21*$E$9*Annahmen!$B$21*Annahmen!$B$24 -> 0.74427896 | I80: =H80*(1-Annahmen!$B$33*$C$9)+I$21*$E$9*Annahmen!$B$21*Annahmen!$B$24 -> 0.95134761 | J80: =I80*(1-Annahmen!$B$33*$C$9)+J$21*$E$9*Annahmen!$B$21*Annahmen!$B$24 -> 1.1559314 | K80: =J80*(1-Annahmen!$B$33*$C$9)+K$21*$E$9*Annahmen!$B$21*Annahmen!$B$24 -> 1.3580603 | ... BJ80: =BI80*(1-Annahmen!$B$33*$C$9)+BJ$21*$E$9*Annahmen!$B$21*Annahmen!$B$24 -> 37.467799
B81: Kunden gesamt | C81: =C77+C78+C79 -> 7.8798 | D81: =D77+D78+D79 -> 10.690576 | E81: =E77+E78+E79 -> 13.434103 | F81: =F77+F78+F79 -> 19.112107 | G81: =G77+G78+G79 -> 24.654147 | H81: =H77+H78+H79 -> 30.063715 | I81: =I77+I78+I79 -> 38.34421 | J81: =J77+J78+J79 -> 46.426818 | ... BJ81: =BJ77+BJ78+BJ79 -> 1275.7431
B82: MRR | C82: =(C77*Annahmen!$B$10+C78*(Annahmen!$B$11+Annahmen!$B$13*Annahmen!$B$22)+C79*(Annahmen!$B$12+Annahmen!$B$14*Annahmen!$B$23)+C80*Annahmen!$B$16)*$D$9 -> 801.92454 | D82: =(D77*Annahmen!$B$10+D78*(Annahmen!$B$11+Annahmen!$B$13*Annahmen!$B$22)+D79*(Annahmen!$B$12+Annahmen!$B$14*Annahmen!$B$23)+D80*Annahmen!$B$16)*$D$9 -> 1090.8945 | E82: =(E77*Annahmen!$B$10+E78*(Annahmen!$B$11+Annahmen!$B$13*Annahmen!$B$22)+E79*(Annahmen!$B$12+Annahmen!$B$14*Annahmen!$B$23)+E80*Annahmen!$B$16)*$D$9 -> 1374.3361 | F82: =(F77*Annahmen!$B$10+F78*(Annahmen!$B$11+Annahmen!$B$13*Annahmen!$B$22)+F79*(Annahmen!$B$12+Annahmen!$B$14*Annahmen!$B$23)+F80*Annahmen!$B$16)*$D$9 -> 1956.7505 | G82: =(G77*Annahmen!$B$10+G78*(Annahmen!$B$11+Annahmen!$B$13*Annahmen!$B$22)+G79*(Annahmen!$B$12+Annahmen!$B$14*Annahmen!$B$23)+G80*Annahmen!$B$16)*$D$9 -> 2528.0111 | H82: =(H77*Annahmen!$B$10+H78*(Annahmen!$B$11+Annahmen!$B$13*Annahmen!$B$22)+H79*(Annahmen!$B$12+Annahmen!$B$14*Annahmen!$B$23)+H80*Annahmen!$B$16)*$D$9 -> 3088.356 | I82: =(I77*Annahmen!$B$10+I78*(Annahmen!$B$11+Annahmen!$B$13*Annahmen!$B$22)+I79*(Annahmen!$B$12+Annahmen!$B$14*Annahmen!$B$23)+I80*Annahmen!$B$16)*$D$9 -> 3942.401 | J82: =(J77*Annahmen!$B$10+J78*(Annahmen!$B$11+Annahmen!$B$13*Annahmen!$B$22)+J79*(Annahmen!$B$12+Annahmen!$B$14*Annahmen!$B$23)+J80*Annahmen!$B$16)*$D$9 -> 4780.1315 | ... BJ82: =(BJ77*Annahmen!$B$10+BJ78*(Annahmen!$B$11+Annahmen!$B$13*Annahmen!$B$22)+BJ79*(Annahmen!$B$12+Annahmen!$B$14*Annahmen!$B$23)+BJ80*Annahmen!$B$16)*$D$9 -> 140429.24
B83: Umsatz | C83: =C82*(1-Annahmen!$B$27)+C$21*$E$9*Annahmen!$B$21*Annahmen!$B$24*Annahmen!$B$15*$D$9 -> 883.61632 | D83: =D82*(1-Annahmen!$B$27)+D$21*$E$9*Annahmen!$B$21*Annahmen!$B$24*Annahmen!$B$15*$D$9 -> 1158.1378 | E83: =E82*(1-Annahmen!$B$27)+E$21*$E$9*Annahmen!$B$21*Annahmen!$B$24*Annahmen!$B$15*$D$9 -> 1427.4073 | F83: =F82*(1-Annahmen!$B$27)+F$21*$E$9*Annahmen!$B$21*Annahmen!$B$24*Annahmen!$B$15*$D$9 -> 2102.489 | G83: =G82*(1-Annahmen!$B$27)+G$21*$E$9*Annahmen!$B$21*Annahmen!$B$24*Annahmen!$B$15*$D$9 -> 2645.1865 | H83: =H82*(1-Annahmen!$B$27)+H$21*$E$9*Annahmen!$B$21*Annahmen!$B$24*Annahmen!$B$15*$D$9 -> 3177.5142 | I83: =I82*(1-Annahmen!$B$27)+I$21*$E$9*Annahmen!$B$21*Annahmen!$B$24*Annahmen!$B$15*$D$9 -> 4110.645 | J83: =J82*(1-Annahmen!$B$27)+J$21*$E$9*Annahmen!$B$21*Annahmen!$B$24*Annahmen!$B$15*$D$9 -> 4906.489 | ... BJ83: =BJ82*(1-Annahmen!$B$27)+BJ$21*$E$9*Annahmen!$B$21*Annahmen!$B$24*Annahmen!$B$15*$D$9 -> 135640.55
B84: Variable Kosten | C84: =C77*Annahmen!$B$52+C78*Annahmen!$B$53+C79*Annahmen!$B$54+C83*Annahmen!$B$55+C81*Annahmen!$B$56+C83*INDEX(Annahmen!$B$58:$F$58,1,C$20)*Annahmen!$B$57+C$21*$E$9*Annahmen!$B$21*Annahmen!$B$24*Annahmen!$B$59 -> 34.534861 | D84: =D77*Annahmen!$B$52+D78*Annahmen!$B$53+D79*Annahmen!$B$54+D83*Annahmen!$B$55+D81*Annahmen!$B$56+D83*INDEX(Annahmen!$B$58:$F$58,1,D$20)*Annahmen!$B$57+D$21*$E$9*Annahmen!$B$21*Annahmen!$B$24*Annahmen!$B$59 -> 42.723356 | E84: =E77*Annahmen!$B$52+E78*Annahmen!$B$53+E79*Annahmen!$B$54+E83*Annahmen!$B$55+E81*Annahmen!$B$56+E83*INDEX(Annahmen!$B$58:$F$58,1,E$20)*Annahmen!$B$57+E$21*$E$9*Annahmen!$B$21*Annahmen!$B$24*Annahmen!$B$59 -> 50.749012 | F84: =F77*Annahmen!$B$52+F78*Annahmen!$B$53+F79*Annahmen!$B$54+F83*Annahmen!$B$55+F81*Annahmen!$B$56+F83*INDEX(Annahmen!$B$58:$F$58,1,F$20)*Annahmen!$B$57+F$21*$E$9*Annahmen!$B$21*Annahmen!$B$24*Annahmen!$B$59 -> 79.033056 | G84: =G77*Annahmen!$B$52+G78*Annahmen!$B$53+G79*Annahmen!$B$54+G83*Annahmen!$B$55+G81*Annahmen!$B$56+G83*INDEX(Annahmen!$B$58:$F$58,1,G$20)*Annahmen!$B$57+G$21*$E$9*Annahmen!$B$21*Annahmen!$B$24*Annahmen!$B$59 -> 95.214124 | H84: =H77*Annahmen!$B$52+H78*Annahmen!$B$53+H79*Annahmen!$B$54+H83*Annahmen!$B$55+H81*Annahmen!$B$56+H83*INDEX(Annahmen!$B$58:$F$58,1,H$20)*Annahmen!$B$57+H$21*$E$9*Annahmen!$B$21*Annahmen!$B$24*Annahmen!$B$59 -> 111.07381 | I84: =I77*Annahmen!$B$52+I78*Annahmen!$B$53+I79*Annahmen!$B$54+I83*Annahmen!$B$55+I81*Annahmen!$B$56+I83*INDEX(Annahmen!$B$58:$F$58,1,I$20)*Annahmen!$B$57+I$21*$E$9*Annahmen!$B$21*Annahmen!$B$24*Annahmen!$B$59 -> 147.03686 | J84: =J77*Annahmen!$B$52+J78*Annahmen!$B$53+J79*Annahmen!$B$54+J83*Annahmen!$B$55+J81*Annahmen!$B$56+J83*INDEX(Annahmen!$B$58:$F$58,1,J$20)*Annahmen!$B$57+J$21*$E$9*Annahmen!$B$21*Annahmen!$B$24*Annahmen!$B$59 -> 170.74532 | ... BJ84: =BJ77*Annahmen!$B$52+BJ78*Annahmen!$B$53+BJ79*Annahmen!$B$54+BJ83*Annahmen!$B$55+BJ81*Annahmen!$B$56+BJ83*INDEX(Annahmen!$B$58:$F$58,1,BJ$20)*Annahmen!$B$57+BJ$21*$E$9*Annahmen!$B$21*Annahmen!$B$24*Annahmen!$B$59 -> 14327.136
B85: EBITDA | C85: =C83-C84-C$22 -> -16110.919 | D85: =D83-D84-D$22 -> -6044.5856 | E85: =E83-E84-E$22 -> -6583.3418 | F85: =F83-F84-F$22 -> -14136.544 | G85: =G83-G84-G$22 -> -4610.0276 | H85: =H83-H84-H$22 -> -4093.5596 | I85: =I83-I84-I$22 -> -9634.3919 | J85: =J83-J84-J$22 -> -7062.2564 | ... BJ85: =BJ83-BJ84-BJ$22 -> 29249.121
B86: Kum. Cashflow vor Steuern | C86: =0+C85-C$23-C$24 -> -16527.585 | D86: =C86+D85-D$23-D$24 -> -22988.837 | E86: =D86+E85-E$23-E$24 -> -29988.846 | F86: =E86+F85-F$23-F$24 -> -44542.057 | G86: =F86+G85-G$23-G$24 -> -49568.751 | H86: =G86+H85-H$23-H$24 -> -54078.977 | I86: =H86+I85-I$23-I$24 -> -64130.036 | J86: =I86+J85-J$23-J$24 -> -71608.959 | K86: =J86+K85-K$23-K$24 -> -78330.445 | ... BJ86: =BI86+BJ85-BJ$23-BJ$24 -> -339115.16
B87: Hilfszeile Break-even | C87: =IF(C85>=0,C$19,999) -> 999 | D87: =IF(D85>=0,D$19,999) -> 999 | E87: =IF(E85>=0,E$19,999) -> 999 | F87: =IF(F85>=0,F$19,999) -> 999 | G87: =IF(G85>=0,G$19,999) -> 999 | H87: =IF(H85>=0,H$19,999) -> 999 | I87: =IF(I85>=0,I$19,999) -> 999 | J87: =IF(J85>=0,J$19,999) -> 999 | ... BJ87: =IF(BJ85>=0,BJ$19,999) -> 60
B88: ="Szenario "&A10&": "&B10 -> Szenario 6: Preise +10 %
B89: Kunden Start | C89: =Annahmen!$B$7*Annahmen!$B$19*(1-Annahmen!$B$31*$C$10)+C$21*$E$10*Annahmen!$B$19 -> 3.925 | D89: =C89*(1-Annahmen!$B$31*$C$10)+D$21*$E$10*Annahmen!$B$19 -> 5.30725 | E89: =D89*(1-Annahmen!$B$31*$C$10)+E$21*$E$10*Annahmen!$B$19 -> 6.6480325 | F89: =E89*(1-Annahmen!$B$31*$C$10)+F$21*$E$10*Annahmen!$B$19 -> 9.4485915 | G89: =F89*(1-Annahmen!$B$31*$C$10)+G$21*$E$10*Annahmen!$B$19 -> 12.165134 | H89: =G89*(1-Annahmen!$B$31*$C$10)+H$21*$E$10*Annahmen!$B$19 -> 14.80018 | I89: =H89*(1-Annahmen!$B$31*$C$10)+I$21*$E$10*Annahmen!$B$19 -> 18.856174 | J89: =I89*(1-Annahmen!$B$31*$C$10)+J$21*$E$10*Annahmen!$B$19 -> 22.790489 | K89: =J89*(1-Annahmen!$B$31*$C$10)+K$21*$E$10*Annahmen!$B$19 -> 26.606774 | ... BJ89: =BI89*(1-Annahmen!$B$31*$C$10)+BJ$21*$E$10*Annahmen!$B$19 -> 574.20269
B90: Kunden Flotte | C90: =Annahmen!$B$7*Annahmen!$B$20*(1-Annahmen!$B$32*$C$10)+C$21*$E$10*Annahmen!$B$20 -> 3.002 | D90: =C90*(1-Annahmen!$B$32*$C$10)+D$21*$E$10*Annahmen!$B$20 -> 4.08196 | E90: =D90*(1-Annahmen!$B$32*$C$10)+E$21*$E$10*Annahmen!$B$20 -> 5.1403208 | F90: =E90*(1-Annahmen!$B$32*$C$10)+F$21*$E$10*Annahmen!$B$20 -> 7.3175144 | G90: =F90*(1-Annahmen!$B$32*$C$10)+G$21*$E$10*Annahmen!$B$20 -> 9.4511641 | H90: =G90*(1-Annahmen!$B$32*$C$10)+H$21*$E$10*Annahmen!$B$20 -> 11.542141 | I90: =H90*(1-Annahmen!$B$32*$C$10)+I$21*$E$10*Annahmen!$B$20 -> 14.731298 | J90: =I90*(1-Annahmen!$B$32*$C$10)+J$21*$E$10*Annahmen!$B$20 -> 17.856672 | K90: =J90*(1-Annahmen!$B$32*$C$10)+K$21*$E$10*Annahmen!$B$20 -> 20.919539 | ... BJ90: =BI90*(1-Annahmen!$B$32*$C$10)+BJ$21*$E$10*Annahmen!$B$20 -> 514.20138
B91: Kunden Premium | C91: =Annahmen!$B$7*Annahmen!$B$21*(1-Annahmen!$B$33*$C$10)+C$21*$E$10*Annahmen!$B$21 -> 0.9528 | D91: =C91*(1-Annahmen!$B$33*$C$10)+D$21*$E$10*Annahmen!$B$21 -> 1.3013664 | E91: =D91*(1-Annahmen!$B$33*$C$10)+E$21*$E$10*Annahmen!$B$21 -> 1.64575 | F91: =E91*(1-Annahmen!$B$33*$C$10)+F$21*$E$10*Annahmen!$B$21 -> 2.346001 | G91: =F91*(1-Annahmen!$B$33*$C$10)+G$21*$E$10*Annahmen!$B$21 -> 3.037849 | H91: =G91*(1-Annahmen!$B$33*$C$10)+H$21*$E$10*Annahmen!$B$21 -> 3.7213948 | I91: =H91*(1-Annahmen!$B$33*$C$10)+I$21*$E$10*Annahmen!$B$21 -> 4.7567381 | J91: =I91*(1-Annahmen!$B$33*$C$10)+J$21*$E$10*Annahmen!$B$21 -> 5.7796572 | K91: =J91*(1-Annahmen!$B$33*$C$10)+K$21*$E$10*Annahmen!$B$21 -> 6.7903013 | ... BJ91: =BI91*(1-Annahmen!$B$33*$C$10)+BJ$21*$E$10*Annahmen!$B$21 -> 187.339
B92: Store-Apps | C92: =Annahmen!$B$7*Annahmen!$B$21*Annahmen!$B$24*(1-Annahmen!$B$33*$C$10)+C$21*$E$10*Annahmen!$B$21*Annahmen!$B$24 -> 0.19056 | D92: =C92*(1-Annahmen!$B$33*$C$10)+D$21*$E$10*Annahmen!$B$21*Annahmen!$B$24 -> 0.26027328 | E92: =D92*(1-Annahmen!$B$33*$C$10)+E$21*$E$10*Annahmen!$B$21*Annahmen!$B$24 -> 0.32915 | F92: =E92*(1-Annahmen!$B$33*$C$10)+F$21*$E$10*Annahmen!$B$21*Annahmen!$B$24 -> 0.4692002 | G92: =F92*(1-Annahmen!$B$33*$C$10)+G$21*$E$10*Annahmen!$B$21*Annahmen!$B$24 -> 0.6075698 | H92: =G92*(1-Annahmen!$B$33*$C$10)+H$21*$E$10*Annahmen!$B$21*Annahmen!$B$24 -> 0.74427896 | I92: =H92*(1-Annahmen!$B$33*$C$10)+I$21*$E$10*Annahmen!$B$21*Annahmen!$B$24 -> 0.95134761 | J92: =I92*(1-Annahmen!$B$33*$C$10)+J$21*$E$10*Annahmen!$B$21*Annahmen!$B$24 -> 1.1559314 | K92: =J92*(1-Annahmen!$B$33*$C$10)+K$21*$E$10*Annahmen!$B$21*Annahmen!$B$24 -> 1.3580603 | ... BJ92: =BI92*(1-Annahmen!$B$33*$C$10)+BJ$21*$E$10*Annahmen!$B$21*Annahmen!$B$24 -> 37.467799
B93: Kunden gesamt | C93: =C89+C90+C91 -> 7.8798 | D93: =D89+D90+D91 -> 10.690576 | E93: =E89+E90+E91 -> 13.434103 | F93: =F89+F90+F91 -> 19.112107 | G93: =G89+G90+G91 -> 24.654147 | H93: =H89+H90+H91 -> 30.063715 | I93: =I89+I90+I91 -> 38.34421 | J93: =J89+J90+J91 -> 46.426818 | ... BJ93: =BJ89+BJ90+BJ91 -> 1275.7431
B94: MRR | C94: =(C89*Annahmen!$B$10+C90*(Annahmen!$B$11+Annahmen!$B$13*Annahmen!$B$22)+C91*(Annahmen!$B$12+Annahmen!$B$14*Annahmen!$B$23)+C92*Annahmen!$B$16)*$D$10 -> 1037.7847 | D94: =(D89*Annahmen!$B$10+D90*(Annahmen!$B$11+Annahmen!$B$13*Annahmen!$B$22)+D91*(Annahmen!$B$12+Annahmen!$B$14*Annahmen!$B$23)+D92*Annahmen!$B$16)*$D$10 -> 1411.7458 | E94: =(E89*Annahmen!$B$10+E90*(Annahmen!$B$11+Annahmen!$B$13*Annahmen!$B$22)+E91*(Annahmen!$B$12+Annahmen!$B$14*Annahmen!$B$23)+E92*Annahmen!$B$16)*$D$10 -> 1778.5525 | F94: =(F89*Annahmen!$B$10+F90*(Annahmen!$B$11+Annahmen!$B$13*Annahmen!$B$22)+F91*(Annahmen!$B$12+Annahmen!$B$14*Annahmen!$B$23)+F92*Annahmen!$B$16)*$D$10 -> 2532.2653 | G94: =(G89*Annahmen!$B$10+G90*(Annahmen!$B$11+Annahmen!$B$13*Annahmen!$B$22)+G91*(Annahmen!$B$12+Annahmen!$B$14*Annahmen!$B$23)+G92*Annahmen!$B$16)*$D$10 -> 3271.5437 | H94: =(H89*Annahmen!$B$10+H90*(Annahmen!$B$11+Annahmen!$B$13*Annahmen!$B$22)+H91*(Annahmen!$B$12+Annahmen!$B$14*Annahmen!$B$23)+H92*Annahmen!$B$16)*$D$10 -> 3996.696 | I94: =(I89*Annahmen!$B$10+I90*(Annahmen!$B$11+Annahmen!$B$13*Annahmen!$B$22)+I91*(Annahmen!$B$12+Annahmen!$B$14*Annahmen!$B$23)+I92*Annahmen!$B$16)*$D$10 -> 5101.9307 | J94: =(J89*Annahmen!$B$10+J90*(Annahmen!$B$11+Annahmen!$B$13*Annahmen!$B$22)+J91*(Annahmen!$B$12+Annahmen!$B$14*Annahmen!$B$23)+J92*Annahmen!$B$16)*$D$10 -> 6186.0526 | ... BJ94: =(BJ89*Annahmen!$B$10+BJ90*(Annahmen!$B$11+Annahmen!$B$13*Annahmen!$B$22)+BJ91*(Annahmen!$B$12+Annahmen!$B$14*Annahmen!$B$23)+BJ92*Annahmen!$B$16)*$D$10 -> 181731.95
B95: Umsatz | C95: =C94*(1-Annahmen!$B$27)+C$21*$E$10*Annahmen!$B$21*Annahmen!$B$24*Annahmen!$B$15*$D$10 -> 1143.5035 | D95: =D94*(1-Annahmen!$B$27)+D$21*$E$10*Annahmen!$B$21*Annahmen!$B$24*Annahmen!$B$15*$D$10 -> 1498.7665 | E95: =E94*(1-Annahmen!$B$27)+E$21*$E$10*Annahmen!$B$21*Annahmen!$B$24*Annahmen!$B$15*$D$10 -> 1847.2329 | F95: =F94*(1-Annahmen!$B$27)+F$21*$E$10*Annahmen!$B$21*Annahmen!$B$24*Annahmen!$B$15*$D$10 -> 2720.8681 | G95: =G94*(1-Annahmen!$B$27)+G$21*$E$10*Annahmen!$B$21*Annahmen!$B$24*Annahmen!$B$15*$D$10 -> 3423.1826 | H95: =H94*(1-Annahmen!$B$27)+H$21*$E$10*Annahmen!$B$21*Annahmen!$B$24*Annahmen!$B$15*$D$10 -> 4112.0772 | I95: =I94*(1-Annahmen!$B$27)+I$21*$E$10*Annahmen!$B$21*Annahmen!$B$24*Annahmen!$B$15*$D$10 -> 5319.6582 | J95: =J94*(1-Annahmen!$B$27)+J$21*$E$10*Annahmen!$B$21*Annahmen!$B$24*Annahmen!$B$15*$D$10 -> 6349.5739 | ... BJ95: =BJ94*(1-Annahmen!$B$27)+BJ$21*$E$10*Annahmen!$B$21*Annahmen!$B$24*Annahmen!$B$15*$D$10 -> 175534.84
B96: Variable Kosten | C96: =C89*Annahmen!$B$52+C90*Annahmen!$B$53+C91*Annahmen!$B$54+C95*Annahmen!$B$55+C93*Annahmen!$B$56+C95*INDEX(Annahmen!$B$58:$F$58,1,C$20)*Annahmen!$B$57+C$21*$E$10*Annahmen!$B$21*Annahmen!$B$24*Annahmen!$B$59 -> 36.613958 | D96: =D89*Annahmen!$B$52+D90*Annahmen!$B$53+D91*Annahmen!$B$54+D95*Annahmen!$B$55+D93*Annahmen!$B$56+D95*INDEX(Annahmen!$B$58:$F$58,1,D$20)*Annahmen!$B$57+D$21*$E$10*Annahmen!$B$21*Annahmen!$B$24*Annahmen!$B$59 -> 45.448386 | E96: =E89*Annahmen!$B$52+E90*Annahmen!$B$53+E91*Annahmen!$B$54+E95*Annahmen!$B$55+E93*Annahmen!$B$56+E95*INDEX(Annahmen!$B$58:$F$58,1,E$20)*Annahmen!$B$57+E$21*$E$10*Annahmen!$B$21*Annahmen!$B$24*Annahmen!$B$59 -> 54.107617 | F96: =F89*Annahmen!$B$52+F90*Annahmen!$B$53+F91*Annahmen!$B$54+F95*Annahmen!$B$55+F93*Annahmen!$B$56+F95*INDEX(Annahmen!$B$58:$F$58,1,F$20)*Annahmen!$B$57+F$21*$E$10*Annahmen!$B$21*Annahmen!$B$24*Annahmen!$B$59 -> 83.980089 | G96: =G89*Annahmen!$B$52+G90*Annahmen!$B$53+G91*Annahmen!$B$54+G95*Annahmen!$B$55+G93*Annahmen!$B$56+G95*INDEX(Annahmen!$B$58:$F$58,1,G$20)*Annahmen!$B$57+G$21*$E$10*Annahmen!$B$21*Annahmen!$B$24*Annahmen!$B$59 -> 101.43809 | H96: =H89*Annahmen!$B$52+H90*Annahmen!$B$53+H91*Annahmen!$B$54+H95*Annahmen!$B$55+H93*Annahmen!$B$56+H95*INDEX(Annahmen!$B$58:$F$58,1,H$20)*Annahmen!$B$57+H$21*$E$10*Annahmen!$B$21*Annahmen!$B$24*Annahmen!$B$59 -> 118.55032 | I96: =I89*Annahmen!$B$52+I90*Annahmen!$B$53+I91*Annahmen!$B$54+I95*Annahmen!$B$55+I93*Annahmen!$B$56+I95*INDEX(Annahmen!$B$58:$F$58,1,I$20)*Annahmen!$B$57+I$21*$E$10*Annahmen!$B$21*Annahmen!$B$24*Annahmen!$B$59 -> 156.70897 | J96: =J89*Annahmen!$B$52+J90*Annahmen!$B$53+J91*Annahmen!$B$54+J95*Annahmen!$B$55+J93*Annahmen!$B$56+J95*INDEX(Annahmen!$B$58:$F$58,1,J$20)*Annahmen!$B$57+J$21*$E$10*Annahmen!$B$21*Annahmen!$B$24*Annahmen!$B$59 -> 182.29 | ... BJ96: =BJ89*Annahmen!$B$52+BJ90*Annahmen!$B$53+BJ91*Annahmen!$B$54+BJ95*Annahmen!$B$55+BJ93*Annahmen!$B$56+BJ95*INDEX(Annahmen!$B$58:$F$58,1,BJ$20)*Annahmen!$B$57+BJ$21*$E$10*Annahmen!$B$21*Annahmen!$B$24*Annahmen!$B$59 -> 17638.361
B97: EBITDA | C97: =C95-C96-C$22 -> -15853.11 | D97: =D95-D96-D$22 -> -5706.6819 | E97: =E95-E96-E$22 -> -6166.8747 | F97: =F95-F96-F$22 -> -13523.112 | G97: =G95-G96-G$22 -> -3838.2555 | H97: =H95-H96-H$22 -> -3166.4732 | I97: =I95-I96-I$22 -> -8435.0508 | J97: =J95-J96-J$22 -> -5630.7161 | ... BJ97: =BJ95-BJ96-BJ$22 -> 65832.176
B98: Kum. Cashflow vor Steuern | C98: =0+C97-C$23-C$24 -> -16269.777 | D98: =C98+D97-D$23-D$24 -> -22393.126 | E98: =D98+E97-E$23-E$24 -> -28976.667 | F98: =E98+F97-F$23-F$24 -> -42916.446 | G98: =F98+G97-G$23-G$24 -> -47171.368 | H98: =G98+H97-H$23-H$24 -> -50754.508 | I98: =H98+I97-I$23-I$24 -> -59606.225 | J98: =I98+J97-J$23-J$24 -> -65653.608 | K98: =J98+K97-K$23-K$24 -> -70715.781 | ... BJ98: =BI98+BJ97-BJ$23-BJ$24 -> 552553.56
B99: Hilfszeile Break-even | C99: =IF(C97>=0,C$19,999) -> 999 | D99: =IF(D97>=0,D$19,999) -> 999 | E99: =IF(E97>=0,E$19,999) -> 999 | F99: =IF(F97>=0,F$19,999) -> 999 | G99: =IF(G97>=0,G$19,999) -> 999 | H99: =IF(H97>=0,H$19,999) -> 999 | I99: =IF(I97>=0,I$19,999) -> 999 | J99: =IF(J97>=0,J$19,999) -> 999 | ... BJ99: =IF(BJ97>=0,BJ$19,999) -> 60
B100: ="Szenario "&A11&": "&B11 -> Szenario 7: Wachstum −30 %
B101: Kunden Start | C101: =Annahmen!$B$7*Annahmen!$B$19*(1-Annahmen!$B$31*$C$11)+C$21*$E$11*Annahmen!$B$19 -> 3.475 | D101: =C101*(1-Annahmen!$B$31*$C$11)+D$21*$E$11*Annahmen!$B$19 -> 4.42075 | E101: =D101*(1-Annahmen!$B$31*$C$11)+E$21*$E$11*Annahmen!$B$19 -> 5.3381275 | F101: =E101*(1-Annahmen!$B$31*$C$11)+F$21*$E$11*Annahmen!$B$19 -> 7.2779837 | G101: =F101*(1-Annahmen!$B$31*$C$11)+G$21*$E$11*Annahmen!$B$19 -> 9.1596442 | H101: =G101*(1-Annahmen!$B$31*$C$11)+H$21*$E$11*Annahmen!$B$19 -> 10.984855 | I101: =H101*(1-Annahmen!$B$31*$C$11)+I$21*$E$11*Annahmen!$B$19 -> 13.805309 | J101: =I101*(1-Annahmen!$B$31*$C$11)+J$21*$E$11*Annahmen!$B$19 -> 16.54115 | K101: =J101*(1-Annahmen!$B$31*$C$11)+K$21*$E$11*Annahmen!$B$19 -> 19.194915 | ... BJ101: =BI101*(1-Annahmen!$B$31*$C$11)+BJ$21*$E$11*Annahmen!$B$19 -> 402.06249
B102: Kunden Flotte | C102: =Annahmen!$B$7*Annahmen!$B$20*(1-Annahmen!$B$32*$C$11)+C$21*$E$11*Annahmen!$B$20 -> 2.66 | D102: =C102*(1-Annahmen!$B$32*$C$11)+D$21*$E$11*Annahmen!$B$20 -> 3.4048 | E102: =D102*(1-Annahmen!$B$32*$C$11)+E$21*$E$11*Annahmen!$B$20 -> 4.134704 | F102: =E102*(1-Annahmen!$B$32*$C$11)+F$21*$E$11*Annahmen!$B$20 -> 5.6480099 | G102: =F102*(1-Annahmen!$B$32*$C$11)+G$21*$E$11*Annahmen!$B$20 -> 7.1310497 | H102: =G102*(1-Annahmen!$B$32*$C$11)+H$21*$E$11*Annahmen!$B$20 -> 8.5844287 | I102: =H102*(1-Annahmen!$B$32*$C$11)+I$21*$E$11*Annahmen!$B$20 -> 10.80674 | J102: =I102*(1-Annahmen!$B$32*$C$11)+J$21*$E$11*Annahmen!$B$20 -> 12.984605 | K102: =J102*(1-Annahmen!$B$32*$C$11)+K$21*$E$11*Annahmen!$B$20 -> 15.118913 | ... BJ102: =BI102*(1-Annahmen!$B$32*$C$11)+BJ$21*$E$11*Annahmen!$B$20 -> 360.11057
B103: Kunden Premium | C103: =Annahmen!$B$7*Annahmen!$B$21*(1-Annahmen!$B$33*$C$11)+C$21*$E$11*Annahmen!$B$21 -> 0.8448 | D103: =C103*(1-Annahmen!$B$33*$C$11)+D$21*$E$11*Annahmen!$B$21 -> 1.0866624 | E103: =D103*(1-Annahmen!$B$33*$C$11)+E$21*$E$11*Annahmen!$B$21 -> 1.3256225 | F103: =E103*(1-Annahmen!$B$33*$C$11)+F$21*$E$11*Annahmen!$B$21 -> 1.813715 | G103: =F103*(1-Annahmen!$B$33*$C$11)+G$21*$E$11*Annahmen!$B$21 -> 2.2959504 | H103: =G103*(1-Annahmen!$B$33*$C$11)+H$21*$E$11*Annahmen!$B$21 -> 2.772399 | I103: =H103*(1-Annahmen!$B$33*$C$11)+I$21*$E$11*Annahmen!$B$21 -> 3.4951302 | J103: =I103*(1-Annahmen!$B$33*$C$11)+J$21*$E$11*Annahmen!$B$21 -> 4.2091886 | K103: =J103*(1-Annahmen!$B$33*$C$11)+K$21*$E$11*Annahmen!$B$21 -> 4.9146784 | ... BJ103: =BI103*(1-Annahmen!$B$33*$C$11)+BJ$21*$E$11*Annahmen!$B$21 -> 131.22453
B104: Store-Apps | C104: =Annahmen!$B$7*Annahmen!$B$21*Annahmen!$B$24*(1-Annahmen!$B$33*$C$11)+C$21*$E$11*Annahmen!$B$21*Annahmen!$B$24 -> 0.16896 | D104: =C104*(1-Annahmen!$B$33*$C$11)+D$21*$E$11*Annahmen!$B$21*Annahmen!$B$24 -> 0.21733248 | E104: =D104*(1-Annahmen!$B$33*$C$11)+E$21*$E$11*Annahmen!$B$21*Annahmen!$B$24 -> 0.26512449 | F104: =E104*(1-Annahmen!$B$33*$C$11)+F$21*$E$11*Annahmen!$B$21*Annahmen!$B$24 -> 0.362743 | G104: =F104*(1-Annahmen!$B$33*$C$11)+G$21*$E$11*Annahmen!$B$21*Annahmen!$B$24 -> 0.45919008 | H104: =G104*(1-Annahmen!$B$33*$C$11)+H$21*$E$11*Annahmen!$B$21*Annahmen!$B$24 -> 0.5544798 | I104: =H104*(1-Annahmen!$B$33*$C$11)+I$21*$E$11*Annahmen!$B$21*Annahmen!$B$24 -> 0.69902604 | J104: =I104*(1-Annahmen!$B$33*$C$11)+J$21*$E$11*Annahmen!$B$21*Annahmen!$B$24 -> 0.84183773 | K104: =J104*(1-Annahmen!$B$33*$C$11)+K$21*$E$11*Annahmen!$B$21*Annahmen!$B$24 -> 0.98293568 | ... BJ104: =BI104*(1-Annahmen!$B$33*$C$11)+BJ$21*$E$11*Annahmen!$B$21*Annahmen!$B$24 -> 26.244907
...
