Workbook

Sheet Annahmen
A1: LiveFX – Finanzmodell Pre-Seed 250.000 € · Annahmen
A2: Alle Werte sind Schätzungen auf Basis von BUSINESSPLAN.md §11 – es gibt noch keine Umsätze. Mittelverwendung, Gates und Bewertung: Vorschlag – mit Steuer-/Rechtsberater prüfen.
A3: Legende: blaue Schrift = Eingabe (änderbar) · schwarz = Formel · grün = Verweis auf anderes Blatt · gelb = Schlüsselannahme. Stand: Oktober 2026, Produkt v2.1. J1 = 2027 (Start Pro-Abo, Closing Jan 2027).
A5: A. Allgemein
A6: Startkasse (Pre-Seed, Closing Monat 1 = Jan 2027) | B6: 250000 | I6: Vom Gründer korrigierte Rundengröße: ca. 250.000 € statt 500.000 € (BP §11.6 alt).
A7: Infrastruktur fix (Server, Domains, Tools) €/Monat | B7: 250 | I7: Schätzung; BP §11.3 Infrastruktur J1 8 T€ – wird hier als fix + variabel modelliert.
A8: Infrastruktur variabel (KI-API nur Pro, Zahlungs-/Store-Gebühren) in % vom Umsatz | B8: 0.08 | I8: Schätzung: Payment-/Store-Gebühren 5–8 % + KI ≈ 0,004 $ je Klassifikation (BP §9). Ergibt J1 ≈ 7 T€ (BP: 8).
A9: Monat im Jahr, in dem B2B-/Pilot-Erlöse zufließen (1–12) | B9: 10 | I9: Annahme: Pilot-/Lizenzzahlung als Einmalbetrag im Oktober des Jahres (J2 → Monat 22).
A10: Ø Preis Creator-Pack (€) | B10: 3.99 | I10: BP §11.1: 1 Pack à Ø 3,99 €.
A11: Agentur-Lizenz €/Monat | B11: 49 | I11: BP §11.1: Agentur-Lizenz à 49 €/Monat (Jahresendbestand × 12, wie im Plan).
A12: Ø zahlende Pro im Jahr J1 (Anteil am Jahresendwert) | B12: 0.5 | I12: BP §11.1: ≈ 50 % des Jahresendwerts in J1.
A13: Ø zahlende Pro im Jahr J2–J5 (Anteil am Jahresendwert) | B13: 0.75 | I13: BP §11.1: 75 % in J2/J3; für J4/J5 fortgeschrieben.
A14: Mindestkasse in Monatskosten (für Folgerunden-Bedarf) | B14: 3 | I14: Annahme: 3 Monatskosten des Jahres J3 als Sicherheitsbestand.
A15: Anteil nachgelagerter Vision-Linien an den Vision-Kosten (Story-Engine, Studio/Auto-Edit, Räume/VR-AR) | B15: 0.6 | I15: INVESTOR-MEMO §10.1 (500-T€-Fassung): Vision 100 T€ = WortBild 40 + Story-Engine 40 + Highlights/Räume 20 → 60 % nicht WortBild.
A16: Vision-Zusatzkosten J2 laut BP §11.5 (€) | B16: 115000 | I16: BP §11.5: Zusatzkosten 30 / 115 / 210 T€.
A17: Vision-Zusatzkosten J3 laut BP §11.5 (€) | B17: 210000 | I17: BP §11.5.
A18: Ausbau-Team startet in Monat (nach Gate 2 / Folgerunde) | B18: 19 | I18: Neu: Einstellungen über das schlanke Pre-Seed-Team hinaus erst nach Gate 2 (Monat 18).
A20: B. Szenarien (Nutzer, Conversion, Preise, Lizenzen, Kosten J3–J5)
A21: Annahme | B21: Einheit | C21: Konservativ | D21: Basis | E21: Optimistisch | I21: Quelle / Begründung
A22: Registrierte Nutzer Ende J1 | B22: Nutzer | C22: 8000 | D22: 20000 | E22: 40000 | I22: BP §11.1
A23: Registrierte Nutzer Ende J2 | B23: Nutzer | C23: 30000 | D23: 80000 | E23: 180000 | I23: BP §11.1
A24: Registrierte Nutzer Ende J3 | B24: Nutzer | C24: 80000 | D24: 250000 | E24: 500000 | I24: BP §11.1 (SOM J3: 5.000–15.000 Zahlende, BP §6)
A25: Nutzerwachstum J4 (ggü. J3) | B25: % | C25: 0.5 | D25: 0.8 | E25: 0.8 | I25: Neu (Fortschreibung): Wachstum verlangsamt sich ggü. J2→J3 (×2,7 / ×3,1 / ×2,8).
A26: Nutzerwachstum J5 (ggü. J4) | B26: % | C26: 0.35 | D26: 0.5 | E26: 0.5 | I26: Neu (Fortschreibung): weitere Verlangsamung; Basis J5 = 675.000 Nutzer ≈ 23–68 % des SAM (1–3 Mio., BP §6).
A27: Conversion Free → Pro J1–J3 | B27: % | C27: 0.03 | D27: 0.04 | E27: 0.05 | I27: BP §11.1
A28: Conversion Free → Pro J4 | B28: % | C28: 0.03 | D28: 0.0425 | E28: 0.0525 | I28: Neu: +0,25 Pkt./Jahr in Basis/Optimistisch (Pro+, Packs, Bindung); konservativ konstant.
A29: Conversion Free → Pro J5 | B29: % | C29: 0.03 | D29: 0.045 | E29: 0.055 | I29: Neu: wie oben.
A30: ARPU Pro (netto, Mix Monat/Jahr) | B30: €/Monat | C30: 8.5 | D30: 8.5 | E30: 8.5 | I30: BP §11.1 (9,99 €/Monat bzw. 79 €/Jahr, netto)
A31: Pack-Käufe pro Jahr (Anteil der Nutzer × 1 Pack) | B31: % | C31: 0.07 | D31: 0.1 | E31: 0.12 | I31: BP §11.1
A32: Agentur-Lizenzen Ende J1 | B32: Anzahl | C32: 2 | D32: 3 | E32: 5 | I32: BP §11.1
A33: Agentur-Lizenzen Ende J2 | B33: Anzahl | C33: 8 | D33: 15 | E33: 30 | I33: BP §11.1
... A46: Referenz: Plan-Kosten J2 (BP 500-T€-Fassung) | B46: € | C46: 230000 | D46: 398000 | E46: 520000 | I46: BP §11.3 – Grundlage für den Ausbau ab Monat 19
A47: Ausbau-Faktor ab Monat 19 (Plan-Kosten J2 Szenario ÷ Basis) | B47: Faktor | C47: =C46/$D$46 -> 0.57788945 | D47: =D46/$D$46 -> 1 | E47: =E46/$D$46 -> 1.3065327 | I47: Formel: Ausbau-Kosten je Szenario skaliert wie die Plan-Kosten J2 (230 / 398 / 520 T€).
A49: C. Kostenlinien Pre-Seed (Monat 1–18) – Vorschlag, schlanker Aufbau mit 250.000 €
A50: Kostenlinie | B50: Budgetbereich | C50: €/Monat | D50: von Monat | E50: bis Monat | F50: Einmalbetrag € | G50: im Monat | H50: Summe M1–18 | I50: Inhalt / Begründung / ersetzt Planzeile
A51: Mobile-/Web-Entwickler:in (Vollzeit, ab Monat 3) | B51: Team/Produkt | C51: 5500 | D51: 3 | E51: 18 | F51: 0 | G51: 1 | H51: =C51*MAX(0,MIN(E51,18)-D51+1)+IF(G51<=18,F51,0) -> 88000 | I51: Erste Einstellung (BP §12). 66 T€/Jahr Vollkosten statt 75 T€ J1 / 160 T€ J2 (BP §11.3: 1 statt 2 Entwickler:innen in J2).
A52: Gründergehalt (anteilig) | B52: Team/Produkt | C52: 2000 | D52: 1 | E52: 18 | F52: 0 | G52: 1 | H52: =C52*MAX(0,MIN(E52,18)-D52+1)+IF(G52<=18,F52,0) -> 36000 | I52: BP §11.3: 30 T€ J1 / 48 T€ J2 → 24 T€/Jahr bis Monat 18.
A53: Entwicklungs-Tools, Testgeräte (iOS/Android) | B53: Team/Produkt | C53: 0 | D53: 1 | E53: 18 | F53: 1000 | G53: 1 | H53: =C53*MAX(0,MIN(E53,18)-D53+1)+IF(G53<=18,F53,0) -> 1000 | I53: Einmalig.
A54: Creator-Programm, Community, Marketing – Phase 1 (TR-Launch) | B54: Markteintritt | C54: 2000 | D54: 1 | E54: 6 | F54: 0 | G54: 1 | H54: =C54*MAX(0,MIN(E54,18)-D54+1)+IF(G54<=18,F54,0) -> 12000 | I54: BP §10 Phase 1; BP §11.3 Marketing 25 T€ J1.
A55: Creator-Programm, Marketing, Marktplätze – Phase 2 (DE/EN, Partner) | B55: Markteintritt | C55: 3000 | D55: 7 | E55: 18 | F55: 0 | G55: 1 | H55: =C55*MAX(0,MIN(E55,18)-D55+1)+IF(G55<=18,F55,0) -> 36000 | I55: BP §10 Phase 2/3: Botschafter:innen, Pack-Drops, OBS/Streamlabs/Stream-Deck-Einträge.
A56: Plattform- oder Bildungspilot (8 Wochen, Material, Reisen) | B56: Markteintritt | C56: 0 | D56: 1 | E56: 18 | F56: 2000 | G56: 9 | H56: =C56*MAX(0,MIN(E56,18)-D56+1)+IF(G56<=18,F56,0) -> 2000 | I56: Einmalig in Monat 9 (BP §14.1: Plattform-Pilot Q3 2027).
A57: Vision-Linie WortBild (Sprachenlernen): Illustration, Sprecher-Audios DE/TR/EN, Didaktik, Kurs-Pilot | B57: WortBild | C57: 3125 | D57: 4 | E57: 15 | F57: 0 | G57: 1 | H57: =C57*MAX(0,MIN(E57,18)-D57+1)+IF(G57<=18,F57,0) -> 37500 | I57: Ersetzt Freelance Design/Sound (BP §11.3: 15 + 25 T€) und den WortBild-Anteil der Vision-Kosten (BP §11.5).
A58: Recht, Marke (DE/EU/TR), Datenschutz/DSFA, Jugendschutz, Steuerberatung | B58: Recht | C58: 1000 | D58: 1 | E58: 18 | F58: 7000 | G58: 1 | H58: =C58*MAX(0,MIN(E58,18)-D58+1)+IF(G58<=18,F58,0) -> 25000 | I58: 7 T€ einmalig (Marke, Beteiligungsvertrag) + 1 T€/Monat. BP §11.3: 12 + 20 T€.
A59: Summe verplante Pre-Seed-Kosten M1–18 | H59: =SUM(H51:H58) -> 237500
A60: Laufende Kosten nach Monat 18 im Fall „ohne Umsatz“ (schlank weiter: Entwicklung, Gründer, Marketing Ph. 2, Recht) | C60: =C51+C52+C55+C58 -> 11500 | I60: Annahme für die Runway ohne Umsatz: keine Neueinstellungen, Pre-Seed-Team läuft weiter.
A62: D. Ausbau-Team ab Monat 19 (nach Gate 2) – Basis = BP §11.3 J2 ÷ 12, andere Szenarien × Ausbau-Faktor
A63: Kostenlinie (BP §11.3) | B63: Kategorie | C63: Plan J2 €/Jahr | D63: €/Monat ab M19 | I63: Hinweis
A64: Personal: Mobile-/Web-Entwicklung (2 Personen) | B64: Mobile/Web | C64: 160000 | D64: =C64/12 -> 13333.333
A65: Personal: Backend/ML, Community/Support | B65: Backend/Community | C65: 60000 | D65: =C65/12 -> 5000
A66: Gründer (Gehalt) | B66: Gründer | C66: 48000 | D66: =C66/12 -> 4000
A67: Freelance Design, Sound, Illustration (Packs, WortBild) | B67: Freelance/WortBild | C67: 25000 | D67: =C67/12 -> 2083.3333
A68: Marketing, Creator-Partnerprogramm, Events | B68: Marketing | C68: 60000 | D68: =C68/12 -> 5000
A69: Recht, Marke, Steuer, Verwaltung | B69: Recht | C69: 20000 | D69: =C69/12 -> 1666.6667
A70: Summe Ausbau Basis €/Monat (ohne Infrastruktur) | C70: =SUM(C64:C69) -> 373000 | D70: =SUM(D64:D69) -> 31083.333 | I70: Infrastruktur läuft separat (fix + % vom Umsatz). Plan J2 gesamt 398 T€ = 373 T€ + Infrastruktur 25 T€.
A72: E. Referenz: Plan-Werte BP §11.2 / §11.4 (T€, 500-T€-Fassung) – nur zum Abgleich
A73: Zeile | B73: Szenario | C73: J1 | D73: J2 | E73: J3 | I73: Hinweis
A74: Umsatz gesamt (Plan) | B74: Konservativ | C74: 15 | D74: 81 | E74: 268
A75: davon Agentur-Lizenz (Plan) | B75: Konservativ | C75: 1 | D75: 4 | E75: 12 | I75: Inkonsistent: 8 × 49 € × 12 = 4,7 T€ und 25 × 49 € × 12 = 14,7 T€ – Modell rechnet mit der Formel (korrigiert).
A76: Ergebnis (Plan) | B76: Konservativ | C76: -105 | D76: -149 | E76: -62
A77: Umsatz gesamt (Plan) | B77: Basis | C77: 51 | D77: 336 | E77: 1039
A78: davon Agentur-Lizenz (Plan) | B78: Basis | C78: 2 | D78: 9 | E78: 24
A79: Ergebnis (Plan) | B79: Basis | C79: -114 | D79: -62 | E79: 329
A80: Umsatz gesamt (Plan) | B80: Optimistisch | C80: 124 | D80: 893 | E80: 2601
A81: davon Agentur-Lizenz (Plan) | B81: Optimistisch | C81: 3 | D81: 18 | E81: 48
A82: Ergebnis (Plan) | B82: Optimistisch | C82: -66 | D82: 373 | E82: 1501
A84: F. Geänderte Annahmen gegenüber BUSINESSPLAN.md (500-T€-Fassung) – dokumentiert
A85: 1. Rundengröße 250.000 € statt 500.000 €; Mittelverwendung über 18 statt 24 Monate (Blatt Mittelverwendung).
A86: 2. Kosten J1–J2 aus dem Monatsplan statt BP §11.3: Pre-Seed-Team (1 Entwickler:in ab M3, Gründergehalt 2 T€/Monat) bis M18; Ausbau-Team gemäß Plan J2 erst ab Monat 19 nach Gate 2 (Backend/ML, Community, 2. Entwickler:in).
A87: 3. Freelance Design/Sound (BP §11.3) geht in der Linie WortBild auf (37,5 T€, M4–M15); Story-Engine, Auto-Edit/Studio und VR/AR wandern in die Folgerunde (60 % der Vision-Kosten BP §11.5 als Bedarf der Folgerunde).
A88: 4. Recht/Marke/Datenschutz 25 T€ in 18 Monaten (Plan: 12 T€ J1 + 20 T€ J2).
A89: 5. Infrastruktur als 250 €/Monat fix + 8 % vom Umsatz statt fester Jahreswerte (J1 ≈ 7 T€ statt 8 T€).
A90: 6. Umsatz J1–J3 unverändert aus BP §11.1 berechnet; Korrektur Agentur-Zeile konservativ (J2 4,7 statt 4 T€, J3 14,7 statt 12 T€); übrige Abweichungen ≤ 1 T€ sind Rundung. Vision-Erlöse (BP §11.5) bleiben – wie im Plan – außerhalb des Ergebnisses.
A91: 7. J4–J5 neu fortgeschrieben (Nutzerwachstum, Conversion, Agenturen, B2B, Kostenwachstum – Abschnitt B).
A92: 8. Monatlicher Umsatzverlauf: J1 linear ab null (Summe = Jahreswert), J2 linear ab dem Dezember-Niveau J1 (Summe = Jahreswert); B2B als Einmalzahlung im Monat laut Abschnitt A.

Sheet GuV 5 Jahre
A1: GuV 5 Jahre (EBITDA-Sicht) – drei Szenarien
A2: Alle Werte sind Schätzungen auf Basis von BUSINESSPLAN.md §11 – es gibt noch keine Umsätze. Mittelverwendung, Gates und Bewertung: Vorschlag – mit Steuer-/Rechtsberater prüfen. J1–J3 aus BP §11.1, Kosten J1–J2 aus dem Monatsplan (250-T€-Runde), J4–J5 fortgeschrieben.
A4: Szenario Konservativ
A5: Position | B5: Einheit | C5: J1 2027 | D5: J2 2028 | E5: J3 2029 | F5: J4 2030 | G5: J5 2031 | H5: Herleitung
A6: Registrierte Nutzer (Jahresende) | B6: Nutzer | C6: =Annahmen!$C$22 -> 8000 | D6: =Annahmen!$C$23 -> 30000 | E6: =Annahmen!$C$24 -> 80000 | F6: =E6*(1+Annahmen!$C$25) -> 120000 | G6: =F6*(1+Annahmen!$C$26) -> 162000 | H6: J1–J3 BP §11.1; J4–J5 = Vorjahr × (1 + Wachstum)
A7: Conversion Free → Pro | B7: % | C7: =Annahmen!$C$27 -> 0.03 | D7: =Annahmen!$C$27 -> 0.03 | E7: =Annahmen!$C$27 -> 0.03 | F7: =Annahmen!$C$28 -> 0.03 | G7: =Annahmen!$C$29 -> 0.03
A8: Zahlende Pro-Nutzer (Jahresende) | B8: Abos | C8: =C6*C7 -> 240 | D8: =D6*D7 -> 900 | E8: =E6*E7 -> 2400 | F8: =F6*F7 -> 3600 | G8: =G6*G7 -> 4860
A9: Zahlende Pro-Nutzer (Jahresdurchschnitt) | B9: Abos | C9: =C8*Annahmen!$B$12 -> 120 | D9: =D8*Annahmen!$B$13 -> 675 | E9: =E8*Annahmen!$B$13 -> 1800 | F9: =F8*Annahmen!$B$13 -> 2700 | G9: =G8*Annahmen!$B$13 -> 3645 | H9: BP §11.1: 50 % des Jahresendwerts in J1, 75 % ab J2
A10: Umsatz Pro-Abo | B10: € | C10: =C9*Annahmen!$C$30*12 -> 12240 | D10: =D9*Annahmen!$C$30*12 -> 68850 | E10: =E9*Annahmen!$C$30*12 -> 183600 | F10: =F9*Annahmen!$C$30*12 -> 275400 | G10: =G9*Annahmen!$C$30*12 -> 371790
A11: Umsatz Creator-Packs | B11: € | C11: =C6*Annahmen!$C$31*Annahmen!$B$10 -> 2234.4 | D11: =D6*Annahmen!$C$31*Annahmen!$B$10 -> 8379 | E11: =E6*Annahmen!$C$31*Annahmen!$B$10 -> 22344 | F11: =F6*Annahmen!$C$31*Annahmen!$B$10 -> 33516 | G11: =G6*Annahmen!$C$31*Annahmen!$B$10 -> 45246.6
A12: Umsatz Agentur-Lizenz | B12: € | C12: =Annahmen!$C$32*Annahmen!$B$11*12 -> 1176 | D12: =Annahmen!$C$33*Annahmen!$B$11*12 -> 4704 | E12: =Annahmen!$C$34*Annahmen!$B$11*12 -> 14700 | F12: =Annahmen!$C$35*Annahmen!$B$11*12 -> 23520 | G12: =Annahmen!$C$36*Annahmen!$B$11*12 -> 35280 | H12: Jahresendbestand × 49 € × 12 (Methode des Plans)
A13: Zwischensumme wiederkehrender Umsatz | B13: € | C13: =C10+C11+C12 -> 15650.4 | D13: =D10+D11+D12 -> 81933 | E13: =E10+E11+E12 -> 220644 | F13: =F10+F11+F12 -> 332436 | G13: =G10+G11+G12 -> 452316.6
A14: Umsatz B2B / Pilot | B14: € | C14: =Annahmen!$C$37 -> 0 | D14: =Annahmen!$C$38 -> 0 | E14: =Annahmen!$C$39 -> 50000 | F14: =Annahmen!$C$40 -> 100000 | G14: =Annahmen!$C$41 -> 150000
A15: Umsatz gesamt | B15: € | C15: =C13+C14 -> 15650.4 | D15: =D13+D14 -> 81933 | E15: =E13+E14 -> 270644 | F15: =F13+F14 -> 432436 | G15: =G13+G14 -> 602316.6
A16: Kosten gesamt (operativ) | B16: € | C16: ='Liquidität 24M'!$AB$65 -> 163377.03 | D16: ='Liquidität 24M'!$AC$65 -> 195706.02 | E16: =Annahmen!$C$42 -> 330000 | F16: =E16*(1+Annahmen!$C$43) -> 396000 | G16: =F16*(1+Annahmen!$C$44) -> 455400 | H16: J1–J2 = Summe Monatsplan (Liquidität 24M); J3 = BP §11.3; J4–J5 = Vorjahr × (1 + Kostenwachstum)
A17: EBITDA (Ergebnis) | B17: € | C17: =C15-C16 -> -147726.63 | D17: =D15-D16 -> -113773.02 | E17: =E15-E16 -> -59356 | F17: =F15-F16 -> 36436 | G17: =G15-G16 -> 146916.6
A18: EBITDA-Marge | B18: % | C18: =IF(C15=0,0,C17/C15) -> -9.4391601 | D18: =IF(D15=0,0,D17/D15) -> -1.3886105 | E18: =IF(E15=0,0,E17/E15) -> -0.21931393 | F18: =IF(F15=0,0,F17/F15) -> 0.084257555 | G18: =IF(G15=0,0,G17/G15) -> 0.24391923
A19: Kumuliertes Ergebnis | B19: € | C19: =C17 -> -147726.63 | D19: =C19+D17 -> -261499.65 | E19: =D19+E17 -> -320855.65 | F19: =E19+F17 -> -284419.65 | G19: =F19+G17 -> -137503.05
A20: Kasse Jahresende (250 T€ Start, ohne Folgerunde) | B20: € | C20: ='Liquidität 24M'!$O$67 -> 102273.37 | D20: ='Liquidität 24M'!$AA$67 -> -11499.654 | E20: =D20+E17 -> -70855.654 | F20: =E20+F17 -> -34419.654 | G20: =F20+G17 -> 112496.95 | H20: J1/J2 aus dem Monatsplan (Monat 12/24); ab J3 Vorjahr + EBITDA (vereinfacht, ohne Steuern/Working Capital)
A21: Referenz: Umsatz laut Plan BP §11.2 (T€) | C21: =Annahmen!$C$74 -> 15 | D21: =Annahmen!$D$74 -> 81 | E21: =Annahmen!$E$74 -> 268
A22: Abweichung Modell − Plan beim Umsatz (T€) | C22: =C15/1000-C21 -> 0.6504 | D22: =D15/1000-D21 -> 0.933 | E22: =E15/1000-E21 -> 2.644 | H22: Rundung; konservativ J2/J3: Korrektur der Agentur-Zeile (siehe Annahmen F)
A23: Referenz: Ergebnis laut Plan BP §11.4 (T€, 500-T€-Kostenbasis) | C23: =Annahmen!$C$76 -> -105 | D23: =Annahmen!$D$76 -> -149 | E23: =Annahmen!$E$76 -> -62
A25: Szenario Basis
A26: Position | B26: Einheit | C26: J1 2027 | D26: J2 2028 | E26: J3 2029 | F26: J4 2030 | G26: J5 2031 | H26: Herleitung
A27: Registrierte Nutzer (Jahresende) | B27: Nutzer | C27: =Annahmen!$D$22 -> 20000 | D27: =Annahmen!$D$23 -> 80000 | E27: =Annahmen!$D$24 -> 250000 | F27: =E27*(1+Annahmen!$D$25) -> 450000 | G27: =F27*(1+Annahmen!$D$26) -> 675000 | H27: J1–J3 BP §11.1; J4–J5 = Vorjahr × (1 + Wachstum)
A28: Conversion Free → Pro | B28: % | C28: =Annahmen!$D$27 -> 0.04 | D28: =Annahmen!$D$27 -> 0.04 | E28: =Annahmen!$D$27 -> 0.04 | F28: =Annahmen!$D$28 -> 0.0425 | G28: =Annahmen!$D$29 -> 0.045
A29: Zahlende Pro-Nutzer (Jahresende) | B29: Abos | C29: =C27*C28 -> 800 | D29: =D27*D28 -> 3200 | E29: =E27*E28 -> 10000 | F29: =F27*F28 -> 19125 | G29: =G27*G28 -> 30375
A30: Zahlende Pro-Nutzer (Jahresdurchschnitt) | B30: Abos | C30: =C29*Annahmen!$B$12 -> 400 | D30: =D29*Annahmen!$B$13 -> 2400 | E30: =E29*Annahmen!$B$13 -> 7500 | F30: =F29*Annahmen!$B$13 -> 14343.75 | G30: =G29*Annahmen!$B$13 -> 22781.25 | H30: BP §11.1: 50 % des Jahresendwerts in J1, 75 % ab J2
A31: Umsatz Pro-Abo | B31: € | C31: =C30*Annahmen!$D$30*12 -> 40800 | D31: =D30*Annahmen!$D$30*12 -> 244800 | E31: =E30*Annahmen!$D$30*12 -> 765000 | F31: =F30*Annahmen!$D$30*12 -> 1463062.5 | G31: =G30*Annahmen!$D$30*12 -> 2323687.5
A32: Umsatz Creator-Packs | B32: € | C32: =C27*Annahmen!$D$31*Annahmen!$B$10 -> 7980 | D32: =D27*Annahmen!$D$31*Annahmen!$B$10 -> 31920 | E32: =E27*Annahmen!$D$31*Annahmen!$B$10 -> 99750 | F32: =F27*Annahmen!$D$31*Annahmen!$B$10 -> 179550 | G32: =G27*Annahmen!$D$31*Annahmen!$B$10 -> 269325
A33: Umsatz Agentur-Lizenz | B33: € | C33: =Annahmen!$D$32*Annahmen!$B$11*12 -> 1764 | D33: =Annahmen!$D$33*Annahmen!$B$11*12 -> 8820 | E33: =Annahmen!$D$34*Annahmen!$B$11*12 -> 23520 | F33: =Annahmen!$D$35*Annahmen!$B$11*12 -> 41160 | G33: =Annahmen!$D$36*Annahmen!$B$11*12 -> 58800 | H33: Jahresendbestand × 49 € × 12 (Methode des Plans)
A34: Zwischensumme wiederkehrender Umsatz | B34: € | C34: =C31+C32+C33 -> 50544 | D34: =D31+D32+D33 -> 285540 | E34: =E31+E32+E33 -> 888270 | F34: =F31+F32+F33 -> 1683772.5 | G34: =G31+G32+G33 -> 2651812.5
A35: Umsatz B2B / Pilot | B35: € | C35: =Annahmen!$D$37 -> 0 | D35: =Annahmen!$D$38 -> 50000 | E35: =Annahmen!$D$39 -> 150000 | F35: =Annahmen!$D$40 -> 300000 | G35: =Annahmen!$D$41 -> 500000
A36: Umsatz gesamt | B36: € | C36: =C34+C35 -> 50544 | D36: =D34+D35 -> 335540 | E36: =E34+E35 -> 1038270 | F36: =F34+F35 -> 1983772.5 | G36: =G34+G35 -> 3151812.5
A37: Kosten gesamt (operativ) | B37: € | C37: ='Liquidität 24M'!$AB$86 -> 166168.52 | D37: ='Liquidität 24M'!$AC$86 -> 294718.2 | E37: =Annahmen!$D$42 -> 710000 | F37: =E37*(1+Annahmen!$D$43) -> 1065000 | G37: =F37*(1+Annahmen!$D$44) -> 1491000 | H37: J1–J2 = Summe Monatsplan (Liquidität 24M); J3 = BP §11.3; J4–J5 = Vorjahr × (1 + Kostenwachstum)
A38: EBITDA (Ergebnis) | B38: € | C38: =C36-C37 -> -115624.52 | D38: =D36-D37 -> 40821.8 | E38: =E36-E37 -> 328270 | F38: =F36-F37 -> 918772.5 | G38: =G36-G37 -> 1660812.5
A39: EBITDA-Marge | B39: % | C39: =IF(C36=0,0,C38/C36) -> -2.2876013 | D39: =IF(D36=0,0,D38/D36) -> 0.12166001 | E39: =IF(E36=0,0,E38/E36) -> 0.31617017 | F39: =IF(F36=0,0,F38/F36) -> 0.46314409 | G39: =IF(G36=0,0,G38/G36) -> 0.52693886
A40: Kumuliertes Ergebnis | B40: € | C40: =C38 -> -115624.52 | D40: =C40+D38 -> -74802.72 | E40: =D40+E38 -> 253467.28 | F40: =E40+F38 -> 1172239.8 | G40: =F40+G38 -> 2833052.3
A41: Kasse Jahresende (250 T€ Start, ohne Folgerunde) | B41: € | C41: ='Liquidität 24M'!$O$88 -> 134375.48 | D41: ='Liquidität 24M'!$AA$88 -> 175197.28 | E41: =D41+E38 -> 503467.28 | F41: =E41+F38 -> 1422239.8 | G41: =F41+G38 -> 3083052.3 | H41: J1/J2 aus dem Monatsplan (Monat 12/24); ab J3 Vorjahr + EBITDA (vereinfacht, ohne Steuern/Working Capital)
A42: Referenz: Umsatz laut Plan BP §11.2 (T€) | C42: =Annahmen!$C$77 -> 51 | D42: =Annahmen!$D$77 -> 336 | E42: =Annahmen!$E$77 -> 1039
A43: Abweichung Modell − Plan beim Umsatz (T€) | C43: =C36/1000-C42 -> -0.456 | D43: =D36/1000-D42 -> -0.46 | E43: =E36/1000-E42 -> -0.73 | H43: Rundung; konservativ J2/J3: Korrektur der Agentur-Zeile (siehe Annahmen F)
A44: Referenz: Ergebnis laut Plan BP §11.4 (T€, 500-T€-Kostenbasis) | C44: =Annahmen!$C$79 -> -114 | D44: =Annahmen!$D$79 -> -62 | E44: =Annahmen!$E$79 -> 329
A46: Szenario Optimistisch
A47: Position | B47: Einheit | C47: J1 2027 | D47: J2 2028 | E47: J3 2029 | F47: J4 2030 | G47: J5 2031 | H47: Herleitung
A48: Registrierte Nutzer (Jahresende) | B48: Nutzer | C48: =Annahmen!$E$22 -> 40000 | D48: =Annahmen!$E$23 -> 180000 | E48: =Annahmen!$E$24 -> 500000 | F48: =E48*(1+Annahmen!$E$25) -> 900000 | G48: =F48*(1+Annahmen!$E$26) -> 1350000 | H48: J1–J3 BP §11.1; J4–J5 = Vorjahr × (1 + Wachstum)
A49: Conversion Free → Pro | B49: % | C49: =Annahmen!$E$27 -> 0.05 | D49: =Annahmen!$E$27 -> 0.05 | E49: =Annahmen!$E$27 -> 0.05 | F49: =Annahmen!$E$28 -> 0.0525 | G49: =Annahmen!$E$29 -> 0.055
A50: Zahlende Pro-Nutzer (Jahresende) | B50: Abos | C50: =C48*C49 -> 2000 | D50: =D48*D49 -> 9000 | E50: =E48*E49 -> 25000 | F50: =F48*F49 -> 47250 | G50: =G48*G49 -> 74250
A51: Zahlende Pro-Nutzer (Jahresdurchschnitt) | B51: Abos | C51: =C50*Annahmen!$B$12 -> 1000 | D51: =D50*Annahmen!$B$13 -> 6750 | E51: =E50*Annahmen!$B$13 -> 18750 | F51: =F50*Annahmen!$B$13 -> 35437.5 | G51: =G50*Annahmen!$B$13 -> 55687.5 | H51: BP §11.1: 50 % des Jahresendwerts in J1, 75 % ab J2
A52: Umsatz Pro-Abo | B52: € | C52: =C51*Annahmen!$E$30*12 -> 102000 | D52: =D51*Annahmen!$E$30*12 -> 688500 | E52: =E51*Annahmen!$E$30*12 -> 1912500 | F52: =F51*Annahmen!$E$30*12 -> 3614625 | G52: =G51*Annahmen!$E$30*12 -> 5680125
A53: Umsatz Creator-Packs | B53: € | C53: =C48*Annahmen!$E$31*Annahmen!$B$10 -> 19152 | D53: =D48*Annahmen!$E$31*Annahmen!$B$10 -> 86184 | E53: =E48*Annahmen!$E$31*Annahmen!$B$10 -> 239400 | F53: =F48*Annahmen!$E$31*Annahmen!$B$10 -> 430920 | G53: =G48*Annahmen!$E$31*Annahmen!$B$10 -> 646380
A54: Umsatz Agentur-Lizenz | B54: € | C54: =Annahmen!$E$32*Annahmen!$B$11*12 -> 2940 | D54: =Annahmen!$E$33*Annahmen!$B$11*12 -> 17640 | E54: =Annahmen!$E$34*Annahmen!$B$11*12 -> 47040 | F54: =Annahmen!$E$35*Annahmen!$B$11*12 -> 82320 | G54: =Annahmen!$E$36*Annahmen!$B$11*12 -> 117600 | H54: Jahresendbestand × 49 € × 12 (Methode des Plans)
A55: Zwischensumme wiederkehrender Umsatz | B55: € | C55: =C52+C53+C54 -> 124092 | D55: =D52+D53+D54 -> 792324 | E55: =E52+E53+E54 -> 2198940 | F55: =F52+F53+F54 -> 4127865 | G55: =G52+G53+G54 -> 6444105
A56: Umsatz B2B / Pilot | B56: € | C56: =Annahmen!$E$37 -> 0 | D56: =Annahmen!$E$38 -> 100000 | E56: =Annahmen!$E$39 -> 400000 | F56: =Annahmen!$E$40 -> 700000 | G56: =Annahmen!$E$41 -> 1000000
A57: Umsatz gesamt | B57: € | C57: =C55+C56 -> 124092 | D57: =D55+D56 -> 892324 | E57: =E55+E56 -> 2598940 | F57: =F55+F56 -> 4827865 | G57: =G55+G56 -> 7444105
A58: Kosten gesamt (operativ) | B58: € | C58: ='Liquidität 24M'!$AB$107 -> 172052.36 | D58: ='Liquidität 24M'!$AC$107 -> 396429.26 | E58: =Annahmen!$E$42 -> 1100000 | F58: =E58*(1+Annahmen!$E$43) -> 1650000 | G58: =F58*(1+Annahmen!$E$44) -> 2310000 | H58: J1–J2 = Summe Monatsplan (Liquidität 24M); J3 = BP §11.3; J4–J5 = Vorjahr × (1 + Kostenwachstum)
A59: EBITDA (Ergebnis) | B59: € | C59: =C57-C58 -> -47960.36 | D59: =D57-D58 -> 495894.74 | E59: =E57-E58 -> 1498940 | F59: =F57-F58 -> 3177865 | G59: =G57-G58 -> 5134105
A60: EBITDA-Marge | B60: % | C60: =IF(C57=0,0,C59/C57) -> -0.38649035 | D60: =IF(D57=0,0,D59/D57) -> 0.55573395 | E60: =IF(E57=0,0,E59/E57) -> 0.57675052 | F60: =IF(F57=0,0,F59/F57) -> 0.65823402 | G60: =IF(G57=0,0,G59/G57) -> 0.68968734
A61: Kumuliertes Ergebnis | B61: € | C61: =C59 -> -47960.36 | D61: =C61+D59 -> 447934.38 | E61: =D61+E59 -> 1946874.4 | F61: =E61+F59 -> 5124739.4 | G61: =F61+G59 -> 10258844
A62: Kasse Jahresende (250 T€ Start, ohne Folgerunde) | B62: € | C62: ='Liquidität 24M'!$O$109 -> 202039.64 | D62: ='Liquidität 24M'!$AA$109 -> 697934.38 | E62: =D62+E59 -> 2196874.4 | F62: =E62+F59 -> 5374739.4 | G62: =F62+G59 -> 10508844 | H62: J1/J2 aus dem Monatsplan (Monat 12/24); ab J3 Vorjahr + EBITDA (vereinfacht, ohne Steuern/Working Capital)
A63: Referenz: Umsatz laut Plan BP §11.2 (T€) | C63: =Annahmen!$C$80 -> 124 | D63: =Annahmen!$D$80 -> 893 | E63: =Annahmen!$E$80 -> 2601
A64: Abweichung Modell − Plan beim Umsatz (T€) | C64: =C57/1000-C63 -> 0.092 | D64: =D57/1000-D63 -> -0.676 | E64: =E57/1000-E63 -> -2.06 | H64: Rundung; konservativ J2/J3: Korrektur der Agentur-Zeile (siehe Annahmen F)
A65: Referenz: Ergebnis laut Plan BP §11.4 (T€, 500-T€-Kostenbasis) | C65: =Annahmen!$C$82 -> -66 | D65: =Annahmen!$D$82 -> 373 | E65: =Annahmen!$E$82 -> 1501
A67: Memo: Vision-Linie WortBild – Erlöse laut BP §11.5 (Basis, NICHT im Ergebnis enthalten)
A68: Position | B68: Einheit | C68: J1 2027 | D68: J2 2028 | E68: J3 2029 | H68: Quelle
A69: WortBild Familie (Ø 0 / 500 / 2.000 Abos × 4,25 € × 12) | B69: € | C69: 0 | D69: 26000 | E69: 102000 | H69: BP §11.5 (Schätzung)
A70: Schullizenzen (5 / 40 / 150 Schulen × Ø 500 €) | B70: € | C70: 2500 | D70: 20000 | E70: 75000 | H70: BP §11.5 (Schätzung)
A71: Kurslizenzen (0 / 200 / 800 Lehrkräfte × 49 €) | B71: € | C71: 0 | D71: 9800 | E71: 39200 | H71: BP §11.5 (Schätzung)
A72: Summe WortBild-Erlöse (Option, Upside) | C72: =SUM(C69:C71) -> 2500 | D72: =SUM(D69:D71) -> 55800 | E72: =SUM(E69:E71) -> 216200

Sheet Mittelverwendung
A1: Mittelverwendung 250.000 € über 18 Monate (Vorschlag)
A2: Vorschlag – mit Steuer-/Rechtsberater prüfen. Story-Engine, Auto-Edit/Studio und VR/AR werden aus der Folgerunde finanziert.
A4: Bereich | B4: Anteil | C4: Betrag | D4: Verplant M1–18 (Monatsplan) | E4: Differenz | F4: €/Monat Ø | G4: Inhalt
A5: Team/Produkt: Mobile-/Web-Entwickler:in, Gründergehalt anteilig, Testgeräte | B5: 0.5 | C5: =B5*Annahmen!$B$6 -> 125000 | D5: ='Liquidität 24M'!$AD$31+'Liquidität 24M'!$AD$32+'Liquidität 24M'!$AD$33 -> 125000 | E5: =C5-D5 -> 0 | F5: =C5/18 -> 6944.4444 | G5: Entwickler:in ab Monat 3 (16 × 5.500 € = 88 T€), Gründer 18 × 2.000 € = 36 T€, Testgeräte 1 T€; Ziel: Pro-Abo, Mobile-App/PWA, Stabilität v2.1
A6: Markteintritt: Creator-Programm, Community, Plattform- und Bildungspiloten | B6: 0.2 | C6: =B6*Annahmen!$B$6 -> 50000 | D6: ='Liquidität 24M'!$AD$34+'Liquidität 24M'!$AD$35+'Liquidität 24M'!$AD$36 -> 50000 | E6: =C6-D6 -> 0 | F6: =C6/18 -> 2777.7778 | G6: TR-Launch, 10–20 Botschafter:innen, Pack-Drops, Marktplatz-Einträge, DE/EN-Launch, 1 Plattform- oder Bildungspilot
A7: Erste Vision-Linie WortBild (Sprachenlernen) | B7: 0.15 | C7: =B7*Annahmen!$B$6 -> 37500 | D7: ='Liquidität 24M'!$AD$37 -> 37500 | E7: =C7-D7 -> 0 | F7: =C7/18 -> 2083.3333 | G7: 300 Wörter, Lesehilfe, Sprecher-Audios DE/TR/EN, Didaktik-Prüfung, Kurs-/Klassen-Pilot (M4–M15)
A8: Recht, Marke, Datenschutz | B8: 0.1 | C8: =B8*Annahmen!$B$6 -> 25000 | D8: ='Liquidität 24M'!$AD$38 -> 25000 | E8: =C8-D8 -> 0 | F8: =C8/18 -> 1388.8889 | G8: Marke LiveFX DE/EU/TR, Beteiligungsvertrag, DSGVO/DSFA Schul-/Familienprofil, Jugendschutz, Steuerberatung
A9: Reserve | B9: 0.05 | C9: =B9*Annahmen!$B$6 -> 12500 | D9: =0 -> 0 | E9: =C9-D9 -> 12500 | F9: =C9/18 -> 694.44444 | G9: Nicht verplant: Verzögerungen bei Einstellung, Store-/Plattform-Freigaben; deckt Infrastruktur-Fixkosten im Fall ohne Umsatz
A10: Summe | B10: =SUM(B5:B9) -> 1 | C10: =SUM(C5:C9) -> 250000 | D10: =SUM(D5:D9) -> 237500 | E10: =C10-D10 -> 12500 | F10: =C10/18 -> 13888.889
A11: Prüfung: Summe Anteile = 100 % und Betrag = Startkasse | C11: =IF(AND(ROUND(B10,4)=1,ROUND(C10-Annahmen!$B$6,0)=0),"OK","PRÜFEN") -> OK
A13: Verschoben in die Folgerunde (nicht aus den 250.000 € finanziert)
A14: • Story-Engine / Erzählfilm (Linie A): Scene-Director, Figuren, Welten-Packs TR/EN
A15: • Studio / Auto-Edit (Linie D): Highlights, Datei-Import, MP4-Export, Pro+
A16: • Räume / VR-AR (Linie C): Bühnen-/Klassenzimmer-Preset, WebXR, Brille
A17: • Backend/ML-Entwickler:in (Streaming-ASR < 300 ms), Community/Support, 2. Entwickler:in – ab Monat 19 nach Gate 2
A19: Kostenabgleich Basis: Plan BP §11.3 (500-T€-Fassung) vs. Modell (250-T€-Runde)
A20: Planzeile BP §11.3 | C20: Plan J1 | D20: Modell J1 | E20: Plan J2 | F20: Modell J2 | G20: Was ändert sich
A21: Personal: Mobile-/Web-Entwicklung | C21: 75000 | D21: ='Liquidität 24M'!$AB$31+'Liquidität 24M'!$AB$33+'Liquidität 24M'!$AB$42 -> 56000 | E21: 160000 | F21: ='Liquidität 24M'!$AC$31+'Liquidität 24M'!$AC$33+'Liquidität 24M'!$AC$42 -> 113000 | G21: 1 Entwickler:in ab M3 statt sofort; 2. Person erst ab M19
A22: Personal: Backend/ML, Community/Support | C22: 0 | D22: ='Liquidität 24M'!$AB$43 -> 0 | E22: 60000 | F22: ='Liquidität 24M'!$AC$43 -> 30000 | G22: erst ab M19 (statt ganz J2)
A23: Gründer (Gehalt) | C23: 30000 | D23: ='Liquidität 24M'!$AB$32+'Liquidität 24M'!$AB$44 -> 24000 | E23: 48000 | F23: ='Liquidität 24M'!$AC$32+'Liquidität 24M'!$AC$44 -> 36000 | G23: 2.000 €/Monat bis M18, danach Plan
A24: Freelance Design, Sound, Illustration → WortBild | C24: 15000 | D24: ='Liquidität 24M'!$AB$37+'Liquidität 24M'!$AB$45 -> 28125 | E24: 25000 | F24: ='Liquidität 24M'!$AC$37+'Liquidität 24M'!$AC$45 -> 21875 | G24: WortBild 37,5 T€ (M4–M15) statt Freelance-Pauschale
A25: Marketing, Creator-Programm, Events, Piloten | C25: 25000 | D25: ='Liquidität 24M'!$AB$34+'Liquidität 24M'!$AB$35+'Liquidität 24M'!$AB$36+'Liquidität 24M'!$AB$46 -> 32000 | E25: 60000 | F25: ='Liquidität 24M'!$AC$34+'Liquidität 24M'!$AC$35+'Liquidität 24M'!$AC$36+'Liquidität 24M'!$AC$46 -> 48000 | G25: 50 T€ in 18 Monaten inkl. 1 Pilot
A26: Infrastruktur, KI-API, Store-Gebühren | C26: 8000 | D26: ='Liquidität 24M'!$AB$85 -> 7043.52 | E26: 25000 | F26: ='Liquidität 24M'!$AC$85 -> 29843.2 | G26: fix 250 €/Monat + 8 % vom Umsatz
A27: Recht, Marke, Steuer, Verwaltung | C27: 12000 | D27: ='Liquidität 24M'!$AB$38+'Liquidität 24M'!$AB$47 -> 19000 | E27: 20000 | F27: ='Liquidität 24M'!$AC$38+'Liquidität 24M'!$AC$47 -> 16000 | G27: 25 T€ in 18 Monaten (Marke DE/EU/TR, DSFA)
A28: Summe Kosten Basis | C28: =SUM(C21:C27) -> 165000 | D28: =SUM(D21:D27) -> 166168.52 | E28: =SUM(E21:E27) -> 398000 | F28: =SUM(F21:F27) -> 294718.2
A29: Kontrolle: = Kosten Basis in der GuV (J1 / J2) | D29: =IF(ROUND(D28-'GuV 5 Jahre'!$C$37,0)=0,"OK","PRÜFEN") -> OK | F29: =IF(ROUND(F28-'GuV 5 Jahre'!$D$37,0)=0,"OK","PRÜFEN") -> OK

Sheet Liquidität 24M
A1: Liquidität monatlich, 24 Monate – Startkasse 250.000 € (Closing Jan 2027)
A2: Alle Werte sind Schätzungen auf Basis von BUSINESSPLAN.md §11 – es gibt noch keine Umsätze. Mittelverwendung, Gates und Bewertung: Vorschlag – mit Steuer-/Rechtsberater prüfen.
A4: Kennzahlen (Ziele/Schätzungen) – Runway, Kasse, Break-even, Folgerunde
A5: Kennzahl | B5: Einheit | C5: Konservativ | D5: Basis | E5: Optimistisch | F5: Ohne Umsatz | G5: Formel / Lesart
A6: Kasse Ende Monat 6 | B6: € | C6: =INDEX($D$67:$AA$67,6) -> 182724.59 | D6: =INDEX($D$88:$AA$88,6) -> 190750.12 | E6: =INDEX($D$109:$AA$109,6) -> 207666.16 | F6: =INDEX($D$117:$AA$117,6) -> 179125 | G6: INDEX in die Kassenzeile
A7: Kasse Ende Monat 12 | B7: € | C7: =INDEX($D$67:$AA$67,12) -> 102273.37 | D7: =INDEX($D$88:$AA$88,12) -> 134375.48 | E7: =INDEX($D$109:$AA$109,12) -> 202039.64 | F7: =INDEX($D$117:$AA$117,12) -> 87875
A8: Kasse Ende Monat 18 | B8: € | C8: =INDEX($D$67:$AA$67,18) -> 49061.051 | D8: =INDEX($D$88:$AA$88,18) -> 145794.06 | E8: =INDEX($D$109:$AA$109,18) -> 368913.1 | F8: =INDEX($D$117:$AA$117,18) -> 8000
A9: Kasse Ende Monat 24 | B9: € | C9: =INDEX($D$67:$AA$67,24) -> -11499.654 | D9: =INDEX($D$88:$AA$88,24) -> 175197.28 | E9: =INDEX($D$109:$AA$109,24) -> 697934.38 | F9: =INDEX($D$117:$AA$117,24) -> -62500
A10: Niedrigster Kassenstand M1–24 | B10: € | C10: =MIN($D$67:$AA$67) -> -11499.654 | D10: =MIN($D$88:$AA$88) -> 125383.57 | E10: =MIN($D$109:$AA$109) -> 196717.61 | F10: =MIN($D$117:$AA$117) -> -62500
A11: Monat des niedrigsten Kassenstands | B11: Monat | C11: =MATCH(MIN($D$67:$AA$67),$D$67:$AA$67,0) -> 24 | D11: =MATCH(MIN($D$88:$AA$88),$D$88:$AA$88,0) -> 15 | E11: =MATCH(MIN($D$109:$AA$109),$D$109:$AA$109,0) -> 9 | F11: =MATCH(MIN($D$117:$AA$117),$D$117:$AA$117,0) -> 24
A12: Cash-out-Monat (erster Monat mit Kasse < 0) | B12: Monat | C12: =IFERROR(MATCH(1,$D$68:$AA$68,0),"keiner bis M24") -> 23 | D12: =IFERROR(MATCH(1,$D$89:$AA$89,0),"keiner bis M24") -> keiner bis M24 | E12: =IFERROR(MATCH(1,$D$110:$AA$110,0),"keiner bis M24") -> keiner bis M24 | F12: =IFERROR(MATCH(1,$D$118:$AA$118,0),"keiner bis M24") -> 19 | G12: Text = Kasse bleibt bis Monat 24 positiv
A13: Runway in Monaten (bis Kasse < 0) | B13: Monate | C13: =IFERROR(MATCH(1,$D$68:$AA$68,0)-1,"> 24") -> 22 | D13: =IFERROR(MATCH(1,$D$89:$AA$89,0)-1,"> 24") -> > 24 | E13: =IFERROR(MATCH(1,$D$110:$AA$110,0)-1,"> 24") -> > 24 | F13: =IFERROR(MATCH(1,$D$118:$AA$118,0)-1,"> 24") -> 18 | G13: Monate mit positiver Kasse
A14: Nachhaltiger Break-even (ab diesem Monat Umsatz ≥ Kosten bis M24) | B14: Monat | C14: =IFERROR(MATCH(1,$D$70:$AA$70,0),"nach M24") -> nach M24 | D14: =IFERROR(MATCH(1,$D$91:$AA$91,0),"nach M24") -> 22 | E14: =IFERROR(MATCH(1,$D$112:$AA$112,0),"nach M24") -> 10 | G14: operativer Monats-Break-even inkl. Ausbau-Team ab M19
A15: Ø Kosten pro Monat M1–18 (Burn ohne Umsatz) | B15: €/Monat | F15: =SUM($D$116:$U$116)/18 -> 13444.444
A16: Kasse fällt unter Mindestkasse (3 laufende Monatskosten) in Monat | B16: Monat | C16: =IFERROR(MATCH(1,$D$71:$AA$71,0),"nie bis M24") -> 19 | D16: =IFERROR(MATCH(1,$D$92:$AA$92,0),"nie bis M24") -> nie bis M24 | E16: =IFERROR(MATCH(1,$D$113:$AA$113,0),"nie bis M24") -> nie bis M24
A17: Kasse Ende J3 ohne Folgerunde (Kasse M24 + EBITDA J3) | B17: € | C17: =C9+'GuV 5 Jahre'!$E$17 -> -70855.654 | D17: =D9+'GuV 5 Jahre'!$E$38 -> 503467.28 | E17: =E9+'GuV 5 Jahre'!$E$59 -> 2196874.4
A18: Mindestkasse = 3 Monatskosten J3 | B18: € | C18: =Annahmen!$B$14*'GuV 5 Jahre'!$E$16/12 -> 82500 | D18: =Annahmen!$B$14*'GuV 5 Jahre'!$E$37/12 -> 177500 | E18: =Annahmen!$B$14*'GuV 5 Jahre'!$E$58/12 -> 275000
A19: Liquiditätslücke bis Ende J3 = MAX(0; Mindestkasse − niedrigster Stand) | B19: € | C19: =MAX(0,C18-MIN(C10,C17)) -> 153355.65 | D19: =MAX(0,D18-MIN(D10,D17)) -> 52116.434 | E19: =MAX(0,E18-MIN(E10,E17)) -> 78282.39
A20: Nachgelagerte Linien (Story-Engine, Studio/Auto-Edit, VR/AR) ab M19 bis Ende J3 | B20: € | C20: =Annahmen!$B$15*(Annahmen!$B$16/2+Annahmen!$B$17) -> 160500 | D20: =Annahmen!$B$15*(Annahmen!$B$16/2+Annahmen!$B$17) -> 160500 | E20: =Annahmen!$B$15*(Annahmen!$B$16/2+Annahmen!$B$17) -> 160500 | G20: 60 % der Vision-Kosten BP §11.5 (½ J2 + J3)
A21: Folgerunde (Seed) – Mindestbedarf | B21: € | C21: =C19+C20 -> 313855.65 | D21: =D19+D20 -> 212616.43 | E21: =E19+E20 -> 238782.39
A22: Folgerunde spätestens abschließen bis Monat (Gate 2 = Monat 18) | B22: Monat | C22: =IF(ISNUMBER(C16),MIN(18,C16),18) -> 18 | D22: =IF(ISNUMBER(D16),MIN(18,D16),18) -> 18 | E22: =IF(ISNUMBER(E16),MIN(18,E16),18) -> 18 | G22: frühestens wenn Gate 2 erfüllt; Gespräche ab Monat 12–15 beginnen
A23: Seed-Richtwert für die Planung (deckt das konservative Szenario, auf 50 T€ gerundet) | B23: € | D23: =CEILING(MAX(C21:E21),50000) -> 350000
A27: Monat | D27: 1 | E27: 2 | F27: 3 | G27: 4 | H27: 5 | I27: 6 | J27: 7 | K27: 8 | L27: 9 | M27: 10 | N27: 11 | O27: 12 | P27: 13 | Q27: 14 | R27: 15 | S27: 16 | T27: 17 | U27: 18 | V27: 19 | W27: 20 | X27: 21 | Y27: 22 | Z27: 23 | AA27: 24 | AB27: Summe J1 | AC27: Summe J2 | AD27: Summe M1–18
A28: Kalendermonat | D28: 01/2027 | E28: 02/2027 | F28: 03/2027 | G28: 04/2027 | H28: 05/2027 | I28: 06/2027 | J28: 07/2027 | K28: 08/2027 | L28: 09/2027 | M28: 10/2027 | N28: 11/2027 | O28: 12/2027 | P28: 01/2028 | Q28: 02/2028 | R28: 03/2028 | S28: 04/2028 | T28: 05/2028 | U28: 06/2028 | V28: 07/2028 | W28: 08/2028 | X28: 09/2028 | Y28: 10/2028 | Z28: 11/2028 | AA28: 12/2028
A30: Kosten Pre-Seed (Monat 1–18, in allen Szenarien gleich) – aus Annahmen C
A31: Mobile-/Web-Entwickler:in (Vollzeit, ab Monat 3) | B31: € | D31: =IF(AND(D$27>=Annahmen!$D$51,D$27<=Annahmen!$E$51),Annahmen!$C$51,0)+IF(D$27=Annahmen!$G$51,Annahmen!$F$51,0) -> 0 | E31: =IF(AND(E$27>=Annahmen!$D$51,E$27<=Annahmen!$E$51),Annahmen!$C$51,0)+IF(E$27=Annahmen!$G$51,Annahmen!$F$51,0) -> 0 | F31: =IF(AND(F$27>=Annahmen!$D$51,F$27<=Annahmen!$E$51),Annahmen!$C$51,0)+IF(F$27=Annahmen!$G$51,Annahmen!$F$51,0) -> 5500 | G31: =IF(AND(G$27>=Annahmen!$D$51,G$27<=Annahmen!$E$51),Annahmen!$C$51,0)+IF(G$27=Annahmen!$G$51,Annahmen!$F$51,0) -> 5500 | H31: =IF(AND(H$27>=Annahmen!$D$51,H$27<=Annahmen!$E$51),Annahmen!$C$51,0)+IF(H$27=Annahmen!$G$51,Annahmen!$F$51,0) -> 5500 | I31: =IF(AND(I$27>=Annahmen!$D$51,I$27<=Annahmen!$E$51),Annahmen!$C$51,0)+IF(I$27=Annahmen!$G$51,Annahmen!$F$51,0) -> 5500 | J31: =IF(AND(J$27>=Annahmen!$D$51,J$27<=Annahmen!$E$51),Annahmen!$C$51,0)+IF(J$27=Annahmen!$G$51,Annahmen!$F$51,0) -> 5500 | K31: =IF(AND(K$27>=Annahmen!$D$51,K$27<=Annahmen!$E$51),Annahmen!$C$51,0)+IF(K$27=Annahmen!$G$51,Annahmen!$F$51,0) -> 5500 | ... AA31: =IF(AND(AA$27>=Annahmen!$D$51,AA$27<=Annahmen!$E$51),Annahmen!$C$51,0)+IF(AA$27=Annahmen!$G$51,Annahmen!$F$51,0) -> 0 | AB31: =SUM(D31:O31) -> 55000 | AC31: =SUM(P31:AA31) -> 33000 | AD31: =SUM(D31:U31) -> 88000
A32: Gründergehalt (anteilig) | B32: € | D32: =IF(AND(D$27>=Annahmen!$D$52,D$27<=Annahmen!$E$52),Annahmen!$C$52,0)+IF(D$27=Annahmen!$G$52,Annahmen!$F$52,0) -> 2000 | E32: =IF(AND(E$27>=Annahmen!$D$52,E$27<=Annahmen!$E$52),Annahmen!$C$52,0)+IF(E$27=Annahmen!$G$52,Annahmen!$F$52,0) -> 2000 | F32: =IF(AND(F$27>=Annahmen!$D$52,F$27<=Annahmen!$E$52),Annahmen!$C$52,0)+IF(F$27=Annahmen!$G$52,Annahmen!$F$52,0) -> 2000 | G32: =IF(AND(G$27>=Annahmen!$D$52,G$27<=Annahmen!$E$52),Annahmen!$C$52,0)+IF(G$27=Annahmen!$G$52,Annahmen!$F$52,0) -> 2000 | H32: =IF(AND(H$27>=Annahmen!$D$52,H$27<=Annahmen!$E$52),Annahmen!$C$52,0)+IF(H$27=Annahmen!$G$52,Annahmen!$F$52,0) -> 2000 | I32: =IF(AND(I$27>=Annahmen!$D$52,I$27<=Annahmen!$E$52),Annahmen!$C$52,0)+IF(I$27=Annahmen!$G$52,Annahmen!$F$52,0) -> 2000 | J32: =IF(AND(J$27>=Annahmen!$D$52,J$27<=Annahmen!$E$52),Annahmen!$C$52,0)+IF(J$27=Annahmen!$G$52,Annahmen!$F$52,0) -> 2000 | K32: =IF(AND(K$27>=Annahmen!$D$52,K$27<=Annahmen!$E$52),Annahmen!$C$52,0)+IF(K$27=Annahmen!$G$52,Annahmen!$F$52,0) -> 2000 | ... AA32: =IF(AND(AA$27>=Annahmen!$D$52,AA$27<=Annahmen!$E$52),Annahmen!$C$52,0)+IF(AA$27=Annahmen!$G$52,Annahmen!$F$52,0) -> 0 | AB32: =SUM(D32:O32) -> 24000 | AC32: =SUM(P32:AA32) -> 12000 | AD32: =SUM(D32:U32) -> 36000
A33: Entwicklungs-Tools, Testgeräte (iOS/Android) | B33: € | D33: =IF(AND(D$27>=Annahmen!$D$53,D$27<=Annahmen!$E$53),Annahmen!$C$53,0)+IF(D$27=Annahmen!$G$53,Annahmen!$F$53,0) -> 1000 | E33: =IF(AND(E$27>=Annahmen!$D$53,E$27<=Annahmen!$E$53),Annahmen!$C$53,0)+IF(E$27=Annahmen!$G$53,Annahmen!$F$53,0) -> 0 | F33: =IF(AND(F$27>=Annahmen!$D$53,F$27<=Annahmen!$E$53),Annahmen!$C$53,0)+IF(F$27=Annahmen!$G$53,Annahmen!$F$53,0) -> 0 | G33: =IF(AND(G$27>=Annahmen!$D$53,G$27<=Annahmen!$E$53),Annahmen!$C$53,0)+IF(G$27=Annahmen!$G$53,Annahmen!$F$53,0) -> 0 | H33: =IF(AND(H$27>=Annahmen!$D$53,H$27<=Annahmen!$E$53),Annahmen!$C$53,0)+IF(H$27=Annahmen!$G$53,Annahmen!$F$53,0) -> 0 | I33: =IF(AND(I$27>=Annahmen!$D$53,I$27<=Annahmen!$E$53),Annahmen!$C$53,0)+IF(I$27=Annahmen!$G$53,Annahmen!$F$53,0) -> 0 | J33: =IF(AND(J$27>=Annahmen!$D$53,J$27<=Annahmen!$E$53),Annahmen!$C$53,0)+IF(J$27=Annahmen!$G$53,Annahmen!$F$53,0) -> 0 | K33: =IF(AND(K$27>=Annahmen!$D$53,K$27<=Annahmen!$E$53),Annahmen!$C$53,0)+IF(K$27=Annahmen!$G$53,Annahmen!$F$53,0) -> 0 | ... AA33: =IF(AND(AA$27>=Annahmen!$D$53,AA$27<=Annahmen!$E$53),Annahmen!$C$53,0)+IF(AA$27=Annahmen!$G$53,Annahmen!$F$53,0) -> 0 | AB33: =SUM(D33:O33) -> 1000 | AC33: =SUM(P33:AA33) -> 0 | AD33: =SUM(D33:U33) -> 1000
A34: Creator-Programm, Community, Marketing – Phase 1 (TR-Launch) | B34: € | D34: =IF(AND(D$27>=Annahmen!$D$54,D$27<=Annahmen!$E$54),Annahmen!$C$54,0)+IF(D$27=Annahmen!$G$54,Annahmen!$F$54,0) -> 2000 | E34: =IF(AND(E$27>=Annahmen!$D$54,E$27<=Annahmen!$E$54),Annahmen!$C$54,0)+IF(E$27=Annahmen!$G$54,Annahmen!$F$54,0) -> 2000 | F34: =IF(AND(F$27>=Annahmen!$D$54,F$27<=Annahmen!$E$54),Annahmen!$C$54,0)+IF(F$27=Annahmen!$G$54,Annahmen!$F$54,0) -> 2000 | G34: =IF(AND(G$27>=Annahmen!$D$54,G$27<=Annahmen!$E$54),Annahmen!$C$54,0)+IF(G$27=Annahmen!$G$54,Annahmen!$F$54,0) -> 2000 | H34: =IF(AND(H$27>=Annahmen!$D$54,H$27<=Annahmen!$E$54),Annahmen!$C$54,0)+IF(H$27=Annahmen!$G$54,Annahmen!$F$54,0) -> 2000 | I34: =IF(AND(I$27>=Annahmen!$D$54,I$27<=Annahmen!$E$54),Annahmen!$C$54,0)+IF(I$27=Annahmen!$G$54,Annahmen!$F$54,0) -> 2000 | J34: =IF(AND(J$27>=Annahmen!$D$54,J$27<=Annahmen!$E$54),Annahmen!$C$54,0)+IF(J$27=Annahmen!$G$54,Annahmen!$F$54,0) -> 0 | K34: =IF(AND(K$27>=Annahmen!$D$54,K$27<=Annahmen!$E$54),Annahmen!$C$54,0)+IF(K$27=Annahmen!$G$54,Annahmen!$F$54,0) -> 0 | ... AA34: =IF(AND(AA$27>=Annahmen!$D$54,AA$27<=Annahmen!$E$54),Annahmen!$C$54,0)+IF(AA$27=Annahmen!$G$54,Annahmen!$F$54,0) -> 0 | AB34: =SUM(D34:O34) -> 12000 | AC34: =SUM(P34:AA34) -> 0 | AD34: =SUM(D34:U34) -> 12000
A35: Creator-Programm, Marketing, Marktplätze – Phase 2 (DE/EN, Partner) | B35: € | D35: =IF(AND(D$27>=Annahmen!$D$55,D$27<=Annahmen!$E$55),Annahmen!$C$55,0)+IF(D$27=Annahmen!$G$55,Annahmen!$F$55,0) -> 0 | E35: =IF(AND(E$27>=Annahmen!$D$55,E$27<=Annahmen!$E$55),Annahmen!$C$55,0)+IF(E$27=Annahmen!$G$55,Annahmen!$F$55,0) -> 0 | F35: =IF(AND(F$27>=Annahmen!$D$55,F$27<=Annahmen!$E$55),Annahmen!$C$55,0)+IF(F$27=Annahmen!$G$55,Annahmen!$F$55,0) -> 0 | G35: =IF(AND(G$27>=Annahmen!$D$55,G$27<=Annahmen!$E$55),Annahmen!$C$55,0)+IF(G$27=Annahmen!$G$55,Annahmen!$F$55,0) -> 0 | H35: =IF(AND(H$27>=Annahmen!$D$55,H$27<=Annahmen!$E$55),Annahmen!$C$55,0)+IF(H$27=Annahmen!$G$55,Annahmen!$F$55,0) -> 0 | I35: =IF(AND(I$27>=Annahmen!$D$55,I$27<=Annahmen!$E$55),Annahmen!$C$55,0)+IF(I$27=Annahmen!$G$55,Annahmen!$F$55,0) -> 0 | J35: =IF(AND(J$27>=Annahmen!$D$55,J$27<=Annahmen!$E$55),Annahmen!$C$55,0)+IF(J$27=Annahmen!$G$55,Annahmen!$F$55,0) -> 3000 | K35: =IF(AND(K$27>=Annahmen!$D$55,K$27<=Annahmen!$E$55),Annahmen!$C$55,0)+IF(K$27=Annahmen!$G$55,Annahmen!$F$55,0) -> 3000 | ... AA35: =IF(AND(AA$27>=Annahmen!$D$55,AA$27<=Annahmen!$E$55),Annahmen!$C$55,0)+IF(AA$27=Annahmen!$G$55,Annahmen!$F$55,0) -> 0 | AB35: =SUM(D35:O35) -> 18000 | AC35: =SUM(P35:AA35) -> 18000 | AD35: =SUM(D35:U35) -> 36000
A36: Plattform- oder Bildungspilot (8 Wochen, Material, Reisen) | B36: € | D36: =IF(AND(D$27>=Annahmen!$D$56,D$27<=Annahmen!$E$56),Annahmen!$C$56,0)+IF(D$27=Annahmen!$G$56,Annahmen!$F$56,0) -> 0 | E36: =IF(AND(E$27>=Annahmen!$D$56,E$27<=Annahmen!$E$56),Annahmen!$C$56,0)+IF(E$27=Annahmen!$G$56,Annahmen!$F$56,0) -> 0 | F36: =IF(AND(F$27>=Annahmen!$D$56,F$27<=Annahmen!$E$56),Annahmen!$C$56,0)+IF(F$27=Annahmen!$G$56,Annahmen!$F$56,0) -> 0 | G36: =IF(AND(G$27>=Annahmen!$D$56,G$27<=Annahmen!$E$56),Annahmen!$C$56,0)+IF(G$27=Annahmen!$G$56,Annahmen!$F$56,0) -> 0 | H36: =IF(AND(H$27>=Annahmen!$D$56,H$27<=Annahmen!$E$56),Annahmen!$C$56,0)+IF(H$27=Annahmen!$G$56,Annahmen!$F$56,0) -> 0 | I36: =IF(AND(I$27>=Annahmen!$D$56,I$27<=Annahmen!$E$56),Annahmen!$C$56,0)+IF(I$27=Annahmen!$G$56,Annahmen!$F$56,0) -> 0 | J36: =IF(AND(J$27>=Annahmen!$D$56,J$27<=Annahmen!$E$56),Annahmen!$C$56,0)+IF(J$27=Annahmen!$G$56,Annahmen!$F$56,0) -> 0 | K36: =IF(AND(K$27>=Annahmen!$D$56,K$27<=Annahmen!$E$56),Annahmen!$C$56,0)+IF(K$27=Annahmen!$G$56,Annahmen!$F$56,0) -> 0 | ... AA36: =IF(AND(AA$27>=Annahmen!$D$56,AA$27<=Annahmen!$E$56),Annahmen!$C$56,0)+IF(AA$27=Annahmen!$G$56,Annahmen!$F$56,0) -> 0 | AB36: =SUM(D36:O36) -> 2000 | AC36: =SUM(P36:AA36) -> 0 | AD36: =SUM(D36:U36) -> 2000
A37: Vision-Linie WortBild (Sprachenlernen): Illustration, Sprecher-Audios DE/TR/EN, Didaktik, Kurs-Pilot | B37: € | D37: =IF(AND(D$27>=Annahmen!$D$57,D$27<=Annahmen!$E$57),Annahmen!$C$57,0)+IF(D$27=Annahmen!$G$57,Annahmen!$F$57,0) -> 0 | E37: =IF(AND(E$27>=Annahmen!$D$57,E$27<=Annahmen!$E$57),Annahmen!$C$57,0)+IF(E$27=Annahmen!$G$57,Annahmen!$F$57,0) -> 0 | F37: =IF(AND(F$27>=Annahmen!$D$57,F$27<=Annahmen!$E$57),Annahmen!$C$57,0)+IF(F$27=Annahmen!$G$57,Annahmen!$F$57,0) -> 0 | G37: =IF(AND(G$27>=Annahmen!$D$57,G$27<=Annahmen!$E$57),Annahmen!$C$57,0)+IF(G$27=Annahmen!$G$57,Annahmen!$F$57,0) -> 3125 | H37: =IF(AND(H$27>=Annahmen!$D$57,H$27<=Annahmen!$E$57),Annahmen!$C$57,0)+IF(H$27=Annahmen!$G$57,Annahmen!$F$57,0) -> 3125 | I37: =IF(AND(I$27>=Annahmen!$D$57,I$27<=Annahmen!$E$57),Annahmen!$C$57,0)+IF(I$27=Annahmen!$G$57,Annahmen!$F$57,0) -> 3125 | J37: =IF(AND(J$27>=Annahmen!$D$57,J$27<=Annahmen!$E$57),Annahmen!$C$57,0)+IF(J$27=Annahmen!$G$57,Annahmen!$F$57,0) -> 3125 | K37: =IF(AND(K$27>=Annahmen!$D$57,K$27<=Annahmen!$E$57),Annahmen!$C$57,0)+IF(K$27=Annahmen!$G$57,Annahmen!$F$57,0) -> 3125 | ... AA37: =IF(AND(AA$27>=Annahmen!$D$57,AA$27<=Annahmen!$E$57),Annahmen!$C$57,0)+IF(AA$27=Annahmen!$G$57,Annahmen!$F$57,0) -> 0 | AB37: =SUM(D37:O37) -> 28125 | AC37: =SUM(P37:AA37) -> 9375 | AD37: =SUM(D37:U37) -> 37500
A38: Recht, Marke (DE/EU/TR), Datenschutz/DSFA, Jugendschutz, Steuerberatung | B38: € | D38: =IF(AND(D$27>=Annahmen!$D$58,D$27<=Annahmen!$E$58),Annahmen!$C$58,0)+IF(D$27=Annahmen!$G$58,Annahmen!$F$58,0) -> 8000 | E38: =IF(AND(E$27>=Annahmen!$D$58,E$27<=Annahmen!$E$58),Annahmen!$C$58,0)+IF(E$27=Annahmen!$G$58,Annahmen!$F$58,0) -> 1000 | F38: =IF(AND(F$27>=Annahmen!$D$58,F$27<=Annahmen!$E$58),Annahmen!$C$58,0)+IF(F$27=Annahmen!$G$58,Annahmen!$F$58,0) -> 1000 | G38: =IF(AND(G$27>=Annahmen!$D$58,G$27<=Annahmen!$E$58),Annahmen!$C$58,0)+IF(G$27=Annahmen!$G$58,Annahmen!$F$58,0) -> 1000 | H38: =IF(AND(H$27>=Annahmen!$D$58,H$27<=Annahmen!$E$58),Annahmen!$C$58,0)+IF(H$27=Annahmen!$G$58,Annahmen!$F$58,0) -> 1000 | I38: =IF(AND(I$27>=Annahmen!$D$58,I$27<=Annahmen!$E$58),Annahmen!$C$58,0)+IF(I$27=Annahmen!$G$58,Annahmen!$F$58,0) -> 1000 | J38: =IF(AND(J$27>=Annahmen!$D$58,J$27<=Annahmen!$E$58),Annahmen!$C$58,0)+IF(J$27=Annahmen!$G$58,Annahmen!$F$58,0) -> 1000 | K38: =IF(AND(K$27>=Annahmen!$D$58,K$27<=Annahmen!$E$58),Annahmen!$C$58,0)+IF(K$27=Annahmen!$G$58,Annahmen!$F$58,0) -> 1000 | ... AA38: =IF(AND(AA$27>=Annahmen!$D$58,AA$27<=Annahmen!$E$58),Annahmen!$C$58,0)+IF(AA$27=Annahmen!$G$58,Annahmen!$F$58,0) -> 0 | AB38: =SUM(D38:O38) -> 19000 | AC38: =SUM(P38:AA38) -> 6000 | AD38: =SUM(D38:U38) -> 25000
A39: Summe Pre-Seed-Kosten | D39: =SUM(D31:D38) -> 13000 | E39: =SUM(E31:E38) -> 5000 | F39: =SUM(F31:F38) -> 10500 | G39: =SUM(G31:G38) -> 13625 | H39: =SUM(H31:H38) -> 13625 | I39: =SUM(I31:I38) -> 13625 | J39: =SUM(J31:J38) -> 14625 | K39: =SUM(K31:K38) -> 14625 | ... AA39: =SUM(AA31:AA38) -> 0 | AB39: =SUM(D39:O39) -> 159125 | AC39: =SUM(P39:AA39) -> 78375 | AD39: =SUM(D39:U39) -> 237500
A41: Ausbau-Team ab Monat 19 (Basis; Szenarien × Ausbau-Faktor) – aus Annahmen D
A42: Personal: Mobile-/Web-Entwicklung (2 Personen) | B42: Mobile/Web | D42: =IF(D$27>=Annahmen!$B$18,Annahmen!$D$64,0) -> 0 | E42: =IF(E$27>=Annahmen!$B$18,Annahmen!$D$64,0) -> 0 | F42: =IF(F$27>=Annahmen!$B$18,Annahmen!$D$64,0) -> 0 | G42: =IF(G$27>=Annahmen!$B$18,Annahmen!$D$64,0) -> 0 | H42: =IF(H$27>=Annahmen!$B$18,Annahmen!$D$64,0) -> 0 | I42: =IF(I$27>=Annahmen!$B$18,Annahmen!$D$64,0) -> 0 | J42: =IF(J$27>=Annahmen!$B$18,Annahmen!$D$64,0) -> 0 | K42: =IF(K$27>=Annahmen!$B$18,Annahmen!$D$64,0) -> 0 | ... AA42: =IF(AA$27>=Annahmen!$B$18,Annahmen!$D$64,0) -> 13333.333 | AB42: =SUM(D42:O42) -> 0 | AC42: =SUM(P42:AA42) -> 80000 | AD42: =SUM(D42:U42) -> 0
A43: Personal: Backend/ML, Community/Support | B43: Backend/Community | D43: =IF(D$27>=Annahmen!$B$18,Annahmen!$D$65,0) -> 0 | E43: =IF(E$27>=Annahmen!$B$18,Annahmen!$D$65,0) -> 0 | F43: =IF(F$27>=Annahmen!$B$18,Annahmen!$D$65,0) -> 0 | G43: =IF(G$27>=Annahmen!$B$18,Annahmen!$D$65,0) -> 0 | H43: =IF(H$27>=Annahmen!$B$18,Annahmen!$D$65,0) -> 0 | I43: =IF(I$27>=Annahmen!$B$18,Annahmen!$D$65,0) -> 0 | J43: =IF(J$27>=Annahmen!$B$18,Annahmen!$D$65,0) -> 0 | K43: =IF(K$27>=Annahmen!$B$18,Annahmen!$D$65,0) -> 0 | ... AA43: =IF(AA$27>=Annahmen!$B$18,Annahmen!$D$65,0) -> 5000 | AB43: =SUM(D43:O43) -> 0 | AC43: =SUM(P43:AA43) -> 30000 | AD43: =SUM(D43:U43) -> 0
A44: Gründer (Gehalt) | B44: Gründer | D44: =IF(D$27>=Annahmen!$B$18,Annahmen!$D$66,0) -> 0 | E44: =IF(E$27>=Annahmen!$B$18,Annahmen!$D$66,0) -> 0 | F44: =IF(F$27>=Annahmen!$B$18,Annahmen!$D$66,0) -> 0 | G44: =IF(G$27>=Annahmen!$B$18,Annahmen!$D$66,0) -> 0 | H44: =IF(H$27>=Annahmen!$B$18,Annahmen!$D$66,0) -> 0 | I44: =IF(I$27>=Annahmen!$B$18,Annahmen!$D$66,0) -> 0 | J44: =IF(J$27>=Annahmen!$B$18,Annahmen!$D$66,0) -> 0 | K44: =IF(K$27>=Annahmen!$B$18,Annahmen!$D$66,0) -> 0 | ... AA44: =IF(AA$27>=Annahmen!$B$18,Annahmen!$D$66,0) -> 4000 | AB44: =SUM(D44:O44) -> 0 | AC44: =SUM(P44:AA44) -> 24000 | AD44: =SUM(D44:U44) -> 0
A45: Freelance Design, Sound, Illustration (Packs, WortBild) | B45: Freelance/WortBild | D45: =IF(D$27>=Annahmen!$B$18,Annahmen!$D$67,0) -> 0 | E45: =IF(E$27>=Annahmen!$B$18,Annahmen!$D$67,0) -> 0 | F45: =IF(F$27>=Annahmen!$B$18,Annahmen!$D$67,0) -> 0 | G45: =IF(G$27>=Annahmen!$B$18,Annahmen!$D$67,0) -> 0 | H45: =IF(H$27>=Annahmen!$B$18,Annahmen!$D$67,0) -> 0 | I45: =IF(I$27>=Annahmen!$B$18,Annahmen!$D$67,0) -> 0 | J45: =IF(J$27>=Annahmen!$B$18,Annahmen!$D$67,0) -> 0 | K45: =IF(K$27>=Annahmen!$B$18,Annahmen!$D$67,0) -> 0 | ... AA45: =IF(AA$27>=Annahmen!$B$18,Annahmen!$D$67,0) -> 2083.3333 | AB45: =SUM(D45:O45) -> 0 | AC45: =SUM(P45:AA45) -> 12500 | AD45: =SUM(D45:U45) -> 0
A46: Marketing, Creator-Partnerprogramm, Events | B46: Marketing | D46: =IF(D$27>=Annahmen!$B$18,Annahmen!$D$68,0) -> 0 | E46: =IF(E$27>=Annahmen!$B$18,Annahmen!$D$68,0) -> 0 | F46: =IF(F$27>=Annahmen!$B$18,Annahmen!$D$68,0) -> 0 | G46: =IF(G$27>=Annahmen!$B$18,Annahmen!$D$68,0) -> 0 | H46: =IF(H$27>=Annahmen!$B$18,Annahmen!$D$68,0) -> 0 | I46: =IF(I$27>=Annahmen!$B$18,Annahmen!$D$68,0) -> 0 | J46: =IF(J$27>=Annahmen!$B$18,Annahmen!$D$68,0) -> 0 | K46: =IF(K$27>=Annahmen!$B$18,Annahmen!$D$68,0) -> 0 | ... AA46: =IF(AA$27>=Annahmen!$B$18,Annahmen!$D$68,0) -> 5000 | AB46: =SUM(D46:O46) -> 0 | AC46: =SUM(P46:AA46) -> 30000 | AD46: =SUM(D46:U46) -> 0
A47: Recht, Marke, Steuer, Verwaltung | B47: Recht | D47: =IF(D$27>=Annahmen!$B$18,Annahmen!$D$69,0) -> 0 | E47: =IF(E$27>=Annahmen!$B$18,Annahmen!$D$69,0) -> 0 | F47: =IF(F$27>=Annahmen!$B$18,Annahmen!$D$69,0) -> 0 | G47: =IF(G$27>=Annahmen!$B$18,Annahmen!$D$69,0) -> 0 | H47: =IF(H$27>=Annahmen!$B$18,Annahmen!$D$69,0) -> 0 | I47: =IF(I$27>=Annahmen!$B$18,Annahmen!$D$69,0) -> 0 | J47: =IF(J$27>=Annahmen!$B$18,Annahmen!$D$69,0) -> 0 | K47: =IF(K$27>=Annahmen!$B$18,Annahmen!$D$69,0) -> 0 | ... AA47: =IF(AA$27>=Annahmen!$B$18,Annahmen!$D$69,0) -> 1666.6667 | AB47: =SUM(D47:O47) -> 0 | AC47: =SUM(P47:AA47) -> 10000 | AD47: =SUM(D47:U47) -> 0
A48: Summe Ausbau (Basis) | D48: =SUM(D42:D47) -> 0 | E48: =SUM(E42:E47) -> 0 | F48: =SUM(F42:F47) -> 0 | G48: =SUM(G42:G47) -> 0 | H48: =SUM(H42:H47) -> 0 | I48: =SUM(I42:I47) -> 0 | J48: =SUM(J42:J47) -> 0 | K48: =SUM(K42:K47) -> 0 | ... AA48: =SUM(AA42:AA47) -> 31083.333 | AB48: =SUM(D48:O48) -> 0 | AC48: =SUM(P48:AA48) -> 186500 | AD48: =SUM(D48:U48) -> 0
A50: Weiterbetrieb schlank ab Monat 19 (nur Fall „ohne Umsatz“) | D50: =IF(D$27>=Annahmen!$B$18,Annahmen!$C$60,0) -> 0 | E50: =IF(E$27>=Annahmen!$B$18,Annahmen!$C$60,0) -> 0 | F50: =IF(F$27>=Annahmen!$B$18,Annahmen!$C$60,0) -> 0 | G50: =IF(G$27>=Annahmen!$B$18,Annahmen!$C$60,0) -> 0 | H50: =IF(H$27>=Annahmen!$B$18,Annahmen!$C$60,0) -> 0 | I50: =IF(I$27>=Annahmen!$B$18,Annahmen!$C$60,0) -> 0 | J50: =IF(J$27>=Annahmen!$B$18,Annahmen!$C$60,0) -> 0 | K50: =IF(K$27>=Annahmen!$B$18,Annahmen!$C$60,0) -> 0 | ... AA50: =IF(AA$27>=Annahmen!$B$18,Annahmen!$C$60,0) -> 11500 | AB50: =SUM(D50:O50) -> 0 | AC50: =SUM(P50:AA50) -> 69000 | AD50: =SUM(D50:U50) -> 0
A52: Szenario Konservativ
A53: Wiederkehrender Umsatz J1 (Pro + Packs + Agentur), Jahr | C53: ='GuV 5 Jahre'!$C$13 -> 15650.4
A54: Wiederkehrender Umsatz J2, Jahr | C54: ='GuV 5 Jahre'!$D$13 -> 81933
A55: Startniveau J2 = Dezember-Umsatz J1 (€/Monat) | C55: =C53*11.5/72 -> 2499.7167 | D55: J1: Monat m = Jahreswert × (m − 0,5) ÷ 72 (linear ab null, Summe = Jahreswert)
A56: Monatlicher Zuwachs J2 (€/Monat) | C56: =(C54-12*C55)/78 -> 665.85128 | D56: J2: Monat m = s + g × (m − 12); g so gewählt, dass die Summe J2 dem Jahreswert entspricht
A57: B2B J1 (Einmalzahlung) | C57: ='GuV 5 Jahre'!$C$14 -> 0
A58: B2B J2 (Einmalzahlung) | C58: ='GuV 5 Jahre'!$D$14 -> 0
A59: Umsatz wiederkehrend (Pro, Packs, Agentur) | D59: =IF(D$27<=12,$C$53*(D$27-0.5)/72,$C$55+$C$56*(D$27-12)) -> 108.68333 | E59: =IF(E$27<=12,$C$53*(E$27-0.5)/72,$C$55+$C$56*(E$27-12)) -> 326.05 | F59: =IF(F$27<=12,$C$53*(F$27-0.5)/72,$C$55+$C$56*(F$27-12)) -> 543.41667 | G59: =IF(G$27<=12,$C$53*(G$27-0.5)/72,$C$55+$C$56*(G$27-12)) -> 760.78333 | H59: =IF(H$27<=12,$C$53*(H$27-0.5)/72,$C$55+$C$56*(H$27-12)) -> 978.15 | I59: =IF(I$27<=12,$C$53*(I$27-0.5)/72,$C$55+$C$56*(I$27-12)) -> 1195.5167 | J59: =IF(J$27<=12,$C$53*(J$27-0.5)/72,$C$55+$C$56*(J$27-12)) -> 1412.8833 | K59: =IF(K$27<=12,$C$53*(K$27-0.5)/72,$C$55+$C$56*(K$27-12)) -> 1630.25 | ... AA59: =IF(AA$27<=12,$C$53*(AA$27-0.5)/72,$C$55+$C$56*(AA$27-12)) -> 10489.932 | AB59: =SUM(D59:O59) -> 15650.4 | AC59: =SUM(P59:AA59) -> 81933 | AD59: =SUM(D59:U59) -> 44631.577
A60: Umsatz B2B/Pilot (Einmalzahlung) | D60: =IF(D$27=Annahmen!$B$9,$C$57,0)+IF(D$27=12+Annahmen!$B$9,$C$58,0) -> 0 | E60: =IF(E$27=Annahmen!$B$9,$C$57,0)+IF(E$27=12+Annahmen!$B$9,$C$58,0) -> 0 | F60: =IF(F$27=Annahmen!$B$9,$C$57,0)+IF(F$27=12+Annahmen!$B$9,$C$58,0) -> 0 | G60: =IF(G$27=Annahmen!$B$9,$C$57,0)+IF(G$27=12+Annahmen!$B$9,$C$58,0) -> 0 | H60: =IF(H$27=Annahmen!$B$9,$C$57,0)+IF(H$27=12+Annahmen!$B$9,$C$58,0) -> 0 | I60: =IF(I$27=Annahmen!$B$9,$C$57,0)+IF(I$27=12+Annahmen!$B$9,$C$58,0) -> 0 | J60: =IF(J$27=Annahmen!$B$9,$C$57,0)+IF(J$27=12+Annahmen!$B$9,$C$58,0) -> 0 | K60: =IF(K$27=Annahmen!$B$9,$C$57,0)+IF(K$27=12+Annahmen!$B$9,$C$58,0) -> 0 | ... AA60: =IF(AA$27=Annahmen!$B$9,$C$57,0)+IF(AA$27=12+Annahmen!$B$9,$C$58,0) -> 0 | AB60: =SUM(D60:O60) -> 0 | AC60: =SUM(P60:AA60) -> 0 | AD60: =SUM(D60:U60) -> 0
A61: Umsatz gesamt | D61: =D59+D60 -> 108.68333 | E61: =E59+E60 -> 326.05 | F61: =F59+F60 -> 543.41667 | G61: =G59+G60 -> 760.78333 | H61: =H59+H60 -> 978.15 | I61: =I59+I60 -> 1195.5167 | J61: =J59+J60 -> 1412.8833 | K61: =K59+K60 -> 1630.25 | ... AA61: =AA59+AA60 -> 10489.932 | AB61: =SUM(D61:O61) -> 15650.4 | AC61: =SUM(P61:AA61) -> 81933 | AD61: =SUM(D61:U61) -> 44631.577
A62: Kosten Pre-Seed-Team und -Budget | D62: =D$39 -> 13000 | E62: =E$39 -> 5000 | F62: =F$39 -> 10500 | G62: =G$39 -> 13625 | H62: =H$39 -> 13625 | I62: =I$39 -> 13625 | J62: =J$39 -> 14625 | K62: =K$39 -> 14625 | ... AA62: =AA$39 -> 0 | AB62: =SUM(D62:O62) -> 159125 | AC62: =SUM(P62:AA62) -> 78375 | AD62: =SUM(D62:U62) -> 237500
A63: Kosten Ausbau-Team (ab M19) | D63: =D$48*Annahmen!$C$47 -> 0 | E63: =E$48*Annahmen!$C$47 -> 0 | F63: =F$48*Annahmen!$C$47 -> 0 | G63: =G$48*Annahmen!$C$47 -> 0 | H63: =H$48*Annahmen!$C$47 -> 0 | I63: =I$48*Annahmen!$C$47 -> 0 | J63: =J$48*Annahmen!$C$47 -> 0 | K63: =K$48*Annahmen!$C$47 -> 0 | ... AA63: =AA$48*Annahmen!$C$47 -> 17962.73 | AB63: =SUM(D63:O63) -> 0 | AC63: =SUM(P63:AA63) -> 107776.38 | AD63: =SUM(D63:U63) -> 0
A64: Infrastruktur (fix + % vom Umsatz) | D64: =Annahmen!$B$7+Annahmen!$B$8*D61 -> 258.69467 | E64: =Annahmen!$B$7+Annahmen!$B$8*E61 -> 276.084 | F64: =Annahmen!$B$7+Annahmen!$B$8*F61 -> 293.47333 | G64: =Annahmen!$B$7+Annahmen!$B$8*G61 -> 310.86267 | H64: =Annahmen!$B$7+Annahmen!$B$8*H61 -> 328.252 | I64: =Annahmen!$B$7+Annahmen!$B$8*I61 -> 345.64133 | J64: =Annahmen!$B$7+Annahmen!$B$8*J61 -> 363.03067 | K64: =Annahmen!$B$7+Annahmen!$B$8*K61 -> 380.42 | ... AA64: =Annahmen!$B$7+Annahmen!$B$8*AA61 -> 1089.1946 | AB64: =SUM(D64:O64) -> 4252.032 | AC64: =SUM(P64:AA64) -> 9554.64 | AD64: =SUM(D64:U64) -> 8070.5262
A65: Kosten gesamt | D65: =D62+D63+D64 -> 13258.695 | E65: =E62+E63+E64 -> 5276.084 | F65: =F62+F63+F64 -> 10793.473 | G65: =G62+G63+G64 -> 13935.863 | H65: =H62+H63+H64 -> 13953.252 | I65: =I62+I63+I64 -> 13970.641 | J65: =J62+J63+J64 -> 14988.031 | K65: =K62+K63+K64 -> 15005.42 | ... AA65: =AA62+AA63+AA64 -> 19051.925 | AB65: =SUM(D65:O65) -> 163377.03 | AC65: =SUM(P65:AA65) -> 195706.02 | AD65: =SUM(D65:U65) -> 245570.53
A66: Netto-Cashflow | D66: =D61-D65 -> -13150.011 | E66: =E61-E65 -> -4950.034 | F66: =F61-F65 -> -10250.057 | G66: =G61-G65 -> -13175.079 | H66: =H61-H65 -> -12975.102 | I66: =I61-I65 -> -12775.125 | J66: =J61-J65 -> -13575.147 | K66: =K61-K65 -> -13375.17 | ... AA66: =AA61-AA65 -> -8561.9928 | AB66: =SUM(D66:O66) -> -147726.63 | AC66: =SUM(P66:AA66) -> -113773.02 | AD66: =SUM(D66:U66) -> -200938.95
A67: Kasse Monatsende | D67: =Annahmen!$B$6+D66 -> 236849.99 | E67: =D67+E66 -> 231899.95 | F67: =E67+F66 -> 221649.9 | G67: =F67+G66 -> 208474.82 | H67: =G67+H66 -> 195499.72 | I67: =H67+I66 -> 182724.59 | J67: =I67+J66 -> 169149.44 | K67: =J67+K66 -> 155774.27 | L67: =K67+L66 -> 140599.08 | ... AA67: =Z67+AA66 -> -11499.654
A68: Hilfszeile: Kasse < 0 (1 = ja) | D68: =IF(D67<0,1,0) -> 0 | E68: =IF(E67<0,1,0) -> 0 | F68: =IF(F67<0,1,0) -> 0 | G68: =IF(G67<0,1,0) -> 0 | H68: =IF(H67<0,1,0) -> 0 | I68: =IF(I67<0,1,0) -> 0 | J68: =IF(J67<0,1,0) -> 0 | K68: =IF(K67<0,1,0) -> 0 | ... AA68: =IF(AA67<0,1,0) -> 1
A69: Hilfszeile: Umsatz ≥ Kosten | D69: =IF(D61>=D65,1,0) -> 0 | E69: =IF(E61>=E65,1,0) -> 0 | F69: =IF(F61>=F65,1,0) -> 0 | G69: =IF(G61>=G65,1,0) -> 0 | H69: =IF(H61>=H65,1,0) -> 0 | I69: =IF(I61>=I65,1,0) -> 0 | J69: =IF(J61>=J65,1,0) -> 0 | K69: =IF(K61>=K65,1,0) -> 0 | ... AA69: =IF(AA61>=AA65,1,0) -> 0
A70: Hilfszeile: Umsatz ≥ Kosten ab hier bis M24 | D70: =IF(AND(D69=1,E70=1),1,0) -> 0 | E70: =IF(AND(E69=1,F70=1),1,0) -> 0 | F70: =IF(AND(F69=1,G70=1),1,0) -> 0 | G70: =IF(AND(G69=1,H70=1),1,0) -> 0 | H70: =IF(AND(H69=1,I70=1),1,0) -> 0 | I70: =IF(AND(I69=1,J70=1),1,0) -> 0 | J70: =IF(AND(J69=1,K70=1),1,0) -> 0 | K70: =IF(AND(K69=1,L70=1),1,0) -> 0 | ... Z70: =IF(AND(Z69=1,AA70=1),1,0) -> 0 | AA70: =IF(AND(AA69=1,1=1),1,0) -> 0
A71: Hilfszeile: Kasse < Mindestkasse (3 Monatskosten) | D71: =IF(D67<Annahmen!$B$14*D65,1,0) -> 0 | E71: =IF(E67<Annahmen!$B$14*E65,1,0) -> 0 | F71: =IF(F67<Annahmen!$B$14*F65,1,0) -> 0 | G71: =IF(G67<Annahmen!$B$14*G65,1,0) -> 0 | H71: =IF(H67<Annahmen!$B$14*H65,1,0) -> 0 | I71: =IF(I67<Annahmen!$B$14*I65,1,0) -> 0 | J71: =IF(J67<Annahmen!$B$14*J65,1,0) -> 0 | K71: =IF(K67<Annahmen!$B$14*K65,1,0) -> 0 | ... AA71: =IF(AA67<Annahmen!$B$14*AA65,1,0) -> 1
A73: Szenario Basis
A74: Wiederkehrender Umsatz J1 (Pro + Packs + Agentur), Jahr | C74: ='GuV 5 Jahre'!$C$34 -> 50544
A75: Wiederkehrender Umsatz J2, Jahr | C75: ='GuV 5 Jahre'!$D$34 -> 285540
A76: Startniveau J2 = Dezember-Umsatz J1 (€/Monat) | C76: =C74*11.5/72 -> 8073 | D76: J1: Monat m = Jahreswert × (m − 0,5) ÷ 72 (linear ab null, Summe = Jahreswert)
A77: Monatlicher Zuwachs J2 (€/Monat) | C77: =(C75-12*C76)/78 -> 2418.7692 | D77: J2: Monat m = s + g × (m − 12); g so gewählt, dass die Summe J2 dem Jahreswert entspricht
A78: B2B J1 (Einmalzahlung) | C78: ='GuV 5 Jahre'!$C$35 -> 0
A79: B2B J2 (Einmalzahlung) | C79: ='GuV 5 Jahre'!$D$35 -> 50000
A80: Umsatz wiederkehrend (Pro, Packs, Agentur) | D80: =IF(D$27<=12,$C$74*(D$27-0.5)/72,$C$76+$C$77*(D$27-12)) -> 351 | E80: =IF(E$27<=12,$C$74*(E$27-0.5)/72,$C$76+$C$77*(E$27-12)) -> 1053 | F80: =IF(F$27<=12,$C$74*(F$27-0.5)/72,$C$76+$C$77*(F$27-12)) -> 1755 | G80: =IF(G$27<=12,$C$74*(G$27-0.5)/72,$C$76+$C$77*(G$27-12)) -> 2457 | H80: =IF(H$27<=12,$C$74*(H$27-0.5)/72,$C$76+$C$77*(H$27-12)) -> 3159 | I80: =IF(I$27<=12,$C$74*(I$27-0.5)/72,$C$76+$C$77*(I$27-12)) -> 3861 | J80: =IF(J$27<=12,$C$74*(J$27-0.5)/72,$C$76+$C$77*(J$27-12)) -> 4563 | K80: =IF(K$27<=12,$C$74*(K$27-0.5)/72,$C$76+$C$77*(K$27-12)) -> 5265 | ... AA80: =IF(AA$27<=12,$C$74*(AA$27-0.5)/72,$C$76+$C$77*(AA$27-12)) -> 37098.231 | AB80: =SUM(D80:O80) -> 50544 | AC80: =SUM(P80:AA80) -> 285540 | AD80: =SUM(D80:U80) -> 149776.15
A81: Umsatz B2B/Pilot (Einmalzahlung) | D81: =IF(D$27=Annahmen!$B$9,$C$78,0)+IF(D$27=12+Annahmen!$B$9,$C$79,0) -> 0 | E81: =IF(E$27=Annahmen!$B$9,$C$78,0)+IF(E$27=12+Annahmen!$B$9,$C$79,0) -> 0 | F81: =IF(F$27=Annahmen!$B$9,$C$78,0)+IF(F$27=12+Annahmen!$B$9,$C$79,0) -> 0 | G81: =IF(G$27=Annahmen!$B$9,$C$78,0)+IF(G$27=12+Annahmen!$B$9,$C$79,0) -> 0 | H81: =IF(H$27=Annahmen!$B$9,$C$78,0)+IF(H$27=12+Annahmen!$B$9,$C$79,0) -> 0 | I81: =IF(I$27=Annahmen!$B$9,$C$78,0)+IF(I$27=12+Annahmen!$B$9,$C$79,0) -> 0 | J81: =IF(J$27=Annahmen!$B$9,$C$78,0)+IF(J$27=12+Annahmen!$B$9,$C$79,0) -> 0 | K81: =IF(K$27=Annahmen!$B$9,$C$78,0)+IF(K$27=12+Annahmen!$B$9,$C$79,0) -> 0 | ... AA81: =IF(AA$27=Annahmen!$B$9,$C$78,0)+IF(AA$27=12+Annahmen!$B$9,$C$79,0) -> 0 | AB81: =SUM(D81:O81) -> 0 | AC81: =SUM(P81:AA81) -> 50000 | AD81: =SUM(D81:U81) -> 0
A82: Umsatz gesamt | D82: =D80+D81 -> 351 | E82: =E80+E81 -> 1053 | F82: =F80+F81 -> 1755 | G82: =G80+G81 -> 2457 | H82: =H80+H81 -> 3159 | I82: =I80+I81 -> 3861 | J82: =J80+J81 -> 4563 | K82: =K80+K81 -> 5265 | ... AA82: =AA80+AA81 -> 37098.231 | AB82: =SUM(D82:O82) -> 50544 | AC82: =SUM(P82:AA82) -> 335540 | AD82: =SUM(D82:U82) -> 149776.15
A83: Kosten Pre-Seed-Team und -Budget | D83: =D$39 -> 13000 | E83: =E$39 -> 5000 | F83: =F$39 -> 10500 | G83: =G$39 -> 13625 | H83: =H$39 -> 13625 | I83: =I$39 -> 13625 | J83: =J$39 -> 14625 | K83: =K$39 -> 14625 | ... AA83: =AA$39 -> 0 | AB83: =SUM(D83:O83) -> 159125 | AC83: =SUM(P83:AA83) -> 78375 | AD83: =SUM(D83:U83) -> 237500
A84: Kosten Ausbau-Team (ab M19) | D84: =D$48*Annahmen!$D$47 -> 0 | E84: =E$48*Annahmen!$D$47 -> 0 | F84: =F$48*Annahmen!$D$47 -> 0 | G84: =G$48*Annahmen!$D$47 -> 0 | H84: =H$48*Annahmen!$D$47 -> 0 | I84: =I$48*Annahmen!$D$47 -> 0 | J84: =J$48*Annahmen!$D$47 -> 0 | K84: =K$48*Annahmen!$D$47 -> 0 | ... AA84: =AA$48*Annahmen!$D$47 -> 31083.333 | AB84: =SUM(D84:O84) -> 0 | AC84: =SUM(P84:AA84) -> 186500 | AD84: =SUM(D84:U84) -> 0
A85: Infrastruktur (fix + % vom Umsatz) | D85: =Annahmen!$B$7+Annahmen!$B$8*D82 -> 278.08 | E85: =Annahmen!$B$7+Annahmen!$B$8*E82 -> 334.24 | F85: =Annahmen!$B$7+Annahmen!$B$8*F82 -> 390.4 | G85: =Annahmen!$B$7+Annahmen!$B$8*G82 -> 446.56 | H85: =Annahmen!$B$7+Annahmen!$B$8*H82 -> 502.72 | I85: =Annahmen!$B$7+Annahmen!$B$8*I82 -> 558.88 | J85: =Annahmen!$B$7+Annahmen!$B$8*J82 -> 615.04 | K85: =Annahmen!$B$7+Annahmen!$B$8*K82 -> 671.2 | ... AA85: =Annahmen!$B$7+Annahmen!$B$8*AA82 -> 3217.8585 | AB85: =SUM(D85:O85) -> 7043.52 | AC85: =SUM(P85:AA85) -> 29843.2 | AD85: =SUM(D85:U85) -> 16482.092
A86: Kosten gesamt | D86: =D83+D84+D85 -> 13278.08 | E86: =E83+E84+E85 -> 5334.24 | F86: =F83+F84+F85 -> 10890.4 | G86: =G83+G84+G85 -> 14071.56 | H86: =H83+H84+H85 -> 14127.72 | I86: =I83+I84+I85 -> 14183.88 | J86: =J83+J84+J85 -> 15240.04 | K86: =K83+K84+K85 -> 15296.2 | ... AA86: =AA83+AA84+AA85 -> 34301.192 | AB86: =SUM(D86:O86) -> 166168.52 | AC86: =SUM(P86:AA86) -> 294718.2 | AD86: =SUM(D86:U86) -> 253982.09
A87: Netto-Cashflow | D87: =D82-D86 -> -12927.08 | E87: =E82-E86 -> -4281.24 | F87: =F82-F86 -> -9135.4 | G87: =G82-G86 -> -11614.56 | H87: =H82-H86 -> -10968.72 | I87: =I82-I86 -> -10322.88 | J87: =J82-J86 -> -10677.04 | K87: =K82-K86 -> -10031.2 | ... AA87: =AA82-AA86 -> 2797.039 | AB87: =SUM(D87:O87) -> -115624.52 | AC87: =SUM(P87:AA87) -> 40821.8 | AD87: =SUM(D87:U87) -> -104205.94
A88: Kasse Monatsende | D88: =Annahmen!$B$6+D87 -> 237072.92 | E88: =D88+E87 -> 232791.68 | F88: =E88+F87 -> 223656.28 | G88: =F88+G87 -> 212041.72 | H88: =G88+H87 -> 201073 | I88: =H88+I87 -> 190750.12 | J88: =I88+J87 -> 180073.08 | K88: =J88+K87 -> 170041.88 | L88: =K88+L87 -> 158656.52 | ... AA88: =Z88+AA87 -> 175197.28
A89: Hilfszeile: Kasse < 0 (1 = ja) | D89: =IF(D88<0,1,0) -> 0 | E89: =IF(E88<0,1,0) -> 0 | F89: =IF(F88<0,1,0) -> 0 | G89: =IF(G88<0,1,0) -> 0 | H89: =IF(H88<0,1,0) -> 0 | I89: =IF(I88<0,1,0) -> 0 | J89: =IF(J88<0,1,0) -> 0 | K89: =IF(K88<0,1,0) -> 0 | ... AA89: =IF(AA88<0,1,0) -> 0
A90: Hilfszeile: Umsatz ≥ Kosten | D90: =IF(D82>=D86,1,0) -> 0 | E90: =IF(E82>=E86,1,0) -> 0 | F90: =IF(F82>=F86,1,0) -> 0 | G90: =IF(G82>=G86,1,0) -> 0 | H90: =IF(H82>=H86,1,0) -> 0 | I90: =IF(I82>=I86,1,0) -> 0 | J90: =IF(J82>=J86,1,0) -> 0 | K90: =IF(K82>=K86,1,0) -> 0 | ... AA90: =IF(AA82>=AA86,1,0) -> 1
A91: Hilfszeile: Umsatz ≥ Kosten ab hier bis M24 | D91: =IF(AND(D90=1,E91=1),1,0) -> 0 | E91: =IF(AND(E90=1,F91=1),1,0) -> 0 | F91: =IF(AND(F90=1,G91=1),1,0) -> 0 | G91: =IF(AND(G90=1,H91=1),1,0) -> 0 | H91: =IF(AND(H90=1,I91=1),1,0) -> 0 | I91: =IF(AND(I90=1,J91=1),1,0) -> 0 | J91: =IF(AND(J90=1,K91=1),1,0) -> 0 | K91: =IF(AND(K90=1,L91=1),1,0) -> 0 | ... Z91: =IF(AND(Z90=1,AA91=1),1,0) -> 1 | AA91: =IF(AND(AA90=1,1=1),1,0) -> 1
A92: Hilfszeile: Kasse < Mindestkasse (3 Monatskosten) | D92: =IF(D88<Annahmen!$B$14*D86,1,0) -> 0 | E92: =IF(E88<Annahmen!$B$14*E86,1,0) -> 0 | F92: =IF(F88<Annahmen!$B$14*F86,1,0) -> 0 | G92: =IF(G88<Annahmen!$B$14*G86,1,0) -> 0 | H92: =IF(H88<Annahmen!$B$14*H86,1,0) -> 0 | I92: =IF(I88<Annahmen!$B$14*I86,1,0) -> 0 | J92: =IF(J88<Annahmen!$B$14*J86,1,0) -> 0 | K92: =IF(K88<Annahmen!$B$14*K86,1,0) -> 0 | ... AA92: =IF(AA88<Annahmen!$B$14*AA86,1,0) -> 0
A94: Szenario Optimistisch
A95: Wiederkehrender Umsatz J1 (Pro + Packs + Agentur), Jahr | C95: ='GuV 5 Jahre'!$C$55 -> 124092
A96: Wiederkehrender Umsatz J2, Jahr | C96: ='GuV 5 Jahre'!$D$55 -> 792324
A97: Startniveau J2 = Dezember-Umsatz J1 (€/Monat) | C97: =C95*11.5/72 -> 19820.25 | D97: J1: Monat m = Jahreswert × (m − 0,5) ÷ 72 (linear ab null, Summe = Jahreswert)
A98: Monatlicher Zuwachs J2 (€/Monat) | C98: =(C96-12*C97)/78 -> 7108.7308 | D98: J2: Monat m = s + g × (m − 12); g so gewählt, dass die Summe J2 dem Jahreswert entspricht
A99: B2B J1 (Einmalzahlung) | C99: ='GuV 5 Jahre'!$C$56 -> 0
A100: B2B J2 (Einmalzahlung) | C100: ='GuV 5 Jahre'!$D$56 -> 100000
A101: Umsatz wiederkehrend (Pro, Packs, Agentur) | D101: =IF(D$27<=12,$C$95*(D$27-0.5)/72,$C$97+$C$98*(D$27-12)) -> 861.75 | E101: =IF(E$27<=12,$C$95*(E$27-0.5)/72,$C$97+$C$98*(E$27-12)) -> 2585.25 | F101: =IF(F$27<=12,$C$95*(F$27-0.5)/72,$C$97+$C$98*(F$27-12)) -> 4308.75 | G101: =IF(G$27<=12,$C$95*(G$27-0.5)/72,$C$97+$C$98*(G$27-12)) -> 6032.25 | H101: =IF(H$27<=12,$C$95*(H$27-0.5)/72,$C$97+$C$98*(H$27-12)) -> 7755.75 | I101: =IF(I$27<=12,$C$95*(I$27-0.5)/72,$C$97+$C$98*(I$27-12)) -> 9479.25 | J101: =IF(J$27<=12,$C$95*(J$27-0.5)/72,$C$97+$C$98*(J$27-12)) -> 11202.75 | K101: =IF(K$27<=12,$C$95*(K$27-0.5)/72,$C$97+$C$98*(K$27-12)) -> 12926.25 | ... AA101: =IF(AA$27<=12,$C$95*(AA$27-0.5)/72,$C$97+$C$98*(AA$27-12)) -> 105125.02 | AB101: =SUM(D101:O101) -> 124092 | AC101: =SUM(P101:AA101) -> 792324 | AD101: =SUM(D101:U101) -> 392296.85
A102: Umsatz B2B/Pilot (Einmalzahlung) | D102: =IF(D$27=Annahmen!$B$9,$C$99,0)+IF(D$27=12+Annahmen!$B$9,$C$100,0) -> 0 | E102: =IF(E$27=Annahmen!$B$9,$C$99,0)+IF(E$27=12+Annahmen!$B$9,$C$100,0) -> 0 | F102: =IF(F$27=Annahmen!$B$9,$C$99,0)+IF(F$27=12+Annahmen!$B$9,$C$100,0) -> 0 | G102: =IF(G$27=Annahmen!$B$9,$C$99,0)+IF(G$27=12+Annahmen!$B$9,$C$100,0) -> 0 | H102: =IF(H$27=Annahmen!$B$9,$C$99,0)+IF(H$27=12+Annahmen!$B$9,$C$100,0) -> 0 | I102: =IF(I$27=Annahmen!$B$9,$C$99,0)+IF(I$27=12+Annahmen!$B$9,$C$100,0) -> 0 | J102: =IF(J$27=Annahmen!$B$9,$C$99,0)+IF(J$27=12+Annahmen!$B$9,$C$100,0) -> 0 | K102: =IF(K$27=Annahmen!$B$9,$C$99,0)+IF(K$27=12+Annahmen!$B$9,$C$100,0) -> 0 | ... AA102: =IF(AA$27=Annahmen!$B$9,$C$99,0)+IF(AA$27=12+Annahmen!$B$9,$C$100,0) -> 0 | AB102: =SUM(D102:O102) -> 0 | AC102: =SUM(P102:AA102) -> 100000 | AD102: =SUM(D102:U102) -> 0
A103: Umsatz gesamt | D103: =D101+D102 -> 861.75 | E103: =E101+E102 -> 2585.25 | F103: =F101+F102 -> 4308.75 | G103: =G101+G102 -> 6032.25 | H103: =H101+H102 -> 7755.75 | I103: =I101+I102 -> 9479.25 | J103: =J101+J102 -> 11202.75 | K103: =K101+K102 -> 12926.25 | ... AA103: =AA101+AA102 -> 105125.02 | AB103: =SUM(D103:O103) -> 124092 | AC103: =SUM(P103:AA103) -> 892324 | AD103: =SUM(D103:U103) -> 392296.85
A104: Kosten Pre-Seed-Team und -Budget | D104: =D$39 -> 13000 | E104: =E$39 -> 5000 | F104: =F$39 -> 10500 | G104: =G$39 -> 13625 | H104: =H$39 -> 13625 | I104: =I$39 -> 13625 | J104: =J$39 -> 14625 | K104: =K$39 -> 14625 | ... AA104: =AA$39 -> 0 | AB104: =SUM(D104:O104) -> 159125 | AC104: =SUM(P104:AA104) -> 78375 | AD104: =SUM(D104:U104) -> 237500
A105: Kosten Ausbau-Team (ab M19) | D105: =D$48*Annahmen!$E$47 -> 0 | E105: =E$48*Annahmen!$E$47 -> 0 | F105: =F$48*Annahmen!$E$47 -> 0 | G105: =G$48*Annahmen!$E$47 -> 0 | H105: =H$48*Annahmen!$E$47 -> 0 | I105: =I$48*Annahmen!$E$47 -> 0 | J105: =J$48*Annahmen!$E$47 -> 0 | K105: =K$48*Annahmen!$E$47 -> 0 | ... AA105: =AA$48*Annahmen!$E$47 -> 40611.39 | AB105: =SUM(D105:O105) -> 0 | AC105: =SUM(P105:AA105) -> 243668.34 | AD105: =SUM(D105:U105) -> 0
A106: Infrastruktur (fix + % vom Umsatz) | D106: =Annahmen!$B$7+Annahmen!$B$8*D103 -> 318.94 | E106: =Annahmen!$B$7+Annahmen!$B$8*E103 -> 456.82 | F106: =Annahmen!$B$7+Annahmen!$B$8*F103 -> 594.7 | G106: =Annahmen!$B$7+Annahmen!$B$8*G103 -> 732.58 | H106: =Annahmen!$B$7+Annahmen!$B$8*H103 -> 870.46 | I106: =Annahmen!$B$7+Annahmen!$B$8*I103 -> 1008.34 | J106: =Annahmen!$B$7+Annahmen!$B$8*J103 -> 1146.22 | K106: =Annahmen!$B$7+Annahmen!$B$8*K103 -> 1284.1 | ... AA106: =Annahmen!$B$7+Annahmen!$B$8*AA103 -> 8660.0015 | AB106: =SUM(D106:O106) -> 12927.36 | AC106: =SUM(P106:AA106) -> 74385.92 | AD106: =SUM(D106:U106) -> 35883.748
A107: Kosten gesamt | D107: =D104+D105+D106 -> 13318.94 | E107: =E104+E105+E106 -> 5456.82 | F107: =F104+F105+F106 -> 11094.7 | G107: =G104+G105+G106 -> 14357.58 | H107: =H104+H105+H106 -> 14495.46 | I107: =I104+I105+I106 -> 14633.34 | J107: =J104+J105+J106 -> 15771.22 | K107: =K104+K105+K106 -> 15909.1 | ... AA107: =AA104+AA105+AA106 -> 49271.392 | AB107: =SUM(D107:O107) -> 172052.36 | AC107: =SUM(P107:AA107) -> 396429.26 | AD107: =SUM(D107:U107) -> 273383.75
A108: Netto-Cashflow | D108: =D103-D107 -> -12457.19 | E108: =E103-E107 -> -2871.57 | F108: =F103-F107 -> -6785.95 | G108: =G103-G107 -> -8325.33 | H108: =H103-H107 -> -6739.71 | I108: =I103-I107 -> -5154.09 | J108: =J103-J107 -> -4568.47 | K108: =K103-K107 -> -2982.85 | ... AA108: =AA103-AA107 -> 55853.627 | AB108: =SUM(D108:O108) -> -47960.36 | AC108: =SUM(P108:AA108) -> 495894.74 | AD108: =SUM(D108:U108) -> 118913.1
A109: Kasse Monatsende | D109: =Annahmen!$B$6+D108 -> 237542.81 | E109: =D109+E108 -> 234671.24 | F109: =E109+F108 -> 227885.29 | G109: =F109+G108 -> 219559.96 | H109: =G109+H108 -> 212820.25 | I109: =H109+I108 -> 207666.16 | J109: =I109+J108 -> 203097.69 | K109: =J109+K108 -> 200114.84 | L109: =K109+L108 -> 196717.61 | ... AA109: =Z109+AA108 -> 697934.38
A110: Hilfszeile: Kasse < 0 (1 = ja) | D110: =IF(D109<0,1,0) -> 0 | E110: =IF(E109<0,1,0) -> 0 | F110: =IF(F109<0,1,0) -> 0 | G110: =IF(G109<0,1,0) -> 0 | H110: =IF(H109<0,1,0) -> 0 | I110: =IF(I109<0,1,0) -> 0 | J110: =IF(J109<0,1,0) -> 0 | K110: =IF(K109<0,1,0) -> 0 | ... AA110: =IF(AA109<0,1,0) -> 0
...

Sheet Gates 18M
A1: Gates / Meilensteine für 18 Monate – alle Werte sind ZIELE (Basis), Schwelle = konservativ
A2: Vorschlag – mit Investor:innen abstimmen. Nutzer/Pro-Ziele aus dem Modell: J1 linear auf den Jahresendwert, J2 linear zwischen den Jahresendwerten.
A4: Gate | B4: Monat | C4: Thema | D4: KPI | E4: Ziel Basis | F4: Schwelle (kons.) | G4: Optimistisch | H4: Status | I4: Gibt frei
A5: G0 | B5: 3 | C5: Start | D5: Pro-Abo live (Zahlung), Mobile-/Web-Entwickler:in an Bord | H5: Ziel (nicht erreicht) | I5: Budget Markteintritt Phase 2
A6: G1 | B6: 6 | C6: Aktivierung | D6: Registrierte Nutzer | E6: =Annahmen!$D$22*6/12 -> 10000 | F6: =Annahmen!$C$22*6/12 -> 4000 | G6: =Annahmen!$E$22*6/12 -> 20000 | H6: Ziel (nicht erreicht) | I6: Mobile-App/PWA-Release
A7: G1 | B7: 6 | C7: Aktivierung | D7: Zahlende Pro-Nutzer | E7: =Annahmen!$D$22*6/12*Annahmen!$D$27 -> 400 | F7: =Annahmen!$C$22*6/12*Annahmen!$C$27 -> 120 | G7: =Annahmen!$E$22*6/12*Annahmen!$E$27 -> 1000 | H7: Ziel (nicht erreicht)
A8: G1 | B8: 6 | C8: Aktivierung | D8: 20 Beta-Creator TR/DE aktiv, 10–20 Botschafter:innen; WortBild mit 300 Wörtern | H8: Ziel (nicht erreicht)
A9: G1 | B9: 6 | C9: Aktivierung | D9: Woche-4-Retention aktiver Streamer ≥ 30 % (Ziel, erste Kohorten) | H9: Ziel (nicht erreicht)
A10: G2a | B10: 12 | C10: Traktion | D10: Registrierte Nutzer | E10: =Annahmen!$D$22*12/12 -> 20000 | F10: =Annahmen!$C$22*12/12 -> 8000 | G10: =Annahmen!$E$22*12/12 -> 40000 | H10: Ziel (nicht erreicht) | I10: DE/EN-Ausbau, Plattform-Gespräche
A11: G2a | B11: 12 | C11: Traktion | D11: Zahlende Pro-Nutzer (Jahresende J1, BP §11.1) | E11: =Annahmen!$D$22*12/12*Annahmen!$D$27 -> 800 | F11: =Annahmen!$C$22*12/12*Annahmen!$C$27 -> 240 | G11: =Annahmen!$E$22*12/12*Annahmen!$E$27 -> 2000 | H11: Ziel (nicht erreicht)
A12: G2a | B12: 12 | C12: Traktion | D12: Wiederkehrender Umsatz im Monat 12 (MRR, €) | E12: =INDEX('Liquidität 24M'!$D$80:$AA$80,12) -> 8073 | F12: =INDEX('Liquidität 24M'!$D$59:$AA$59,12) -> 2499.7167 | G12: =INDEX('Liquidität 24M'!$D$101:$AA$101,12) -> 19820.25 | H12: Ziel (nicht erreicht)
A13: G2a | B13: 12 | C13: Traktion | D13: 1 Plattform- oder Bildungspilot gestartet; WortBild-Pilot in ≥ 3 Kursen/Klassen | H13: Ziel (nicht erreicht)
A14: G2 | B14: 18 | C14: Folgerunde | D14: Registrierte Nutzer | E14: =(Annahmen!$D$22+(Annahmen!$D$23-Annahmen!$D$22)*6/12) -> 50000 | F14: =(Annahmen!$C$22+(Annahmen!$C$23-Annahmen!$C$22)*6/12) -> 19000 | G14: =(Annahmen!$E$22+(Annahmen!$E$23-Annahmen!$E$22)*6/12) -> 110000 | H14: Ziel (nicht erreicht) | I14: Seed-Runde, Ausbau-Team ab M19, Story-Engine/Studio
A15: G2 | B15: 18 | C15: Folgerunde | D15: Zahlende Pro-Nutzer | E15: =(Annahmen!$D$22+(Annahmen!$D$23-Annahmen!$D$22)*6/12)*Annahmen!$D$27 -> 2000 | F15: =(Annahmen!$C$22+(Annahmen!$C$23-Annahmen!$C$22)*6/12)*Annahmen!$C$27 -> 570 | G15: =(Annahmen!$E$22+(Annahmen!$E$23-Annahmen!$E$22)*6/12)*Annahmen!$E$27 -> 5500 | H15: Ziel (nicht erreicht)
A16: G2 | B16: 18 | C16: Folgerunde | D16: Wiederkehrender Umsatz im Monat 18 (MRR, €) | E16: =INDEX('Liquidität 24M'!$D$80:$AA$80,18) -> 22585.615 | F16: =INDEX('Liquidität 24M'!$D$59:$AA$59,18) -> 6494.8244 | G16: =INDEX('Liquidität 24M'!$D$101:$AA$101,18) -> 62472.635 | H16: Ziel (nicht erreicht)
A17: G2 | B17: 18 | C17: Folgerunde | D17: Monat-3-Retention Pro ≥ 75 %; Conversion Free → Pro ≥ 3 % (Schwelle) / 4 % (Ziel) | H17: Ziel (nicht erreicht)
A18: G2 | B18: 18 | C18: Folgerunde | D18: WortBild-Pilot ausgewertet; ≥ 5 zahlende Schulen oder Kurse (BP §11.5) | H18: Ziel (nicht erreicht)
A20: Lesart: Gate erfüllt, wenn mindestens die Schwelle (konservatives Szenario) erreicht ist; das Ziel ist das Basis-Szenario.

Sheet Bewertung
A1: Bewertung Pre-Seed – Referenzmethoden (Investorensicht) und Angebot der Gründer (Vorschlag – mit Steuer-/Rechtsberater prüfen)
A2: Alle Eingaben blau; Quellen in Spalte G. „Gründer-Sicht“ = bewusst großzügig gerechnet, jede Annahme belegt und als Gründer-Annahme gekennzeichnet; „konservativ“ = frühere Investorensicht zum Vergleich. Keine Umsätze, Produkt v2.1.
A3: Teil A (1–5): Referenzmethoden (Investorensicht) – Berkus, Scorecard, VC-Methode, Risk Factor Summation. Teil B (6–10): Angebot der Gründer, Verhandlungsspanne, 10×-Prüfung, Begründung, Wandeldarlehen/SAFE. $→€ jeweils 1:1 (Annahme).
A5: 1. Referenzmethode (Investorensicht): Berkus – Gründer-Sicht und konservativ
A6: Max. € je Faktor – Gründer-Sicht (moderne „moderate 2×“-Variante) | B6: 1000000 | G6: Gründer-Annahme: moderne Berkus-Anpassung „moderat (2×)“ mit 0–1 Mio. $ je Faktor, max. 5 Mio. $ (valu.vc 2026; icanpitch 2026). Begründung: Berkus zuletzt 2016 aktualisiert, Seed-Bewertungen seitdem deutlich gestiegen.
A7: Max. € je Faktor – konservativ (klassisch, Dave Berkus) | B7: 500000 | G7: Original-Methode: bis 0,5 Mio. $ je Faktor, max. 2,5 Mio. $ (berkus.com).
A8: Faktor | B8: Score Gründer (0–1) | C8: Wert Gründer € | D8: Score konservativ | E8: Wert konservativ € | G8: Begründung (Gründer-Sicht · konservativ)
A9: Idee / Grundwert (Problem, Markt) | B9: 0.7 | C9: =Bewertung!$B$6*B9 -> 700000 | D9: 0.6 | E9: =Bewertung!$B$7*D9 -> 300000 | G9: Hoch: neuer Auslöser Stimme → Effekt, großer Markt (BP §6) · konservativ: Zahlungsbereitschaft unbewiesen.
A10: Prototyp / Produkt (Technologierisiko) | B10: 0.8 | C10: =Bewertung!$B$6*B10 -> 800000 | D10: 0.7 | E10: =Bewertung!$B$7*D10 -> 350000 | G10: Hoch: v2.1 funktionsfähig und getestet (575+ automatisierte Tests, e2e-Suite), 238 Trigger + 143 freie Sticker, Leistungsmodus, sichere GIF-Suche, im Einsatz in eigenen Streams · nicht 1,0: noch keine zahlenden Nutzer.
A11: Team (Umsetzungsqualität) | B11: 0.5 | C11: =Bewertung!$B$6*B11 -> 500000 | D11: 0.3 | E11: =Bewertung!$B$7*D11 -> 150000 | G11: Mittel: Gründer hat Produkt allein bis v2.1 gebaut + Investor Relations · konservativ: Solo-Gründer, Ein-Personen-Risiko (BP §13).
A12: Strategische Beziehungen | B12: 0.25 | C12: =Bewertung!$B$6*B12 -> 250000 | D12: 0.1 | E12: =Bewertung!$B$7*D12 -> 50000 | G12: Niedrig–mittel: eigene TR-Community, Gespräche mit Plattform-/Bildungspartnern geplant · keine Partnerschaft unterzeichnet.
A13: Produkteinführung / Umsatz | B13: 0.1 | C13: =Bewertung!$B$6*B13 -> 100000 | D13: 0.1 | E13: =Bewertung!$B$7*D13 -> 50000 | G13: Niedrig (beide Sichten): noch kein Umsatz; Pro-Abo ab Monat 3.
A14: Berkus-Wert (Pre-Money) | C14: =SUM(C9:C13) -> 2350000 | E14: =SUM(E9:E13) -> 900000
A16: 2. Referenzmethode (Investorensicht): Scorecard (Payne) – Gründer-Sicht und konservativ
A17: Referenz-Pre-Money Pre-Seed – Gründer-Sicht | B17: 2500000 | G17: Gründer-Annahme 2,5 Mio. €: im unteren Teil der DACH-Pre-Seed-Spanne 1,5–5 Mio. € (upxcale; Mitte wäre 3,25 Mio. €) und DE 1–5 Mio. € (capvisory; Mitte 3 Mio. €), deutlich unter dem Europa-Median 4,57 Mio. $ ≈ 4,2 Mio. € (Equidam Q1 2025).
A18: Referenz-Pre-Money Pre-Seed – konservativ (DACH/TR, Solo, pre-revenue) | B18: 1500000 | G18: DE Pre-Seed typ. 0,5–1,5 Mio. € (upxcale); Türkiye niedriger → 1,5 Mio. € (Schätzung, frühere Investorensicht).
A19: Faktor | B19: Gewicht | C19: Vergleich Gründer (100 % = Referenz) | D19: Beitrag Gründer | E19: Vergleich konservativ | F19: Beitrag konservativ | G19: Begründung (Gründer-Sicht · konservativ)
A20: Team | B20: 0.3 | C20: 1 | D20: =B20*C20 -> 0.3 | E20: 0.6 | F20: =B20*E20 -> 0.18 | G20: Durchschnitt: Produkt bis v2.1 allein gebaut, Streamer/Autor mit Community · konservativ: Solo, Hires offen
A21: Marktgröße / Chance | B21: 0.25 | C21: 1.4 | D21: =B21*C21 -> 0.35 | E21: 1.25 | F21: =B21*E21 -> 0.3125 | G21: Stark: Live-Streaming 97–157 Mrd. USD, SAM 1–3 Mio. Creator (BP §6) + Vision-Märkte A–D
A22: Produkt / Technologie | B22: 0.15 | C22: 1.4 | D22: =B22*C22 -> 0.21 | E22: 1.2 | F22: =B22*E22 -> 0.18 | G22: Stark: ausgeliefertes v2.1 mit 575+ Tests und e2e-Suite, lokale Verarbeitung, geringe Grenzkosten
A23: Wettbewerbsumfeld | B23: 0.1 | C23: 1.3 | D23: =B23*C23 -> 0.13 | E23: 0.9 | F23: =B23*E23 -> 0.09 | G23: Günstig: kein direkter Sprach-Trigger-Wettbewerber (Nische) · Risiko: Plattformen können nachbauen
A24: Marketing / Vertrieb / Partner | B24: 0.1 | C24: 0.8 | D24: =B24*C24 -> 0.08 | E24: 0.7 | F24: =B24*E24 -> 0.07 | G24: Unter Durchschnitt: eigene Streams + TR-Community, noch keine Partner/Vertrieb
A25: Bedarf weiterer Finanzierung | B25: 0.05 | C25: 1 | D25: =B25*C25 -> 0.05 | E25: 1 | F25: =B25*E25 -> 0.05 | G25: Neutral: schlanke Runde mit Gates; Folgerunde nötig (siehe Liquidität)
A26: Sonstiges (IP, Bildung, Datenschutz lokal) | B26: 0.05 | C26: 1.2 | D26: =B26*C26 -> 0.06 | E26: 1.1 | F26: =B26*E26 -> 0.055 | G26: Eigene Inhalte/IP, WortBild als zweites Standbein, offline-fähig
A27: Summe Gewichte / Faktor | B27: =SUM(B20:B26) -> 1 | D27: =SUM(D20:D26) -> 1.18 | F27: =SUM(F20:F26) -> 0.9375
A28: Scorecard-Wert (Pre-Money) | D28: =Bewertung!$B$17*D27 -> 2950000 | F28: =Bewertung!$B$18*F27 -> 1406250
A30: 3. Referenzmethode (Investorensicht): VC-Methode (Exit Jahr 5)
A31: Position | B31: Gründer: Optimistisch (Upside) | C31: Gründer: Basis (2. Linie) | D31: Konservativ: Basis | G31: Quelle / Kennzeichnung
A32: Umsatz J5 (aus GuV) | B32: ='GuV 5 Jahre'!$G$57 -> 7444105 | C32: ='GuV 5 Jahre'!$G$36 -> 3151812.5 | D32: ='GuV 5 Jahre'!$G$36 -> 3151812.5 | G32: GuV 5 Jahre, J5 (2031): optimistisches bzw. Basis-Szenario
A33: Exit-Multiple (Umsatz) | B33: 6 | C33: 6 | D33: 4 | G33: Gründer-Annahme 6,0x: SaaS Capital 2025 – VC-finanzierte private SaaS 5,3x (bootstrapped 4,8x) + Wachstumsaufschlag; konservativ 4,0x (B2C-/Creator-Abschlag, unter 2 Mio. USD ARR 2–3,5x).
A34: Exit-Wert Jahr 5 = Umsatz × Multiple | B34: =B32*B33 -> 44664630 | C34: =C32*C33 -> 18910875 | D34: =D32*D33 -> 12607250
A35: Ziel-Rendite (Multiple auf Einsatz) | B35: 10 | C35: 10 | D35: 15 | G35: Gründer-Annahme 10x = Untergrenze der Pre-Seed-üblichen 10–20x; konservativ Mittelwert 15x.
A36: Verwässerung durch spätere Runden (Seed, Series A, ESOP) | B36: 0.4 | C36: 0.4 | D36: 0.45 | G36: Carta 2025: Seed ≈ 20 %, Series A ≈ 18 % → 1 − 0,8 × 0,82 ≈ 34 %; Gründer-Annahme 40 % (ohne vollen ESOP), konservativ 45 % (inkl. ESOP ≈ 10 %).
A37: Post-Money heute = Exit ÷ Ziel-Rendite × (1 − Verwässerung) | B37: =B34/B35*(1-B36) -> 2679877.8 | C37: =C34/C35*(1-C36) -> 1134652.5 | D37: =D34/D35*(1-D36) -> 462265.83
A38: Investition (Pre-Seed) | B38: =Annahmen!$B$6 -> 250000 | C38: =Annahmen!$B$6 -> 250000 | D38: =Annahmen!$B$6 -> 250000
A39: VC-Wert (Pre-Money) = Post-Money − Investition | B39: =MAX(0,B37-B38) -> 2429877.8 | C39: =MAX(0,C37-C38) -> 884652.5 | D39: =MAX(0,D37-D38) -> 212265.83 | G39: Untergrenze 0
A41: VC-Methode (Umsatz J5 Basis, Verwässerung konservativ): Pre-Money bei Exit-Multiple (Zeilen) × Ziel-Rendite (Spalten)
A42: Multiple ↓ / Rendite → | B42: 10 | C42: 15 | D42: 20
A43: 3 | B43: =MAX(0,Bewertung!$D$32*$A43/B$42*(1-Bewertung!$D$36)-Bewertung!$D$38) -> 270049.06 | C43: =MAX(0,Bewertung!$D$32*$A43/C$42*(1-Bewertung!$D$36)-Bewertung!$D$38) -> 96699.375 | D43: =MAX(0,Bewertung!$D$32*$A43/D$42*(1-Bewertung!$D$36)-Bewertung!$D$38) -> 10024.531
A44: 4 | B44: =MAX(0,Bewertung!$D$32*$A44/B$42*(1-Bewertung!$D$36)-Bewertung!$D$38) -> 443398.75 | C44: =MAX(0,Bewertung!$D$32*$A44/C$42*(1-Bewertung!$D$36)-Bewertung!$D$38) -> 212265.83 | D44: =MAX(0,Bewertung!$D$32*$A44/D$42*(1-Bewertung!$D$36)-Bewertung!$D$38) -> 96699.375
A45: 5 | B45: =MAX(0,Bewertung!$D$32*$A45/B$42*(1-Bewertung!$D$36)-Bewertung!$D$38) -> 616748.44 | C45: =MAX(0,Bewertung!$D$32*$A45/C$42*(1-Bewertung!$D$36)-Bewertung!$D$38) -> 327832.29 | D45: =MAX(0,Bewertung!$D$32*$A45/D$42*(1-Bewertung!$D$36)-Bewertung!$D$38) -> 183374.22
A46: 6 | B46: =MAX(0,Bewertung!$D$32*$A46/B$42*(1-Bewertung!$D$36)-Bewertung!$D$38) -> 790098.12 | C46: =MAX(0,Bewertung!$D$32*$A46/C$42*(1-Bewertung!$D$36)-Bewertung!$D$38) -> 443398.75 | D46: =MAX(0,Bewertung!$D$32*$A46/D$42*(1-Bewertung!$D$36)-Bewertung!$D$38) -> 270049.06
A48: 4. Referenzmethode (Investorensicht): Risk Factor Summation – nur Gründer-Sicht
A49: Basiswert = Scorecard-Referenz Gründer-Sicht | B49: =Bewertung!$B$17 -> 2500000 | G49: Methode (Ohio TechAngels/Payne): 12 Risiken, je −2 … +2, je Stufe ± 250.000 $ auf den regionalen Vergleichswert (eqvista; rho.co).
A50: Betrag je Stufe (€) | B50: 250000
A51: Risikofaktor | B51: Score (−2 … +2) | C51: Zu-/Abschlag € | G51: Begründung (Gründer-Sicht)
A52: Management | B52: -1 | C52: =B52*Bewertung!$B$50 -> -250000 | G52: Solo-Gründer, erste Einstellung offen
A53: Entwicklungsstadium | B53: 1 | C53: =B53*Bewertung!$B$50 -> 250000 | G53: v2.1 ausgeliefert und in eigenen Streams im Einsatz; noch kein Umsatz
A54: Gesetzgebung / Politik | B54: 0 | C54: =B54*Bewertung!$B$50 -> 0 | G54: DSGVO/DSFA, Jugendschutz budgetiert; lokale Verarbeitung
A55: Herstellung / Lieferkette | B55: 1 | C55: =B55*Bewertung!$B$50 -> 250000 | G55: reine Software, keine Lieferkette
A56: Vertrieb / Marketing | B56: -1 | C56: =B56*Bewertung!$B$50 -> -250000 | G56: noch kein Vertrieb, keine Partner
A57: Kapitalbeschaffung | B57: -1 | C57: =B57*Bewertung!$B$50 -> -250000 | G57: Folgerunde (Seed) nötig – siehe Liquidität
A58: Wettbewerb | B58: 1 | C58: =B58*Bewertung!$B$50 -> 250000 | G58: kein direkter Sprach-Trigger-Wettbewerber; Nachbau durch Plattformen möglich
A59: Technologie | B59: 1 | C59: =B59*Bewertung!$B$50 -> 250000 | G59: funktionsfähig, 575+ Tests + e2e; Streaming-ASR < 300 ms noch offen
A60: Rechtsstreit | B60: 0 | C60: =B60*Bewertung!$B$50 -> 0 | G60: GIF über KLIPY/GIPHY-API; Marke noch nicht eingetragen
A61: International | B61: 1 | C61: =B61*Bewertung!$B$50 -> 250000 | G61: DE/TR/EN von Beginn an, türkische Nische
A62: Reputation | B62: 0 | C62: =B62*Bewertung!$B$50 -> 0 | G62: neutral
A63: Exit-Potenzial | B63: 0 | C63: =B63*Bewertung!$B$50 -> 0 | G63: strategische Käufer denkbar, aber unbelegt → neutral
A64: Summe Scores / Zu-/Abschlag | B64: =SUM(B52:B63) -> 2 | C64: =SUM(C52:C63) -> 500000
A65: Risk-Factor-Summation-Wert (Pre-Money) | C65: =Bewertung!$B$49+Bewertung!$C$64 -> 3000000
A67: 5. Referenzmethoden (Investorensicht) – Zusammenfassung
A68: Methode | B68: Gründer-Sicht € | C68: Gewicht | D68: Konservativ € | E68: Gewicht | G68: Lesart
A69: Berkus | B69: =Bewertung!$C$14 -> 2350000 | C69: 0.25 | D69: =Bewertung!$E$14 -> 900000 | E69: 0.4 | G69: Gründer: 2×-Variante; konservativ: klassisch
A70: Scorecard | B70: =Bewertung!$D$28 -> 2950000 | C70: 0.3 | D70: =Bewertung!$F$28 -> 1406250 | E70: 0.4 | G70: Marktvergleich; Gründer-Referenz 2,5 Mio. €, konservativ 1,5 Mio. €
A71: VC-Methode | B71: =Bewertung!$B$39 -> 2429877.8 | C71: 0.2 | D71: =Bewertung!$D$39 -> 212265.83 | E71: 0.2 | G71: Gründer: optimistisches Szenario (Upside), Basis-Linie siehe unten; konservativ: Basis
A72: Risk Factor Summation | B72: =Bewertung!$C$65 -> 3000000 | C72: 0.25 | D72: 0 | E72: 0 | G72: nur Gründer-Sicht (konservative Sicht nutzte drei Methoden)
A73: Spanne (Minimum) | B73: =MIN(B69:B72) -> 2350000 | D73: =MIN(D69:D71) -> 212265.83
A74: Spanne (Maximum) | B74: =MAX(B69:B72) -> 3000000 | D74: =MAX(D69:D71) -> 1406250
A75: Gewichteter Mittelwert | B75: =SUMPRODUCT(B69:B72,C69:C72)/SUM(C69:C72) -> 2708475.6 | D75: =SUMPRODUCT(D69:D72,E69:E72)/SUM(E69:E72) -> 964953.17
A76: Gewichteter Mittelwert Gründer-Sicht mit VC-Basis-Linie statt optimistisch | B76: =Bewertung!$B$75+C71*(Bewertung!$C$39-Bewertung!$B$39)/SUM(C69:C72) -> 2399430.5 | G76: Zeigt, wie stark der Gründer-Mittelwert am optimistischen Szenario hängt.
A77: Konservativ: gewichteter Mittelwert auf 50 T€ gerundet (frühere Empfehlung, nur Referenz) | D77: =ROUND(Bewertung!$D$75/50000,0)*50000 -> 950000
A78: Kontrolle: Gewichte je Sicht = 100 % | B78: =IF(AND(ROUND(SUM(C69:C72),4)=1,ROUND(SUM(E69:E72),4)=1),"OK","PRÜFEN") -> OK
A80: 6. Angebot der Gründer – max. 10 % für 250.000 €
A81: Investition (Pre-Seed) | B81: =Annahmen!$B$6 -> 250000
A82: Angebotener Anteil Investor:innen | B82: 0.1 | G82: Vorgabe der Gründer: höchstens 10 % für 250.000 €.
A83: Post-Money = Investition ÷ Anteil | B83: =Annahmen!$B$6/Bewertung!$B$82 -> 2500000
A84: Pre-Money = Post-Money − Investition | B84: =Bewertung!$B$83-Annahmen!$B$6 -> 2250000
A85: Anteil Gründer nach der Runde (ohne ESOP) | B85: =1-Bewertung!$B$82 -> 0.9
A86: Kontrolle: Post-Money × Anteil = Investition | B86: =IF(ROUND(Bewertung!$B$83*Bewertung!$B$82-Annahmen!$B$6,2)=0,"OK","PRÜFEN") -> OK
A88: Abstand zu den Referenzmethoden (transparent)
A89: Angebot Pre-Money ÷ gewichteter Mittelwert Gründer-Sicht | B89: =Bewertung!$B$84/Bewertung!$B$75 -> 0.83072561
A90: Angebot Pre-Money − gewichteter Mittelwert Gründer-Sicht (€) | B90: =Bewertung!$B$84-Bewertung!$B$75 -> -458475.56
A91: Angebot Pre-Money ÷ Gründer-Mittelwert mit VC-Basis-Linie | B91: =Bewertung!$B$84/Bewertung!$B$76 -> 0.93772251
A92: Angebot Pre-Money ÷ Minimum der Gründer-Spanne | B92: =Bewertung!$B$84/Bewertung!$B$73 -> 0.95744681
A93: Angebot Pre-Money ÷ gewichteter Mittelwert konservativ | B93: =Bewertung!$B$84/Bewertung!$D$75 -> 2.3317194
A94: Einordnung ggü. Gründer-Spanne (Formel) | B94: =IF(Bewertung!$B$84<Bewertung!$B$73,"unterhalb der Gründer-Spanne – unter allen vier Methoden",IF(Bewertung!$B$84<=Bewertung!$B$75,"innerhalb der Gründer-Spanne, unter dem gewichteten Mittel",IF(Bewertung!$B$84<=Bewertung!$B$74,"innerhalb der Gründer-Spanne, über dem gewichteten Mittel","oberhalb der Gründer-Spanne"))) -> unterhalb der Gründer-Spanne – unter allen vier Methoden
A95: Einordnung ggü. konservativer Investorensicht (Formel) | B95: =IF(Bewertung!$B$84>Bewertung!$D$74,"oberhalb aller konservativen Methoden",IF(Bewertung!$B$84>=Bewertung!$D$75,"über dem konservativen Mittel","unter dem konservativen Mittel")) -> oberhalb aller konservativen Methoden
A96: Lesart: Gegenüber der großzügigen, belegten Gründer-Sicht ist das Angebot zurückhaltend; gegenüber der konservativen Investorensicht ist es ambitioniert – Verhandlungsgrundlage sind die Argumente in Abschnitt 9.
A98: 7. Verhandlungsspanne – Anteil Investor:innen → Bewertung
A99: Anteil Investor:innen | B99: Post-Money € | C99: Pre-Money € | D99: Anteil Gründer | E99: Pre ÷ Gründer-Mittel | F99: Pre ÷ konservatives Mittel | G99: Lesart
A100: 0.08 | B100: =Annahmen!$B$6/A100 -> 3125000 | C100: =B100-Annahmen!$B$6 -> 2875000 | D100: =1-A100 -> 0.92 | E100: =C100/Bewertung!$B$75 -> 1.0614827 | F100: =C100/Bewertung!$D$75 -> 2.9794192 | G100: höhere Bewertung als das Angebot (Gründer-freundlich)
A101: 0.1 | B101: =Annahmen!$B$6/A101 -> 2500000 | C101: =B101-Annahmen!$B$6 -> 2250000 | D101: =1-A101 -> 0.9 | E101: =C101/Bewertung!$B$75 -> 0.83072561 | F101: =C101/Bewertung!$D$75 -> 2.3317194 | G101: Angebot der Gründer (Obergrenze laut Gründer)
A102: 0.125 | B102: =Annahmen!$B$6/A102 -> 2000000 | C102: =B102-Annahmen!$B$6 -> 1750000 | D102: =1-A102 -> 0.875 | E102: =C102/Bewertung!$B$75 -> 0.64611992 | F102: =C102/Bewertung!$D$75 -> 1.8135595 | G102: Verhandlungskorridor bis hier: 10–12,5 % → Pre-Money 1,75–2,25 Mio. €
A103: 0.15 | B103: =Annahmen!$B$6/A103 -> 1666666.7 | C103: =B103-Annahmen!$B$6 -> 1416666.7 | D103: =1-A103 -> 0.85 | E103: =C103/Bewertung!$B$75 -> 0.52304946 | F103: =C103/Bewertung!$D$75 -> 1.4681196 | G103: außerhalb der Gründer-Vorgabe (nur Vergleich)
A105: 8. Was müsste für 10× Investor-Rendite gelten? (Prüfung des Angebots)
A106: Post-Money (Angebot der Gründer) | B106: =Bewertung!$B$83 -> 2500000
A107: Verwässerung durch spätere Runden (Prüfannahme, Investorensicht) | B107: 0.45 | G107: Bewusst die konservative Annahme (Carta + ESOP); mit Gründer-Annahme 40 % siehe Spalte E der Szenario-Tabelle.
A108: Exit-Multiples auf den Umsatz J5 (Prüfwerte) | B108: 4 | C108: 6 | G108: 4x = konservativ (B2C-Abschlag), 6x = Gründer-Annahme (SaaS Capital 5,3x + Wachstumsaufschlag).
A109: Ziel-Rendite | B109: Nötiger Exit-Wert J5 € | C109: Nötiger Umsatz J5 bei 4x € | D109: Nötiger Umsatz J5 bei 6x € | E109: Getragen ab Szenario (4x) | F109: Getragen ab Szenario (6x) | G109: Formel
A110: 5 | B110: =Bewertung!$B$106*A110/(1-Bewertung!$B$107) -> 22727273 | C110: =B110/Bewertung!$B$108 -> 5681818.2 | D110: =B110/Bewertung!$C$108 -> 3787878.8 | E110: =IF('GuV 5 Jahre'!$G$15>=C110,"Konservativ",IF('GuV 5 Jahre'!$G$36>=C110,"Basis",IF('GuV 5 Jahre'!$G$57>=C110,"Optimistisch","keines"))) -> Optimistisch | F110: =IF('GuV 5 Jahre'!$G$15>=D110,"Konservativ",IF('GuV 5 Jahre'!$G$36>=D110,"Basis",IF('GuV 5 Jahre'!$G$57>=D110,"Optimistisch","keines"))) -> Optimistisch | G110: Exit = Post-Money × Ziel-Rendite ÷ (1 − Verwässerung); Umsatz = Exit ÷ Multiple; Szenario = niedrigstes, dessen Umsatz J5 reicht
...

Sheet Sensitivität
A1: Sensitivität (Basis-Szenario): Umsatz J3 und Runway
A2: Conversion ±1 Pkt., ARPU ±20 %, Nutzer ±30 % – je Fall alle Jahre; Kosten wie Basis (Infrastruktur variabel mit Umsatz).
A4: Fall | B4: Δ Conversion | C4: ARPU-Faktor | D4: Nutzer-Faktor | E4: Umsatz J3 € | F4: Δ zu Basis | G4: Wiederk. J1 € | H4: Wiederk. J2 € | I4: s (Dez J1) | J4: g (Zuwachs J2) | K4: Runway (Monate) | L4: Cash-out-Monat | M4: Kasse M12 € | N4: Kasse M18 € | O4: Kasse M24 € | P4: Min. Kasse €
A5: Basis | B5: 0 | C5: 1 | D5: 1 | E5: =('GuV 5 Jahre'!$E$27*$D5)*('GuV 5 Jahre'!$E$28+$B5)*Annahmen!$B$13*Annahmen!$D$30*$C5*12+('GuV 5 Jahre'!$E$27*$D5)*Annahmen!$D$31*Annahmen!$B$10+'GuV 5 Jahre'!$E$33+'GuV 5 Jahre'!$E$35 -> 1038270 | F5: =E5/$E$5-1 -> 0 | G5: =('GuV 5 Jahre'!$C$27*$D5)*('GuV 5 Jahre'!$C$28+$B5)*Annahmen!$B$12*Annahmen!$D$30*$C5*12+('GuV 5 Jahre'!$C$27*$D5)*Annahmen!$D$31*Annahmen!$B$10+'GuV 5 Jahre'!$C$33 -> 50544 | H5: =('GuV 5 Jahre'!$D$27*$D5)*('GuV 5 Jahre'!$D$28+$B5)*Annahmen!$B$13*Annahmen!$D$30*$C5*12+('GuV 5 Jahre'!$D$27*$D5)*Annahmen!$D$31*Annahmen!$B$10+'GuV 5 Jahre'!$D$33 -> 285540 | I5: =G5*11.5/72 -> 8073 | J5: =(H5-12*I5)/78 -> 2418.7692 | K5: =IFERROR(MATCH(1,$E$18:$AB$18,0)-1,"> 24") -> > 24 | L5: =IFERROR(MATCH(1,$E$18:$AB$18,0),"keiner") -> keiner | M5: =INDEX($E$17:$AB$17,12) -> 134375.48 | N5: =INDEX($E$17:$AB$17,18) -> 145794.06 | O5: =INDEX($E$17:$AB$17,24) -> 175197.28 | P5: =MIN($E$17:$AB$17) -> 125383.57
A6: Conversion −1 Pkt. | B6: -0.01 | C6: 1 | D6: 1 | E6: =('GuV 5 Jahre'!$E$27*$D6)*('GuV 5 Jahre'!$E$28+$B6)*Annahmen!$B$13*Annahmen!$D$30*$C6*12+('GuV 5 Jahre'!$E$27*$D6)*Annahmen!$D$31*Annahmen!$B$10+'GuV 5 Jahre'!$E$33+'GuV 5 Jahre'!$E$35 -> 847020 | F6: =E6/$E$5-1 -> -0.18420064 | G6: =('GuV 5 Jahre'!$C$27*$D6)*('GuV 5 Jahre'!$C$28+$B6)*Annahmen!$B$12*Annahmen!$D$30*$C6*12+('GuV 5 Jahre'!$C$27*$D6)*Annahmen!$D$31*Annahmen!$B$10+'GuV 5 Jahre'!$C$33 -> 40344 | H6: =('GuV 5 Jahre'!$D$27*$D6)*('GuV 5 Jahre'!$D$28+$B6)*Annahmen!$B$13*Annahmen!$D$30*$C6*12+('GuV 5 Jahre'!$D$27*$D6)*Annahmen!$D$31*Annahmen!$B$10+'GuV 5 Jahre'!$D$33 -> 224340 | I6: =G6*11.5/72 -> 6443.8333 | J6: =(H6-12*I6)/78 -> 1884.7949 | K6: =IFERROR(MATCH(1,$E$22:$AB$22,0)-1,"> 24") -> > 24 | L6: =IFERROR(MATCH(1,$E$22:$AB$22,0),"keiner") -> keiner | M6: =INDEX($E$21:$AB$21,12) -> 124991.48 | N6: =INDEX($E$21:$AB$21,18) -> 117100.68 | O6: =INDEX($E$21:$AB$21,24) -> 109509.28 | P6: =MIN($E$21:$AB$21) -> 82501.928
A7: Conversion +1 Pkt. | B7: 0.01 | C7: 1 | D7: 1 | E7: =('GuV 5 Jahre'!$E$27*$D7)*('GuV 5 Jahre'!$E$28+$B7)*Annahmen!$B$13*Annahmen!$D$30*$C7*12+('GuV 5 Jahre'!$E$27*$D7)*Annahmen!$D$31*Annahmen!$B$10+'GuV 5 Jahre'!$E$33+'GuV 5 Jahre'!$E$35 -> 1229520 | F7: =E7/$E$5-1 -> 0.18420064 | G7: =('GuV 5 Jahre'!$C$27*$D7)*('GuV 5 Jahre'!$C$28+$B7)*Annahmen!$B$12*Annahmen!$D$30*$C7*12+('GuV 5 Jahre'!$C$27*$D7)*Annahmen!$D$31*Annahmen!$B$10+'GuV 5 Jahre'!$C$33 -> 60744 | H7: =('GuV 5 Jahre'!$D$27*$D7)*('GuV 5 Jahre'!$D$28+$B7)*Annahmen!$B$13*Annahmen!$D$30*$C7*12+('GuV 5 Jahre'!$D$27*$D7)*Annahmen!$D$31*Annahmen!$B$10+'GuV 5 Jahre'!$D$33 -> 346740 | I7: =G7*11.5/72 -> 9702.1667 | J7: =(H7-12*I7)/78 -> 2952.7436 | K7: =IFERROR(MATCH(1,$E$26:$AB$26,0)-1,"> 24") -> > 24 | L7: =IFERROR(MATCH(1,$E$26:$AB$26,0),"keiner") -> keiner | M7: =INDEX($E$25:$AB$25,12) -> 143759.48 | N7: =INDEX($E$25:$AB$25,18) -> 174487.45 | O7: =INDEX($E$25:$AB$25,24) -> 240885.28 | P7: =MIN($E$25:$AB$25) -> 140011.04
A8: ARPU −20 % | B8: 0 | C8: 0.8 | D8: 1 | E8: =('GuV 5 Jahre'!$E$27*$D8)*('GuV 5 Jahre'!$E$28+$B8)*Annahmen!$B$13*Annahmen!$D$30*$C8*12+('GuV 5 Jahre'!$E$27*$D8)*Annahmen!$D$31*Annahmen!$B$10+'GuV 5 Jahre'!$E$33+'GuV 5 Jahre'!$E$35 -> 885270 | F8: =E8/$E$5-1 -> -0.14736051 | G8: =('GuV 5 Jahre'!$C$27*$D8)*('GuV 5 Jahre'!$C$28+$B8)*Annahmen!$B$12*Annahmen!$D$30*$C8*12+('GuV 5 Jahre'!$C$27*$D8)*Annahmen!$D$31*Annahmen!$B$10+'GuV 5 Jahre'!$C$33 -> 42384 | H8: =('GuV 5 Jahre'!$D$27*$D8)*('GuV 5 Jahre'!$D$28+$B8)*Annahmen!$B$13*Annahmen!$D$30*$C8*12+('GuV 5 Jahre'!$D$27*$D8)*Annahmen!$D$31*Annahmen!$B$10+'GuV 5 Jahre'!$D$33 -> 236580 | I8: =G8*11.5/72 -> 6769.6667 | J8: =(H8-12*I8)/78 -> 1991.5897 | K8: =IFERROR(MATCH(1,$E$30:$AB$30,0)-1,"> 24") -> > 24 | L8: =IFERROR(MATCH(1,$E$30:$AB$30,0),"keiner") -> keiner | M8: =INDEX($E$29:$AB$29,12) -> 126868.28 | N8: =INDEX($E$29:$AB$29,18) -> 122839.35 | O8: =INDEX($E$29:$AB$29,24) -> 122646.88 | P8: =MIN($E$29:$AB$29) -> 91497.935
A9: ARPU +20 % | B9: 0 | C9: 1.2 | D9: 1 | E9: =('GuV 5 Jahre'!$E$27*$D9)*('GuV 5 Jahre'!$E$28+$B9)*Annahmen!$B$13*Annahmen!$D$30*$C9*12+('GuV 5 Jahre'!$E$27*$D9)*Annahmen!$D$31*Annahmen!$B$10+'GuV 5 Jahre'!$E$33+'GuV 5 Jahre'!$E$35 -> 1191270 | F9: =E9/$E$5-1 -> 0.14736051 | G9: =('GuV 5 Jahre'!$C$27*$D9)*('GuV 5 Jahre'!$C$28+$B9)*Annahmen!$B$12*Annahmen!$D$30*$C9*12+('GuV 5 Jahre'!$C$27*$D9)*Annahmen!$D$31*Annahmen!$B$10+'GuV 5 Jahre'!$C$33 -> 58704 | H9: =('GuV 5 Jahre'!$D$27*$D9)*('GuV 5 Jahre'!$D$28+$B9)*Annahmen!$B$13*Annahmen!$D$30*$C9*12+('GuV 5 Jahre'!$D$27*$D9)*Annahmen!$D$31*Annahmen!$B$10+'GuV 5 Jahre'!$D$33 -> 334500 | I9: =G9*11.5/72 -> 9376.3333 | J9: =(H9-12*I9)/78 -> 2845.9487 | K9: =IFERROR(MATCH(1,$E$34:$AB$34,0)-1,"> 24") -> > 24 | L9: =IFERROR(MATCH(1,$E$34:$AB$34,0),"keiner") -> keiner | M9: =INDEX($E$33:$AB$33,12) -> 141882.68 | N9: =INDEX($E$33:$AB$33,18) -> 168748.77 | O9: =INDEX($E$33:$AB$33,24) -> 227747.68 | P9: =MIN($E$33:$AB$33) -> 137239.95
A10: Nutzer −30 % | B10: 0 | C10: 1 | D10: 0.7 | E10: =('GuV 5 Jahre'!$E$27*$D10)*('GuV 5 Jahre'!$E$28+$B10)*Annahmen!$B$13*Annahmen!$D$30*$C10*12+('GuV 5 Jahre'!$E$27*$D10)*Annahmen!$D$31*Annahmen!$B$10+'GuV 5 Jahre'!$E$33+'GuV 5 Jahre'!$E$35 -> 778845 | F10: =E10/$E$5-1 -> -0.24986275 | G10: =('GuV 5 Jahre'!$C$27*$D10)*('GuV 5 Jahre'!$C$28+$B10)*Annahmen!$B$12*Annahmen!$D$30*$C10*12+('GuV 5 Jahre'!$C$27*$D10)*Annahmen!$D$31*Annahmen!$B$10+'GuV 5 Jahre'!$C$33 -> 35910 | H10: =('GuV 5 Jahre'!$D$27*$D10)*('GuV 5 Jahre'!$D$28+$B10)*Annahmen!$B$13*Annahmen!$D$30*$C10*12+('GuV 5 Jahre'!$D$27*$D10)*Annahmen!$D$31*Annahmen!$B$10+'GuV 5 Jahre'!$D$33 -> 202524 | I10: =G10*11.5/72 -> 5735.625 | J10: =(H10-12*I10)/78 -> 1714.0577 | K10: =IFERROR(MATCH(1,$E$38:$AB$38,0)-1,"> 24") -> > 24 | L10: =IFERROR(MATCH(1,$E$38:$AB$38,0),"keiner") -> keiner | M10: =INDEX($E$37:$AB$37,12) -> 120912.2 | N10: =INDEX($E$37:$AB$37,18) -> 105813.44 | O10: =INDEX($E$37:$AB$37,24) -> 85359.28 | P10: =MIN($E$37:$AB$37) -> 65490.163
A11: Nutzer +30 % | B11: 0 | C11: 1 | D11: 1.3 | E11: =('GuV 5 Jahre'!$E$27*$D11)*('GuV 5 Jahre'!$E$28+$B11)*Annahmen!$B$13*Annahmen!$D$30*$C11*12+('GuV 5 Jahre'!$E$27*$D11)*Annahmen!$D$31*Annahmen!$B$10+'GuV 5 Jahre'!$E$33+'GuV 5 Jahre'!$E$35 -> 1297695 | F11: =E11/$E$5-1 -> 0.24986275 | G11: =('GuV 5 Jahre'!$C$27*$D11)*('GuV 5 Jahre'!$C$28+$B11)*Annahmen!$B$12*Annahmen!$D$30*$C11*12+('GuV 5 Jahre'!$C$27*$D11)*Annahmen!$D$31*Annahmen!$B$10+'GuV 5 Jahre'!$C$33 -> 65178 | H11: =('GuV 5 Jahre'!$D$27*$D11)*('GuV 5 Jahre'!$D$28+$B11)*Annahmen!$B$13*Annahmen!$D$30*$C11*12+('GuV 5 Jahre'!$D$27*$D11)*Annahmen!$D$31*Annahmen!$B$10+'GuV 5 Jahre'!$D$33 -> 368556 | I11: =G11*11.5/72 -> 10410.375 | J11: =(H11-12*I11)/78 -> 3123.4808 | K11: =IFERROR(MATCH(1,$E$42:$AB$42,0)-1,"> 24") -> > 24 | L11: =IFERROR(MATCH(1,$E$42:$AB$42,0),"keiner") -> keiner | M11: =INDEX($E$41:$AB$41,12) -> 147838.76 | N11: =INDEX($E$41:$AB$41,18) -> 185774.68 | O11: =INDEX($E$41:$AB$41,24) -> 265035.28 | P11: =MIN($E$41:$AB$41) -> 145414.91
A13: Monat | E13: 1 | F13: 2 | G13: 3 | H13: 4 | I13: 5 | J13: 6 | K13: 7 | L13: 8 | M13: 9 | N13: 10 | O13: 11 | P13: 12 | Q13: 13 | R13: 14 | S13: 15 | T13: 16 | U13: 17 | V13: 18 | W13: 19 | X13: 20 | Y13: 21 | Z13: 22 | AA13: 23 | AB13: 24
A14: Fixkosten Basis (Pre-Seed + Ausbau + Infrastruktur fix) | E14: ='Liquidität 24M'!D$39+'Liquidität 24M'!D$48*Annahmen!$D$47+Annahmen!$B$7 -> 13250 | F14: ='Liquidität 24M'!E$39+'Liquidität 24M'!E$48*Annahmen!$D$47+Annahmen!$B$7 -> 5250 | G14: ='Liquidität 24M'!F$39+'Liquidität 24M'!F$48*Annahmen!$D$47+Annahmen!$B$7 -> 10750 | H14: ='Liquidität 24M'!G$39+'Liquidität 24M'!G$48*Annahmen!$D$47+Annahmen!$B$7 -> 13875 | I14: ='Liquidität 24M'!H$39+'Liquidität 24M'!H$48*Annahmen!$D$47+Annahmen!$B$7 -> 13875 | J14: ='Liquidität 24M'!I$39+'Liquidität 24M'!I$48*Annahmen!$D$47+Annahmen!$B$7 -> 13875 | K14: ='Liquidität 24M'!J$39+'Liquidität 24M'!J$48*Annahmen!$D$47+Annahmen!$B$7 -> 14875 | L14: ='Liquidität 24M'!K$39+'Liquidität 24M'!K$48*Annahmen!$D$47+Annahmen!$B$7 -> 14875 | ... AB14: ='Liquidität 24M'!AA$39+'Liquidität 24M'!AA$48*Annahmen!$D$47+Annahmen!$B$7 -> 31333.333
A16: Basis: Umsatz | E16: =IF(E$13<=12,$G$5*(E$13-0.5)/72,$I$5+$J$5*(E$13-12))+IF(E$13=12+Annahmen!$B$9,'GuV 5 Jahre'!$D$35,0)+IF(E$13=Annahmen!$B$9,'GuV 5 Jahre'!$C$35,0) -> 351 | F16: =IF(F$13<=12,$G$5*(F$13-0.5)/72,$I$5+$J$5*(F$13-12))+IF(F$13=12+Annahmen!$B$9,'GuV 5 Jahre'!$D$35,0)+IF(F$13=Annahmen!$B$9,'GuV 5 Jahre'!$C$35,0) -> 1053 | G16: =IF(G$13<=12,$G$5*(G$13-0.5)/72,$I$5+$J$5*(G$13-12))+IF(G$13=12+Annahmen!$B$9,'GuV 5 Jahre'!$D$35,0)+IF(G$13=Annahmen!$B$9,'GuV 5 Jahre'!$C$35,0) -> 1755 | H16: =IF(H$13<=12,$G$5*(H$13-0.5)/72,$I$5+$J$5*(H$13-12))+IF(H$13=12+Annahmen!$B$9,'GuV 5 Jahre'!$D$35,0)+IF(H$13=Annahmen!$B$9,'GuV 5 Jahre'!$C$35,0) -> 2457 | I16: =IF(I$13<=12,$G$5*(I$13-0.5)/72,$I$5+$J$5*(I$13-12))+IF(I$13=12+Annahmen!$B$9,'GuV 5 Jahre'!$D$35,0)+IF(I$13=Annahmen!$B$9,'GuV 5 Jahre'!$C$35,0) -> 3159 | J16: =IF(J$13<=12,$G$5*(J$13-0.5)/72,$I$5+$J$5*(J$13-12))+IF(J$13=12+Annahmen!$B$9,'GuV 5 Jahre'!$D$35,0)+IF(J$13=Annahmen!$B$9,'GuV 5 Jahre'!$C$35,0) -> 3861 | K16: =IF(K$13<=12,$G$5*(K$13-0.5)/72,$I$5+$J$5*(K$13-12))+IF(K$13=12+Annahmen!$B$9,'GuV 5 Jahre'!$D$35,0)+IF(K$13=Annahmen!$B$9,'GuV 5 Jahre'!$C$35,0) -> 4563 | L16: =IF(L$13<=12,$G$5*(L$13-0.5)/72,$I$5+$J$5*(L$13-12))+IF(L$13=12+Annahmen!$B$9,'GuV 5 Jahre'!$D$35,0)+IF(L$13=Annahmen!$B$9,'GuV 5 Jahre'!$C$35,0) -> 5265 | ... AB16: =IF(AB$13<=12,$G$5*(AB$13-0.5)/72,$I$5+$J$5*(AB$13-12))+IF(AB$13=12+Annahmen!$B$9,'GuV 5 Jahre'!$D$35,0)+IF(AB$13=Annahmen!$B$9,'GuV 5 Jahre'!$C$35,0) -> 37098.231
A17: Basis: Kasse | E17: =Annahmen!$B$6+E16*(1-Annahmen!$B$8)-E$14 -> 237072.92 | F17: =E17+F16*(1-Annahmen!$B$8)-F$14 -> 232791.68 | G17: =F17+G16*(1-Annahmen!$B$8)-G$14 -> 223656.28 | H17: =G17+H16*(1-Annahmen!$B$8)-H$14 -> 212041.72 | I17: =H17+I16*(1-Annahmen!$B$8)-I$14 -> 201073 | J17: =I17+J16*(1-Annahmen!$B$8)-J$14 -> 190750.12 | K17: =J17+K16*(1-Annahmen!$B$8)-K$14 -> 180073.08 | L17: =K17+L16*(1-Annahmen!$B$8)-L$14 -> 170041.88 | M17: =L17+M16*(1-Annahmen!$B$8)-M$14 -> 158656.52 | ... AB17: =AA17+AB16*(1-Annahmen!$B$8)-AB$14 -> 175197.28
A18: Basis: Kasse < 0 | E18: =IF(E17<0,1,0) -> 0 | F18: =IF(F17<0,1,0) -> 0 | G18: =IF(G17<0,1,0) -> 0 | H18: =IF(H17<0,1,0) -> 0 | I18: =IF(I17<0,1,0) -> 0 | J18: =IF(J17<0,1,0) -> 0 | K18: =IF(K17<0,1,0) -> 0 | L18: =IF(L17<0,1,0) -> 0 | ... AB18: =IF(AB17<0,1,0) -> 0
A20: Conversion −1 Pkt.: Umsatz | E20: =IF(E$13<=12,$G$6*(E$13-0.5)/72,$I$6+$J$6*(E$13-12))+IF(E$13=12+Annahmen!$B$9,'GuV 5 Jahre'!$D$35,0)+IF(E$13=Annahmen!$B$9,'GuV 5 Jahre'!$C$35,0) -> 280.16667 | F20: =IF(F$13<=12,$G$6*(F$13-0.5)/72,$I$6+$J$6*(F$13-12))+IF(F$13=12+Annahmen!$B$9,'GuV 5 Jahre'!$D$35,0)+IF(F$13=Annahmen!$B$9,'GuV 5 Jahre'!$C$35,0) -> 840.5 | G20: =IF(G$13<=12,$G$6*(G$13-0.5)/72,$I$6+$J$6*(G$13-12))+IF(G$13=12+Annahmen!$B$9,'GuV 5 Jahre'!$D$35,0)+IF(G$13=Annahmen!$B$9,'GuV 5 Jahre'!$C$35,0) -> 1400.8333 | H20: =IF(H$13<=12,$G$6*(H$13-0.5)/72,$I$6+$J$6*(H$13-12))+IF(H$13=12+Annahmen!$B$9,'GuV 5 Jahre'!$D$35,0)+IF(H$13=Annahmen!$B$9,'GuV 5 Jahre'!$C$35,0) -> 1961.1667 | I20: =IF(I$13<=12,$G$6*(I$13-0.5)/72,$I$6+$J$6*(I$13-12))+IF(I$13=12+Annahmen!$B$9,'GuV 5 Jahre'!$D$35,0)+IF(I$13=Annahmen!$B$9,'GuV 5 Jahre'!$C$35,0) -> 2521.5 | J20: =IF(J$13<=12,$G$6*(J$13-0.5)/72,$I$6+$J$6*(J$13-12))+IF(J$13=12+Annahmen!$B$9,'GuV 5 Jahre'!$D$35,0)+IF(J$13=Annahmen!$B$9,'GuV 5 Jahre'!$C$35,0) -> 3081.8333 | K20: =IF(K$13<=12,$G$6*(K$13-0.5)/72,$I$6+$J$6*(K$13-12))+IF(K$13=12+Annahmen!$B$9,'GuV 5 Jahre'!$D$35,0)+IF(K$13=Annahmen!$B$9,'GuV 5 Jahre'!$C$35,0) -> 3642.1667 | L20: =IF(L$13<=12,$G$6*(L$13-0.5)/72,$I$6+$J$6*(L$13-12))+IF(L$13=12+Annahmen!$B$9,'GuV 5 Jahre'!$D$35,0)+IF(L$13=Annahmen!$B$9,'GuV 5 Jahre'!$C$35,0) -> 4202.5 | ... AB20: =IF(AB$13<=12,$G$6*(AB$13-0.5)/72,$I$6+$J$6*(AB$13-12))+IF(AB$13=12+Annahmen!$B$9,'GuV 5 Jahre'!$D$35,0)+IF(AB$13=Annahmen!$B$9,'GuV 5 Jahre'!$C$35,0) -> 29061.372
A21: Conversion −1 Pkt.: Kasse | E21: =Annahmen!$B$6+E20*(1-Annahmen!$B$8)-E$14 -> 237007.75 | F21: =E21+F20*(1-Annahmen!$B$8)-F$14 -> 232531.01 | G21: =F21+G20*(1-Annahmen!$B$8)-G$14 -> 223069.78 | H21: =G21+H20*(1-Annahmen!$B$8)-H$14 -> 210999.05 | I21: =H21+I20*(1-Annahmen!$B$8)-I$14 -> 199443.83 | J21: =I21+J20*(1-Annahmen!$B$8)-J$14 -> 188404.12 | K21: =J21+K20*(1-Annahmen!$B$8)-K$14 -> 176879.91 | L21: =K21+L20*(1-Annahmen!$B$8)-L$14 -> 165871.21 | M21: =L21+M20*(1-Annahmen!$B$8)-M$14 -> 153378.02 | ... AB21: =AA21+AB20*(1-Annahmen!$B$8)-AB$14 -> 109509.28
A22: Conversion −1 Pkt.: Kasse < 0 | E22: =IF(E21<0,1,0) -> 0 | F22: =IF(F21<0,1,0) -> 0 | G22: =IF(G21<0,1,0) -> 0 | H22: =IF(H21<0,1,0) -> 0 | I22: =IF(I21<0,1,0) -> 0 | J22: =IF(J21<0,1,0) -> 0 | K22: =IF(K21<0,1,0) -> 0 | L22: =IF(L21<0,1,0) -> 0 | ... AB22: =IF(AB21<0,1,0) -> 0
A24: Conversion +1 Pkt.: Umsatz | E24: =IF(E$13<=12,$G$7*(E$13-0.5)/72,$I$7+$J$7*(E$13-12))+IF(E$13=12+Annahmen!$B$9,'GuV 5 Jahre'!$D$35,0)+IF(E$13=Annahmen!$B$9,'GuV 5 Jahre'!$C$35,0) -> 421.83333 | F24: =IF(F$13<=12,$G$7*(F$13-0.5)/72,$I$7+$J$7*(F$13-12))+IF(F$13=12+Annahmen!$B$9,'GuV 5 Jahre'!$D$35,0)+IF(F$13=Annahmen!$B$9,'GuV 5 Jahre'!$C$35,0) -> 1265.5 | G24: =IF(G$13<=12,$G$7*(G$13-0.5)/72,$I$7+$J$7*(G$13-12))+IF(G$13=12+Annahmen!$B$9,'GuV 5 Jahre'!$D$35,0)+IF(G$13=Annahmen!$B$9,'GuV 5 Jahre'!$C$35,0) -> 2109.1667 | H24: =IF(H$13<=12,$G$7*(H$13-0.5)/72,$I$7+$J$7*(H$13-12))+IF(H$13=12+Annahmen!$B$9,'GuV 5 Jahre'!$D$35,0)+IF(H$13=Annahmen!$B$9,'GuV 5 Jahre'!$C$35,0) -> 2952.8333 | I24: =IF(I$13<=12,$G$7*(I$13-0.5)/72,$I$7+$J$7*(I$13-12))+IF(I$13=12+Annahmen!$B$9,'GuV 5 Jahre'!$D$35,0)+IF(I$13=Annahmen!$B$9,'GuV 5 Jahre'!$C$35,0) -> 3796.5 | J24: =IF(J$13<=12,$G$7*(J$13-0.5)/72,$I$7+$J$7*(J$13-12))+IF(J$13=12+Annahmen!$B$9,'GuV 5 Jahre'!$D$35,0)+IF(J$13=Annahmen!$B$9,'GuV 5 Jahre'!$C$35,0) -> 4640.1667 | K24: =IF(K$13<=12,$G$7*(K$13-0.5)/72,$I$7+$J$7*(K$13-12))+IF(K$13=12+Annahmen!$B$9,'GuV 5 Jahre'!$D$35,0)+IF(K$13=Annahmen!$B$9,'GuV 5 Jahre'!$C$35,0) -> 5483.8333 | L24: =IF(L$13<=12,$G$7*(L$13-0.5)/72,$I$7+$J$7*(L$13-12))+IF(L$13=12+Annahmen!$B$9,'GuV 5 Jahre'!$D$35,0)+IF(L$13=Annahmen!$B$9,'GuV 5 Jahre'!$C$35,0) -> 6327.5 | ... AB24: =IF(AB$13<=12,$G$7*(AB$13-0.5)/72,$I$7+$J$7*(AB$13-12))+IF(AB$13=12+Annahmen!$B$9,'GuV 5 Jahre'!$D$35,0)+IF(AB$13=Annahmen!$B$9,'GuV 5 Jahre'!$C$35,0) -> 45135.09
A25: Conversion +1 Pkt.: Kasse | E25: =Annahmen!$B$6+E24*(1-Annahmen!$B$8)-E$14 -> 237138.09 | F25: =E25+F24*(1-Annahmen!$B$8)-F$14 -> 233052.35 | G25: =F25+G24*(1-Annahmen!$B$8)-G$14 -> 224242.78 | H25: =G25+H24*(1-Annahmen!$B$8)-H$14 -> 213084.39 | I25: =H25+I24*(1-Annahmen!$B$8)-I$14 -> 202702.17 | J25: =I25+J24*(1-Annahmen!$B$8)-J$14 -> 193096.12 | K25: =J25+K24*(1-Annahmen!$B$8)-K$14 -> 183266.25 | L25: =K25+L24*(1-Annahmen!$B$8)-L$14 -> 174212.55 | M25: =L25+M24*(1-Annahmen!$B$8)-M$14 -> 163935.02 | ... AB25: =AA25+AB24*(1-Annahmen!$B$8)-AB$14 -> 240885.28
A26: Conversion +1 Pkt.: Kasse < 0 | E26: =IF(E25<0,1,0) -> 0 | F26: =IF(F25<0,1,0) -> 0 | G26: =IF(G25<0,1,0) -> 0 | H26: =IF(H25<0,1,0) -> 0 | I26: =IF(I25<0,1,0) -> 0 | J26: =IF(J25<0,1,0) -> 0 | K26: =IF(K25<0,1,0) -> 0 | L26: =IF(L25<0,1,0) -> 0 | ... AB26: =IF(AB25<0,1,0) -> 0
A28: ARPU −20 %: Umsatz | E28: =IF(E$13<=12,$G$8*(E$13-0.5)/72,$I$8+$J$8*(E$13-12))+IF(E$13=12+Annahmen!$B$9,'GuV 5 Jahre'!$D$35,0)+IF(E$13=Annahmen!$B$9,'GuV 5 Jahre'!$C$35,0) -> 294.33333 | F28: =IF(F$13<=12,$G$8*(F$13-0.5)/72,$I$8+$J$8*(F$13-12))+IF(F$13=12+Annahmen!$B$9,'GuV 5 Jahre'!$D$35,0)+IF(F$13=Annahmen!$B$9,'GuV 5 Jahre'!$C$35,0) -> 883 | G28: =IF(G$13<=12,$G$8*(G$13-0.5)/72,$I$8+$J$8*(G$13-12))+IF(G$13=12+Annahmen!$B$9,'GuV 5 Jahre'!$D$35,0)+IF(G$13=Annahmen!$B$9,'GuV 5 Jahre'!$C$35,0) -> 1471.6667 | H28: =IF(H$13<=12,$G$8*(H$13-0.5)/72,$I$8+$J$8*(H$13-12))+IF(H$13=12+Annahmen!$B$9,'GuV 5 Jahre'!$D$35,0)+IF(H$13=Annahmen!$B$9,'GuV 5 Jahre'!$C$35,0) -> 2060.3333 | I28: =IF(I$13<=12,$G$8*(I$13-0.5)/72,$I$8+$J$8*(I$13-12))+IF(I$13=12+Annahmen!$B$9,'GuV 5 Jahre'!$D$35,0)+IF(I$13=Annahmen!$B$9,'GuV 5 Jahre'!$C$35,0) -> 2649 | J28: =IF(J$13<=12,$G$8*(J$13-0.5)/72,$I$8+$J$8*(J$13-12))+IF(J$13=12+Annahmen!$B$9,'GuV 5 Jahre'!$D$35,0)+IF(J$13=Annahmen!$B$9,'GuV 5 Jahre'!$C$35,0) -> 3237.6667 | K28: =IF(K$13<=12,$G$8*(K$13-0.5)/72,$I$8+$J$8*(K$13-12))+IF(K$13=12+Annahmen!$B$9,'GuV 5 Jahre'!$D$35,0)+IF(K$13=Annahmen!$B$9,'GuV 5 Jahre'!$C$35,0) -> 3826.3333 | L28: =IF(L$13<=12,$G$8*(L$13-0.5)/72,$I$8+$J$8*(L$13-12))+IF(L$13=12+Annahmen!$B$9,'GuV 5 Jahre'!$D$35,0)+IF(L$13=Annahmen!$B$9,'GuV 5 Jahre'!$C$35,0) -> 4415 | ... AB28: =IF(AB$13<=12,$G$8*(AB$13-0.5)/72,$I$8+$J$8*(AB$13-12))+IF(AB$13=12+Annahmen!$B$9,'GuV 5 Jahre'!$D$35,0)+IF(AB$13=Annahmen!$B$9,'GuV 5 Jahre'!$C$35,0) -> 30668.744
A29: ARPU −20 %: Kasse | E29: =Annahmen!$B$6+E28*(1-Annahmen!$B$8)-E$14 -> 237020.79 | F29: =E29+F28*(1-Annahmen!$B$8)-F$14 -> 232583.15 | G29: =F29+G28*(1-Annahmen!$B$8)-G$14 -> 223187.08 | H29: =G29+H28*(1-Annahmen!$B$8)-H$14 -> 211207.59 | I29: =H29+I28*(1-Annahmen!$B$8)-I$14 -> 199769.67 | J29: =I29+J28*(1-Annahmen!$B$8)-J$14 -> 188873.32 | K29: =J29+K28*(1-Annahmen!$B$8)-K$14 -> 177518.55 | L29: =K29+L28*(1-Annahmen!$B$8)-L$14 -> 166705.35 | M29: =L29+M28*(1-Annahmen!$B$8)-M$14 -> 154433.72 | ... AB29: =AA29+AB28*(1-Annahmen!$B$8)-AB$14 -> 122646.88
A30: ARPU −20 %: Kasse < 0 | E30: =IF(E29<0,1,0) -> 0 | F30: =IF(F29<0,1,0) -> 0 | G30: =IF(G29<0,1,0) -> 0 | H30: =IF(H29<0,1,0) -> 0 | I30: =IF(I29<0,1,0) -> 0 | J30: =IF(J29<0,1,0) -> 0 | K30: =IF(K29<0,1,0) -> 0 | L30: =IF(L29<0,1,0) -> 0 | ... AB30: =IF(AB29<0,1,0) -> 0
A32: ARPU +20 %: Umsatz | E32: =IF(E$13<=12,$G$9*(E$13-0.5)/72,$I$9+$J$9*(E$13-12))+IF(E$13=12+Annahmen!$B$9,'GuV 5 Jahre'!$D$35,0)+IF(E$13=Annahmen!$B$9,'GuV 5 Jahre'!$C$35,0) -> 407.66667 | F32: =IF(F$13<=12,$G$9*(F$13-0.5)/72,$I$9+$J$9*(F$13-12))+IF(F$13=12+Annahmen!$B$9,'GuV 5 Jahre'!$D$35,0)+IF(F$13=Annahmen!$B$9,'GuV 5 Jahre'!$C$35,0) -> 1223 | G32: =IF(G$13<=12,$G$9*(G$13-0.5)/72,$I$9+$J$9*(G$13-12))+IF(G$13=12+Annahmen!$B$9,'GuV 5 Jahre'!$D$35,0)+IF(G$13=Annahmen!$B$9,'GuV 5 Jahre'!$C$35,0) -> 2038.3333 | H32: =IF(H$13<=12,$G$9*(H$13-0.5)/72,$I$9+$J$9*(H$13-12))+IF(H$13=12+Annahmen!$B$9,'GuV 5 Jahre'!$D$35,0)+IF(H$13=Annahmen!$B$9,'GuV 5 Jahre'!$C$35,0) -> 2853.6667 | I32: =IF(I$13<=12,$G$9*(I$13-0.5)/72,$I$9+$J$9*(I$13-12))+IF(I$13=12+Annahmen!$B$9,'GuV 5 Jahre'!$D$35,0)+IF(I$13=Annahmen!$B$9,'GuV 5 Jahre'!$C$35,0) -> 3669 | J32: =IF(J$13<=12,$G$9*(J$13-0.5)/72,$I$9+$J$9*(J$13-12))+IF(J$13=12+Annahmen!$B$9,'GuV 5 Jahre'!$D$35,0)+IF(J$13=Annahmen!$B$9,'GuV 5 Jahre'!$C$35,0) -> 4484.3333 | K32: =IF(K$13<=12,$G$9*(K$13-0.5)/72,$I$9+$J$9*(K$13-12))+IF(K$13=12+Annahmen!$B$9,'GuV 5 Jahre'!$D$35,0)+IF(K$13=Annahmen!$B$9,'GuV 5 Jahre'!$C$35,0) -> 5299.6667 | L32: =IF(L$13<=12,$G$9*(L$13-0.5)/72,$I$9+$J$9*(L$13-12))+IF(L$13=12+Annahmen!$B$9,'GuV 5 Jahre'!$D$35,0)+IF(L$13=Annahmen!$B$9,'GuV 5 Jahre'!$C$35,0) -> 6115 | ... AB32: =IF(AB$13<=12,$G$9*(AB$13-0.5)/72,$I$9+$J$9*(AB$13-12))+IF(AB$13=12+Annahmen!$B$9,'GuV 5 Jahre'!$D$35,0)+IF(AB$13=Annahmen!$B$9,'GuV 5 Jahre'!$C$35,0) -> 43527.718
A33: ARPU +20 %: Kasse | E33: =Annahmen!$B$6+E32*(1-Annahmen!$B$8)-E$14 -> 237125.05 | F33: =E33+F32*(1-Annahmen!$B$8)-F$14 -> 233000.21 | G33: =F33+G32*(1-Annahmen!$B$8)-G$14 -> 224125.48 | H33: =G33+H32*(1-Annahmen!$B$8)-H$14 -> 212875.85 | I33: =H33+I32*(1-Annahmen!$B$8)-I$14 -> 202376.33 | J33: =I33+J32*(1-Annahmen!$B$8)-J$14 -> 192626.92 | K33: =J33+K32*(1-Annahmen!$B$8)-K$14 -> 182627.61 | L33: =K33+L32*(1-Annahmen!$B$8)-L$14 -> 173378.41 | M33: =L33+M32*(1-Annahmen!$B$8)-M$14 -> 162879.32 | ... AB33: =AA33+AB32*(1-Annahmen!$B$8)-AB$14 -> 227747.68
A34: ARPU +20 %: Kasse < 0 | E34: =IF(E33<0,1,0) -> 0 | F34: =IF(F33<0,1,0) -> 0 | G34: =IF(G33<0,1,0) -> 0 | H34: =IF(H33<0,1,0) -> 0 | I34: =IF(I33<0,1,0) -> 0 | J34: =IF(J33<0,1,0) -> 0 | K34: =IF(K33<0,1,0) -> 0 | L34: =IF(L33<0,1,0) -> 0 | ... AB34: =IF(AB33<0,1,0) -> 0
A36: Nutzer −30 %: Umsatz | E36: =IF(E$13<=12,$G$10*(E$13-0.5)/72,$I$10+$J$10*(E$13-12))+IF(E$13=12+Annahmen!$B$9,'GuV 5 Jahre'!$D$35,0)+IF(E$13=Annahmen!$B$9,'GuV 5 Jahre'!$C$35,0) -> 249.375 | F36: =IF(F$13<=12,$G$10*(F$13-0.5)/72,$I$10+$J$10*(F$13-12))+IF(F$13=12+Annahmen!$B$9,'GuV 5 Jahre'!$D$35,0)+IF(F$13=Annahmen!$B$9,'GuV 5 Jahre'!$C$35,0) -> 748.125 | G36: =IF(G$13<=12,$G$10*(G$13-0.5)/72,$I$10+$J$10*(G$13-12))+IF(G$13=12+Annahmen!$B$9,'GuV 5 Jahre'!$D$35,0)+IF(G$13=Annahmen!$B$9,'GuV 5 Jahre'!$C$35,0) -> 1246.875 | H36: =IF(H$13<=12,$G$10*(H$13-0.5)/72,$I$10+$J$10*(H$13-12))+IF(H$13=12+Annahmen!$B$9,'GuV 5 Jahre'!$D$35,0)+IF(H$13=Annahmen!$B$9,'GuV 5 Jahre'!$C$35,0) -> 1745.625 | I36: =IF(I$13<=12,$G$10*(I$13-0.5)/72,$I$10+$J$10*(I$13-12))+IF(I$13=12+Annahmen!$B$9,'GuV 5 Jahre'!$D$35,0)+IF(I$13=Annahmen!$B$9,'GuV 5 Jahre'!$C$35,0) -> 2244.375 | J36: =IF(J$13<=12,$G$10*(J$13-0.5)/72,$I$10+$J$10*(J$13-12))+IF(J$13=12+Annahmen!$B$9,'GuV 5 Jahre'!$D$35,0)+IF(J$13=Annahmen!$B$9,'GuV 5 Jahre'!$C$35,0) -> 2743.125 | K36: =IF(K$13<=12,$G$10*(K$13-0.5)/72,$I$10+$J$10*(K$13-12))+IF(K$13=12+Annahmen!$B$9,'GuV 5 Jahre'!$D$35,0)+IF(K$13=Annahmen!$B$9,'GuV 5 Jahre'!$C$35,0) -> 3241.875 | L36: =IF(L$13<=12,$G$10*(L$13-0.5)/72,$I$10+$J$10*(L$13-12))+IF(L$13=12+Annahmen!$B$9,'GuV 5 Jahre'!$D$35,0)+IF(L$13=Annahmen!$B$9,'GuV 5 Jahre'!$C$35,0) -> 3740.625 | ... AB36: =IF(AB$13<=12,$G$10*(AB$13-0.5)/72,$I$10+$J$10*(AB$13-12))+IF(AB$13=12+Annahmen!$B$9,'GuV 5 Jahre'!$D$35,0)+IF(AB$13=Annahmen!$B$9,'GuV 5 Jahre'!$C$35,0) -> 26304.317
A37: Nutzer −30 %: Kasse | E37: =Annahmen!$B$6+E36*(1-Annahmen!$B$8)-E$14 -> 236979.42 | F37: =E37+F36*(1-Annahmen!$B$8)-F$14 -> 232417.7 | G37: =F37+G36*(1-Annahmen!$B$8)-G$14 -> 222814.83 | H37: =G37+H36*(1-Annahmen!$B$8)-H$14 -> 210545.8 | I37: =H37+I36*(1-Annahmen!$B$8)-I$14 -> 198735.62 | J37: =I37+J36*(1-Annahmen!$B$8)-J$14 -> 187384.3 | K37: =J37+K36*(1-Annahmen!$B$8)-K$14 -> 175491.83 | L37: =K37+L36*(1-Annahmen!$B$8)-L$14 -> 164058.2 | M37: =L37+M36*(1-Annahmen!$B$8)-M$14 -> 151083.42 | ... AB37: =AA37+AB36*(1-Annahmen!$B$8)-AB$14 -> 85359.28
A38: Nutzer −30 %: Kasse < 0 | E38: =IF(E37<0,1,0) -> 0 | F38: =IF(F37<0,1,0) -> 0 | G38: =IF(G37<0,1,0) -> 0 | H38: =IF(H37<0,1,0) -> 0 | I38: =IF(I37<0,1,0) -> 0 | J38: =IF(J37<0,1,0) -> 0 | K38: =IF(K37<0,1,0) -> 0 | L38: =IF(L37<0,1,0) -> 0 | ... AB38: =IF(AB37<0,1,0) -> 0
A40: Nutzer +30 %: Umsatz | E40: =IF(E$13<=12,$G$11*(E$13-0.5)/72,$I$11+$J$11*(E$13-12))+IF(E$13=12+Annahmen!$B$9,'GuV 5 Jahre'!$D$35,0)+IF(E$13=Annahmen!$B$9,'GuV 5 Jahre'!$C$35,0) -> 452.625 | F40: =IF(F$13<=12,$G$11*(F$13-0.5)/72,$I$11+$J$11*(F$13-12))+IF(F$13=12+Annahmen!$B$9,'GuV 5 Jahre'!$D$35,0)+IF(F$13=Annahmen!$B$9,'GuV 5 Jahre'!$C$35,0) -> 1357.875 | G40: =IF(G$13<=12,$G$11*(G$13-0.5)/72,$I$11+$J$11*(G$13-12))+IF(G$13=12+Annahmen!$B$9,'GuV 5 Jahre'!$D$35,0)+IF(G$13=Annahmen!$B$9,'GuV 5 Jahre'!$C$35,0) -> 2263.125 | H40: =IF(H$13<=12,$G$11*(H$13-0.5)/72,$I$11+$J$11*(H$13-12))+IF(H$13=12+Annahmen!$B$9,'GuV 5 Jahre'!$D$35,0)+IF(H$13=Annahmen!$B$9,'GuV 5 Jahre'!$C$35,0) -> 3168.375 | I40: =IF(I$13<=12,$G$11*(I$13-0.5)/72,$I$11+$J$11*(I$13-12))+IF(I$13=12+Annahmen!$B$9,'GuV 5 Jahre'!$D$35,0)+IF(I$13=Annahmen!$B$9,'GuV 5 Jahre'!$C$35,0) -> 4073.625 | J40: =IF(J$13<=12,$G$11*(J$13-0.5)/72,$I$11+$J$11*(J$13-12))+IF(J$13=12+Annahmen!$B$9,'GuV 5 Jahre'!$D$35,0)+IF(J$13=Annahmen!$B$9,'GuV 5 Jahre'!$C$35,0) -> 4978.875 | K40: =IF(K$13<=12,$G$11*(K$13-0.5)/72,$I$11+$J$11*(K$13-12))+IF(K$13=12+Annahmen!$B$9,'GuV 5 Jahre'!$D$35,0)+IF(K$13=Annahmen!$B$9,'GuV 5 Jahre'!$C$35,0) -> 5884.125 | L40: =IF(L$13<=12,$G$11*(L$13-0.5)/72,$I$11+$J$11*(L$13-12))+IF(L$13=12+Annahmen!$B$9,'GuV 5 Jahre'!$D$35,0)+IF(L$13=Annahmen!$B$9,'GuV 5 Jahre'!$C$35,0) -> 6789.375 | ... AB40: =IF(AB$13<=12,$G$11*(AB$13-0.5)/72,$I$11+$J$11*(AB$13-12))+IF(AB$13=12+Annahmen!$B$9,'GuV 5 Jahre'!$D$35,0)+IF(AB$13=Annahmen!$B$9,'GuV 5 Jahre'!$C$35,0) -> 47892.144
A41: Nutzer +30 %: Kasse | E41: =Annahmen!$B$6+E40*(1-Annahmen!$B$8)-E$14 -> 237166.42 | F41: =E41+F40*(1-Annahmen!$B$8)-F$14 -> 233165.66 | G41: =F41+G40*(1-Annahmen!$B$8)-G$14 -> 224497.73 | H41: =G41+H40*(1-Annahmen!$B$8)-H$14 -> 213537.64 | I41: =H41+I40*(1-Annahmen!$B$8)-I$14 -> 203410.38 | J41: =I41+J40*(1-Annahmen!$B$8)-J$14 -> 194115.94 | K41: =J41+K40*(1-Annahmen!$B$8)-K$14 -> 184654.33 | L41: =K41+L40*(1-Annahmen!$B$8)-L$14 -> 176025.56 | M41: =L41+M40*(1-Annahmen!$B$8)-M$14 -> 166229.61 | ... AB41: =AA41+AB40*(1-Annahmen!$B$8)-AB$14 -> 265035.28
A42: Nutzer +30 %: Kasse < 0 | E42: =IF(E41<0,1,0) -> 0 | F42: =IF(F41<0,1,0) -> 0 | G42: =IF(G41<0,1,0) -> 0 | H42: =IF(H41<0,1,0) -> 0 | I42: =IF(I41<0,1,0) -> 0 | J42: =IF(J41<0,1,0) -> 0 | K42: =IF(K41<0,1,0) -> 0 | L42: =IF(L41<0,1,0) -> 0 | ... AB42: =IF(AB41<0,1,0) -> 0
A45: Kontrolle: Basis-Fall Kasse M24 = Liquidität Basis M24 | E45: =IF(ROUND(O5-'Liquidität 24M'!$D$9,0)=0,"OK","PRÜFEN") -> OK | F45: =IF(ROUND(E5-'GuV 5 Jahre'!$E$36,0)=0,"OK","PRÜFEN") -> OK

Sheet Diagramme
A1: Diagramme
A3: Basis (€) | B3: Umsatz | C3: Kosten | D3: EBITDA | F3: Monat | G3: Konservativ | H3: Basis | I3: Optimistisch | J3: Ohne Umsatz
A4: J1 2027 | B4: ='GuV 5 Jahre'!C36 -> 50544 | C4: ='GuV 5 Jahre'!C37 -> 166168.52 | D4: ='GuV 5 Jahre'!C38 -> -115624.52 | F4: 1 | G4: ='Liquidität 24M'!D67 -> 236849.99 | H4: ='Liquidität 24M'!D88 -> 237072.92 | I4: ='Liquidität 24M'!D109 -> 237542.81 | J4: ='Liquidität 24M'!D117 -> 236750
A5: J2 2028 | B5: ='GuV 5 Jahre'!D36 -> 335540 | C5: ='GuV 5 Jahre'!D37 -> 294718.2 | D5: ='GuV 5 Jahre'!D38 -> 40821.8 | F5: 2 | G5: ='Liquidität 24M'!E67 -> 231899.95 | H5: ='Liquidität 24M'!E88 -> 232791.68 | I5: ='Liquidität 24M'!E109 -> 234671.24 | J5: ='Liquidität 24M'!E117 -> 231500
A6: J3 2029 | B6: ='GuV 5 Jahre'!E36 -> 1038270 | C6: ='GuV 5 Jahre'!E37 -> 710000 | D6: ='GuV 5 Jahre'!E38 -> 328270 | F6: 3 | G6: ='Liquidität 24M'!F67 -> 221649.9 | H6: ='Liquidität 24M'!F88 -> 223656.28 | I6: ='Liquidität 24M'!F109 -> 227885.29 | J6: ='Liquidität 24M'!F117 -> 220750
A7: J4 2030 | B7: ='GuV 5 Jahre'!F36 -> 1983772.5 | C7: ='GuV 5 Jahre'!F37 -> 1065000 | D7: ='GuV 5 Jahre'!F38 -> 918772.5 | F7: 4 | G7: ='Liquidität 24M'!G67 -> 208474.82 | H7: ='Liquidität 24M'!G88 -> 212041.72 | I7: ='Liquidität 24M'!G109 -> 219559.96 | J7: ='Liquidität 24M'!G117 -> 206875
A8: J5 2031 | B8: ='GuV 5 Jahre'!G36 -> 3151812.5 | C8: ='GuV 5 Jahre'!G37 -> 1491000 | D8: ='GuV 5 Jahre'!G38 -> 1660812.5 | F8: 5 | G8: ='Liquidität 24M'!H67 -> 195499.72 | H8: ='Liquidität 24M'!H88 -> 201073 | I8: ='Liquidität 24M'!H109 -> 212820.25 | J8: ='Liquidität 24M'!H117 -> 193000
F9: 6 | G9: ='Liquidität 24M'!I67 -> 182724.59 | H9: ='Liquidität 24M'!I88 -> 190750.12 | I9: ='Liquidität 24M'!I109 -> 207666.16 | J9: ='Liquidität 24M'!I117 -> 179125
F10: 7 | G10: ='Liquidität 24M'!J67 -> 169149.44 | H10: ='Liquidität 24M'!J88 -> 180073.08 | I10: ='Liquidität 24M'!J109 -> 203097.69 | J10: ='Liquidität 24M'!J117 -> 164250
F11: 8 | G11: ='Liquidität 24M'!K67 -> 155774.27 | H11: ='Liquidität 24M'!K88 -> 170041.88 | I11: ='Liquidität 24M'!K109 -> 200114.84 | J11: ='Liquidität 24M'!K117 -> 149375
F12: 9 | G12: ='Liquidität 24M'!L67 -> 140599.08 | H12: ='Liquidität 24M'!L88 -> 158656.52 | I12: ='Liquidität 24M'!L109 -> 196717.61 | J12: ='Liquidität 24M'!L117 -> 132500
F13: 10 | G13: ='Liquidität 24M'!M67 -> 127623.87 | H13: ='Liquidität 24M'!M88 -> 149917 | I13: ='Liquidität 24M'!M109 -> 196906 | J13: ='Liquidität 24M'!M117 -> 117625
F14: 11 | G14: ='Liquidität 24M'!N67 -> 114848.63 | H14: ='Liquidität 24M'!N88 -> 141823.32 | I14: ='Liquidität 24M'!N109 -> 198680.01 | J14: ='Liquidität 24M'!N117 -> 102750
F15: 12 | G15: ='Liquidität 24M'!O67 -> 102273.37 | H15: ='Liquidität 24M'!O88 -> 134375.48 | I15: ='Liquidität 24M'!O109 -> 202039.64 | J15: ='Liquidität 24M'!O117 -> 87875
F16: 13 | G16: ='Liquidität 24M'!P67 -> 90310.691 | H16: ='Liquidität 24M'!P88 -> 129152.91 | I16: ='Liquidität 24M'!P109 -> 211939.3 | J16: ='Liquidität 24M'!P117 -> 73000
F17: 14 | G17: ='Liquidität 24M'!Q67 -> 78960.596 | H17: ='Liquidität 24M'!Q88 -> 126155.6 | I17: ='Liquidität 24M'!Q109 -> 228379 | J17: ='Liquidität 24M'!Q117 -> 58125
F18: 15 | G18: ='Liquidität 24M'!R67 -> 68223.085 | H18: ='Liquidität 24M'!R88 -> 125383.57 | I18: ='Liquidität 24M'!R109 -> 251358.72 | J18: ='Liquidität 24M'!R117 -> 43250
F19: 16 | G19: ='Liquidität 24M'!S67 -> 61223.157 | H19: ='Liquidität 24M'!S88 -> 129961.8 | I19: ='Liquidität 24M'!S109 -> 284003.48 | J19: ='Liquidität 24M'!S117 -> 31500
F20: 17 | G20: ='Liquidität 24M'!T67 -> 54835.812 | H20: ='Liquidität 24M'!T88 -> 136765.3 | I20: ='Liquidität 24M'!T109 -> 323188.27 | J20: ='Liquidität 24M'!T117 -> 19750
F21: 18 | G21: ='Liquidität 24M'!U67 -> 49061.051 | H21: ='Liquidität 24M'!U88 -> 145794.06 | I21: ='Liquidität 24M'!U109 -> 368913.1 | J21: ='Liquidität 24M'!U117 -> 8000
F22: 19 | G22: ='Liquidität 24M'!V67 -> 37436.142 | H22: ='Liquidität 24M'!V88 -> 137464.76 | I22: ='Liquidität 24M'!V109 -> 392066.56 | J22: ='Liquidität 24M'!V117 -> -3750
F23: 20 | G23: ='Liquidität 24M'!W67 -> 26423.816 | H23: ='Liquidität 24M'!W88 -> 131360.73 | I23: ='Liquidität 24M'!W109 -> 421760.06 | J23: ='Liquidität 24M'!W117 -> -15500
F24: 21 | G24: ='Liquidität 24M'!X67 -> 16024.074 | H24: ='Liquidität 24M'!X88 -> 127481.97 | I24: ='Liquidität 24M'!X109 -> 457993.59 | J24: ='Liquidität 24M'!X117 -> -27250
F25: 22 | G25: ='Liquidität 24M'!Y67 -> 6236.9149 | H25: ='Liquidität 24M'!Y88 -> 171828.47 | I25: ='Liquidität 24M'!Y109 -> 592767.16 | J25: ='Liquidität 24M'!Y117 -> -39000
F26: 23 | G26: ='Liquidität 24M'!Z67 -> -2937.6611 | H26: ='Liquidität 24M'!Z88 -> 172400.24 | I26: ='Liquidität 24M'!Z109 -> 642080.75 | J26: ='Liquidität 24M'!Z117 -> -50750
F27: 24 | G27: ='Liquidität 24M'!AA67 -> -11499.654 | H27: ='Liquidität 24M'!AA88 -> 175197.28 | I27: ='Liquidität 24M'!AA109 -> 697934.38 | J27: ='Liquidität 24M'!AA117 -> -62500

Sheet Übersetzung
A1: Übersetzung der wichtigsten Begriffe / Çeviri / Translation
A3: Deutsch | B3: Türkçe | C3: English
A4: Annahmen | B4: Varsayımlar | C4: Assumptions
A5: GuV 5 Jahre | B5: 5 yıllık gelir tablosu | C5: 5-year P&L
A6: Mittelverwendung | B6: Fonların kullanımı | C6: Use of funds
A7: Liquidität monatlich, 24 Monate | B7: Aylık nakit akışı, 24 ay | C7: Monthly cash flow, 24 months
A8: Gates / Meilensteine (Ziele) | B8: Kilometre taşları / hedefler | C8: Gates / milestones (targets)
A9: Bewertung | B9: Değerleme | C9: Valuation
A10: Sensitivität | B10: Duyarlılık analizi | C10: Sensitivity
A11: Konservativ / Basis / Optimistisch | B11: Temkinli / Baz / İyimser | C11: Conservative / Base / Optimistic
A12: Registrierte Nutzer | B12: Kayıtlı kullanıcılar | C12: Registered users
A13: Conversion Free → Pro | B13: Ücretsizden Pro'ya dönüşüm | C13: Free-to-Pro conversion
A14: Zahlende Pro-Nutzer | B14: Ödeme yapan Pro kullanıcılar | C14: Paying Pro users
... A40: Schätzung | B40: Tahmin | C40: Estimate
